Workbook

Sheet ESTOQUE BXD2 (2)
A1: ✏️ Manual | B1: ✏️ Manual | C1: ✏️ Manual | D1: ✅ Fórmula | E1: ✅ Fórmula | F1: ✅ Fórmula | G1: ✏️ Manual
A2: Cod.SAP | C2: unidade | D2: Entrada | E2: Saída | F2: Saldo Estoque | G2: ATUALIZAÇÃO
A3: =_xlfn.XLOOKUP(B3,'Entrada de Materiais'!C:C,'Entrada de Materiais'!B:B) -> 4010017 | B3: *ROLAMENTO ESF RIG 6226/C3 SKF | C3: UND | D3: =SUMIFS('Entrada de Materiais'!D:D, 'Entrada de Materiais'!C:C, B3) -> 4 | E3: =SUMIFS('SAIDA DE MATERIAIS'!F:F,'SAIDA DE MATERIAIS'!C:C,B3) -> 2 | F3: =+D3-E3 -> 2
A4: =_xlfn.XLOOKUP(B4,'Entrada de Materiais'!C:C,'Entrada de Materiais'!B:B) -> 5532022 | B4: _CHAVE SECCIONADORA POTENCIA - 160 A | C4: UND | D4: =SUMIFS('Entrada de Materiais'!D:D, 'Entrada de Materiais'!C:C, B4) -> 1 | E4: =SUMIFS('SAIDA DE MATERIAIS'!F:F,'SAIDA DE MATERIAIS'!C:C,B4) -> 0 | F4: =+D4-E4 -> 1
A5: =_xlfn.XLOOKUP(B5,'Entrada de Materiais'!C:C,'Entrada de Materiais'!B:B) -> 5532023 | B5: _CHAVE SECCIONADORA POTENCIA - 250 A | C5: UND | D5: =SUMIFS('Entrada de Materiais'!D:D, 'Entrada de Materiais'!C:C, B5) -> 2 | E5: =SUMIFS('SAIDA DE MATERIAIS'!F:F,'SAIDA DE MATERIAIS'!C:C,B5) -> 0 | F5: =+D5-E5 -> 2
A6: =_xlfn.XLOOKUP(B6,'Entrada de Materiais'!C:C,'Entrada de Materiais'!B:B) -> 5532024 | B6: _CHAVE SECCIONADORA POTENCIA - 400 A | C6: UND | D6: =SUMIFS('Entrada de Materiais'!D:D, 'Entrada de Materiais'!C:C, B6) -> 2 | E6: =SUMIFS('SAIDA DE MATERIAIS'!F:F,'SAIDA DE MATERIAIS'!C:C,B6) -> 0 | F6: =+D6-E6 -> 2
A7: =_xlfn.XLOOKUP(B7,'Entrada de Materiais'!C:C,'Entrada de Materiais'!B:B) -> 5532025 | B7: _CHAVE SECCIONADORA POTENCIA - 630 A | C7: UND | D7: =SUMIFS('Entrada de Materiais'!D:D, 'Entrada de Materiais'!C:C, B7) -> 2 | E7: =SUMIFS('SAIDA DE MATERIAIS'!F:F,'SAIDA DE MATERIAIS'!C:C,B7) -> 0 | F7: =+D7-E7 -> 2
A8: =_xlfn.XLOOKUP(B8,'Entrada de Materiais'!C:C,'Entrada de Materiais'!B:B) -> 5532031 | B8: _CHAVE SECCIONADORA PUNHO 3P 250A C/FUS | C8: UND | D8: =SUMIFS('Entrada de Materiais'!D:D, 'Entrada de Materiais'!C:C, B8) -> 1 | E8: =SUMIFS('SAIDA DE MATERIAIS'!F:F,'SAIDA DE MATERIAIS'!C:C,B8) -> 0 | F8: =+D8-E8 -> 1
A9: =_xlfn.XLOOKUP(B9,'Entrada de Materiais'!C:C,'Entrada de Materiais'!B:B) -> 5028401 | B9: _CONTATOR 3P 220V CA 1NA 80A | C9: UND | D9: =SUMIFS('Entrada de Materiais'!D:D, 'Entrada de Materiais'!C:C, B9) -> 2 | E9: =SUMIFS('SAIDA DE MATERIAIS'!F:F,'SAIDA DE MATERIAIS'!C:C,B9) -> 0 | F9: =+D9-E9 -> 2
A10: =_xlfn.XLOOKUP(B10,'Entrada de Materiais'!C:C,'Entrada de Materiais'!B:B) -> 5029619 | B10: _RELE SOBRECARGA TERMICO REG 95-120A | C10: UND | D10: =SUMIFS('Entrada de Materiais'!D:D, 'Entrada de Materiais'!C:C, B10) -> 1 | E10: =SUMIFS('SAIDA DE MATERIAIS'!F:F,'SAIDA DE MATERIAIS'!C:C,B10) -> 0 | F10: =+D10-E10 -> 1
A11: =_xlfn.XLOOKUP(B11,'Entrada de Materiais'!C:C,'Entrada de Materiais'!B:B) -> #N/A | B11: _TRANSMISSOR PRESSAO AI A1 TIPO G 0-6BAR | C11: UND | D11: =SUMIFS('Entrada de Materiais'!D:D, 'Entrada de Materiais'!C:C, B11) -> 0 | E11: =SUMIFS('SAIDA DE MATERIAIS'!F:F,'SAIDA DE MATERIAIS'!C:C,B11) -> 0 | F11: =+D11-E11 -> 0
A12: =_xlfn.XLOOKUP(B12,'Entrada de Materiais'!C:C,'Entrada de Materiais'!B:B) -> 3009327 | B12: ABRACADEIRA BAP AC GALV 1200MM 33 FUROS | C12: UND | D12: =SUMIFS('Entrada de Materiais'!D:D, 'Entrada de Materiais'!C:C, B12) -> 23 | E12: =SUMIFS('SAIDA DE MATERIAIS'!F:F,'SAIDA DE MATERIAIS'!C:C,B12) -> 1 | F12: =+D12-E12 -> 22
A13: =_xlfn.XLOOKUP(B13,'Entrada de Materiais'!C:C,'Entrada de Materiais'!B:B) -> 3000011 | B13: ABRACADEIRA COP AC 1020 CZ 1POL 25,4MM | C13: UND | D13: =SUMIFS('Entrada de Materiais'!D:D, 'Entrada de Materiais'!C:C, B13) -> 3 | E13: =SUMIFS('SAIDA DE MATERIAIS'!F:F,'SAIDA DE MATERIAIS'!C:C,B13) -> 0 | F13: =+D13-E13 -> 3
A14: =_xlfn.XLOOKUP(B14,'Entrada de Materiais'!C:C,'Entrada de Materiais'!B:B) -> 3000010 | B14: ABRACADEIRA COP AC 1020 NAT 3/4POL | C14: UND | D14: =SUMIFS('Entrada de Materiais'!D:D, 'Entrada de Materiais'!C:C, B14) -> 3 | E14: =SUMIFS('SAIDA DE MATERIAIS'!F:F,'SAIDA DE MATERIAIS'!C:C,B14) -> 0 | F14: =+D14-E14 -> 3
... A97: =_xlfn.XLOOKUP(B97,'Entrada de Materiais'!C:C,'Entrada de Materiais'!B:B) -> 5000800 | B97: BUCHA RED PVC-R AF DE2X1POL | C97: UNID | D97: =SUMIFS('Entrada de Materiais'!D:D, 'Entrada de Materiais'!C:C, B97) -> 15 | E97: =SUMIFS('SAIDA DE MATERIAIS'!F:F,'SAIDA DE MATERIAIS'!C:C,B97) -> 0 | F97: =+D97-E97 -> 15
A98: 5000699 | B98: BUCHA RED PVC-R AF DE3/4X1/2POL | C98: UND | D98: =SUMIFS('Entrada de Materiais'!D:D, 'Entrada de Materiais'!C:C, B98) -> 30 | E98: =SUMIFS('SAIDA DE MATERIAIS'!F:F,'SAIDA DE MATERIAIS'!C:C,B98) -> 4 | F98: =+D98-E98 -> 26
A99: =_xlfn.XLOOKUP(B99,'Entrada de Materiais'!C:C,'Entrada de Materiais'!B:B) -> 5510706 | B99: BUCHA REDUCAO LAT 1/2POL 1/4POL ( MANOMETRO ) | C99: UND | D99: =SUMIFS('Entrada de Materiais'!D:D, 'Entrada de Materiais'!C:C, B99) -> 20 | E99: =SUMIFS('SAIDA DE MATERIAIS'!F:F,'SAIDA DE MATERIAIS'!C:C,B99) -> 0 | F99: =+D99-E99 -> 20
A100: =_xlfn.XLOOKUP(B100,'Entrada de Materiais'!C:C,'Entrada de Materiais'!B:B) -> 5025191 | B100: CABO AUTOMACAO PVC 70GRC PT 4VIAS 26AWG | C100: UND | D100: =SUMIFS('Entrada de Materiais'!D:D, 'Entrada de Materiais'!C:C, B100) -> 500 | E100: =SUMIFS('SAIDA DE MATERIAIS'!F:F,'SAIDA DE MATERIAIS'!C:C,B100) -> 22 | F100: =+D100-E100 -> 478
A101: =_xlfn.XLOOKUP(B101,'Entrada de Materiais'!C:C,'Entrada de Materiais'!B:B) -> 5021081 | B101: CABO COB PP 1KV 3X10MM2 PT | C101: UND | D101: =SUMIFS('Entrada de Materiais'!D:D, 'Entrada de Materiais'!C:C, B101) -> 50 | E101: =SUMIFS('SAIDA DE MATERIAIS'!F:F,'SAIDA DE MATERIAIS'!C:C,B101) -> 50 | F101: =+D101-E101 -> 0
A102: =_xlfn.XLOOKUP(B102,'Entrada de Materiais'!C:C,'Entrada de Materiais'!B:B) -> 5014924 | B102: CABO COB PP 1KV 3X2,5MM2 PT | C102: UND | D102: =SUMIFS('Entrada de Materiais'!D:D, 'Entrada de Materiais'!C:C, B102) -> 555 | E102: =SUMIFS('SAIDA DE MATERIAIS'!F:F,'SAIDA DE MATERIAIS'!C:C,B102) -> 0 | F102: =+D102-E102 -> 555
A103: =_xlfn.XLOOKUP(B103,'Entrada de Materiais'!C:C,'Entrada de Materiais'!B:B) -> 5001053 | B103: CABO COBRE NU TMD CL2A 1X16MM | C103: UND | D103: =SUMIFS('Entrada de Materiais'!D:D, 'Entrada de Materiais'!C:C, B103) -> 350 | E103: =SUMIFS('SAIDA DE MATERIAIS'!F:F,'SAIDA DE MATERIAIS'!C:C,B103) -> 0 | F103: =+D103-E103 -> 350
A104: =_xlfn.XLOOKUP(B104,'Entrada de Materiais'!C:C,'Entrada de Materiais'!B:B) -> 5001073 | B104: CABO ELE PP 450/ 750V 1X4MM | C104: M | D104: =SUMIFS('Entrada de Materiais'!D:D, 'Entrada de Materiais'!C:C, B104) -> 2 | E104: =SUMIFS('SAIDA DE MATERIAIS'!F:F,'SAIDA DE MATERIAIS'!C:C,B104) -> 2 | F104: =+D104-E104 -> 0
A105: =_xlfn.XLOOKUP(B105,'Entrada de Materiais'!C:C,'Entrada de Materiais'!B:B) -> 5027101 | B105: CABO ELET 0,6/1KV 240MM CL4 PT | C105: UND | D105: =SUMIFS('Entrada de Materiais'!D:D, 'Entrada de Materiais'!C:C, B105) -> 26.9 | E105: =SUMIFS('SAIDA DE MATERIAIS'!F:F,'SAIDA DE MATERIAIS'!C:C,B105) -> 0 | F105: =+D105-E105 -> 26.9
A106: =_xlfn.XLOOKUP(B106,'Entrada de Materiais'!C:C,'Entrada de Materiais'!B:B) -> 5017911 | B106: CABO ELET FLEX 0,6/1KV 1 X 4MM2 PT | C106: M | D106: =SUMIFS('Entrada de Materiais'!D:D, 'Entrada de Materiais'!C:C, B106) -> 0 | E106: =SUMIFS('SAIDA DE MATERIAIS'!F:F,'SAIDA DE MATERIAIS'!C:C,B106) -> 0 | F106: =+D106-E106 -> 0
A107: 5015300 | B107: CABO ELET FLEX 0,6/1KV 10MM2 CL5 PT | C107: UND | D107: =SUMIFS('Entrada de Materiais'!D:D, 'Entrada de Materiais'!C:C, B107) -> 300 | E107: =SUMIFS('SAIDA DE MATERIAIS'!F:F,'SAIDA DE MATERIAIS'!C:C,B107) -> 0 | F107: =+D107-E107 -> 300
A108: =_xlfn.XLOOKUP(B108,'Entrada de Materiais'!C:C,'Entrada de Materiais'!B:B) -> 5017979 | B108: CABO ELET FLEX 0,6/1KV 1X25MM2 PT | C108: M | D108: =SUMIFS('Entrada de Materiais'!D:D, 'Entrada de Materiais'!C:C, B108) -> 0 | E108: =SUMIFS('SAIDA DE MATERIAIS'!F:F,'SAIDA DE MATERIAIS'!C:C,B108) -> 0 | F108: =+D108-E108 -> 0
A109: =_xlfn.XLOOKUP(B109,'Entrada de Materiais'!C:C,'Entrada de Materiais'!B:B) -> 5016434 | B109: CABO ELET FLEX 0,6/1KV 3 X 25MM2 PT | C109: M | D109: =SUMIFS('Entrada de Materiais'!D:D, 'Entrada de Materiais'!C:C, B109) -> 4 | E109: =SUMIFS('SAIDA DE MATERIAIS'!F:F,'SAIDA DE MATERIAIS'!C:C,B109) -> 4 | F109: =+D109-E109 -> 0
A110: =_xlfn.XLOOKUP(B110,'Entrada de Materiais'!C:C,'Entrada de Materiais'!B:B) -> 5021333 | B110: CABO ELET FLEX 0,6/1KV 70MM2 CL5 PT | C110: M | D110: =SUMIFS('Entrada de Materiais'!D:D, 'Entrada de Materiais'!C:C, B110) -> 0 | E110: =SUMIFS('SAIDA DE MATERIAIS'!F:F,'SAIDA DE MATERIAIS'!C:C,B110) -> 0 | F110: =+D110-E110 -> 0
A111: =_xlfn.XLOOKUP(B111,'Entrada de Materiais'!C:C,'Entrada de Materiais'!B:B) -> 5019991 | B111: CABO ELET FLEX 0,6/1KV1X185MM2 | C111: M | D111: =SUMIFS('Entrada de Materiais'!D:D, 'Entrada de Materiais'!C:C, B111) -> 800 | E111: =SUMIFS('SAIDA DE MATERIAIS'!F:F,'SAIDA DE MATERIAIS'!C:C,B111) -> 18 | F111: =+D111-E111 -> 782
A112: =_xlfn.XLOOKUP(B112,'Entrada de Materiais'!C:C,'Entrada de Materiais'!B:B) -> 5001146 | B112: CABO ELET FLEX 1 X 16MM2 PT | C112: M | D112: =SUMIFS('Entrada de Materiais'!D:D, 'Entrada de Materiais'!C:C, B112) -> 60 | E112: =SUMIFS('SAIDA DE MATERIAIS'!F:F,'SAIDA DE MATERIAIS'!C:C,B112) -> 60 | F112: =+D112-E112 -> 0
A113: =_xlfn.XLOOKUP(B113,'Entrada de Materiais'!C:C,'Entrada de Materiais'!B:B) -> 5001151 | B113: CABO ELET FLEX 1 X 95MM2 PT | C113: M | D113: =SUMIFS('Entrada de Materiais'!D:D, 'Entrada de Materiais'!C:C, B113) -> 200 | E113: =SUMIFS('SAIDA DE MATERIAIS'!F:F,'SAIDA DE MATERIAIS'!C:C,B113) -> 0 | F113: =+D113-E113 -> 200
A114: =_xlfn.XLOOKUP(B114,'Entrada de Materiais'!C:C,'Entrada de Materiais'!B:B) -> 5018072 | B114: CABO ELET FLEX 450/750V 1MM2 CL4 | C114: M | D114: =SUMIFS('Entrada de Materiais'!D:D, 'Entrada de Materiais'!C:C, B114) -> 900 | E114: =SUMIFS('SAIDA DE MATERIAIS'!F:F,'SAIDA DE MATERIAIS'!C:C,B114) -> 102 | F114: =+D114-E114 -> 798
A115: =_xlfn.XLOOKUP(B115,'Entrada de Materiais'!C:C,'Entrada de Materiais'!B:B) -> 5019778 | B115: CABO ELET FLEX 450/750V 1MM2 CL4 CZ | C115: M | D115: =SUMIFS('Entrada de Materiais'!D:D, 'Entrada de Materiais'!C:C, B115) -> 600 | E115: =SUMIFS('SAIDA DE MATERIAIS'!F:F,'SAIDA DE MATERIAIS'!C:C,B115) -> 0 | F115: =+D115-E115 -> 600
A116: =_xlfn.XLOOKUP(B116,'Entrada de Materiais'!C:C,'Entrada de Materiais'!B:B) -> 5019701 | B116: CABO ELET FLEX 750V 1MM2 PT | C116: M | D116: =SUMIFS('Entrada de Materiais'!D:D, 'Entrada de Materiais'!C:C, B116) -> 0 | E116: =SUMIFS('SAIDA DE MATERIAIS'!F:F,'SAIDA DE MATERIAIS'!C:C,B116) -> 0 | F116: =+D116-E116 -> 0
A117: =_xlfn.XLOOKUP(B117,'Entrada de Materiais'!C:C,'Entrada de Materiais'!B:B) -> 5019782 | B117: CABO ELET FLEX 750V 1MM2 CINZA | C117: M | D117: =SUMIFS('Entrada de Materiais'!D:D, 'Entrada de Materiais'!C:C, B117) -> 0 | E117: =SUMIFS('SAIDA DE MATERIAIS'!F:F,'SAIDA DE MATERIAIS'!C:C,B117) -> 0 | F117: =+D117-E117 -> 0
A118: =_xlfn.XLOOKUP(B118,'Entrada de Materiais'!C:C,'Entrada de Materiais'!B:B) -> 5001357 | B118: CABO ELET FLEX 750V 6MM | C118: M | D118: =SUMIFS('Entrada de Materiais'!D:D, 'Entrada de Materiais'!C:C, B118) -> 0 | E118: =SUMIFS('SAIDA DE MATERIAIS'!F:F,'SAIDA DE MATERIAIS'!C:C,B118) -> 0 | F118: =+D118-E118 -> 0
A119: =_xlfn.XLOOKUP(B119,'Entrada de Materiais'!C:C,'Entrada de Materiais'!B:B) -> 5001074 | B119: CABO ELET PP 450 / 750 V 4 X 6MM2 | C119: M | D119: =SUMIFS('Entrada de Materiais'!D:D, 'Entrada de Materiais'!C:C, B119) -> 85 | E119: =SUMIFS('SAIDA DE MATERIAIS'!F:F,'SAIDA DE MATERIAIS'!C:C,B119) -> 85 | F119: =+D119-E119 -> 0
... A131: =_xlfn.XLOOKUP(B131,'Entrada de Materiais'!C:C,'Entrada de Materiais'!B:B) -> 5025952 | B131: CABO FLEX EPR ATOX 0,6/1KV 1X95MM VD | C131: M | D131: =SUMIFS('Entrada de Materiais'!D:D, 'Entrada de Materiais'!C:C, B131) -> 20 | E131: =SUMIFS('SAIDA DE MATERIAIS'!F:F,'SAIDA DE MATERIAIS'!C:C,B131) -> 0 | F131: =+D131-E131 -> 20
A132: 5025965 | B132: CABO FLEX HEPR ATOX 0,6/1KV 1X16MM2 PT | C132: UND | D132: =SUMIFS('Entrada de Materiais'!D:D, 'Entrada de Materiais'!C:C, B132) -> 300 | E132: =SUMIFS('SAIDA DE MATERIAIS'!F:F,'SAIDA DE MATERIAIS'!C:C,B132) -> 0 | F132: =+D132-E132 -> 300
A133: =_xlfn.XLOOKUP(B133,'Entrada de Materiais'!C:C,'Entrada de Materiais'!B:B) -> 5001373 | B133: CABO FLEXIVEL 1KV 150MM *BOBINA +- | C133: M | D133: =SUMIFS('Entrada de Materiais'!D:D, 'Entrada de Materiais'!C:C, B133) -> 0 | E133: =SUMIFS('SAIDA DE MATERIAIS'!F:F,'SAIDA DE MATERIAIS'!C:C,B133) -> 0 | F133: =+D133-E133 -> 0
A134: =_xlfn.XLOOKUP(B134,'Entrada de Materiais'!C:C,'Entrada de Materiais'!B:B) -> 5017977 | B134: CABO FLEXIVEL 1KV 35MM 1KV | C134: M | D134: =SUMIFS('Entrada de Materiais'!D:D, 'Entrada de Materiais'!C:C, B134) -> 0 | E134: =SUMIFS('SAIDA DE MATERIAIS'!F:F,'SAIDA DE MATERIAIS'!C:C,B134) -> 0 | F134: =+D134-E134 -> 0
A135: =_xlfn.XLOOKUP(B135,'Entrada de Materiais'!C:C,'Entrada de Materiais'!B:B) -> 5000990 | B135: CABO FLEXÍVEL 1KV 50MM | C135: M | D135: =SUMIFS('Entrada de Materiais'!D:D, 'Entrada de Materiais'!C:C, B135) -> 30 | E135: =SUMIFS('SAIDA DE MATERIAIS'!F:F,'SAIDA DE MATERIAIS'!C:C,B135) -> 0 | F135: =+D135-E135 -> 30
A136: =_xlfn.XLOOKUP(B136,'Entrada de Materiais'!C:C,'Entrada de Materiais'!B:B) -> 5021809 | B136: CABO FLEXIVEL PP 1KV 4X16MM2 PT | C136: M | D136: =SUMIFS('Entrada de Materiais'!D:D, 'Entrada de Materiais'!C:C, B136) -> 0 | E136: =SUMIFS('SAIDA DE MATERIAIS'!F:F,'SAIDA DE MATERIAIS'!C:C,B136) -> 0 | F136: =+D136-E136 -> 0
A137: =_xlfn.XLOOKUP(B137,'Entrada de Materiais'!C:C,'Entrada de Materiais'!B:B) -> 5000938 | B137: CABO FLEXIVEL PP 1KV 3X1,5MM PRETO | C137: M | D137: =SUMIFS('Entrada de Materiais'!D:D, 'Entrada de Materiais'!C:C, B137) -> 150 | E137: =SUMIFS('SAIDA DE MATERIAIS'!F:F,'SAIDA DE MATERIAIS'!C:C,B137) -> 50 | F137: =+D137-E137 -> 100
A138: =_xlfn.XLOOKUP(B138,'Entrada de Materiais'!C:C,'Entrada de Materiais'!B:B) -> 5021224 | B138: CABO FLEXIVEL PP 0,6 /1KV 2X1.5MM PT | C138: M | D138: =SUMIFS('Entrada de Materiais'!D:D, 'Entrada de Materiais'!C:C, B138) -> 0 | E138: =SUMIFS('SAIDA DE MATERIAIS'!F:F,'SAIDA DE MATERIAIS'!C:C,B138) -> 0 | F138: =+D138-E138 -> 0
A139: =_xlfn.XLOOKUP(B139,'Entrada de Materiais'!C:C,'Entrada de Materiais'!B:B) -> 5000943 | B139: CABO FLEXIVEL PP 750V 4X2,5MM PT | C139: M | D139: =SUMIFS('Entrada de Materiais'!D:D, 'Entrada de Materiais'!C:C, B139) -> 165 | E139: =SUMIFS('SAIDA DE MATERIAIS'!F:F,'SAIDA DE MATERIAIS'!C:C,B139) -> 90 | F139: =+D139-E139 -> 75
A140: =_xlfn.XLOOKUP(B140,'Entrada de Materiais'!C:C,'Entrada de Materiais'!B:B) -> 5000942 | B140: CABO FLEXIVEL PP 750V4X10MM2 PT | C140: M | D140: =SUMIFS('Entrada de Materiais'!D:D, 'Entrada de Materiais'!C:C, B140) -> 0 | E140: =SUMIFS('SAIDA DE MATERIAIS'!F:F,'SAIDA DE MATERIAIS'!C:C,B140) -> 0 | F140: =+D140-E140 -> 0
A141: =_xlfn.XLOOKUP(B141,'Entrada de Materiais'!C:C,'Entrada de Materiais'!B:B) -> 5001517 | B141: CABO INSTRUMENTAÇÃO 3 VIAS | C141: M | D141: =SUMIFS('Entrada de Materiais'!D:D, 'Entrada de Materiais'!C:C, B141) -> 200 | E141: =SUMIFS('SAIDA DE MATERIAIS'!F:F,'SAIDA DE MATERIAIS'!C:C,B141) -> 30 | F141: =+D141-E141 -> 170
A142: =_xlfn.XLOOKUP(B142,'Entrada de Materiais'!C:C,'Entrada de Materiais'!B:B) -> 5001517 | B142: CABO INSTRUMENTACAO 3C 0,75MM2 ( AUTOMAÇÃO ) | C142: M | D142: =SUMIFS('Entrada de Materiais'!D:D, 'Entrada de Materiais'!C:C, B142) -> 390 | E142: =SUMIFS('SAIDA DE MATERIAIS'!F:F,'SAIDA DE MATERIAIS'!C:C,B142) -> 0 | F142: =+D142-E142 -> 390
A143: =_xlfn.XLOOKUP(B143,'Entrada de Materiais'!C:C,'Entrada de Materiais'!B:B) -> 5001605 | B143: CABO REDE F/UTF CAT 6 4PAR 23AWG | C143: UND | D143: =SUMIFS('Entrada de Materiais'!D:D, 'Entrada de Materiais'!C:C, B143) -> 305 | E143: =SUMIFS('SAIDA DE MATERIAIS'!F:F,'SAIDA DE MATERIAIS'!C:C,B143) -> 0 | F143: =+D143-E143 -> 305
A144: =_xlfn.XLOOKUP(B144,'Entrada de Materiais'!C:C,'Entrada de Materiais'!B:B) -> 5001634 | B144: CABO SINAL/INSTRUMENT COB ESTAN MOLE PVC 3VIA | C144: M | D144: =SUMIFS('Entrada de Materiais'!D:D, 'Entrada de Materiais'!C:C, B144) -> 150 | E144: =SUMIFS('SAIDA DE MATERIAIS'!F:F,'SAIDA DE MATERIAIS'!C:C,B144) -> 0 | F144: =+D144-E144 -> 150
... A713: =_xlfn.XLOOKUP(B713,'Entrada de Materiais'!C:C,'Entrada de Materiais'!B:B) -> 5010089 | B713: VOLTÍMETRO 96X96 - LINHA TF ESCALA FIXA 500V | C713: UND | D713: =SUMIFS('Entrada de Materiais'!D:D, 'Entrada de Materiais'!C:C, B713) -> 1 | E713: =SUMIFS('SAIDA DE MATERIAIS'!F:F,'SAIDA DE MATERIAIS'!C:C,B713) -> 0 | F713: =+D713-E713 -> 1
A714: =_xlfn.XLOOKUP(B714,'Entrada de Materiais'!C:C,'Entrada de Materiais'!B:B) -> #N/A | C714: UND | D714: =SUMIFS('Entrada de Materiais'!D:D, 'Entrada de Materiais'!C:C, B714) -> 0 | E714: =SUMIFS('SAIDA DE MATERIAIS'!F:F,'SAIDA DE MATERIAIS'!C:C,B714) -> 0 | F714: =+D714-E714 -> 0
A715: =_xlfn.XLOOKUP(B715,'Entrada de Materiais'!C:C,'Entrada de Materiais'!B:B) -> #N/A | C715: UND | D715: =SUMIFS('Entrada de Materiais'!D:D, 'Entrada de Materiais'!C:C, B715) -> 0 | E715: =SUMIFS('SAIDA DE MATERIAIS'!F:F,'SAIDA DE MATERIAIS'!C:C,B715) -> 0 | F715: =+D715-E715 -> 0
A716: =_xlfn.XLOOKUP(B716,'Entrada de Materiais'!C:C,'Entrada de Materiais'!B:B) -> #N/A | C716: UND | D716: =SUMIFS('Entrada de Materiais'!D:D, 'Entrada de Materiais'!C:C, B716) -> 0 | E716: =SUMIFS('SAIDA DE MATERIAIS'!F:F,'SAIDA DE MATERIAIS'!C:C,B716) -> 0 | F716: =+D716-E716 -> 0
A717: =_xlfn.XLOOKUP(B717,'Entrada de Materiais'!C:C,'Entrada de Materiais'!B:B) -> #N/A | C717: UND | D717: =SUMIFS('Entrada de Materiais'!D:D, 'Entrada de Materiais'!C:C, B717) -> 0 | E717: =SUMIFS('SAIDA DE MATERIAIS'!F:F,'SAIDA DE MATERIAIS'!C:C,B717) -> 0 | F717: =+D717-E717 -> 0
A718: =_xlfn.XLOOKUP(B718,'Entrada de Materiais'!C:C,'Entrada de Materiais'!B:B) -> #N/A | C718: UND | D718: =SUMIFS('Entrada de Materiais'!D:D, 'Entrada de Materiais'!C:C, B718) -> 0 | E718: =SUMIFS('SAIDA DE MATERIAIS'!F:F,'SAIDA DE MATERIAIS'!C:C,B718) -> 0 | F718: =+D718-E718 -> 0
A719: =_xlfn.XLOOKUP(B719,'Entrada de Materiais'!C:C,'Entrada de Materiais'!B:B) -> #N/A | C719: UND | D719: =SUMIFS('Entrada de Materiais'!D:D, 'Entrada de Materiais'!C:C, B719) -> 0 | E719: =SUMIFS('SAIDA DE MATERIAIS'!F:F,'SAIDA DE MATERIAIS'!C:C,B719) -> 0 | F719: =+D719-E719 -> 0
A720: =_xlfn.XLOOKUP(B720,'Entrada de Materiais'!C:C,'Entrada de Materiais'!B:B) -> #N/A | C720: UND | D720: =SUMIFS('Entrada de Materiais'!D:D, 'Entrada de Materiais'!C:C, B720) -> 0 | E720: =SUMIFS('SAIDA DE MATERIAIS'!F:F,'SAIDA DE MATERIAIS'!C:C,B720) -> 0 | F720: =+D720-E720 -> 0
A721: =_xlfn.XLOOKUP(B721,'Entrada de Materiais'!C:C,'Entrada de Materiais'!B:B) -> #N/A | C721: UND | D721: =SUMIFS('Entrada de Materiais'!D:D, 'Entrada de Materiais'!C:C, B721) -> 0 | E721: =SUMIFS('SAIDA DE MATERIAIS'!F:F,'SAIDA DE MATERIAIS'!C:C,B721) -> 0 | F721: =+D721-E721 -> 0
A722: =_xlfn.XLOOKUP(B722,'Entrada de Materiais'!C:C,'Entrada de Materiais'!B:B) -> #N/A | C722: UND | D722: =SUMIFS('Entrada de Materiais'!D:D, 'Entrada de Materiais'!C:C, B722) -> 0 | E722: =SUMIFS('SAIDA DE MATERIAIS'!F:F,'SAIDA DE MATERIAIS'!C:C,B722) -> 0 | F722: =+D722-E722 -> 0
A723: =_xlfn.XLOOKUP(B723,'Entrada de Materiais'!C:C,'Entrada de Materiais'!B:B) -> #N/A | C723: UND | D723: =SUMIFS('Entrada de Materiais'!D:D, 'Entrada de Materiais'!C:C, B723) -> 0 | E723: =SUMIFS('SAIDA DE MATERIAIS'!F:F,'SAIDA DE MATERIAIS'!C:C,B723) -> 0 | F723: =+D723-E723 -> 0
A724: =_xlfn.XLOOKUP(B724,'Entrada de Materiais'!C:C,'Entrada de Materiais'!B:B) -> #N/A | C724: UND | D724: =SUMIFS('Entrada de Materiais'!D:D, 'Entrada de Materiais'!C:C, B724) -> 0 | E724: =SUMIFS('SAIDA DE MATERIAIS'!F:F,'SAIDA DE MATERIAIS'!C:C,B724) -> 0 | F724: =+D724-E724 -> 0
A725: =_xlfn.XLOOKUP(B725,'Entrada de Materiais'!C:C,'Entrada de Materiais'!B:B) -> #N/A | C725: UND | D725: =SUMIFS('Entrada de Materiais'!D:D, 'Entrada de Materiais'!C:C, B725) -> 0 | E725: =SUMIFS('SAIDA DE MATERIAIS'!F:F,'SAIDA DE MATERIAIS'!C:C,B725) -> 0 | F725: =+D725-E725 -> 0
... A736: =_xlfn.XLOOKUP(B736,'Entrada de Materiais'!C:C,'Entrada de Materiais'!B:B) -> #N/A | C736: UND | D736: =SUMIFS('Entrada de Materiais'!D:D, 'Entrada de Materiais'!C:C, B736) -> 0 | E736: =SUMIFS('SAIDA DE MATERIAIS'!F:F,'SAIDA DE MATERIAIS'!C:C,B736) -> 0 | F736: =+D736-E736 -> 0
A737: =_xlfn.XLOOKUP(B737,'Entrada de Materiais'!C:C,'Entrada de Materiais'!B:B) -> #N/A | D737: =SUMIFS('Entrada de Materiais'!D:D, 'Entrada de Materiais'!C:C, B737) -> 0 | E737: =SUMIFS('SAIDA DE MATERIAIS'!F:F,'SAIDA DE MATERIAIS'!C:C,B737) -> 0 | F737: =+D737-E737 -> 0
A738: =_xlfn.XLOOKUP(B738,'Entrada de Materiais'!C:C,'Entrada de Materiais'!B:B) -> #N/A | C738: UND | D738: =SUMIFS('Entrada de Materiais'!D:D, 'Entrada de Materiais'!C:C, B738) -> 0 | E738: =SUMIFS('SAIDA DE MATERIAIS'!F:F,'SAIDA DE MATERIAIS'!C:C,B738) -> 0 | F738: =+D738-E738 -> 0
A739: =_xlfn.XLOOKUP(B739,'Entrada de Materiais'!C:C,'Entrada de Materiais'!B:B) -> #N/A | C739: UND | D739: =SUMIFS('Entrada de Materiais'!D:D, 'Entrada de Materiais'!C:C, B739) -> 0 | E739: =SUMIFS('SAIDA DE MATERIAIS'!F:F,'SAIDA DE MATERIAIS'!C:C,B739) -> 0 | F739: =+D739-E739 -> 0
A740: =_xlfn.XLOOKUP(B740,'Entrada de Materiais'!C:C,'Entrada de Materiais'!B:B) -> #N/A | C740: UND | D740: =SUMIFS('Entrada de Materiais'!D:D, 'Entrada de Materiais'!C:C, B740) -> 0 | E740: =SUMIFS('SAIDA DE MATERIAIS'!F:F,'SAIDA DE MATERIAIS'!C:C,B740) -> 0 | F740: =+D740-E740 -> 0
A741: =_xlfn.XLOOKUP(B741,'Entrada de Materiais'!C:C,'Entrada de Materiais'!B:B) -> #N/A | C741: UND | D741: =SUMIFS('Entrada de Materiais'!D:D, 'Entrada de Materiais'!C:C, B741) -> 0 | E741: =SUMIFS('SAIDA DE MATERIAIS'!F:F,'SAIDA DE MATERIAIS'!C:C,B741) -> 0 | F741: =+D741-E741 -> 0
A742: =_xlfn.XLOOKUP(B742,'Entrada de Materiais'!C:C,'Entrada de Materiais'!B:B) -> #N/A | C742: UND | D742: =SUMIFS('Entrada de Materiais'!D:D, 'Entrada de Materiais'!C:C, B742) -> 0 | E742: =SUMIFS('SAIDA DE MATERIAIS'!F:F,'SAIDA DE MATERIAIS'!C:C,B742) -> 0 | F742: =+D742-E742 -> 0
A743: =_xlfn.XLOOKUP(B743,'Entrada de Materiais'!C:C,'Entrada de Materiais'!B:B) -> #N/A | C743: UND | D743: =SUMIFS('Entrada de Materiais'!D:D, 'Entrada de Materiais'!C:C, B743) -> 0 | E743: =SUMIFS('SAIDA DE MATERIAIS'!F:F,'SAIDA DE MATERIAIS'!C:C,B743) -> 0 | F743: =+D743-E743 -> 0
A744: =_xlfn.XLOOKUP(B744,'Entrada de Materiais'!C:C,'Entrada de Materiais'!B:B) -> #N/A | C744: UND | D744: =SUMIFS('Entrada de Materiais'!D:D, 'Entrada de Materiais'!C:C, B744) -> 0 | E744: =SUMIFS('SAIDA DE MATERIAIS'!F:F,'SAIDA DE MATERIAIS'!C:C,B744) -> 0 | F744: =+D744-E744 -> 0
A745: =_xlfn.XLOOKUP(B745,'Entrada de Materiais'!C:C,'Entrada de Materiais'!B:B) -> #N/A | C745: UND | D745: =SUMIFS('Entrada de Materiais'!D:D, 'Entrada de Materiais'!C:C, B745) -> 0 | E745: =SUMIFS('SAIDA DE MATERIAIS'!F:F,'SAIDA DE MATERIAIS'!C:C,B745) -> 0 | F745: =+D745-E745 -> 0
A746: =_xlfn.XLOOKUP(B746,'Entrada de Materiais'!C:C,'Entrada de Materiais'!B:B) -> 0 | C746: UND | D746: =SUMIFS('Entrada de Materiais'!D:D, 'Entrada de Materiais'!C:C, B746) -> 0 | E746: =SUMIFS('SAIDA DE MATERIAIS'!F:F,'SAIDA DE MATERIAIS'!C:C,B746) -> 0 | F746: =+D746-E746 -> 0
A747: =_xlfn.XLOOKUP(B747,'Entrada de Materiais'!C:C,'Entrada de Materiais'!B:B) -> 0 | C747: UND | D747: =SUMIFS('Entrada de Materiais'!D:D, 'Entrada de Materiais'!C:C, B747) -> 0 | E747: =SUMIFS('SAIDA DE MATERIAIS'!F:F,'SAIDA DE MATERIAIS'!C:C,B747) -> 0 | F747: =+D747-E747 -> 0
A748: =_xlfn.XLOOKUP(B748,'Entrada de Materiais'!C:C,'Entrada de Materiais'!B:B) -> 0 | C748: UND | D748: =SUMIFS('Entrada de Materiais'!D:D, 'Entrada de Materiais'!C:C, B748) -> 0 | E748: =SUMIFS('SAIDA DE MATERIAIS'!F:F,'SAIDA DE MATERIAIS'!C:C,B748) -> 0 | F748: =+D748-E748 -> 0
A749: =_xlfn.XLOOKUP(B749,'Entrada de Materiais'!C:C,'Entrada de Materiais'!B:B) -> 0 | C749: UND | D749: =SUMIFS('Entrada de Materiais'!D:D, 'Entrada de Materiais'!C:C, B749) -> 0 | E749: =SUMIFS('SAIDA DE MATERIAIS'!F:F,'SAIDA DE MATERIAIS'!C:C,B749) -> 0 | F749: =+D749-E749 -> 0
D750: =SUMIFS('Entrada de Materiais'!D:D, 'Entrada de Materiais'!C:C, B750) -> 0 | E750: =SUMIFS('SAIDA DE MATERIAIS'!F:F,'SAIDA DE MATERIAIS'!C:C,B750) -> 0 | F750: =+D750-E750 -> 0
D751: =SUMIFS('Entrada de Materiais'!D:D, 'Entrada de Materiais'!C:C, B751) -> 0 | E751: =SUMIFS('SAIDA DE MATERIAIS'!F:F,'SAIDA DE MATERIAIS'!C:C,B751) -> 0 | F751: =+D751-E751 -> 0
D752: =SUMIFS('Entrada de Materiais'!D:D, 'Entrada de Materiais'!C:C, B752) -> 0 | E752: =SUMIFS('SAIDA DE MATERIAIS'!F:F,'SAIDA DE MATERIAIS'!C:C,B752) -> 0 | F752: =+D752-E752 -> 0
D753: =SUMIFS('Entrada de Materiais'!D:D, 'Entrada de Materiais'!C:C, B753) -> 0 | E753: =SUMIFS('SAIDA DE MATERIAIS'!F:F,'SAIDA DE MATERIAIS'!C:C,B753) -> 0 | F753: =+D753-E753 -> 0

Sheet Entrada de Materiais
A1: Data | B1: Cód.do Material | C1: Descrição do material | D1: Qntd. | E1: Medida | F1: LOCAL | G1: Recebedor | H1: Observações
B2: 4010017 | C2: *ROLAMENTO ESF RIG 6226/C3 SKF | D2: 4 | E2: UN | J2: ANILHA P/IDENTIFICAÇÃO CABOS 1,5-2,5MM LA
B3: 5532022 | C3: _CHAVE SECCIONADORA POTENCIA - 160 A | D3: 1 | E3: UN | J3: ANILHA P/IDENTIFICAÇÃO CABOS N01
B4: 5532023 | C4: _CHAVE SECCIONADORA POTENCIA - 250 A | D4: 2 | E4: UN | J4: ANILHA P/IDENTIFICAÇÃO CABOS N02
B5: 5532024 | C5: _CHAVE SECCIONADORA POTENCIA - 400 A | D5: 2 | E5: UN | J5: ANILHA P/IDENTIFICAÇÃO CABOS N09
B6: 5532025 | C6: _CHAVE SECCIONADORA POTENCIA - 630 A | D6: 2 | E6: UN
B7: 5532031 | C7: _CHAVE SECCIONADORA PUNHO 3P 250A C/FUS | D7: 1 | E7: UN
B8: 5028401 | C8: _CONTATOR 3P 220V CA 1NA 80A | D8: 2 | E8: UN
B9: 5029619 | C9: _RELE SOBRECARGA TERMICO REG 95-120A | D9: 1 | E9: UN
B10: 3009327 | C10: ABRACADEIRA BAP AC GALV 1200MM 33 FUROS | D10: 23 | E10: UN
B11: 3000011 | C11: ABRACADEIRA COP AC 1020 CZ 1POL 25,4MM | D11: 3 | E11: UN
B12: 3000010 | C12: ABRACADEIRA COP AC 1020 NAT 3/4POL | D12: 3 | E12: UN
B13: 3012931 | C13: ABRACADEIRA COPO AC 1/2POL | D13: 0 | E13: UN
B14: 3008944 | C14: ABRACADEIRA NYLON PT 4,8X200MM 100UN | D14: 20 | E14: UN
B15: 3000136 | C15: ABRACADEIRA PRESSAO LAT 1/4POL 10MM 13MM | D15: 12 | E15: UN
A16: 02.02.2026 | B16: 5019622 | C16: ABRACADEIRA REPARO MONO AI DN50 C300 | D16: 1 | E16: UN
B17: 5000071 | C17: ADAPTADOR CT PVC-S AF BRM DE60MMX2POL | D17: 5 | E17: UN
B18: 5024513 | C18: ADESIVO PLAST INCOLOR P/PVC-S AF 175G | D18: 3 | E18: UN
B19: 5024686 | C19: ADESIVO PLAST INCOLOR P/PVC-S AF 75G | D19: 0 | E19: UN
A20: 30.01.2026 | B20: 3009240 | C20: ADESIVO RESINA EPOXI 16G | D20: 10 | E20: UN
A21: 22.01.2026 | B21: 5506313 | C21: ALICATE AMPERIMETRO DIGITAL 20/200/1000A | D21: 7 | E21: UN
B22: 5024567 | C22: ANEL BORR PBA DN50MM | D22: 3 | E22: UN
B23: 5024565 | C23: ANEL BORR PBA DN75MM | D23: 5 | E23: UN
B24: 4009039 | C24: ANILHA P/ IDENTIF CABOS 0,3-1,5MM2 C | D24: 100 | E24: UN
B25: 4009044 | C25: ANILHA P/ IDENTIF CABOS 0,3-1,5MM2 W | D25: 200 | E25: UN
B26: 4009037 | C26: ANILHA P/ IDENTIF CABOS 1,5-2,5MM2 A | D26: 50 | E26: UN
B27: 4004067 | C27: ANILHA P/ IDENTIFICACAO CABOS NUMERO 1 | D27: 0 | E27: UN
B28: 4004068 | C28: ANILHA P/ IDENTIFICACAO CABOS NUMERO 2 | D28: 50 | E28: UN
B29: 4004075 | C29: ANILHA P/ IDENTIFICACAO CABOS NUMERO 9 | D29: 50 | E29: UN
B30: 5000505 | C30: ANTENA WIRELESS 900MHZ 902-928GHZ | D30: 5 | E30: UN
B31: 4000911 | C31: ARMACAO SECUNDARIA ACO C/ISOLAD 110,5MM | D31: 2 | E31: UN
B32: 3000582 | C32: ARRUELA LIS AC 1020 S/ T 5/16POL | D32: 0 | E32: UN
B33: 3000607 | C33: ARRUELA LIS AI S/ T 5/8POL | D33: 0 | E33: UN
B34: 3000466 | C34: ARRUELA LISA AC 1/2POL | D34: 95 | E34: UN
B35: 3000355 | C35: ARRUELA LISA AC 1020 3/16POL | D35: 0 | E35: UN
B36: 3009549 | C36: ARRUELA LISA AC 3/4POL | D36: 0 | E36: UN
B37: 3000581 | C37: ARRUELA LISA AC1020 3/8POL | D37: 44 | E37: UN
B38: 3000439 | C38: ARRUELA LISA AC1020 5/8POL | D38: 70 | E38: UN
B39: 3000479 | C39: ARRUELA LISA AI 1/4POL | D39: 0 | E39: UN
B40: 5025208 | C40: BANCO CAPACITOR TRIF 220V 7,5KVAR | D40: 1 | E40: UN
B41: 5024702 | C41: BARRA ROSCADA AC 1020 1/4POL UNC 1M | D41: 0 | E41: UN
B42: 5025255 | C42: BARRA ROSCADA AC 1POL UNC 1M | D42: 8 | E42: UN
B43: 5024701 | C43: BARRA ROSCADA DE AÇO 1/2" X 1000 | D43: 4 | E43: UN
B44: 5024706 | C44: BARRA ROSCADA DE AÇO 3/4" X 1000 | D44: 13 | E44: UN
B45: 5024711 | C45: BARRA ROSCADA DE AÇO 5/8" X 1000 | D45: 12 | E45: UN
B46: 5024713 | C46: BARRA ROSCADA DE AÇO 7/8" X 1000 | D46: 1 | E46: UN
B47: 5000324 | C47: BASE RELE RET PT 250V 10A 15,6MM | D47: 53 | E47: UN
B48: 5000315 | C48: BASE UNIPOLAR 250A /690v | D48: 1 | E48: UN
A49: 46002 | B49: 4007463 | C49: BATERIA ALCAL RECARREGAVEL 9V 250MAH | D49: 20 | E49: UN
B50: 5023164 | C50: BLOCO CONTATO AUX 2NA+2NF | D50: 2 | E50: UN
B51: 5517135 | C51: BOMBA CENTRIFUCA AG 125L/S 85MCA | D51: 0 | E51: UN
A52: 29.09.25 | B52: 5501606 | C52: =_xlfn.XLOOKUP(B52,'Lista de Materiais'!A:A,'Lista de Materiais'!B:B) -> BOMBA SUBMERSIVEL 8,6M3/H 8,5MCA 0,5CV | D52: 5 | E52: UN
A53: 22.01.2026 | B53: 5501606 | C53: =_xlfn.XLOOKUP(B53,'Lista de Materiais'!A:A,'Lista de Materiais'!B:B) -> BOMBA SUBMERSIVEL 8,6M3/H 8,5MCA 0,5CV | D53: 3 | E53: UN
B54: 5503631 | C54: BOTÃO DE COMANDO 22MM COR VERDE | D54: 0 | E54: UN
B55: 5503633 | C55: BOTÃO DE COMANDO 22MM COR VERMELHO | D55: 0 | E55: UN
B56: 5019127 | C56: BOX RETO ELETRODUTO AL D1POL | D56: 19 | E56: UN
B57: 5025311 | C57: BOX RETO ELETRODUTO AL D2 | D57: 0 | E57: UN
B58: 5507206 | C58: BROCA DE AÇO RAPIDO 3,5MM | D58: 0 | E58: UN
B59: 5507217 | C59: BROCA DE AÇO RAPIDO 4MM | D59: 0 | E59: UN
B60: 5507189 | C60: BROCA HELIC CIL HSS DIR 1/4POL 4POL | D60: 0 | E60: UN
B61: 5507191 | C61: BROCA HELIC CIL HSS DIR 10MM | D61: 0 | E61: UN
B62: 5507194 | C62: BROCA HELIC CIL HSS DIR 11MM 142MM | D62: 0 | E62: UN
B63: 5507199 | C63: BROCA HELIC CIL HSS DIR 13MM 151MM | D63: 4 | E63: UN
B64: 5507209 | C64: BROCA HELIC CIL HSS DIR 3/16POL 91MM | D64: 0 | E64: UN
B65: 5507213 | C65: BROCA HELIC CIL HSS DIR 3MM 61MM | D65: 2 | E65: UN
B66: 5507215 | C66: BROCA HELIC CIL HSS DIR 4,5MM 80MM | D66: 18 | E66: UN
B67: 5507218 | C67: BROCA HELIC CIL HSS DIR 5,5MM 93MM | D67: 0 | E67: UN
B68: 5507251 | C68: BROCA HELIC CIL HSS DIR 5MM 39MM | D68: 4 | E68: UN
B69: 5507226 | C69: BROCA HELIC CIL HSS DIR 6MM 93MM | D69: 0 | E69: UN
B70: 5507247 | C70: BROCA HELIC CIL HSS DIR 7MM 109MM | D70: 4 | E70: UN
B71: 5507232 | C71: BROCA HELIC CIL HSS DIR 9MM X 125MM | D71: 0 | E71: UN
B72: 5016254 | C72: BUCHA REDUÇÃO PVC 3/4"X1/2" | D72: 0 | E72: UN
B73: 3010321 | C73: BUCHA ALUMINIO PARA ELETRODUTO Ø1" | D73: 130 | E73: UN
B74: 3012510 | C74: BUCHA FIX FU PA 6MM | D74: 500 | E74: UN
B75: 3000808 | C75: BUCHA FIXAÇÃO NYLON S10 | D75: 206 | E75: UN
B76: 3000807 | C76: BUCHA FIXAÇÃO NYLON S12 | D76: 30 | E76: UN
B77: 3008014 | C77: BUCHA FIXAÇÃO NYLON S8 | D77: 0 | E77: UN
B78: 5000731 | C78: BUCHA RED GALV RMF BSP D1.1/2X1 | D78: 2 | E78: UN
B79: 5000738 | C79: BUCHA RED GALV RMF BSP D1X3/4 | D79: 3 | E79: UN
B80: 5000745 | C80: BUCHA RED GALV RMF BSP D2X1 | D80: 2 | E80: UN
B81: 5000752 | C81: BUCHA RED GALV RMF BSP D3X2 | D81: 1 | E81: UN
B82: 5000667 | C82: BUCHA RED PVC SOLD 1.1/2"X 1" | D82: 0 | E82: UN
B83: 5000693 | C83: BUCHA RED PVC-R AF DE 1.1/2X1POL | D83: 1 | E83: UN
B84: 5000696 | C84: BUCHA RED PVC-R AF DE 2X1.1/2"POL | D84: 5 | E84: UN
B85: 5000800 | C85: BUCHA RED PVC-R AF DE 2X1POL | D85: 5 | E85: UN
B86: 5016254 | C86: BUCHA RED PVC-R AF DE1X1/2POL | D86: 15 | E86: UN
B87: 5017847 | C87: BUCHA RED PVC-R AF DE1X3/4POL | D87: 21 | E87: UN
B88: 5510706 | C88: BUCHA REDUCAO LAT 1/2POL 1/4POL ( MANOMETRO ) | D88: 20 | E88: UN
B89: 5001053 | C89: CABO COBRE NU TMD CL2A 1X16MM | D89: 350 | E89: M
B90: 5001073 | C90: CABO ELE PP 450/ 750V 1X4MM | D90: 2 | E90: M
B91: 5017911 | C91: CABO ELET FLEX 0,6/1KV 1 X 4MM2 PT | D91: 0 | E91: M
B92: 5017979 | C92: CABO ELET FLEX 0,6/1KV 1X25MM2 PT | D92: 0 | E92: M
A93: 45971 | B93: 5016434 | C93: CABO ELET FLEX 0,6/1KV 3 X 25MM2 PT | D93: 4 | E93: M
B94: 5021333 | C94: CABO ELET FLEX 0,6/1KV 70MM2 CL5 PT | D94: 0 | E94: M
B95: 5021333 | C95: CABO ELET FLEX 0,6/1KV 70MM2 CL5 PT | D95: 0 | E95: M | H95: AJUSTES
A96: 46001 | B96: 5019991 | C96: CABO ELET FLEX 0,6/1KV1X185MM2 | D96: 800 | E96: M
B97: 5001146 | C97: CABO ELET FLEX 1 X 16MM2 PT | D97: 60 | E97: M
A98: 17.12.2025 | B98: 5001151 | C98: CABO ELET FLEX 1 X 95MM2 PT | D98: 200 | E98: M
A99: 22.01.2026 | B99: 5018072 | C99: CABO ELET FLEX 450/750V 1MM2 CL4 | D99: 900 | E99: M
A100: 22.01.2026 | B100: 5019778 | C100: CABO ELET FLEX 450/750V 1MM2 CL4 CZ | D100: 600 | E100: M
...

Sheet Planilha1
A1: 3009327 | B1: ABRACADEIRA BAP AC GALV 1200MM 33 FUROS | D1: 3009327 | E1: ABRACADEIRA BAP AC GALV 1200MM 33 FUROS
A2: 3008944 | B2: ABRACADEIRA NYLON PT 4,8X200MM 100UN | D2: 3008944 | E2: ABRACADEIRA NYLON PT 4,8X200MM 100UN
A3: 3000136 | B3: ABRACADEIRA PRESSAO LAT 1/4POL 10MM 13MM | D3: 3000136 | E3: ABRACADEIRA PRESSAO LAT 1/4POL 10MM 13MM
B4: ABRAÇADEIRA SERRA COPO AL 1" | E4: ABRAÇADEIRA SERRA COPO AL 1"
B5: ABRAÇADEIRA SERRA COPO AL 1/2" | E5: ABRAÇADEIRA SERRA COPO AL 1/2"
B6: ABRAÇADEIRA SERRA COPO AL 3/4" | E6: ABRAÇADEIRA SERRA COPO AL 3/4"
B7: ACOPLAMENTO EFLEX E-112MM | E7: ACOPLAMENTO EFLEX E-148MM
B8: ACOPLAMENTO EFLEX E-148MM | E8: ACOPLAMENTO EFLEX E-168MM
B9: ACOPLAMENTO EFLEX E-168MM | D9: 4006867 | E9: LUVA ACOPLAMENTO 194MM
A10: 4006867 | B10: LUVA ACOPLAMENTO 194MM | D10: 5000071 | E10: ADAPTADOR CT PVC-S AF BRM DE60MMX2POL
A11: 5000071 | B11: ADAPTADOR CT PVC-S AF BRM DE60MMX2POL | D11: 5024686 | E11: ADESIVO PLAST INCOLOR P/PVC-S AF 75G
A12: 5024513 | B12: ADESIVO PLAST INCOLOR P/PVC-S AF 175G | D12: 4004067 | E12: ANILHA P/ IDENTIFICACAO CABOS NUMERO 1
A13: 5024686 | B13: ADESIVO PLAST INCOLOR P/PVC-S AF 75G | E13: ARMAÇÃO EM AÇO REX MONOF. C/ ISOLADO DE LOUÇA
B14: AMPERÍMETRO 96X96 - LINHA TFINTERC. 500/5A | E14: ARRUELA GALV LISA 13/16"
A15: 5024567 | B15: ANEL BORR PBA DN50MM | D15: 3000355 | E15: ARRUELA LISA AC 1020 3/16POL | F15: UN
A16: 5024565 | B16: ANEL BORR PBA DN75MM | D16: 3000607 | E16: ARRUELA LIS AI S/ T 5/8POL | F16: UN
A17: 4009039 | B17: ANILHA P/ IDENTIF CABOS 0,3-1,5MM2 C | D17: 3000582 | E17: ARRUELA LIS AC 1020 S/ T 5/16POL | F17: UN
A18: 4009044 | B18: ANILHA P/ IDENTIF CABOS 0,3-1,5MM2 W | D18: 3000466 | E18: ARRUELA LISA AC 1/2POL | F18: UN
A19: 4009037 | B19: ANILHA P/ IDENTIF CABOS 1,5-2,5MM2 A | D19: 3000479 | E19: ARRUELA LISA AI 1/4POL | F19: UN
A20: 4004067 | B20: ANILHA P/ IDENTIFICACAO CABOS NUMERO 1 | E20: ARRUELA GALV LISA 15/16"
A21: 4004068 | B21: ANILHA P/ IDENTIFICACAO CABOS NUMERO 2 | D21: 3009549 | E21: ARRUELA LISA AC 3/4POL | F21: UN
A22: 4004075 | B22: ANILHA P/ IDENTIFICACAO CABOS NUMERO 9 | D22: 3000581 | E22: ARRUELA LIS AC 1020 S/ T 3/8POL | F22: UN
A23: 5513934 | B23: ANTENA WIRELESS 900MHZ 902-928GHZ | E23: ARRUELA GALV PRESSÃO 3/8"
A24: 4000911 | B24: ARMACAO SECUNDARIA ACO C/ISOLAD 110,5MM | E24: ARRUELA GALV PRESSÃO 1/4"
B25: ARMAÇÃO EM AÇO REX MONOF. C/ ISOLADO DE LOUÇA | E25: ARRUELA GALV PRESSÃO 3/16"
B26: ARRUELA GALV LISA 13/16" | D26: 3000439 | E26: ARRUELA LISA AC1020 5/8POL
A27: 3000355 | B27: ARRUELA LISA AC 1020 3/16POL | D27: 5025208 | E27: BANCO CAPACITOR TRIF 220V 7,5KVAR
A28: 3000607 | B28: =_xlfn.XLOOKUP(A28,'Lista de Materiais'!A:A,'Lista de Materiais'!B:B) -> ARRUELA LIS AI S/ T 5/8POL | D28: 5024701 | E28: BARRA ROSCADA AC 1020 1/2POL UNC 1M
A29: 3000582 | B29: ARRUELA LIS AC 1020 S/ T 5/16POL | E29: BARRA ROSCADA DE AÇO 1/4" X 1000
A30: 3000466 | B30: ARRUELA LISA AC 1/2POL | D30: 5024706 | E30: BARRA ROSCADA AC 1020 3/4POL UNC 1M
A31: 3000479 | B31: ARRUELA LISA AI 1/4POL | D31: 5024711 | E31: BARRA ROSCADA AC 1020 5/8POL UNC 1M
B32: ARRUELA GALV LISA 15/16" | D32: 5024713 | E32: BARRA ROSCADA AC 1020 7/8POL UNC 1M
A33: 3009549 | B33: ARRUELA LISA AC 3/4POL | E33: BARRA ROSCADA DE AÇO 7/16" X 1000
A34: 3000581 | B34: =_xlfn.XLOOKUP(A34,'Lista de Materiais'!A:A,'Lista de Materiais'!B:B) -> ARRUELA LIS AC 1020 S/ T 3/8POL | E34: BASE DE INTERFACE 10A RSZE1S48M 250V PRETO
B35: ARRUELA GALV PRESSÃO 3/8" | E35: BASE UNIPOLAR 300A /690
B36: ARRUELA GALV PRESSÃO 1/4" | D36: 5517135 | E36: BOMBA CENTRIFUGA AG 125L/S 82MCA
B37: ARRUELA GALV PRESSÃO 3/16" | E37: BORNE CONECTOR SAK 2 5MM
A38: 3000439 | B38: =_xlfn.XLOOKUP(A38,'Lista de Materiais'!A:A,'Lista de Materiais'!B:B) -> ARRUELA LISA AC1020 5/8POL | D38: 5503631 | E38: BOTAO COMANDO VD FACE 1NA 1NF
A39: 5025208 | B39: BANCO CAPACITOR TRIF 220V 7,5KVAR | D39: 5503633 | E39: BOTAO COMANDO VM FACE 1NA
A40: 5025255 | B40: BARRA ROSCADA AC 1POL UNC 1M | E40: BOTOEIRA LIGA/DESLIGA SP6019
A41: 5024701 | B41: =_xlfn.XLOOKUP(A41,'Lista de Materiais'!A:A,'Lista de Materiais'!B:B) -> BARRA ROSCADA AC 1020 1/2POL UNC 1M | D41: 5019127 | E41: BOX RETO ELETRODUTO AL D1POL
B42: BARRA ROSCADA DE AÇO 1/4" X 1000 | D42: 5025311 | E42: BOX RETO ELETRODUTO AL D2
A43: 5024706 | B43: =_xlfn.XLOOKUP(A43,'Lista de Materiais'!A:A,'Lista de Materiais'!B:B) -> BARRA ROSCADA AC 1020 3/4POL UNC 1M | D43: 5507206 | E43: BROCA HELIC CIL HSS DIR 3,5MM 70MM
A44: 5024711 | B44: =_xlfn.XLOOKUP(A44,'Lista de Materiais'!A:A,'Lista de Materiais'!B:B) -> BARRA ROSCADA AC 1020 5/8POL UNC 1M | D44: 5507217 | E44: BROCA HELIC CIL HSS DIR 4MM 75MM
A45: 5024713 | B45: =_xlfn.XLOOKUP(A45,'Lista de Materiais'!A:A,'Lista de Materiais'!B:B) -> BARRA ROSCADA AC 1020 7/8POL UNC 1M | D45: 5507189 | E45: BROCA HELIC CIL HSS DIR 1/4POL 4POL
B46: BARRA ROSCADA DE AÇO 7/16" X 1000 | D46: 5507191 | E46: BROCA HELIC CIL HSS DIR 10MM
B47: BASE DE INTERFACE 10A RSZE1S48M 250V PRETO | D47: 5507194 | E47: BROCA HELIC CIL HSS DIR 11MM 142MM
A48: 5000315 | B48: BASE FUS NH 0 1 500V 250A 1 POLO | D48: 5507199 | E48: BROCA HELIC CIL HSS DIR 13MM 151MM
A49: =_xlfn.XLOOKUP(B49,'Lista de Materiais'!B:B,'Lista de Materiais'!A:A) -> #N/A | B49: BASE UNIPOLAR 300A /690 | D49: 5507209 | E49: BROCA HELIC CIL HSS DIR 3/16POL 91MM
B50: BASE UNIPOLAR 300A /690 | D50: 5507213 | E50: BROCA HELIC CIL HSS DIR 3MM 61MM
A51: 5517135 | B51: =_xlfn.XLOOKUP(A51,'Lista de Materiais'!A:A,'Lista de Materiais'!B:B) -> BOMBA CENTRIFUGA AG 125L/S 82MCA | D51: 5507215 | E51: BROCA HELIC CIL HSS DIR 4,5MM 80MM
A52: 5501606 | B52: BOMBA SUBMERSIVEL 8,6M3/H 8,5MCA 0,5CV MOD FI T1000.1 220V60Hz | D52: 5507218 | E52: BROCA HELIC CIL HSS DIR 5,5MM 93MM
A53: 5501606 | B53: BOMBA SUBMERSIVEL 8,6M3/H 8,5MCA 0,5CV MOD FI T1000.1 220V60Hz | D53: 5507251 | E53: BROCA HELIC CIL HSS DIR 5MM 39MM
B54: BORNE CONECTOR SAK 2 5MM | D54: 5507226 | E54: BROCA HELIC CIL HSS DIR 6MM 93MM
A55: 5503631 | B55: BOTAO COMANDO VD FACE 1NA 1NF | D55: 5507247 | E55: BROCA HELIC CIL MET DUR DIR 7MM 109MM
A56: 5503633 | B56: BOTAO COMANDO VM FACE 1NA | D56: 5507232 | E56: BROCA HELIC CIL HSS DIR 9MM 125MM
B57: BOTOEIRA LIGA/DESLIGA SP6019 | E57: BUCHA REDUÇÃO PVC 1 X 1/2"
A58: 5019127 | B58: =_xlfn.XLOOKUP(A58,'Lista de Materiais'!A:A,'Lista de Materiais'!B:B) -> BOX RETO ELETRODUTO AL D1POL | E58: BUCHA REDUÇÃO PVC 1" X 3/4"
A59: 5025311 | B59: BOX RETO ELETRODUTO AL D2 | D59: 5000699 | E59: BUCHA RED PVC-R AF DE3/4X1/2POL | F59: UN
A60: 5507206 | B60: =_xlfn.XLOOKUP(A60,'Lista de Materiais'!A:A,'Lista de Materiais'!B:B) -> BROCA HELIC CIL HSS DIR 3,5MM 70MM | E60: BUCHA DE FERRO GALV. 2"X 1"
A61: 5507217 | B61: =_xlfn.XLOOKUP(A61,'Lista de Materiais'!A:A,'Lista de Materiais'!B:B) -> BROCA HELIC CIL HSS DIR 4MM 75MM | E61: BUCHA DE FERRO GALV. 3"X 2.1/2"
A62: 5507189 | B62: BROCA HELIC CIL HSS DIR 1/4POL 4POL | E62: BUCHA DE ALUMINIO 1"
A63: 5507191 | B63: BROCA HELIC CIL HSS DIR 10MM | E63: BUCHA DE ALUMINIO C/ARRUELA 2"
A64: 5507194 | B64: BROCA HELIC CIL HSS DIR 11MM 142MM | E64: BUCHA DE ALUMINIO C/ARRUELA 3/4"
A65: 5507199 | B65: BROCA HELIC CIL HSS DIR 13MM 151MM | E65: BUCHA DE FERRO GALV. 4"X 3"
A66: 5507209 | B66: BROCA HELIC CIL HSS DIR 3/16POL 91MM | E66: BUCHA DE FERRO GALV. 4"X2"
A67: 5507213 | B67: BROCA HELIC CIL HSS DIR 3MM 61MM | E67: BUCHA DE REDUÇÃO FERRO GALV. 1.1/2"X 1/2"
A68: 5507215 | B68: =_xlfn.XLOOKUP(A68,'Lista de Materiais'!A:A,'Lista de Materiais'!B:B) -> BROCA HELIC CIL HSS DIR 4,5MM 80MM | E68: BUCHA DE REDUÇÃO FERRO GALV. 2"X 3/4"
A69: 5507218 | B69: BROCA HELIC CIL HSS DIR 5,5MM 93MM | E69: BUCHA DE REDUÇÃO FERRO GALV. 2"X1.1/2"
A70: 5507251 | B70: =_xlfn.XLOOKUP(A70,'Lista de Materiais'!A:A,'Lista de Materiais'!B:B) -> BROCA HELIC CIL HSS DIR 5MM 39MM | E70: BUCHA DE REDUÇÃO GALV. 3/4"X1/2"
A71: 5507226 | B71: BROCA HELIC CIL HSS DIR 6MM 93MM | D71: 3000808 | E71: BUCHA FIXACAO PARAFUSO PA CZ S10
A72: 5507247 | B72: =_xlfn.XLOOKUP(A72,'Lista de Materiais'!A:A,'Lista de Materiais'!B:B) -> BROCA HELIC CIL MET DUR DIR 7MM 109MM | D72: 3000807 | E72: BUCHA FIXACAO PARAFUSO PA CZ S12 ALV
A73: 5507232 | B73: BROCA HELIC CIL HSS DIR 9MM 125MM | E73: BUCHA FIXAÇÃO NYLON S6
B74: BUCHA REDUÇÃO PVC 1 X 1/2" | E74: BUCHA FIXAÇÃO NYLON S8
B75: BUCHA REDUÇÃO PVC 1" X 3/4" | D75: 5000745 | E75: BUCHA RED GALV RMF BSP D2X1
A76: 5000699 | B76: BUCHA RED PVC-R AF DE3/4X1/2POL | C76: UN | D76: 5000667 | E76: BUCHA RED CPVC SOLD DN1.1/2X1POL
B77: BUCHA DE FERRO GALV. 2"X 1" | D77: 5000693 | E77: BUCHA RED PVC-R AF DE1.1/2X1POL
B78: BUCHA DE FERRO GALV. 3"X 2.1/2" | D78: 5510706 | E78: BUCHA REDUCAO LAT 1/2POL 1/4POL
B79: BUCHA DE ALUMINIO 1" | E79: CABEÇOTE DE ELETRICA ALUMINIO 2"
B80: BUCHA DE ALUMINIO C/ARRUELA 2" | D80: 5001053 | E80: CABO ELET COB NU 16MM2
B81: BUCHA DE ALUMINIO C/ARRUELA 3/4" | E81: CABO DE REDE 8X26AWG ( AUTOMAÇÃO )
B82: BUCHA DE FERRO GALV. 4"X 3" | D82: 5001073 | E82: CABO ELET PP 450 / 750 V 4 X 1MM2
B83: BUCHA DE FERRO GALV. 4"X2" | D83: 5017911 | E83: CABO ELET FLEX 0,6/1KV 1 X 4MM2 PT
B84: BUCHA DE REDUÇÃO FERRO GALV. 1.1/2"X 1/2" | D84: 5017979 | E84: CABO ELET FLEX 0,6/1KV 1X25MM2 PT
B85: BUCHA DE REDUÇÃO FERRO GALV. 2"X 3/4" | D85: 5021333 | E85: CABO ELET FLEX 0,6/1KV 70MM2 CL5 PT
B86: BUCHA DE REDUÇÃO FERRO GALV. 2"X1.1/2" | D86: 5001146 | E86: CABO ELET FLEX 1 X 16MM2 PT
B87: BUCHA DE REDUÇÃO GALV. 3/4"X1/2" | D87: 5019701 | E87: CABO ELET FLEX 750V 1MM2 PT
A88: 3000808 | B88: =_xlfn.XLOOKUP(A88,'Lista de Materiais'!A:A,'Lista de Materiais'!B:B) -> BUCHA FIXACAO PARAFUSO PA CZ S10 | D88: 5019778 | E88: CABO ELET FLEX 750V 1MM2 CZ | F88: M
A89: 3000807 | B89: =_xlfn.XLOOKUP(A89,'Lista de Materiais'!A:A,'Lista de Materiais'!B:B) -> BUCHA FIXACAO PARAFUSO PA CZ S12 ALV | D89: 5001357 | E89: CABO ELETRICO FLX 750V 6MM2 | F89: M
B90: BUCHA FIXAÇÃO NYLON S6 | D90: 5001074 | E90: CABO ELET PP 450 / 750 V 4 X 6MM2
B91: BUCHA FIXAÇÃO NYLON S8 | D91: 5020122 | E91: CABO ELET FLEX 0,6/1KV 1X1,5MM2 CL4
A92: 5000731 | B92: BUCHA RED GALV RMF BSP D1.1/2X1 | D92: 5017790 | E92: CABO ELET FLEX 0,6/1KV 2,5MM2 CL5 PT
A93: 5000738 | B93: BUCHA RED GALV RMF BSP D1X3/4 | D93: 5000970 | E93: CABO ELETRICO 1,5MM2
A94: 5000745 | B94: BUCHA RED GALV RMF BSP D2X1 | D94: 5001409 | E94: CABO ELETRICO POT 0,6/1KV 95MM2 CL5
A95: 5000752 | B95: BUCHA RED GALV RMF BSP D3X2 | D95: 5025964 | E95: CABO FLEX ATOX 450/750V 1X2,5MM2 PT
A96: 5000667 | B96: BUCHA RED CPVC SOLD DN1.1/2X1POL | D96: 5001141 | E96: CABO ELET FLEX 450/750V1X2,50MM2 VM
A97: 5000693 | B97: BUCHA RED PVC-R AF DE1.1/2X1POL | D97: 5025913 | E97: CABO FLEX EPR ATOX 0,6/1KV 1X95MM2 PT
A98: 5000696 | B98: =_xlfn.XLOOKUP(A98,'Lista de Materiais'!A:A,'Lista de Materiais'!B:B) -> BUCHA RED PVC-R AF DE2X1.1/2POL | D98: 5025952 | E98: CABO FLEX EPR ATOX 0,6/1KV 1X95MM2 VD
A99: 5000800 | B99: BUCHA RED PVC-R AF DE2X1POL | E99: CABO FLEXIVEL 1KV 10MM
A100: 5510706 | B100: =_xlfn.XLOOKUP(A100,'Lista de Materiais'!A:A,'Lista de Materiais'!B:B) -> BUCHA REDUCAO LAT 1/2POL 1/4POL | E100: CABO FLEXIVEL 1KV 120MM *BOBINA
...

Sheet Ajustes de Saida
A1: Data | B1: Cód.do Material | C1: Descrição do material | D1: CONDIÇÃO | E1: Baixa | F1: Qntd. | G1: Medida | H1: Destino | I1: Solicitante | J1: Responsável pela Saída | K1: Observações | M1: _ARRUELA PRESSAO INOX 304 NAT 3/8''
A2: ANTIGO | B2: 3009327 | C2: ABRACADEIRA BAP AC GALV 1200MM 33 FUROS | E2: FALSE | F2: 79 | G2: =_xlfn.XLOOKUP(B:B,'Lista de Materiais'!A:A,'Lista de Materiais'!C:C) -> UN | H2: AJUSTE | M2: _BARRA ROSCADA ACO CARB GALVAN 7/8''
A3: ANTIGO | C3: ABRACADEIRA COP AC 1020 NAT 3/4POL | E3: FALSE | F3: 44 | G3: =_xlfn.XLOOKUP(B:B,'Lista de Materiais'!A:A,'Lista de Materiais'!C:C) -> #N/A | H3: AJUSTE | M3: _CABO PP FLEXIVEL 2X2,5 06/1KV
A4: ANTIGO | C4: ABRACADEIRA COPO AC 1/2POL | E4: FALSE | F4: 7 | G4: =_xlfn.XLOOKUP(B:B,'Lista de Materiais'!A:A,'Lista de Materiais'!C:C) -> #N/A | H4: AJUSTE | M4: _PAINEL PCP - EXT
A5: ANTIGO | C5: ABRACADEIRA COPO AC 1POL | E5: FALSE | F5: 89 | G5: =_xlfn.XLOOKUP(B:B,'Lista de Materiais'!A:A,'Lista de Materiais'!C:C) -> #N/A | H5: AJUSTE | M5: ABRACADEIRA BAP AC GALV 1200MM 33 FUROS
A6: ANTIGO | B6: 3008944 | C6: ABRACADEIRA NYLON PT 4,8X200MM 100UN | E6: FALSE | F6: 10 | G6: =_xlfn.XLOOKUP(B:B,'Lista de Materiais'!A:A,'Lista de Materiais'!C:C) -> UN | H6: AJUSTE | M6: ABRACADEIRA COP AC 1020 NAT 3/4POL
A7: ANTIGO | B7: 3000136 | C7: ABRACADEIRA PRESSAO LAT 1/4POL 10MM 13MM | E7: FALSE | F7: 18 | G7: =_xlfn.XLOOKUP(B:B,'Lista de Materiais'!A:A,'Lista de Materiais'!C:C) -> UN | H7: AJUSTE | M7: ABRACADEIRA COPO AC 1/2POL
A8: ANTIGO | B8: 4006867 | C8: LUVA ACOPLAMENTO 194MM | E8: FALSE | F8: 2 | G8: =_xlfn.XLOOKUP(B:B,'Lista de Materiais'!A:A,'Lista de Materiais'!C:C) -> UN | H8: AJUSTE | M8: ABRACADEIRA COPO AC 1POL
A9: ANTIGO | B9: 5000071 | C9: ADAPTADOR CT PVC-S AF BRM DE60MMX2POL | E9: FALSE | F9: 5 | G9: =_xlfn.XLOOKUP(B:B,'Lista de Materiais'!A:A,'Lista de Materiais'!C:C) -> UN | H9: AJUSTE | M9: ABRACADEIRA NYLON PT 4,8X200MM 100UN
A10: ANTIGO | B10: 5024686 | C10: ADESIVO PLAST INCOLOR P/PVC-S AF 75G | E10: FALSE | F10: 2 | G10: =_xlfn.XLOOKUP(B:B,'Lista de Materiais'!A:A,'Lista de Materiais'!C:C) -> #N/A | H10: AJUSTE | M10: ABRACADEIRA PRESSAO LAT 1/4POL 10MM 13MM
A11: ANTIGO | B11: 4004067 | C11: ANILHA P/ IDENTIFICACAO CABOS NUMERO 1 | E11: FALSE | F11: 60 | G11: =_xlfn.XLOOKUP(B:B,'Lista de Materiais'!A:A,'Lista de Materiais'!C:C) -> UN | H11: AJUSTE | M11: ADAPTADOR CT PVC-S AF BRM DE60MMX2POL
A12: ANTIGO | C12: ARMACAO SECUNDARIA ACO C/ISOLAD 110,5MM | E12: FALSE | F12: 5 | G12: =_xlfn.XLOOKUP(B:B,'Lista de Materiais'!A:A,'Lista de Materiais'!C:C) -> #N/A | H12: AJUSTE | M12: ADESIVO PLAST INCOLOR P/PVC-S AF 175G
A13: ANTIGO | C13: ARRUELA GALV LISA 13/16" | E13: FALSE | F13: 41 | G13: =_xlfn.XLOOKUP(B:B,'Lista de Materiais'!A:A,'Lista de Materiais'!C:C) -> #N/A | H13: AJUSTE | M13: ADESIVO PLAST INCOLOR P/PVC-S AF 75G
A14: ANTIGO | C14: ARRUELA GALV LISA 15/16" | E14: FALSE | F14: 34 | G14: =_xlfn.XLOOKUP(B:B,'Lista de Materiais'!A:A,'Lista de Materiais'!C:C) -> #N/A | H14: AJUSTE | M14: AMPERÍMETRO 96X96 - LINHA TFINTERC. 500/5A
A15: ANTIGO | C15: ARRUELA LISA AC1020 3/8POL | E15: FALSE | F15: 240 | G15: =_xlfn.XLOOKUP(B:B,'Lista de Materiais'!A:A,'Lista de Materiais'!C:C) -> #N/A | H15: AJUSTE | M15: ANEL BORR PBA DN50MM
A16: ANTIGO | C16: ARRUELA LISA AI 1/4POL | E16: FALSE | F16: 666 | G16: =_xlfn.XLOOKUP(B:B,'Lista de Materiais'!A:A,'Lista de Materiais'!C:C) -> #N/A | H16: AJUSTE | M16: ANEL BORR PBA DN75MM
A17: ANTIGO | C17: ARRUELA LISA AC 1020 3/16POL | E17: FALSE | F17: 114 | G17: =_xlfn.XLOOKUP(B:B,'Lista de Materiais'!A:A,'Lista de Materiais'!C:C) -> #N/A | H17: AJUSTE | M17: ANILHA P/ IDENTIF CABOS 0,3-1,5MM2 C
A18: ANTIGO | B18: 3000582 | C18: ARRUELA LIS AC 1020 S/ T 5/16POL | E18: FALSE | F18: 61 | G18: =_xlfn.XLOOKUP(B:B,'Lista de Materiais'!A:A,'Lista de Materiais'!C:C) -> #N/A | H18: AJUSTE | M18: ANILHA P/ IDENTIF CABOS 0,3-1,5MM2 W
A19: ANTIGO | B19: 3000607 | C19: ARRUELA LIS AI S/ T 5/8POL | E19: FALSE | F19: 83 | G19: =_xlfn.XLOOKUP(B:B,'Lista de Materiais'!A:A,'Lista de Materiais'!C:C) -> UN | H19: AJUSTE | M19: ANILHA P/ IDENTIF CABOS 1,5-2,5MM2 A
A20: ANTIGO | B20: 3000466 | C20: ARRUELA LISA AC 1/2POL | E20: FALSE | F20: 132 | G20: =_xlfn.XLOOKUP(B:B,'Lista de Materiais'!A:A,'Lista de Materiais'!C:C) -> #N/A | H20: AJUSTE | M20: ANILHA P/ IDENTIFICACAO CABOS NUMERO 1
A21: ANTIGO | B21: 3000355 | C21: ARRUELA LISA AC 1020 3/16POL | E21: FALSE | F21: 379 | G21: =_xlfn.XLOOKUP(B:B,'Lista de Materiais'!A:A,'Lista de Materiais'!C:C) -> #N/A | H21: AJUSTE | M21: ANILHA P/ IDENTIFICACAO CABOS NUMERO 2
A22: ANTIGO | B22: 3000439 | C22: ARRUELA LISA AC1020 5/8POL | E22: FALSE | F22: 6 | G22: =_xlfn.XLOOKUP(B:B,'Lista de Materiais'!A:A,'Lista de Materiais'!C:C) -> UN | H22: AJUSTE | M22: ANILHA P/ IDENTIFICACAO CABOS NUMERO 9
A23: ANTIGO | B23: 3009549 | C23: ARRUELA LISA AC 3/4POL | E23: FALSE | F23: 11 | G23: =_xlfn.XLOOKUP(B:B,'Lista de Materiais'!A:A,'Lista de Materiais'!C:C) -> #N/A | H23: AJUSTE | M23: ANTENA WIRELESS 900MHZ 902-928GHZ
A24: ANTIGO | B24: 3000581 | C24: ARRUELA LISA AC1020 3/8POL | E24: FALSE | F24: 333 | G24: =_xlfn.XLOOKUP(B:B,'Lista de Materiais'!A:A,'Lista de Materiais'!C:C) -> UN | H24: AJUSTE | M24: ARMACAO SECUNDARIA ACO C/ISOLAD 110,5MM
A25: ANTIGO | B25: 3000479 | C25: ARRUELA LISA AI 1/4POL | E25: FALSE | F25: 608 | G25: =_xlfn.XLOOKUP(B:B,'Lista de Materiais'!A:A,'Lista de Materiais'!C:C) -> #N/A | H25: AJUSTE | M25: ARRUELA GALV PRESSÃO 1/4"
A26: ANTIGO | B26: 5025208 | C26: BANCO CAPACITOR TRIF 220V 7,5KVAR | E26: FALSE | F26: 7 | G26: =_xlfn.XLOOKUP(B:B,'Lista de Materiais'!A:A,'Lista de Materiais'!C:C) -> #N/A | H26: AJUSTE | M26: ARRUELA GALV PRESSÃO 3/16"
A27: ANTIGO | B27: 5024701 | C27: BARRA ROSCADA AC 1020 1/2POL UNC 1M | E27: FALSE | F27: 10 | G27: =_xlfn.XLOOKUP(B:B,'Lista de Materiais'!A:A,'Lista de Materiais'!C:C) -> UN | H27: AJUSTE | M27: ARRUELA LIS AC 1020 S/ T 5/16POL
A28: ANTIGO | C28: BARRA ROSCADA AC 1020 1/4POL UNC 1M | E28: FALSE | F28: 22 | G28: =_xlfn.XLOOKUP(B:B,'Lista de Materiais'!A:A,'Lista de Materiais'!C:C) -> #N/A | H28: AJUSTE | M28: ARRUELA LIS AI S/ T 5/8POL
A29: ANTIGO | B29: 5024706 | C29: BARRA ROSCADA AC 1020 3/4POL UNC 1M | E29: FALSE | F29: 6 | G29: =_xlfn.XLOOKUP(B:B,'Lista de Materiais'!A:A,'Lista de Materiais'!C:C) -> UN | H29: AJUSTE | M29: ARRUELA LISA AC 1/2POL
A30: ANTIGO | B30: 5024711 | C30: BARRA ROSCADA AC 1020 5/8POL UNC 1M | E30: FALSE | F30: 19 | G30: =_xlfn.XLOOKUP(B:B,'Lista de Materiais'!A:A,'Lista de Materiais'!C:C) -> UN | H30: AJUSTE | M30: ARRUELA LISA AC 1020 3/16POL
A31: ANTIGO | B31: 5024713 | C31: BARRA ROSCADA AC 1020 7/8POL UNC 1M | E31: FALSE | F31: 4 | G31: =_xlfn.XLOOKUP(B:B,'Lista de Materiais'!A:A,'Lista de Materiais'!C:C) -> UN | H31: AJUSTE | M31: ARRUELA LISA AC 3/4POL
A32: ANTIGO | C32: BASE DE INTERFACE 10A RSZE1S48M 250V PRETO | E32: FALSE | F32: 117 | G32: =_xlfn.XLOOKUP(B:B,'Lista de Materiais'!A:A,'Lista de Materiais'!C:C) -> #N/A | H32: AJUSTE | M32: ARRUELA LISA AC1020 5/8POL
A33: ANTIGO | C33: BASE UNIPOLAR 300A /690 | E33: FALSE | F33: 5 | G33: =_xlfn.XLOOKUP(B:B,'Lista de Materiais'!A:A,'Lista de Materiais'!C:C) -> #N/A | H33: AJUSTE | M33: ARRUELA LISA AI 1/4POL
A34: ANTIGO | B34: 5517135 | C34: BOMBA CENTRIFUGA AG 125L/S 82MCA | E34: FALSE | F34: 1 | G34: =_xlfn.XLOOKUP(B:B,'Lista de Materiais'!A:A,'Lista de Materiais'!C:C) -> UN | H34: AJUSTE | M34: BANCO CAPACITOR TRIF 220V 7,5KVAR
A35: ANTIGO | C35: BORNE CONECTOR SAK 2 5MM | E35: FALSE | F35: 100 | G35: =_xlfn.XLOOKUP(B:B,'Lista de Materiais'!A:A,'Lista de Materiais'!C:C) -> #N/A | H35: AJUSTE | M35: BARRA ROSCADA AC 1020 1/2POL UNC 1M
A36: ANTIGO | B36: 5503631 | C36: BOTAO COMANDO VD FACE 1NA 1NF | E36: FALSE | F36: 6 | G36: =_xlfn.XLOOKUP(B:B,'Lista de Materiais'!A:A,'Lista de Materiais'!C:C) -> #N/A | H36: AJUSTE | M36: BARRA ROSCADA AC 1020 1/4POL UNC 1M
A37: ANTIGO | B37: 5503633 | C37: BOTAO COMANDO VM FACE 1NA | E37: FALSE | F37: 6 | G37: =_xlfn.XLOOKUP(B:B,'Lista de Materiais'!A:A,'Lista de Materiais'!C:C) -> #N/A | H37: AJUSTE | M37: BARRA ROSCADA AC 1020 3/4POL UNC 1M
A38: ANTIGO | B38: 5508637 | C38: BOTOEIRA MONT ABS 2 BOT | E38: FALSE | F38: 2 | G38: =_xlfn.XLOOKUP(B:B,'Lista de Materiais'!A:A,'Lista de Materiais'!C:C) -> UN | H38: AJUSTE | M38: BARRA ROSCADA AC 1020 5/8POL UNC 1M
A39: ANTIGO | B39: 5019127 | C39: BOX RETO ELETRODUTO AL D1POL | E39: FALSE | F39: 137 | G39: =_xlfn.XLOOKUP(B:B,'Lista de Materiais'!A:A,'Lista de Materiais'!C:C) -> UN | H39: AJUSTE | M39: BARRA ROSCADA AC 1020 7/8POL UNC 1M
A40: ANTIGO | B40: 5025311 | C40: BOX RETO ELETRODUTO AL D2 | E40: FALSE | F40: 8 | G40: =_xlfn.XLOOKUP(B:B,'Lista de Materiais'!A:A,'Lista de Materiais'!C:C) -> #N/A | H40: AJUSTE | M40: BARRA ROSCADA AC 1POL UNC 1M
A41: ANTIGO | B41: 5507206 | C41: BROCA HELIC CIL HSS DIR 3,5MM 70MM | E41: FALSE | F41: 3 | G41: =_xlfn.XLOOKUP(B:B,'Lista de Materiais'!A:A,'Lista de Materiais'!C:C) -> UN | H41: AJUSTE | M41: BASE DE INTERFACE 10A RSZE1S48M 250V PRETO
A42: ANTIGO | B42: 5507217 | C42: BROCA HELIC CIL HSS DIR 4MM 75MM | E42: FALSE | F42: 6 | G42: =_xlfn.XLOOKUP(B:B,'Lista de Materiais'!A:A,'Lista de Materiais'!C:C) -> UN | H42: AJUSTE | M42: BASE UNIPOLAR 300A /690
A43: ANTIGO | B43: 5507189 | C43: BROCA HELIC CIL HSS DIR 1/4POL 4POL | E43: FALSE | F43: 1 | G43: =_xlfn.XLOOKUP(B:B,'Lista de Materiais'!A:A,'Lista de Materiais'!C:C) -> #N/A | H43: AJUSTE | M43: BOMBA CENTRIFUGA AG 125L/S 82MCA
A44: ANTIGO | B44: 5507191 | C44: BROCA HELIC CIL HSS DIR 10MM | E44: FALSE | F44: 15 | G44: =_xlfn.XLOOKUP(B:B,'Lista de Materiais'!A:A,'Lista de Materiais'!C:C) -> #N/A | H44: AJUSTE | M44: BORNE CONECTOR SAK 2 5MM
A45: ANTIGO | B45: 5507194 | C45: BROCA HELIC CIL HSS DIR 11MM 142MM | E45: FALSE | F45: 3 | G45: =_xlfn.XLOOKUP(B:B,'Lista de Materiais'!A:A,'Lista de Materiais'!C:C) -> #N/A | H45: AJUSTE | M45: BOTAO COMANDO VD FACE 1NA 1NF
A46: ANTIGO | B46: 5507199 | C46: BROCA HELIC CIL HSS DIR 13MM 151MM | E46: FALSE | F46: 2 | G46: =_xlfn.XLOOKUP(B:B,'Lista de Materiais'!A:A,'Lista de Materiais'!C:C) -> #N/A | H46: AJUSTE | M46: BOTAO COMANDO VM FACE 1NA
A47: ANTIGO | B47: 5507209 | C47: BROCA HELIC CIL HSS DIR 3/16POL 91MM | E47: FALSE | F47: 3 | G47: =_xlfn.XLOOKUP(B:B,'Lista de Materiais'!A:A,'Lista de Materiais'!C:C) -> #N/A | H47: AJUSTE | M47: BOTOEIRA MONT ABS 2 BOT
A48: ANTIGO | B48: 5507213 | C48: BROCA HELIC CIL HSS DIR 3MM 61MM | E48: FALSE | F48: 7 | G48: =_xlfn.XLOOKUP(B:B,'Lista de Materiais'!A:A,'Lista de Materiais'!C:C) -> #N/A | H48: AJUSTE | M48: BOX RETO ELETRODUTO AL D1POL
A49: ANTIGO | B49: 5507215 | C49: BROCA HELIC CIL HSS DIR 4,5MM 80MM | E49: FALSE | F49: 16 | G49: =_xlfn.XLOOKUP(B:B,'Lista de Materiais'!A:A,'Lista de Materiais'!C:C) -> UN | H49: AJUSTE | M49: BOX RETO ELETRODUTO AL D2
A50: ANTIGO | B50: 5507218 | C50: BROCA HELIC CIL HSS DIR 5,5MM 93MM | E50: FALSE | F50: 10 | G50: =_xlfn.XLOOKUP(B:B,'Lista de Materiais'!A:A,'Lista de Materiais'!C:C) -> #N/A | H50: AJUSTE | M50: BROCA HELIC CIL HSS DIR 1/4POL 4POL
A51: ANTIGO | B51: 5507251 | C51: BROCA HELIC CIL HSS DIR 5MM 39MM | E51: FALSE | F51: 3 | G51: =_xlfn.XLOOKUP(B:B,'Lista de Materiais'!A:A,'Lista de Materiais'!C:C) -> UN | H51: AJUSTE | M51: BROCA HELIC CIL HSS DIR 10MM
A52: ANTIGO | B52: 5507226 | C52: BROCA HELIC CIL HSS DIR 6MM 93MM | E52: FALSE | F52: 9 | G52: =_xlfn.XLOOKUP(B:B,'Lista de Materiais'!A:A,'Lista de Materiais'!C:C) -> #N/A | H52: AJUSTE | M52: BROCA HELIC CIL HSS DIR 11MM 142MM
A53: ANTIGO | B53: 5507247 | C53: BROCA HELIC CIL HSS DIR 7MM 109MM | E53: FALSE | F53: 2 | G53: =_xlfn.XLOOKUP(B:B,'Lista de Materiais'!A:A,'Lista de Materiais'!C:C) -> UN | H53: AJUSTE | M53: BROCA HELIC CIL HSS DIR 13MM 151MM
A54: ANTIGO | B54: 5507232 | C54: BROCA HELIC CIL HSS DIR 9MM 125MM | E54: FALSE | F54: 10 | G54: =_xlfn.XLOOKUP(B:B,'Lista de Materiais'!A:A,'Lista de Materiais'!C:C) -> UN | H54: AJUSTE | M54: BROCA HELIC CIL HSS DIR 3,5MM 70MM
A55: ANTIGO | B55: 5016254 | C55: BUCHA RED PVC-R AF DE1X1/2POL | E55: FALSE | F55: 9 | G55: =_xlfn.XLOOKUP(B:B,'Lista de Materiais'!A:A,'Lista de Materiais'!C:C) -> UN | H55: AJUSTE | M55: BROCA HELIC CIL HSS DIR 3/16POL 91MM
A56: ANTIGO | B56: 5017847 | C56: BUCHA RED PVC-R AF DE1X3/4POL | E56: FALSE | F56: 27 | G56: =_xlfn.XLOOKUP(B:B,'Lista de Materiais'!A:A,'Lista de Materiais'!C:C) -> UN | H56: AJUSTE | M56: BROCA HELIC CIL HSS DIR 3MM 61MM
A57: ANTIGO | B57: 5016254 | C57: BUCHA REDUÇÃO PVC 3/4"X1/2" | E57: FALSE | F57: 35 | G57: =_xlfn.XLOOKUP(B:B,'Lista de Materiais'!A:A,'Lista de Materiais'!C:C) -> UN | H57: AJUSTE | M57: BROCA HELIC CIL HSS DIR 4,5MM 80MM
A58: ANTIGO | B58: 5000745 | C58: BUCHA RED GALV RMF BSP D2X1 | E58: FALSE | F58: 1 | G58: =_xlfn.XLOOKUP(B:B,'Lista de Materiais'!A:A,'Lista de Materiais'!C:C) -> UN | H58: AJUSTE | M58: BROCA HELIC CIL HSS DIR 4MM 75MM
A59: ANTIGO | B59: 5000751 | C59: BUCHA RED GALV RMF BSP D3X2.1/2 | E59: FALSE | F59: 1 | G59: =_xlfn.XLOOKUP(B:B,'Lista de Materiais'!A:A,'Lista de Materiais'!C:C) -> UN | H59: AJUSTE | M59: BROCA HELIC CIL HSS DIR 5,5MM 93MM
A60: ANTIGO | C60: BUCHA DE ALUMINIO 1" | E60: FALSE | F60: 25 | G60: =_xlfn.XLOOKUP(B:B,'Lista de Materiais'!A:A,'Lista de Materiais'!C:C) -> #N/A | H60: AJUSTE | M60: BROCA HELIC CIL HSS DIR 5MM 39MM
A61: ANTIGO | C61: BUCHA DE ALUMINIO C/ARRUELA 2" | E61: FALSE | F61: 27 | G61: =_xlfn.XLOOKUP(B:B,'Lista de Materiais'!A:A,'Lista de Materiais'!C:C) -> #N/A | H61: AJUSTE | M61: BROCA HELIC CIL HSS DIR 6MM 93MM
A62: ANTIGO | C62: BUCHA DE ALUMINIO C/ARRUELA 3/4" | E62: FALSE | F62: 30 | G62: =_xlfn.XLOOKUP(B:B,'Lista de Materiais'!A:A,'Lista de Materiais'!C:C) -> #N/A | H62: AJUSTE | M62: BROCA HELIC CIL HSS DIR 7MM 109MM
A63: ANTIGO | C63: BUCHA DE FERRO GALV. 4"X 3" | E63: FALSE | F63: 1 | G63: =_xlfn.XLOOKUP(B:B,'Lista de Materiais'!A:A,'Lista de Materiais'!C:C) -> #N/A | H63: AJUSTE | M63: BROCA HELIC CIL HSS DIR 9MM 125MM
A64: ANTIGO | C64: BUCHA DE FERRO GALV. 4"X2" | E64: FALSE | F64: 1 | G64: =_xlfn.XLOOKUP(B:B,'Lista de Materiais'!A:A,'Lista de Materiais'!C:C) -> #N/A | H64: AJUSTE | M64: BUCHA REDUÇÃO PVC 3/4"X1/2"
A65: ANTIGO | C65: BUCHA DE REDUÇÃO FERRO GALV. 1.1/2"X 1/2" | E65: FALSE | F65: 1 | G65: =_xlfn.XLOOKUP(B:B,'Lista de Materiais'!A:A,'Lista de Materiais'!C:C) -> #N/A | H65: AJUSTE | M65: BUCHA DE ALUMINIO C/ARRUELA 2"
A66: ANTIGO | C66: BUCHA DE REDUÇÃO FERRO GALV. 2"X 3/4" | E66: FALSE | F66: 1 | G66: =_xlfn.XLOOKUP(B:B,'Lista de Materiais'!A:A,'Lista de Materiais'!C:C) -> #N/A | H66: AJUSTE | M66: BUCHA DE ALUMINIO C/ARRUELA 3/4"
A67: ANTIGO | C67: BUCHA DE REDUÇÃO FERRO GALV. 2"X1.1/2" | E67: FALSE | F67: 2 | G67: =_xlfn.XLOOKUP(B:B,'Lista de Materiais'!A:A,'Lista de Materiais'!C:C) -> #N/A | H67: AJUSTE | M67: BUCHA DE REDUÇÃO GALV. 3/4"X1/2"
A68: ANTIGO | C68: BUCHA DE REDUÇÃO GALV. 3/4"X1/2" | E68: FALSE | F68: 1 | G68: =_xlfn.XLOOKUP(B:B,'Lista de Materiais'!A:A,'Lista de Materiais'!C:C) -> #N/A | H68: AJUSTE | M68: BUCHA FIXACAO PARAFUSO PA CZ S10
A69: ANTIGO | B69: 3000808 | C69: BUCHA FIXAÇÃO NYLON S10 | E69: FALSE | F69: 300 | G69: =_xlfn.XLOOKUP(B:B,'Lista de Materiais'!A:A,'Lista de Materiais'!C:C) -> UN | H69: AJUSTE | M69: BUCHA FIXACAO PARAFUSO PA CZ S12 ALV
A70: ANTIGO | B70: 3000807 | C70: BUCHA FIXAÇÃO NYLON S12 | E70: FALSE | F70: 6 | G70: =_xlfn.XLOOKUP(B:B,'Lista de Materiais'!A:A,'Lista de Materiais'!C:C) -> UN | H70: AJUSTE | M70: BUCHA FIXACAO PARAFUSO S6 S/ ANEL
A71: ANTIGO | C71: BUCHA FIXAÇÃO NYLON S6 | E71: FALSE | F71: 260 | G71: =_xlfn.XLOOKUP(B:B,'Lista de Materiais'!A:A,'Lista de Materiais'!C:C) -> #N/A | H71: AJUSTE | M71: BUCHA FIXACAO PARAFUSO S8 S/ ANEL
A72: ANTIGO | C72: BUCHA FIXAÇÃO NYLON S8 | E72: FALSE | F72: 100 | G72: =_xlfn.XLOOKUP(B:B,'Lista de Materiais'!A:A,'Lista de Materiais'!C:C) -> #N/A | H72: AJUSTE | M72: BUCHA IGUAL AL 1POL 1POL
A73: ANTIGO | B73: 5000745 | C73: BUCHA RED GALV RMF BSP D2X1 | E73: FALSE | F73: 2 | G73: =_xlfn.XLOOKUP(B:B,'Lista de Materiais'!A:A,'Lista de Materiais'!C:C) -> #N/A | H73: AJUSTE | M73: BUCHA RED CPVC SOLD DN1.1/2X1POL
A74: ANTIGO | B74: 5000667 | C74: BUCHA RED PVC SOLD 1.1/2"X 1" | E74: FALSE | F74: 1 | G74: =_xlfn.XLOOKUP(B:B,'Lista de Materiais'!A:A,'Lista de Materiais'!C:C) -> #N/A | H74: AJUSTE | M74: BUCHA RED GALV RMF BSP D1.1/2X1
A75: ANTIGO | B75: 5000693 | C75: BUCHA RED PVC-R AF DE 1.1/2X1POL | E75: FALSE | F75: 1 | G75: =_xlfn.XLOOKUP(B:B,'Lista de Materiais'!A:A,'Lista de Materiais'!C:C) -> #N/A | H75: AJUSTE | M75: BUCHA RED GALV RMF BSP D1.1/2X1/2
A76: ANTIGO | B76: 5510706 | C76: BUCHA REDUCAO LAT 1/2POL 1/4POL ( MANOMETRO ) | E76: FALSE | F76: 40 | G76: =_xlfn.XLOOKUP(B:B,'Lista de Materiais'!A:A,'Lista de Materiais'!C:C) -> UN | H76: AJUSTE | M76: BUCHA RED GALV RMF BSP D1X3/4
A77: ANTIGO | C77: CABEÇOTE DE ELETRICA ALUMINIO 2" | E77: FALSE | F77: 2 | G77: =_xlfn.XLOOKUP(B:B,'Lista de Materiais'!A:A,'Lista de Materiais'!C:C) -> #N/A | H77: AJUSTE | M77: BUCHA RED GALV RMF BSP D2X1
A78: ANTIGO | B78: 5001053 | C78: CABO COBRE NU TMD CL2A 1X16MM | E78: FALSE | F78: 450 | G78: =_xlfn.XLOOKUP(B:B,'Lista de Materiais'!A:A,'Lista de Materiais'!C:C) -> M | H78: AJUSTE | M78: BUCHA RED GALV RMF BSP D2X1
A79: ANTIGO | C79: CABO DE REDE 8X26AWG ( AUTOMAÇÃO ) | E79: FALSE | F79: 800 | G79: =_xlfn.XLOOKUP(B:B,'Lista de Materiais'!A:A,'Lista de Materiais'!C:C) -> #N/A | H79: AJUSTE | M79: BUCHA RED GALV RMF BSP D2X1.1/2
A80: ANTIGO | B80: 5001073 | C80: CABO ELE PP 450/ 750V 1X4MM | E80: FALSE | F80: 2 | G80: =_xlfn.XLOOKUP(B:B,'Lista de Materiais'!A:A,'Lista de Materiais'!C:C) -> M | H80: AJUSTE | M80: BUCHA RED GALV RMF BSP D2X3/4
A81: ANTIGO | B81: 5017911 | C81: CABO ELET FLEX 0,6/1KV 1 X 4MM2 PT | E81: FALSE | F81: 1420 | G81: =_xlfn.XLOOKUP(B:B,'Lista de Materiais'!A:A,'Lista de Materiais'!C:C) -> #N/A | H81: AJUSTE | M81: BUCHA RED GALV RMF BSP D3X2
A82: ANTIGO | B82: 5017979 | C82: CABO ELET FLEX 0,6/1KV 1X25MM2 PT | E82: FALSE | F82: 300 | G82: =_xlfn.XLOOKUP(B:B,'Lista de Materiais'!A:A,'Lista de Materiais'!C:C) -> #N/A | H82: AJUSTE | M82: BUCHA RED GALV RMF BSP D3X2.1/2
A83: ANTIGO | B83: 5021333 | C83: CABO ELET FLEX 0,6/1KV 70MM2 CL5 PT | E83: FALSE | F83: 124 | G83: =_xlfn.XLOOKUP(B:B,'Lista de Materiais'!A:A,'Lista de Materiais'!C:C) -> #N/A | H83: AJUSTE | M83: BUCHA RED GALV RMF BSP D4X2
A84: ANTIGO | B84: 5001146 | C84: CABO ELET FLEX 1 X 16MM2 PT | E84: FALSE | F84: 580 | G84: =_xlfn.XLOOKUP(B:B,'Lista de Materiais'!A:A,'Lista de Materiais'!C:C) -> #N/A | H84: AJUSTE | M84: BUCHA RED GALV RMF BSP D4X3
A85: ANTIGO | B85: 5019701 | C85: CABO ELET FLEX 750V 1MM2 PT | E85: FALSE | F85: 8500 | G85: =_xlfn.XLOOKUP(B:B,'Lista de Materiais'!A:A,'Lista de Materiais'!C:C) -> #N/A | H85: AJUSTE | M85: BUCHA RED PVC-R AF DE1.1/2X1POL
A86: ANTIGO | B86: 5019782 | C86: CABO ELET FLEX 750V 1MM2 CINZA | E86: FALSE | F86: 500 | G86: =_xlfn.XLOOKUP(B:B,'Lista de Materiais'!A:A,'Lista de Materiais'!C:C) -> M | H86: AJUSTE | M86: BUCHA RED PVC-R AF DE1X1/2POL
A87: ANTIGO | B87: 5001357 | C87: CABO ELET FLEX 750V 6MM | E87: FALSE | F87: 100 | G87: =_xlfn.XLOOKUP(B:B,'Lista de Materiais'!A:A,'Lista de Materiais'!C:C) -> M | H87: AJUSTE | M87: BUCHA RED PVC-R AF DE1X1/2POL
A88: ANTIGO | B88: 5001074 | C88: CABO ELET PP 450 / 750 V 4 X 6MM2 | E88: FALSE | F88: 520 | G88: =_xlfn.XLOOKUP(B:B,'Lista de Materiais'!A:A,'Lista de Materiais'!C:C) -> #N/A | H88: AJUSTE | M88: BUCHA RED PVC-R AF DE1X3/4POL
A89: ANTIGO | B89: 5020122 | C89: CABO ELET. FLEX 0.6/1KV 1X1.5MM CL4 C/100mts | E89: FALSE | F89: 100 | G89: =_xlfn.XLOOKUP(B:B,'Lista de Materiais'!A:A,'Lista de Materiais'!C:C) -> M | H89: AJUSTE | M89: BUCHA RED PVC-R AF DE2X1.1/2POL
A90: ANTIGO | B90: 5017790 | C90: CABO ELET. FLEX 0.6/1KV 1X2.5MM CL5 C/100mts | E90: FALSE | F90: 400 | G90: =_xlfn.XLOOKUP(B:B,'Lista de Materiais'!A:A,'Lista de Materiais'!C:C) -> M | H90: AJUSTE | M90: BUCHA RED PVC-R AF DE2X1POL
A91: ANTIGO | B91: 5000970 | C91: CABO ELETRICO 1,5MM | E91: FALSE | F91: 100 | G91: =_xlfn.XLOOKUP(B:B,'Lista de Materiais'!A:A,'Lista de Materiais'!C:C) -> M | H91: AJUSTE | M91: BUCHA RED PVC-R AF DE3/4X1/2POL
A92: ANTIGO | B92: 5001409 | C92: CABO ELETRICO POT 0,6/1KV 95MM2 CL5 | E92: FALSE | F92: 170 | G92: =_xlfn.XLOOKUP(B:B,'Lista de Materiais'!A:A,'Lista de Materiais'!C:C) -> #N/A | H92: AJUSTE | M92: BUCHA REDUCAO LAT 1/2POL 1/4POL
A93: ANTIGO | B93: 5025964 | C93: CABO FLEX ATOX 450/750V 1X2.5MM PT | E93: FALSE | F93: 100 | G93: =_xlfn.XLOOKUP(B:B,'Lista de Materiais'!A:A,'Lista de Materiais'!C:C) -> M | H93: AJUSTE | M93: CABEÇOTE DE ELETRICA ALUMINIO 2"
A94: ANTIGO | B94: 5001141 | C94: CABO FLEX ATOX 450/750V 1X2.5MM VERMELHO | E94: FALSE | F94: 1300 | G94: =_xlfn.XLOOKUP(B:B,'Lista de Materiais'!A:A,'Lista de Materiais'!C:C) -> M | H94: AJUSTE | M94: CABO COB PP 1KV 2X1,5MM2 PT
A95: ANTIGO | B95: 5025913 | C95: CABO FLEX EPR ATOX 0,6/1KV 1X95MM PT | E95: FALSE | F95: 75 | G95: =_xlfn.XLOOKUP(B:B,'Lista de Materiais'!A:A,'Lista de Materiais'!C:C) -> M | H95: AJUSTE | M95: CABO COB PP 1KV 4X16MM2 PT
A96: ANTIGO | B96: 5025952 | C96: CABO FLEX EPR ATOX 0,6/1KV 1X95MM VD | E96: FALSE | F96: 75 | G96: =_xlfn.XLOOKUP(B:B,'Lista de Materiais'!A:A,'Lista de Materiais'!C:C) -> M | H96: AJUSTE | M96: CABO COB PP 750V3X1,5MM2 PT
A97: ANTIGO | C97: CABO FLEXIVEL 1KV 10MM | E97: FALSE | F97: 160 | G97: =_xlfn.XLOOKUP(B:B,'Lista de Materiais'!A:A,'Lista de Materiais'!C:C) -> #N/A | H97: AJUSTE | M97: CABO COB PP 750V4X10MM2 PT
A98: ANTIGO | C98: CABO FLEXIVEL 1KV 120MM *BOBINA | E98: FALSE | F98: 150 | G98: =_xlfn.XLOOKUP(B:B,'Lista de Materiais'!A:A,'Lista de Materiais'!C:C) -> #N/A | H98: AJUSTE | M98: CABO COB PP 750V4X2,5MM2 PT
A99: ANTIGO | B99: 5001373 | C99: CABO FLEXIVEL 1KV 150MM *BOBINA +- | E99: FALSE | F99: 100 | G99: =_xlfn.XLOOKUP(B:B,'Lista de Materiais'!A:A,'Lista de Materiais'!C:C) -> M | H99: AJUSTE | M99: CABO DE REDE 8X26AWG ( AUTOMAÇÃO )
A100: ANTIGO | B100: 5017977 | C100: CABO FLEXIVEL 1KV 35MM 1KV | E100: FALSE | F100: 218.5 | G100: =_xlfn.XLOOKUP(B:B,'Lista de Materiais'!A:A,'Lista de Materiais'!C:C) -> M | H100: AJUSTE | M100: CABO ELET COB NU 16MM2
...

Sheet SAIDA DE MATERIAIS
A1: Data | B1: Cód.do Material | C1: Descrição do material | D1: CONDIÇÃO | E1: Baixa | F1: Qntd. | G1: Medida | H1: Destino | I1: Solicitante | J1: Responsável pela Saída | K1: Observações
A2: 02.03.2026 | B2: 5517146 | C2: TRANSMISSOR PRES COMP M12 IP67 100MCA | E2: TRUE | F2: 1 | G2: UN | H2: BOOSTER BRASILIA | I2: ANDREW | J2: ANDREW
A3: 02.03.2026 | B3: 2002904 | C3: LIXA FERRO GR100 225X275MM 50UNID | E3: TRUE | F3: 1 | G3: UN | H3: ELEVATORIA GRAMA | I3: DIEGO / MARCIO | J3: DIEGO
A4: 02.03.2026 | B4: 4007458 | C4: =_xlfn.XLOOKUP(B4,'Lista de Materiais'!A:A,'Lista de Materiais'!B:B) -> SELO MECANICO TS-P 1.3/4POL | E4: TRUE | F4: 1 | G4: UN | H4: ELEVATORIA GRAMA | I4: DIEGO / MARCIO | J4: DIEGO
A5: 04.03.2026 | B5: 5006218 | C5: LAMINA DE SERRA STARRET 1232 | E5: TRUE | F5: 2 | G5: UN | H5: BASE NOVA IGUAÇU | I5: CLOVIS | J5: MARCIOMC
A6: 04.03.2026 | B6: 5024639 | C6: FITA VEDA ROSCA BR 18MM ROL 50M | E6: TRUE | F6: 4 | G6: UN | H6: BASE NOVA IGUAÇU | I6: CLOVIS / VAGNER | J6: MARCIOMC
A7: 05.03.2026 | B7: 3000808 | C7: BUCHA FIXAÇÃO NYLON S10 | E7: TRUE | F7: 4 | G7: UN | H7: BOOSTER JK | I7: CLOVIS / VAGNER | J7: MARCIOMC | K7: PARA DO GUANDU
A8: 05.03.2026 | B8: 3000807 | C8: BUCHA FIXAÇÃO NYLON S12 | E8: TRUE | F8: 4 | G8: UN | H8: BOOSTER JK | I8: CLOVIS / VAGNER | J8: MARCIOMC | K8: PARA DO GUANDU
A9: 05.03.2026 | B9: 2002904 | C9: LIXA FERRO GR100 225X275MM 50UNID | E9: TRUE | F9: 2 | G9: UN | H9: BOOSTER JK | I9: CLOVIS / VAGNER | J9: MARCIOMC | K9: PARA DO GUANDU
A10: 05.03.2026 | B10: 3009924 | C10: PANO LIMPEZA RETALHO COST EQUIP OL/GX SACO C/ 25KG | E10: TRUE | F10: 1 | G10: KG | H10: BOOSTER JK | I10: CLOVIS / VAGNER | J10: MARCIOMC | K10: PARA DO GUANDU
A11: 05.03.2026 | B11: 5504610 | C11: TERMINAL ELET COMP 185MM2 | E11: TRUE | F11: 3 | G11: UN | H11: BOOSTER JK | I11: CLOVIS / VAGNER | J11: MARCIOMC | K11: PARA DO GUANDU
A12: 05.03.2026 | B12: 4007729 | C12: ROLAMENTO ESF RIG 6312 - 2Z/C3 | E12: TRUE | F12: 2 | G12: UN | H12: BOOSTER JK | I12: CLOVIS / VAGNER | J12: MARCIOMC | K12: PARA DO GUANDU
A13: 05.03.2026 | B13: 5024527 | C13: FITA ISOL PR 750V 19MM ROL 20M P44 | E13: TRUE | F13: 1 | G13: UN | H13: BOOSTER JK | I13: CLOVIS / VAGNER | J13: MARCIOMC | K13: PARA DO GUANDU
A14: 05.03.2026 | B14: 5534866 | C14: FITA AUTA TENSÃO FUSÃO19MMX10MTS | E14: TRUE | F14: 1 | G14: UN | H14: BOOSTER JK | I14: CLOVIS / VAGNER | J14: MARCIOMC | K14: PARA DO GUANDU
A15: 05.03.2026 | B15: 5504610 | C15: TERMINAL ELET COMP 185MM2 | E15: TRUE | F15: 6 | G15: UN | H15: BOOSTER JK | I15: CLOVIS / VAGNER | J15: MARCIOMC | K15: PARA DO GUANDU
A16: 05.03.2026 | B16: 5019991 | C16: CABO ELET FLEX 0,6/1KV1X185MM2 | E16: TRUE | F16: 18 | G16: M | H16: BOOSTER JK | I16: CLOVIS / VAGNER | J16: MARCIOMC | K16: PARA DO GUANDU
A17: 06.03.2026 | B17: 4007458 | C17: SELO MECÂNICO TS-P 1.3/4" | E17: TRUE | F17: 1 | G17: UN | H17: ELEVATORIA DA SERRA | I17: PAULO SERGIO /ERICK | J17: MARCIOMC
A18: 06.03.2026 | B18: 4007727 | C18: ROLAMENTO ESF RIG 6309-2Z/C3 SKF | E18: TRUE | F18: 1 | G18: UN | H18: ELEVATORIA DA SERRA | I18: PAULO SERGIO /ERICK | J18: MARCIOMC
A19: 06.03.2026 | B19: 4003682 | C19: ROLAMENTO ESF RIG 6209-2Z SKF | E19: TRUE | F19: 1 | G19: UN | H19: ELEVATORIA DA SERRA | I19: PAULO SERGIO /ERICK | J19: MARCIOMC
A20: 06.03.2026 | B20: 3009592 | C20: COLA MULTIUSO SPRAY 330G | E20: TRUE | F20: 2 | G20: UN | H20: BOOSTER JK | I20: CLOVIS | J20: MARCIOMC | K20: PARA DO GUANDU
A21: 06.03.2026 | B21: 4003682 | C21: ROLAMENTO ESF RIG 6209-2Z SKF | E21: TRUE | F21: 2 | G21: UN | H21: AJUSTE | J21: DAVI
A22: 02.03.2026 | B22: 5000738 | C22: BUCHA RED GALV RMF BSP D1X3/4 | D22: ATUALIZAÇÃO 02.03.26 | E22: TRUE | F22: 1 | G22: UN | H22: AJUSTE | J22: ATUALIZAÇÃO 02.03.26
A23: 02.03.2026 | B23: 5006963 | C23: LUVA RED GALV RF BSP D3/4X1/2 | D23: ATUALIZAÇÃO 02.03.26 | E23: TRUE | F23: 5 | G23: UN | H23: AJUSTE | J23: ATUALIZAÇÃO 02.03.26
A24: 02.03.2026 | B24: 5006901 | C24: LUVA RED GALV RF BSP D1.1/2X1 | D24: ATUALIZAÇÃO 02.03.26 | E24: TRUE | F24: 1 | G24: UN | H24: AJUSTE | J24: ATUALIZAÇÃO 02.03.26
A25: 02.03.2026 | B25: 5018313 | C25: NIPLE GALV RM BSP D1 | D25: ATUALIZAÇÃO 02.03.26 | E25: TRUE | F25: 2 | G25: UN | H25: AJUSTE | J25: ATUALIZAÇÃO 02.03.26
A26: 06.03.2026 | B26: 5504841 | C26: ELETRODUTO FLEXIVEL CORRUG PVC 2POL | E26: TRUE | F26: 30 | G26: M | H26: VILA RORAIMA II | I26: VAGNER | J26: MARCIOMC | K26: SERÁ MEDIDO NO LOCAL
A27: 06.03.2026 | B27: 5001146 | C27: CABO ELET FLEX 1 X 16MM2 PT | E27: TRUE | F27: 30 | G27: M | H27: VILA RORAIMA II | I27: VAGNER | J27: MARCIOMC
A28: 06.03.2026 | B28: 5504365 | C28: CURVA ELETRODUTO PVC 90X2" | E28: TRUE | F28: 2 | G28: UN | H28: VILA RORAIMA II | I28: VAGNER | J28: MARCIOMC
A29: 06.03.2026 | B29: 3008277 | C29: BUCHA ELETRODUTO AL 2POL | E29: TRUE | F29: 2 | G29: UN | H29: VILA RORAIMA II | I29: VAGNER | J29: MARCIOMC
A30: 06.03.2026 | B30: 3000328 | C30: ARRUELA ELETROD RED AL NPT 2POL | E30: TRUE | F30: 2 | G30: UN | H30: VILA RORAIMA II | I30: VAGNER | J30: MARCIOMC
A31: 06.03.2026 | B31: 5004508 | C31: DISJUNTOR MINI 3P 220 3XC80A | E31: TRUE | F31: 1 | G31: UN | H31: VILA RORAIMA II | I31: VAGNER | J31: MARCIOMC
A32: 06.03.2026 | B32: 3009327 | C32: ABRACADEIRA BAP AC GALV 1200MM 33 FUROS | E32: TRUE | F32: 1 | G32: UN | H32: VILA RORAIMA II | I32: VAGNER | J32: MARCIOMC
A33: 09.03.2026 | B33: 5534866 | C33: FITA AUTA TENSÃO FUSÃO19MMX10MTS | E33: TRUE | F33: 1 | G33: UN | H33: BOOSTER NILOPOLIS | I33: ERICK | J33: MARCIOMC
A34: 09.03.2026 | B34: 4007732 | C34: ROLAMENTO ESF RIG 6316 2Z C3 SKF | E34: TRUE | F34: 1 | G34: UN | H34: BOOSTER NILOPOLIS | I34: CLOVIS / VINICIUS | J34: MARCIOMC
A35: 09.03.2026 | B35: 4003557 | C35: ROLAMENTO ESF RIG 6319 C3 SKF | E35: TRUE | F35: 1 | G35: UN | H35: BOOSTER NILOPOLIS | I35: CLOVIS / VINICIUS | J35: MARCIOMC
A36: 09.03.2026 | B36: 5534866 | C36: FITA AUTA TENSÃO FUSÃO19MMX10MTS | E36: TRUE | F36: 2 | G36: UN | H36: AJUSTE
A37: 09.03.2026 | B37: 5024527 | C37: FITA ISOL PR 750V 19MM ROL 20M P44 | E37: TRUE | F37: 8 | G37: UN | H37: AJUSTE
A38: 09.03.2026 | B38: 5024531 | C38: FITA ISOLANTE AM 750V 18MM ROL 20M | E38: TRUE | F38: 2 | G38: UN | H38: AJUSTE
A39: 09.03.2026 | B39: 5001146 | C39: CABO ELET FLEX 1 X 16MM2 PT | E39: TRUE | F39: 30 | G39: M | H39: AJUSTE
A40: 10.03.2026 | B40: 5004525 | C40: DISJUNTOR MINI 3P 415VCA 3X125A | E40: TRUE | F40: 1 | G40: UN | H40: BXD1 - ELEVATORIA MANOEL GAMA II | I40: WENDREL / BRUNO | J40: MARCIOMC
A41: 11.03.2026 | B41: 5000970 | C41: CABO ELETRICO 1,5MM2 | E41: TRUE | F41: 3 | G41: M | H41: ELEVATORIA CEFET | I41: CLOVIS | J41: MARCIOMC
A42: 11.03.2027 | B42: 3009240 | C42: ADESIVO RESINA EPOXI 16G | E42: TRUE | F42: 1 | G42: UN | H42: ELEVATORIA CEFET | I42: CLOVIS | J42: MARCIOMC
A43: 11.03.2028 | B43: 2004301 | C43: MASSA PLAST PLAST CZ LT 400GR | E43: TRUE | F43: 1 | G43: UN | H43: ELEVATORIA CEFET | I43: CLOVIS | J43: MARCIOMC
A44: 12.02.26 | B44: 3009240 | C44: ADESIVO RESINA EPOXI 16G | E44: TRUE | F44: 1 | G44: UN | H44: ELEVATORIA PRAÇA DA BIBLIA | I44: ALEXANDRE FERREIRA | J44: DAVI ADM
A45: 11.03.2026 | B45: 5016434 | C45: CABO ELET FLEX 0,6/1KV 3 X 25MM2 PT | E45: TRUE | F45: 4 | G45: M | H45: AJUSTE
A46: 11.03.2026 | B46: 5001073 | C46: CABO ELE PP 450/ 750V 1X4MM | E46: TRUE | F46: 2 | G46: M | H46: AJUSTE
A47: 11.03.2026 | B47: 5000938 | C47: CABO FLEXIVEL PP 1KV 3X1,5MM PRETO | E47: TRUE | F47: 50 | G47: M | H47: AJUSTE
A48: 11.03.2026 | B48: 5001442 | C48: CABO ELETRICO POT 1KV 120MM2 CL5 | E48: TRUE | F48: 150 | G48: M | H48: AJUSTE
A49: 11.03.2026 | B49: 5505174 | C49: LUVA EMENDACAB COBRE 25MM | E49: TRUE | F49: 2 | G49: UN | H49: ELEVATORIA ENGENHARIA | I49: ERICK | J49: MARCIOMC
A50: 11.03.2026 | B50: 5534866 | C50: FITA AUTA TENSÃO FUSÃO19MMX10MTS | E50: TRUE | F50: 1 | G50: UN | H50: ELEVATORIA CEFET | I50: CLOVIS | J50: CLOVIS
A51: 12.03.2026 | B51: 3009592 | C51: COLA MULTIUSO SPRAY 330G | E51: TRUE | F51: 1 | G51: UN | H51: ELEVATORIA CEFET | I51: JORGE | J51: MARCIOMC
A52: 12.03.2026 | B52: 5505448 | C52: ELEMENTO ELASTICO ACOPLAMENTO AG194 | E52: TRUE | F52: 1 | G52: UN | H52: BOOSTER NILOPOLIS | I52: CLOVIS | J52: MARCIOMC
A53: 12.03.2026 | B53: 3009592 | C53: COLA MULTIUSO SPRAY 330G | E53: TRUE | F53: 15 | G53: UN | H53: AJUSTE | J53: MARCIOMC | K53: VALIDADE VENCIDA
A54: 11.03.2026 | B54: 5006722 | C54: LUVA GALV RF BSP D2.1/2 | E54: TRUE | F54: 1 | G54: UN | H54: ELEVATORIA CEFET | I54: CLOVIS | J54: MARCIOMC
A55: 12.03.2026 | B55: 5000745 | C55: BUCHA RED GALV RMF BSP D2X1 | E55: TRUE | F55: 1 | G55: UN | H55: AJUSTE | J55: MARCIOMC
A56: 12.03.2026 | B56: 5018308 | C56: NIPLE GALV RM BSP D2 | E56: TRUE | F56: 4 | G56: UN | H56: AJUSTE | J56: MARCIOMC
A57: 12.03.2026 | B57: 5020775 | C57: NIPLE GALV RM BSP D1.1/2 | E57: TRUE | F57: 19 | G57: UN | H57: AJUSTE | J57: MARCIOMC
A58: 12.03.2026 | B58: 3008944 | C58: ABRACADEIRA NYLON PT 4,8X200MM 100UN | E58: TRUE | F58: 2 | G58: UN | H58: AJUSTE | J58: MARCIOMC
A59: 12.03.2026 | B59: 5009440 | C59: TE PVC-R AF RF DE2POL | E59: TRUE | F59: 1 | G59: UN | H59: AJUSTE | J59: MARCIOMC
A60: 12.03.2026 | B60: 5001074 | C60: CABO ELET PP 450 / 750 V 4 X 6MM2 | E60: TRUE | F60: 20 | G60: M | H60: AJUSTE | J60: MARCIOMC
A61: 13.03.2026 | B61: 5534866 | C61: FITA AUTA TENSÃO FUSÃO19MMX10MTS | E61: TRUE | F61: 1 | G61: UN | H61: ELEVATORIA QUEIMADOS DISTRITO | I61: RONALDO | J61: MARCIOMC
A62: 13.03.2026 | B62: 5024527 | C62: FITA ISOL PR 750V 19MM ROL 20M P44 | E62: TRUE | F62: 1 | G62: UN | H62: ELEVATORIA QUEIMADOS DISTRITO | I62: RONALDO | J62: MARCIOMC
A63: 13.03.2026 | B63: 4007727 | C63: ROLAMENTO ESF RIG 6309-2Z/C3 SKF | E63: TRUE | F63: 1 | G63: UN | H63: ELEVATORIA QUEIMADOS DISTRITO | I63: JORGE | J63: MARCIOMC
A64: 13.03.2026 | B64: 4003682 | C64: ROLAMENTO ESF RIG 6209-2Z SKF | E64: TRUE | F64: 1 | G64: UN | H64: ELEVATORIA QUEIMADOS DISTRITO | I64: JORGE | J64: MARCIOMC
A65: 13.03.2026 | B65: 4007458 | C65: SELO MECÂNICO TS-P 1.3/4" | E65: TRUE | F65: 1 | G65: UN | H65: ELEVATORIA QUEIMADOS DISTRITO | I65: JORGE | J65: MARCIOMC
A66: 13.03.2026 | B66: 5534866 | C66: FITA AUTA TENSÃO FUSÃO19MMX10MTS | E66: TRUE | F66: 1 | G66: UN | H66: SERVIÇO DE MANUTENÇÃO | I66: ALEXSANDRO | J66: ALEXSANDRO
A67: 16.03.2026 | B67: 5004549 | C67: DISJUNTOR MINI 3P 400VCA 3XC20 | E67: TRUE | F67: 1 | G67: UN | H67: BXD1 | I67: RODRIGO | J67: MARCIOMC
A68: 17.03.2026 | B68: 5534866 | C68: FITA AUTA TENSÃO FUSÃO19MMX10MTS | E68: TRUE | F68: 1 | G68: UN | H68: BOOSTER NILOPOLIS | I68: VAGNER | J68: MARCIOMC
A69: 19.03.2026 | B69: 5004508 | C69: DISJUNTOR MINI 3P 220 3XC80A | E69: TRUE | F69: 1 | G69: UN | H69: ELEVATORIA DINAMARCO REIS | I69: DOUGLAS | J69: DAVI
A70: 20.03.2026 | B70: 4007458 | C70: SELO MECÂNICO TS-P 1.3/4" | E70: TRUE | F70: 1 | G70: UN | H70: ELEVATORIA MESQUITA G1 | I70: CLOVIS / JORGE | J70: MARCIOMC
A71: 20.03.2026 | B71: 5025191 | C71: CABO AUTOMACAO PVC 70GRC PT 4VIAS 26AWG | E71: TRUE | F71: 22 | G71: M | H71: BXD1 REDUQUE | I71: SERGIO | J71: MARCIOMC
A72: 23.03.2026 | B72: 5017138 | C72: FILTRO Y FOFO AG FFDIN100MM PN10 | E72: TRUE | F72: 1 | G72: UN | H72: BOOSTER MONTE LÍBANO | I72: CRISTIANO | J72: MARCIOMC
A73: 23.03.2026 | B73: 4007458 | C73: SELO MECÂNICO TS-P 1.3/4" | E73: TRUE | F73: 1 | G73: UN | H73: COMUNIDADE ENG DENTRO | I73: ROBERTO | J73: MARCIOMC
A74: 23.03.2026 | B74: 5008159 | C74: NIPLE PVC-R AF RM DE3/4POL | E74: TRUE | F74: 2 | G74: UN | H74: BOOSTER ENG PEDREIRA | I74: ANDRE | J74: MARCIOMC
A75: 23.03.2026 | B75: 5009441 | C75: TE PVC ROSCA 3/4" | E75: TRUE | F75: 1 | G75: UN | H75: BOOSTER ENG PEDREIRA | I75: ANDRE | J75: MARCIOMC
A76: 23.03.2026 | B76: 5015047 | C76: REGISTRO ESF PVC-R AF RMF BORB DE 3/4POL BRANCO | E76: TRUE | F76: 1 | G76: UN | H76: BOOSTER ENG PEDREIRA | I76: ANDRE | J76: MARCIOMC
A77: 23.03.2026 | B77: 5004475 | C77: DISJUNTOR MINI 3P 400VCA 3X25A | E77: TRUE | F77: 1 | G77: UN | H77: BOOSTER ENG PEDREIRA | I77: DOUGLAS | J77: MARCIOMC
A78: 23.03.2026 | B78: 5024527 | C78: FITA ISOL PR 750V 19MM ROL 20M P44 | E78: TRUE | F78: 1 | G78: UN | H78: BOOSTER NILOPOLIS | I78: JHONATA | J78: MARCIOMC
A79: 23.03.2026 | B79: 5024639 | C79: FITA VEDA ROSCA BR 18MM ROL 50M | E79: TRUE | F79: 1 | G79: UN | H79: BOOSTER NILOPOLIS | I79: JHONATA | J79: MARCIOMC
A80: 23.03.2026 | B80: 4000911 | C80: ARMACAO SECUNDARIA ACO C/ISOLAD 110,5MM | E80: TRUE | F80: 1 | G80: UN | H80: BOOSTER NILOPOLIS | I80: JHONATA | J80: MARCIOMC
A81: 24.03.2026 | B81: 5534866 | C81: FITA AUTA TENSÃO FUSÃO19MMX10MTS | E81: TRUE | F81: 1 | G81: UN | H81: BOOSTER ENG PEDREIRA | I81: RONALDO | J81: MARCIOMC
A82: 24.03.2026 | B82: 5024527 | C82: FITA ISOL PR 750V 19MM ROL 20M P44 | E82: TRUE | F82: 1 | G82: UN | H82: BOOSTER ENG PEDREIRA | I82: RONALDO | J82: MARCIOMC
A83: 24.03.2026 | B83: 5024527 | C83: FITA ISOL PR 750V 19MM ROL 20M P44 | E83: TRUE | F83: 1 | G83: UN | H83: SERVIÇO DE MANUTENÇÃO | I83: ALEXANDRE FERREIRA | J83: MARCIOMC
A84: 25.03.2026 | B84: 4007458 | C84: SELO MECÂNICO TS-P 1.3/4" | E84: TRUE | F84: 1 | G84: UN | H84: BOOSTER MESQUITA G1 | I84: CLOVIS | J84: MARCIOMC
A85: 25.03.2026 | B85: 5534866 | C85: FITA AUTA TENSÃO FUSÃO19MMX10MTS | E85: TRUE | F85: 1 | G85: UN | H85: BOOSTER MESQUITA G2 | I85: ALEXANDRE FERREIRA | J85: MARCIOMC
A86: 25.03.2026 | B86: 5534866 | C86: FITA AUTA TENSÃO FUSÃO19MMX10MTS | E86: TRUE | F86: 1 | G86: UN | H86: BOOSTER ENG PEDREIRA | I86: RONALDO | J86: MARCIOMC
A87: 25.03.2026 | B87: 5024527 | C87: FITA ISOL PR 750V 19MM ROL 20M P44 | E87: TRUE | F87: 1 | G87: UN | H87: BOOSTER ENG PEDREIRA | I87: RONALDO | J87: MARCIOMC
A88: 25032026 | B88: 4007727 | C88: ROLAMENTO ESF RIG 6309-2Z/C3 SKF | E88: TRUE | F88: 2 | G88: UN | H88: BOOSTER CABUÇU ALTO | I88: ROBERTO | J88: MARCIOMC | K88: WORKMEC
A89: 26.03.2026 | B89: 5020122 | C89: CABO ELET. FLEX 0.6/1KV 1X1.5MM CL4 C/100mts | E89: TRUE | F89: 100 | G89: M | H89: BXD1 | I89: WILLIAN | J89: ALEXSANDRO
A90: 26.03.2026 | B90: 5004369 | C90: DISJUNTOR MINI 2P 400VCA 2XC10 | E90: TRUE | F90: 1 | G90: UN | H90: BOOSTER NILOPOLIS | I90: ALEXANDRE FERREIRA | J90: MARCIOMC
A91: 27.03.2026 | B91: 5024527 | C91: FITA ISOL PR 750V 19MM ROL 20M P44 | E91: TRUE | F91: 1 | G91: UN | H91: RESERVATÓRIO NILOPOLIS | I91: ANDREW | J91: MARCIOMC
A92: 27.03.2026 | B92: 5004508 | C92: DISJUNTOR MINI 3P 220 3XC80A | E92: TRUE | F92: 1 | G92: UN | H92: RESERVATÓRIO NILOPOLIS | I92: ANDREW | J92: MARCIOMC
A93: 31.03.2026 | B93: 5504189 | C93: CHAVE BOIA NIVEL 25A INF/SUP CABO 1,5M/1,2M | E93: TRUE | F93: 1 | G93: UN | H93: ELEVATORIA PALHADA | I93: ANDRE | J93: MARCIOMC
A94: 31.03.2026 | B94: 5012947 | C94: UNIAO PVC-R AF RF DE2POL | E94: TRUE | F94: 1 | G94: UN | H94: RESERVATORIO NILOPOLIS | I94: ANDRE | J94: MARCIOMC
A95: 31.03.2026 | B95: 5024639 | C95: FITA VEDA ROSCA BR 18MM ROL 50M | E95: TRUE | F95: 1 | G95: UN | H95: RESERVATORIO NILOPOLIS | I95: ANDRE | J95: MARCIOMC
A96: 31.03.2026 | B96: 5006218 | C96: LAMINA DE SERRA STARRET 1232 | E96: TRUE | F96: 2 | G96: UN | H96: ELEVATORIA LAGOINHA | I96: CLOVIS / VINICIUS | J96: MARCIOMC
A97: 31.03.2026 | B97: 5006218 | C97: LAMINA DE SERRA STARRET 1232 | E97: TRUE | F97: 2 | G97: UN | H97: AJUSTE | J97: MARCIOMC
A98: 31.03.2026 | B98: 5012947 | C98: UNIAO PVC-R AF RF DE2POL | E98: TRUE | F98: 1 | G98: UN | H98: AJUSTE | J98: MARCIOMC
A99: 31.03.2026 | B99: 5004369 | C99: DISJUNTOR MINI 2P 400VCA 2XC10 | E99: TRUE | F99: 1 | G99: UN | H99: AJUSTE | J99: MARCIOMC
A100: 31.03.2026 | B100: 5004502 | C100: DISJUNTOR MINI 1P 230VCA 1XC2 | E100: TRUE | F100: 1 | G100: UN | H100: AJUSTE | J100: MARCIOMC
...

Sheet Lista de Materiais
A2: Material | B2: TxtBreveMaterial | C2: UMB | G2: Teste
A3: 3000087 | B3: *ABRACADEIRA MANG AC 1020 150MM | C3: UN | M3: ='Lista de Materiais'!B5430 -> _TRANSMISSOR PRE COMP BLUET M12 IP67
A4: 3000092 | B4: *ABRACADEIRA MANG AC 1020 150MM | C4: UN
A5: 3012505 | B5: *ADESIVO EPOXI BICOMP LIQ 46G | C5: UN
A6: 3012506 | B6: *ADESIVO EPOXI BICOMP LIQ 46G | C6: UN
A7: 4000024 | B7: *ADITIVO LIQUIDO EMBALAGEM 200ML | C7: UN
A8: 4000022 | B8: *ADITIVO LIQUIDO EMBALAGEM 200ML | C8: UN
A9: 4000026 | B9: *ADITIVO LIQUIDO EMBALAGEM 200ML | C9: UN
A10: 4000029 | B10: *ADITIVO LIQUIDO EMBALAGEM 500ML | C10: UN
A11: 4000025 | B11: *ADITIVO LIQUIDO EMBALAGEM 500ML | C11: UN
A12: 4000027 | B12: *ADITIVO LIQUIDO EMBALAGEM 500ML | C12: UN
A13: 4004363 | B13: *AMORTECEDOR VEICULOS LEVES | C13: UN
A14: 4004987 | B14: *BANDEJA SUSPENSAO VEICULOS LEVES | C14: UN
A15: 4006025 | B15: *BIELA VEICULOS LEVES | C15: UN
... A56512: 1500235 | B56512: ZINCO ZINCOVER 5 PP 20ML HACH 100UN | C56512: UN
A56513: SEM | C56513: UN

Sheet ELEVATÓRIAS BXD2
A1: TIPO | B1: ELEVATORIA | C1: CADEADOS PADRÃO | D1: QTDD | E1: ROLAMENTO MOTOR | F1: ROLAMENTO BOMBA | G1: B. ACOPLAMENTO | H1: GAXETA | I1: SELO MECÃNICO | J1: DATA DA TROCA
B2: ALTO MILITÃO | C2: SIM | D2: 2
B3: ADOLFO BERGAMINI | C3: NÃO
B4: AMAURI GUIMARAES
A5: ABRIGADA | B5: ANGELA MARIA | E5: 6203 ZZ C3 | I5: 5/8" | J5: 22.01.26
A6: ABRIGADA | B6: ANTONIO VALDIGEM | C6: SIM | D6: 1 | I6: 1.1/8" | J6: 29.01.26
A7: ABRIGADA | B7: ASSEMBLEIA | C7: SIM | D7: 1
A8: ABRIGADA | B8: BELO HORIZONTE | C8: SIM | D8: 1
A9: ABRIGADA | B9: BURITI | E9: 6307/6206
A10: ABRIGADA | B10: CAIÇARA | C10: SIM | D10: 1 | E10: 6309/6209
B11: PRAÇA DA BÍBLIA | E11: 6309/6207
A12: ABRIGADA | B12: CAIXA VELHA | C12: SIM | D12: 1
B13: CANADENSE
A14: ABRIGADA | B14: CAONZE | C14: SIM | D14: 1
A15: ABRIGADA | B15: CARAMUJOS | C15: SIM | D15: 1
A16: ABRIGADA | B16: CARLOS SAMPAIO | C16: SIM | D16: 1
B17: CEFET
A18: ABRIGADA | B18: CHATUBA | C18: SIM | D18: 1
A19: ABRIGADA | B19: CITROPOLIS | C19: SIM | D19: 1 | E19: 6309 | F19: 6207 | J19: 29.04.2026
A20: ABRIGADA | B20: CLUBE 34 | C20: SIM | D20: 1
A21: ABRIGADA | B21: DA SERRA | C21: SIM | D21: 1 | E21: 6309Z2/C3 | F21: 6209Z2/C3 | I21: 1.3/4" | J21: 05.03.2026
A22: ABRIGADA | B22: DANON | C22: SIM | D22: 1
A23: ABRIGADA | B23: DAS ROSAS
B24: DINAMARCO REIS
A25: ABRIGADA | B25: DIVINO | C25: SIM | D25: 1
A26: ABRIGADA | B26: EDNA
A27: ABRIGADA | B27: EDUARDO CELIDÔNIO | C27: SIM | D27: 1
A28: ABRIGADA | B28: EEAT BOOSTER AUSTIN G1/G2/G3 | C28: SIM | D28: 4
A29: ABRIGADA | B29: EEAT BOOSTER CABUÇU ALTO | C29: SIM | D29: 1 | E29: 6312 / 6212 (G1 G2 G3 ) | F29: 6309/6309 | G29: 128 | H29: 1/2" | J29: 27.03.2026
A30: ABRIGADA | B30: EEAT BOOSTER CABUÇU BAIXO | C30: SIM | D30: 5 | E30: 6309 C3 | F30: 6309 C3
A31: ABRIGADA | B31: EEAT BOOSTER ENG.PEDREIRA G1/G2 | C31: SIM | D31: 5 | E31: 6311 | G31: 195 | H31: 1/2" | J31: 23.03.26
A32: ABRIGADA | B32: EEAT BOOSTER BRASÍLIA | C32: SIM | D32: 2 | E32: 6313 ZZ C3 | G32: 214
A33: ABRIGADA | B33: EEAT BOOSTER JK G1/G2/G3/G4 | C33: SIM | D33: 2 | E33: G3 /G4 6319 6316 | F33: G3/G4 6411 / G1/G2 6312 | G33: G3/G4 168 | H33: 1/2" 9/16" | J33: 45509
A34: ABRIGADA | B34: EEAT BOOSTER POSSE G1/G2/G3/G4 | C34: SIM | D34: 2 | F34: G4/G2 6311 / 6311 | H34: 1/2"
A35: ABRIGADA | B35: EEAT CABUCU ALTO G1/G2/G3 | C35: SIM | D35: 2 | H35: 1/2"
A36: ABRIGADA | B36: EEAT MESQUITA G1/G2 | C36: SIM | D36: 2 | I36: 1.3/4" | J36: 26.11.25
A37: ABRIGADA | B37: EEAT-BOOSTER NILOPOLIS G1/G2/G3 | C37: SIM | D37: 2 | E37: G1/G2/G3 6319 | F37: G1/G2/G3 6316 | G37: G1/194 | H37: 1/2" | J37: 45509
A38: ABRIGADA | B38: EEE LAGOINHA 1 | C38: SIM | D38: 2 | E38: 6309 /6209
A39: ABRIGADA | B39: EEE LAGOINNHA 2 | C39: SIM | D39: 2 | E39: 6309 /6209
B40: BVOLANTE TÓQUIO | C40: SIM | D40: 1 | E40: 6308/6207
B41: EL SHADAY
B42: ENGENHARIA | C42: NÃO
A43: ABRIGADA | B43: ESPLANADA | C43: SIM | D43: 1
A44: ABRIGADA | B44: ETE CHATUBA | C44: SIM | D44: 1
A45: ABRIGADA | B45: ETE LAGOINHA
A46: ABRIGADA | B46: ETE SANTO ELIAS G1/G2 | C46: SIM | D46: 1
A47: ABRIGADA | B47: ETE SÃO JORGE
B48: EXPEDICIONARIOS
A49: ABRIGADA | B49: FLORESTA MIRANDA | C49: SIM | D49: 1
A50: ABRIGADA | B50: FRANCISCO XAVIER | C50: SIM | D50: 1
B51: GAMA | C51: NÃO
B52: GOLDEN GATE | E52: 6309 C3 / 6308 C3 | I52: 1.3/8"
B53: GRAMA | C53: NÃO | I53: 1.3/4" | J53: 02.03.26
A54: ABRIGADA | B54: GRANJA ROZALINA | C54: SIM | D54: 1 | E54: 6309/6207
A55: ABRIGADA | B55: HADDOCK LOBO | C55: SIM | D55: 1 | E55: 6309/6207
A56: ABRIGADA | B56: IARA | C56: SIM | D56: 1
B57: INDIA PORTUGUESA
A58: ABRIGADA | B58: ITAPAJÉ | C58: SIM | D58: 1 | E58: 6307 2ZC3 | F58: 6206 | I58: 1" | J58: 23.01.26
A59: ABRIGADA | B59: ITAPEMIRIM | C59: SIM | D59: 1 | E59: 6309/6209
B60: ITORORO
B61: IVO MIRANDA
A62: ABRIGADA | B62: JOSE VIRGILIO DO PRADO
B63: LIBANEA
B64: LUCIO TAVARES
A65: ABRIGADA | B65: MACIEL | C65: SIM | D65: 1 | I65: 1.1/4" | J65: 03.12.25
B66: MANOEL REIS
B67: MAURICIA BORGES
B68: MELVIN JONES
B69: MENA BARRETO
A70: ABRIGADA | B70: MIRANTE | E70: 6309/6207
B71: MORRO DA COCADA | C71: NÃO
B72: MORRO DA MOENDA
B73: MORRO DO TEMPERO
A74: ABRIGADA | B74: MORRO DOS 40
A75: ABRIGADA | B75: NESTOR MARINHO | I75: 1.3/8" | J75: 31.01.2
B76: NILO PEÇANHA (CEMITERIO)
B77: NOEMIA VIEIRA
A78: ABRIGADA | B78: ODILON BRAGA | C78: SIM | D78: 1
B79: OLIVIA MARIA MACHADO | E79: 6309/6207
B80: PADRE VIEIRA
B81: PAIOL
B82: PALHADA | I82: 1.3/8" | J82: 25.01.26
A83: ABRIGADA | B83: LIBERDADE
B84: PARQUE MARAVILHA
B85: PINDORAMA
A86: ABRIGADA | B86: PST ANTÔNIO MARTINS
A87: ABRIGADA | B87: QUEIMADOS | E87: 6309/6209
B88: QUISSUCO | C88: NÃO
B89: RESERVATÓRIA ALVORADA | C89: SIM | D89: 1
B90: RESERVATÓRIA AUSTIN | C90: SIM | D90: 1
B91: RODILANDIA
B92: ROLDAO GONCALVES
B93: SANTO ANTONIO
B94: SÃO JOAQUIM
A95: ABRIGADA | B95: SHEIK REJANE
B96: TABELIÃO MURILO COSTA
A97: ABRIGADA | B97: TACIANO MANACA | C97: SIM | D97: 1
A98: ABRIGADA | B98: TIMBO | C98: SIM | D98: 1
B99: TERCEIRA LINHA PRETA | C99: SIM | D99: 3
A100: ABRIGADA | B100: TRÊS CORACOES | C100: SIM | D100: 1
...

Sheet Saidas até 28.02.2026
A1: Data | B1: Cód.do Material | C1: Descrição do material | D1: CONDIÇÃO | E1: Baixa | F1: Qntd. | G1: Medida | H1: Destino | I1: Solicitante | J1: Responsável pela Saída | K1: Observações
A2: 15.09.25 | B2: 5004372 | C2: DISJUNTOR MINI 3P 380V 63A 54MM | E2: TRUE | F2: 1 | G2: =_xlfn.XLOOKUP(B:B,'Lista de Materiais'!A:A,'Lista de Materiais'!C:C) -> UN | H2: BXD1 ELEVATÓRIA PINHEIRO MACHADO | I2: WENDREL/RODRIGO | J2: MÁRCIOMC
A3: 15.09.25 | B3: 5006526 | C3: LUVA RED PVC-R AF RF 1X3/4" | E3: TRUE | F3: 1 | G3: =_xlfn.XLOOKUP(B:B,'Lista de Materiais'!A:A,'Lista de Materiais'!C:C) -> UN | H3: BXD2 ELEVATÓRIA ANGELA MARIA | I3: ALEXSANDRO | J3: MÁRCIOMC
A4: 15.09.25 | B4: 5024639 | C4: FITA VEDA ROSCA BR 18MM ROL 50M | E4: TRUE | F4: 1 | G4: =_xlfn.XLOOKUP(B:B,'Lista de Materiais'!A:A,'Lista de Materiais'!C:C) -> UN | H4: BXD2 ELEVATÓRIA ANGELA MARIA | I4: ALEXSANDRO | J4: MÁRCIOMC
A5: 15.09.25 | B5: 5008157 | C5: NIPLE PVC-R AF RM DE 1" | E5: TRUE | F5: 1 | G5: =_xlfn.XLOOKUP(B:B,'Lista de Materiais'!A:A,'Lista de Materiais'!C:C) -> UN | H5: BXD2 ELEVATÓRIA ANGELA MARIA | I5: ALEXSANDRO | J5: MÁRCIOMC
A6: 16.09.25 | B6: 5018562 | C6: RELE MODULAR INTERFACE 6A 250V 24V AZUL | E6: TRUE | F6: 1 | G6: =_xlfn.XLOOKUP(B:B,'Lista de Materiais'!A:A,'Lista de Materiais'!C:C) -> UN | H6: BXD2 ELEVATÓRIA INDIA PORTUGUESA | I6: WENDREL/RODRIGO | J6: MÁRCIOMC
A7: 16.09.25 | B7: 5000667 | C7: BUCHA RED PVC SOLD 1.1/2"X 1" | E7: TRUE | F7: 1 | G7: =_xlfn.XLOOKUP(B:B,'Lista de Materiais'!A:A,'Lista de Materiais'!C:C) -> UN | H7: BXD2 ELEVATÓRIA ANGELA MARIA | I7: ANDRÉ / ALEXANDRE | J7: MÁRCIOMC
A8: 16.09.25 | B8: 5024639 | C8: FITA VEDA ROSCA BR 18MM ROL 50M | E8: TRUE | F8: 1 | G8: =_xlfn.XLOOKUP(B:B,'Lista de Materiais'!A:A,'Lista de Materiais'!C:C) -> UN | H8: BXD2 ELEVATÓRIA ANGELA MARIA | I8: ANDRÉ / ALEXANDRE | J8: MÁRCIOMC
A9: 16.09.25 | B9: 5004475 | C9: DISJUNTOR MINI 3P 400VCA 3X25A | E9: TRUE | F9: 1 | G9: =_xlfn.XLOOKUP(B:B,'Lista de Materiais'!A:A,'Lista de Materiais'!C:C) -> UN | H9: BXD1 ELEVATÓRIA SCHANGRILA | I9: JORGE / ANDRÉ | J9: MÁRCIOMC
A10: 17.09.25 | B10: 5018562 | C10: RELE INTERFACE 6A - 250V 24V AZUL | E10: TRUE | F10: 2 | G10: UN | H10: BXD2 ELEVATÓRIA LÚCIO TAVARES | I10: ANDREW | J10: MÁRCIOMC
A11: 17.09.25 | B11: 5001073 | C11: CABO ELETRICO 750V 1MM2 | E11: TRUE | F11: 1 | G11: M | H11: BXD2 ELEVATÓRIA LÚCIO TAVARES | I11: ANDREW | J11: MÁRCIOMC
A12: 17.09.25 | B12: 3000010 | C12: ABRAÇADEIRA SERRA COPO 3/4" | E12: TRUE | F12: 8 | G12: UN | H12: BXD2 OFICINA | I12: ALEXSANDRO / JHONATA | J12: MÁRCIOMC
A13: 17.09.25 | B13: 3006047 | C13: PARAFUSO AUTOATARRAXANTE PHILLIPS 3,5MMX6,5MM | E13: TRUE | F13: 15 | G13: UN | H13: BXD2 OFICINA | I13: ALEXSANDRO / JHONATA | J13: MÁRCIOMC
A14: 17.09.25 | B14: 3006163 | C14: PARAFUSO AÇO PB 4,2MMX13MM | E14: TRUE | F14: 15 | G14: UN | H14: BXD2 OFICINA | I14: ALEXSANDRO / JHONATA | J14: MÁRCIOMC
A15: 17.09.25 | B15: 5006821 | C15: LUVA PVC-R 1/2" | E15: TRUE | F15: 2 | G15: UN | H15: BXD2 OFICINA | I15: ALEXSANDRO / JHONATA | J15: MÁRCIOMC
A16: 17.09.25 | B16: 5025283 | C16: NIPLE PVC-R AF 1/2" | E16: TRUE | F16: 1 | G16: UN | H16: BXD2 OFICINA | I16: ALEXSANDRO / JHONATA | J16: MÁRCIOMC
A17: 19.09.25 | B17: 5025447 | C17: FITA ISOLANTE PR 750V 19MM P44 | E17: TRUE | F17: 1 | G17: UN | H17: BXD2 PREVENTIVA | I17: ALEXENDRE | J17: MÁRCIOMC
A18: 19.09.25 | B18: 5022362 | C18: CONTACTOR TRIPOLAR CAPACITOR CWMC32 | E18: TRUE | F18: 1 | G18: UN | H18: BXD2 ELEVATÓRIA MESQUITA G1 | I18: VAGNER / ALEXANDRE | J18: MÁRCIOMC
A19: 21.09.25 | B19: =_xlfn.XLOOKUP(C19,'Lista de Materiais'!B:B,'Lista de Materiais'!A:A) -> 5025447 | C19: FITA ISOLANTE AUTOFUSAO PT 10M 19MM | E19: TRUE | F19: 1 | G19: =_xlfn.XLOOKUP(B:B,'Lista de Materiais'!A:A,'Lista de Materiais'!C:C) -> UN | H19: BXD2 BOOSTER AUSTIN | I19: ERICK | J19: MÁRCIOMC
A20: 21.09.25 | B20: 3006225 | C20: PARAFUSO SEXT 5/8"X 2.1/2"" | E20: TRUE | F20: 5 | G20: UN | H20: BXD2 BOOSTER AUSTIN | I20: JORGE | J20: MÁRCIOMC
A21: 22.09.25 | B21: 5025447 | C21: FITA ISOLANTE PR 750V 19MM P44 | E21: TRUE | F21: 1 | G21: UN | H21: ATUALIZAÇÃO ESTOQUE | I21: ATUALIZAÇÃO ESTOQUE | J21: MÁRCIOMC
A22: 22.09.25 | B22: 5025447 | C22: FITA ISOLANTE AM 750V 19MM | E22: TRUE | F22: 1 | G22: UN | H22: ATUALIZAÇÃO ESTOQUE | I22: ATUALIZAÇÃO ESTOQUE | J22: MÁRCIOMC
A23: 22.09.25 | B23: =_xlfn.XLOOKUP(C23,'Lista de Materiais'!B:B,'Lista de Materiais'!A:A) -> #N/A | C23: CONTATOR TRIPOLAR AC 3 45A 400V | E23: TRUE | F23: 1 | G23: UN | H23: ELEVATÓRIA VILA RORAIMA | I23: ERICK | J23: MÁRCIOMC
A24: 23.09.25 | B24: 4007455 | C24: =_xlfn.XLOOKUP(B24,'Lista de Materiais'!A:A,'Lista de Materiais'!B:B) -> SELO MECANICO TS-P 1.1/4POL | E24: TRUE | F24: 1 | G24: UN | H24: ELEVATÓRIA VILA RORAIMA | I24: RONALDO / VALMIR | J24: MÁRCIOMC
A25: 23.09.25 | B25: =_xlfn.XLOOKUP(C25,'Lista de Materiais'!B:B,'Lista de Materiais'!A:A) -> #N/A | C25: TERMINAL ELETRIC OLHAL 1 FURO 4-6MM AMARELO | E25: TRUE | F25: 6 | G25: UN | H25: ELEVATÓRIA VILA RORAIMA | I25: RONALDO / VALMIR | J25: MÁRCIOMC
A26: 23.09.25 | B26: =_xlfn.XLOOKUP(C26,'Lista de Materiais'!B:B,'Lista de Materiais'!A:A) -> #N/A | C26: FUSÍVEL NH00 RETARDADO 63A | E26: TRUE | F26: 1 | G26: UN | H26: ELEVATÓRIA VILA RORAIMA | I26: RONALDO / VALMIR | J26: MÁRCIOMC
A27: 24.09.25 | B27: =_xlfn.XLOOKUP(C27,'Lista de Materiais'!B:B,'Lista de Materiais'!A:A) -> 3009830 | C27: PARAFUSO CHAVE PHILIPS AC 9MM 25MM 3,5MM | E27: TRUE | F27: 15 | G27: =_xlfn.XLOOKUP(B:B,'Lista de Materiais'!A:A,'Lista de Materiais'!C:C) -> UN | H27: OFICINA | I27: VAGNER / VINICIUS | J27: MÁRCIOMC
A28: 24.09.25 | B28: =_xlfn.XLOOKUP(C28,'Lista de Materiais'!B:B,'Lista de Materiais'!A:A) -> 5025447 | C28: FITA ISOLANTE AUTOFUSAO PT 10M 19MM | E28: TRUE | F28: 1 | G28: =_xlfn.XLOOKUP(B:B,'Lista de Materiais'!A:A,'Lista de Materiais'!C:C) -> UN | H28: PREVENTIVAS | I28: DOUGLAS | J28: ALEXSANDRO
A29: 24.09.25 | B29: =_xlfn.XLOOKUP(C29,'Lista de Materiais'!B:B,'Lista de Materiais'!A:A) -> #N/A | C29: FITA ISOL PR 750V 19MM ROL 20M P44 | E29: TRUE | F29: 1 | G29: =_xlfn.XLOOKUP(B:B,'Lista de Materiais'!A:A,'Lista de Materiais'!C:C) -> #N/A | H29: PREVENTIVAS | I29: DOUGLAS | J29: ALEXSANDRO
A30: 24.09.25 | B30: =_xlfn.XLOOKUP(C30,'Lista de Materiais'!B:B,'Lista de Materiais'!A:A) -> 5025447 | C30: FITA ISOLANTE AUTOFUSAO PT 10M 19MM | E30: TRUE | F30: 1 | G30: =_xlfn.XLOOKUP(B:B,'Lista de Materiais'!A:A,'Lista de Materiais'!C:C) -> UN | H30: ELEVATÓRIA DINAMARCO REIS | I30: ANDREW | J30: MÁRCIOMC
A31: 24.09.25 | B31: =_xlfn.XLOOKUP(C31,'Lista de Materiais'!B:B,'Lista de Materiais'!A:A) -> #N/A | C31: FITA ISOL PR 750V 19MM ROL 20M P44 | E31: TRUE | F31: 1 | G31: =_xlfn.XLOOKUP(B:B,'Lista de Materiais'!A:A,'Lista de Materiais'!C:C) -> #N/A | H31: ELEVATÓRIA DINAMARCO REIS | I31: ANDREW | J31: MÁRCIOMC
A32: 25.09.25 | B32: =_xlfn.XLOOKUP(C32,'Lista de Materiais'!B:B,'Lista de Materiais'!A:A) -> #N/A | C32: NIPLE PVC 3/4" | E32: TRUE | F32: 8 | G32: =_xlfn.XLOOKUP(B:B,'Lista de Materiais'!A:A,'Lista de Materiais'!C:C) -> #N/A | H32: ELEVATÓRIA CIRILO | I32: ANDREW / JHONATA | J32: MÁRCIOMC
A33: 25.09.25 | B33: =_xlfn.XLOOKUP(C33,'Lista de Materiais'!B:B,'Lista de Materiais'!A:A) -> #N/A | C33: TE PVC 3/4" | E33: TRUE | F33: 2 | G33: =_xlfn.XLOOKUP(B:B,'Lista de Materiais'!A:A,'Lista de Materiais'!C:C) -> #N/A | H33: ELEVATÓRIA CIRILO | I33: ANDREW / JHONATA | J33: MÁRCIOMC
A34: 25.09.25 | B34: =_xlfn.XLOOKUP(C34,'Lista de Materiais'!B:B,'Lista de Materiais'!A:A) -> #N/A | C34: LUVA PVC 3/4" | E34: TRUE | F34: 4 | G34: =_xlfn.XLOOKUP(B:B,'Lista de Materiais'!A:A,'Lista de Materiais'!C:C) -> #N/A | H34: ELEVATÓRIA CIRILO | I34: ANDREW / JHONATA | J34: MÁRCIOMC
A35: 25.09.25 | B35: =_xlfn.XLOOKUP(C35,'Lista de Materiais'!B:B,'Lista de Materiais'!A:A) -> #N/A | C35: JOELHP PVC 90X3/4" | E35: TRUE | F35: 2 | G35: =_xlfn.XLOOKUP(B:B,'Lista de Materiais'!A:A,'Lista de Materiais'!C:C) -> #N/A | H35: ELEVATÓRIA CIRILO | I35: ANDREW / JHONATA | J35: MÁRCIOMC
A36: 25.09.25 | B36: =_xlfn.XLOOKUP(C36,'Lista de Materiais'!B:B,'Lista de Materiais'!A:A) -> #N/A | C36: LUVA RED PVC-R AF 1"X3/4" | E36: TRUE | F36: 1 | G36: =_xlfn.XLOOKUP(B:B,'Lista de Materiais'!A:A,'Lista de Materiais'!C:C) -> #N/A | H36: ELEVATÓRIA CIRILO | I36: ANDREW / JHONATA | J36: MÁRCIOMC
A37: 25.09.25 | B37: =_xlfn.XLOOKUP(C37,'Lista de Materiais'!B:B,'Lista de Materiais'!A:A) -> #N/A | C37: ELETRO HASTE METAL 3/4" | E37: TRUE | F37: 2 | G37: =_xlfn.XLOOKUP(B:B,'Lista de Materiais'!A:A,'Lista de Materiais'!C:C) -> #N/A | H37: ELEVATÓRIA CIRILO | I37: ANDREW / JHONATA | J37: MÁRCIOMC
A38: 25.09.25 | B38: =_xlfn.XLOOKUP(C38,'Lista de Materiais'!B:B,'Lista de Materiais'!A:A) -> #N/A | C38: FITA VEDA ROSCA BR | E38: TRUE | F38: 1 | G38: =_xlfn.XLOOKUP(B:B,'Lista de Materiais'!A:A,'Lista de Materiais'!C:C) -> #N/A | H38: ELEVATÓRIA CIRILO | I38: ANDREW / JHONATA | J38: MÁRCIOMC
A39: 25.09.25 | B39: =_xlfn.XLOOKUP(C39,'Lista de Materiais'!B:B,'Lista de Materiais'!A:A) -> #N/A | C39: ELETRODO DE NIVEL | D39: USADO | E39: TRUE | F39: 1 | G39: =_xlfn.XLOOKUP(B:B,'Lista de Materiais'!A:A,'Lista de Materiais'!C:C) -> #N/A | H39: ELEVATÓRIA CIRILO | I39: ANDREW / JHONATA | J39: MÁRCIOMC
A40: 25.09.25 | B40: =_xlfn.XLOOKUP(C40,'Lista de Materiais'!B:B,'Lista de Materiais'!A:A) -> #N/A | C40: TIMER DIGITA | D40: USADO | E40: TRUE | F40: 1 | G40: =_xlfn.XLOOKUP(B:B,'Lista de Materiais'!A:A,'Lista de Materiais'!C:C) -> #N/A | H40: ELEVATÓRIA CIRILO | I40: ANDREW / JHONATA | J40: MÁRCIOMC
A41: 25.09.25 | B41: =_xlfn.XLOOKUP(C41,'Lista de Materiais'!B:B,'Lista de Materiais'!A:A) -> #N/A | C41: RELE DE TEMPO | D41: USADO | E41: TRUE | F41: 2 | G41: =_xlfn.XLOOKUP(B:B,'Lista de Materiais'!A:A,'Lista de Materiais'!C:C) -> #N/A | H41: ELEVATÓRIA CIRILO | I41: ANDREW / JHONATA | J41: MÁRCIOMC
A42: 25.09.25 | B42: =_xlfn.XLOOKUP(C42,'Lista de Materiais'!B:B,'Lista de Materiais'!A:A) -> #N/A | C42: VENTOSA 1" | D42: USADO | E42: TRUE | F42: 1 | G42: =_xlfn.XLOOKUP(B:B,'Lista de Materiais'!A:A,'Lista de Materiais'!C:C) -> #N/A | H42: ELEVATÓRIA CIRILO | I42: ANDREW / JHONATA | J42: MÁRCIOMC
A43: 26.09.25 | B43: =_xlfn.XLOOKUP(C43,'Lista de Materiais'!B:B,'Lista de Materiais'!A:A) -> 4003530 | C43: ROLAMENTO ESF RIG 6314 SKF | E43: TRUE | F43: 2 | G43: =_xlfn.XLOOKUP(B:B,'Lista de Materiais'!A:A,'Lista de Materiais'!C:C) -> UN | H43: BOOSTER MESQUITA G01 | I43: JORGE | J43: MÁRCIOMC
A44: 26.09.25 | B44: =_xlfn.XLOOKUP(C44,'Lista de Materiais'!B:B,'Lista de Materiais'!A:A) -> 4007458 | C44: SELO MECANICO TS-P 1.3/4POL | E44: TRUE | F44: 1 | G44: =_xlfn.XLOOKUP(B:B,'Lista de Materiais'!A:A,'Lista de Materiais'!C:C) -> UN | H44: BOOSTER MESQUITA G01 | I44: JORGE | J44: MÁRCIOMC
A45: 29.09.25 | B45: =_xlfn.XLOOKUP(C45,'Lista de Materiais'!B:B,'Lista de Materiais'!A:A) -> 5024639 | C45: FITA VEDA ROSCA BR 18MM ROL 50M | E45: TRUE | F45: 1 | G45: =_xlfn.XLOOKUP(B:B,'Lista de Materiais'!A:A,'Lista de Materiais'!C:C) -> UN | H45: ELEVATÓRIA K11 | I45: CLOVIS / VAGNER | J45: MÁRCIOMC
A46: 29.09.25 | B46: =_xlfn.XLOOKUP(C46,'Lista de Materiais'!B:B,'Lista de Materiais'!A:A) -> 5023372 | C46: REGISTRO GAV COBRE RF VOL 2POL PN10 | E46: TRUE | F46: 1 | G46: =_xlfn.XLOOKUP(B:B,'Lista de Materiais'!A:A,'Lista de Materiais'!C:C) -> UN | H46: ELEVATÓRIA K11 | I46: CLOVIS / VAGNER | J46: MÁRCIOMC
A47: 30.09.25 | B47: =_xlfn.XLOOKUP(C47,'Lista de Materiais'!B:B,'Lista de Materiais'!A:A) -> #N/A | C47: RELE TEMPORIZADOR 220/240V 1NAF 3S-30S ( SEGUNDOS ) | E47: TRUE | F47: 1 | G47: =_xlfn.XLOOKUP(B:B,'Lista de Materiais'!A:A,'Lista de Materiais'!C:C) -> #N/A | H47: ELEVATÓRIA MESQUITA G1 | I47: VAGNER | J47: MÁRCIOMC
A48: 30.09.25 | B48: =_xlfn.XLOOKUP(C48,'Lista de Materiais'!B:B,'Lista de Materiais'!A:A) -> #N/A | C48: DISJUNTOR MINI 3P 220 3XC80A | E48: TRUE | F48: 1 | G48: =_xlfn.XLOOKUP(B:B,'Lista de Materiais'!A:A,'Lista de Materiais'!C:C) -> #N/A | H48: ELEVATORIA YULANDA | I48: ERICK / PAULO | J48: MÁRCIOMC
A49: 30.09.25 | B49: =_xlfn.XLOOKUP(C49,'Lista de Materiais'!B:B,'Lista de Materiais'!A:A) -> #N/A | C49: FITA ISOL PR 750V 19MM ROL 20M P44 | E49: TRUE | F49: 1 | G49: =_xlfn.XLOOKUP(B:B,'Lista de Materiais'!A:A,'Lista de Materiais'!C:C) -> #N/A | H49: ELEVATORIA YULANDA | I49: ERICK / PAULO | J49: MÁRCIOMC
A50: 30.09.25 | B50: =_xlfn.XLOOKUP(C50,'Lista de Materiais'!B:B,'Lista de Materiais'!A:A) -> 4007727 | C50: ROLAMENTO ESF RIG 6309-2Z/C3 SKF | E50: TRUE | F50: 4 | G50: =_xlfn.XLOOKUP(B:B,'Lista de Materiais'!A:A,'Lista de Materiais'!C:C) -> UN | H50: BXD1 | I50: WILLIAN | J50: MÁRCIOMC
A51: 01.10.25 | B51: =_xlfn.XLOOKUP(C51,'Lista de Materiais'!B:B,'Lista de Materiais'!A:A) -> #N/A | C51: JOELHO 90 PVC-R AF 2 POL | E51: TRUE | F51: 3 | G51: =_xlfn.XLOOKUP(B:B,'Lista de Materiais'!A:A,'Lista de Materiais'!C:C) -> #N/A | H51: ELEVATÓRIA DINAMARCO REIS | I51: JHONATA | J51: MÁRCIOMC
A52: 01.10.25 | B52: =_xlfn.XLOOKUP(C52,'Lista de Materiais'!B:B,'Lista de Materiais'!A:A) -> 5012947 | C52: UNIAO PVC-R AF RF DE2POL | E52: TRUE | F52: 1 | G52: =_xlfn.XLOOKUP(B:B,'Lista de Materiais'!A:A,'Lista de Materiais'!C:C) -> UN | H52: ELEVATÓRIA DINAMARCO REIS | I52: JHONATA | J52: MÁRCIOMC
A53: 01.10.25 | B53: =_xlfn.XLOOKUP(C53,'Lista de Materiais'!B:B,'Lista de Materiais'!A:A) -> #N/A | C53: VALVULA RET VERT LT 2POL PN16 | E53: TRUE | F53: 1 | G53: =_xlfn.XLOOKUP(B:B,'Lista de Materiais'!A:A,'Lista de Materiais'!C:C) -> #N/A | H53: ELEVATÓRIA DINAMARCO REIS | I53: JHONATA | J53: MÁRCIOMC
A54: 01.10.25 | B54: =_xlfn.XLOOKUP(C54,'Lista de Materiais'!B:B,'Lista de Materiais'!A:A) -> 5024639 | C54: FITA VEDA ROSCA BR 18MM ROL 50M | E54: TRUE | F54: 1 | G54: =_xlfn.XLOOKUP(B:B,'Lista de Materiais'!A:A,'Lista de Materiais'!C:C) -> UN | H54: ELEVATÓRIA DINAMARCO REIS | I54: JHONATA | J54: MÁRCIOMC
... A70: 06.10.25 | B70: =_xlfn.XLOOKUP(C70,'Lista de Materiais'!B:B,'Lista de Materiais'!A:A) -> #N/A | C70: TERMINAL ELETRIC OLHAL 1 FURO 4-6MM AMARELO | E70: TRUE | F70: 6 | G70: =_xlfn.XLOOKUP(B:B,'Lista de Materiais'!A:A,'Lista de Materiais'!C:C) -> #N/A | H70: BXD2 PREVENTIVA GERAL | I70: ALEXANDRE | J70: LETICIABORGES
A71: 04.10.25 | B71: 5000942 | C71: CABO FLEXIVEL PP 750V4X10MM2 PT | E71: TRUE | F71: 7 | G71: M | H71: ELEVATORIA MORRO DA MOENDA | I71: ALEXSANDRO | J71: ALEXSANDRO
A72: 04.10.25 | B72: 5024527 | C72: FITA ISOL PR 750V 19MM ROL 20M P44 | E72: TRUE | F72: 2 | G72: UN | H72: ELEVATORIA MORRO DA MOENDA | I72: ALEXSANDRO | J72: ALEXSANDRO
A73: 04.10.25 | B73: 5534866 | C73: FITA AUTA TENSÃO FUSÃO19MMX10MTS | E73: TRUE | F73: 2 | G73: UN | H73: ELEVATORIA MORRO DA MOENDA | I73: ALEXSANDRO | J73: ALEXSANDRO
A74: 04.10.25 | B74: 5023084 | C74: DISCO CORTE S/REV 115MM 22,22MM 1MM META | E74: TRUE | F74: 1 | G74: UN | H74: ELEVATORIA MORRO DA MOENDA | I74: ALEXSANDRO | J74: ALEXSANDRO
A75: 06.10.25 | B75: 4007727 | C75: ROLAMENTO ESF RIG 6309-2Z/C3 SKF | E75: TRUE | F75: 1 | G75: UN | H75: ELEVATORIA MARCIEL | I75: VALMIR | J75: MÁRCIOMC
A76: 06.10.25 | B76: 4003591/4003590 | C76: ROLAMENTO ESF RIG 6207-2Z SKF | E76: TRUE | F76: 1 | G76: UN | H76: ELEVATORIA MARCIEL | I76: VALMIR | J76: LETICIABORGES
A77: 06.10.25 | B77: 4007455 | C77: =_xlfn.XLOOKUP(B77,'Lista de Materiais'!A:A,'Lista de Materiais'!B:B) -> SELO MECANICO TS-P 1.1/4POL | E77: TRUE | F77: 1 | G77: UN | H77: ELEVATORIA MARCIEL | I77: VALMIR | J77: LETICIABORGES
A78: 06.10.25 | B78: 5018562 | C78: RELE MODULAR INTERFACE 6A 250V 24V AZUL | E78: TRUE | F78: 2 | G78: UN | H78: ELEVATÓRIA PAIOL | I78: ANDREW | J78: LETICIABORGES
A79: 06.10.25 | B79: 3009327 | C79: ABRACADEIRA BAP AC GALV 1200MM 33 FUROS | E79: TRUE | F79: 2 | G79: UN | H79: ELEVATÓRIA PAIOL | I79: ANDREW | J79: LETICIABORGES
A80: 06.10.25 | B80: 4003682 | C80: ROLAMENTO ESF RIG 6209-2Z SKF | E80: TRUE | F80: 1 | G80: UN | H80: ELEVATÓRIA ESPLANADA | I80: ANDRÉ / ALEXANDRE | J80: LETICIABORGES
A81: 07.10.25 | B81: 5504935 | C81: TERMINAL PINO COM 16MM COR AZUL | E81: TRUE | F81: 9 | G81: UN | H81: ELEVATÓRIA MORRO DA MOENDA | I81: VAGNER / CLÓVIS | J81: LETICIABORGES
A82: 08.10.25 | B82: 5501606 | C82: =_xlfn.XLOOKUP(B82,'Lista de Materiais'!A:A,'Lista de Materiais'!B:B) -> BOMBA SUBMERSIVEL 8,6M3/H 8,5MCA 0,5CV | E82: TRUE | F82: 1 | G82: UN | H82: ELEVATÓRIA GOLDEN GATE | I82: JHONATA / VINICIUS | J82: LETICIABORGES | K82: RJB-24177
A83: 08.10.25 | B83: 5024527 | C83: FITA ISOL PR 750V 19MM ROL 20M P44 | E83: TRUE | F83: 1 | G83: UN | H83: ELEVATÓRIA GOLDEN GATE | I83: JHONATA / VINICIUS | J83: LETICIABORGES
A84: 09.10.25 | B84: 5005941 | C84: JOELHO 90° PVC-R AF RF DE 2POL | E84: TRUE | F84: 4 | G84: UN | H84: ELEVATÓRIA GOLDEN GATE | I84: JHONATA / VINICIUS | J84: LETICIABORGES
A85: 09.10.25 | B85: 5006723 | C85: LUVA GALV RF BSP D 2" | E85: TRUE | F85: 1 | G85: UN | H85: ELEVATÓRIA GOLDEN GATE | I85: JHONATA / VINICIUS | J85: LETICIABORGES
A86: 09.10.25 | B86: 5504189 | C86: CHAVE BOIA NIVEL 25A INF/SUP CABO 1,5M/1,2M | E86: TRUE | F86: 1 | G86: UN | H86: ELEVATÓRIA GOLDEN GATE | I86: JHONATA / VINICIUS | J86: LETICIABORGES
A87: 09.10.25 | B87: 5006824 | C87: LUVA PVC-R AF RF DE 2POL | E87: TRUE | F87: 1 | G87: UN | H87: ELEVATÓRIA GOLDEN GATE | I87: JHONATA / VINICIUS | J87: LETICIABORGES
A88: 10.10.25 | B88: 5009024 | C88: RELE SOBRECARGA 3P 4 A 6,3A 690V CC | E88: TRUE | F88: 1 | G88: UN | H88: ELEVATÓRIA GOLDEN GATE | I88: JHONATA / VINICIUS | J88: LETICIABORGES
A89: 10.10.25 | B89: 5003469 | C89: CONTATOR PRINCIPAL 3P 32A 220VCA 1NA | E89: TRUE | F89: 1 | G89: UN | H89: ELEVATÓRIA GOLDEN GATE | I89: JHONATA / VINICIUS | J89: LETICIABORGES
A90: 13.10.25 | B90: 5004199 | C90: DISCO CORTE S/REV 4.1/2POL 1/8POL AI | E90: TRUE | F90: 2 | G90: UN | H90: ELEVATÓRIA ESPLANADA | I90: JHONATA | J90: LETICIABORGES
A91: 14.10.25 | B91: 4009169 | C91: ELEMENTO ELASTICO ACOPLAMENTO E-148 VULKAN | E91: TRUE | F91: 1 | G91: UN | H91: BOOSTER BRASÍLIA | I91: DOUGLAS / DIEGO | J91: LETICIABORGES
A92: 15.10.25 | B92: 5003474 | C92: CONTATOR AC - 3 40A 400V 18,5KW 220V 50Hz/60Hz 11E 1NO+1NC | E92: TRUE | F92: 1 | G92: UN | H92: ELEVATÓRIA PALHADA | I92: ANDREW | J92: LETICIABORGES
A93: 15.10.25 | B93: 5009024 | C93: RELE SOBRECARGA 3P 4 A 6,3A 690V CC | E93: TRUE | F93: 1 | G93: UN | H93: ELEVATÓRIA PALHADA | I93: ANDREW | J93: LETICIABORGES
A94: 15.10.25 | B94: 5004369 | C94: DISJUNTOR MINI 2P 400VCA 2XC10 | E94: TRUE | F94: 1 | G94: UN | H94: ELEVATÓRIA PALHADA | I94: ANDREW | J94: LETICIABORGES
A95: 15.10.25 | B95: 5004512 | C95: DISJUNTOR MINI 3P 400VCA 3XC10 | E95: TRUE | F95: 1 | G95: UN | H95: ELEVATÓRIA PALHADA | I95: ANDREW | J95: LETICIABORGES
A96: 15.10.25 | B96: 5008987 | C96: RELE FALTA FASE 220V CA 5 A RMW17-FF01D65 | E96: TRUE | F96: 1 | G96: UN | H96: ELEVATÓRIA MONTE LÍBANO | I96: VAGNER | J96: LETICIABORGES
A97: 15.10.25 | B97: 5018562 | C97: RELE MODULAR INTERFACE 6A 250V 24V AZUL | E97: TRUE | F97: 3 | G97: UN | H97: ELEVATÓRIA PALHADA | I97: ANDREW | J97: LETICIABORGES
A98: 15.10.25 | B98: 5005941 | C98: JOELHO 90° PVC-R AF RF DE 2POL | E98: TRUE | F98: 4 | G98: UN | H98: ELEVATÓRIA PALHADA | I98: JHONATA | J98: LETICIABORGES
A99: 15.10.25 | B99: 5012974 | C99: UNIÃO PVC 2" | E99: TRUE | F99: 1 | G99: UN | H99: ELEVATÓRIA PALHADA | I99: JHONATA | J99: LETICIABORGES
A100: 15.10.25 | B100: 5006723 | C100: LUVA GALV RF BSP D 2" | E100: TRUE | F100: 1 | G100: UN | H100: ELEVATÓRIA PALHADA | I100: JHONATA | J100: LETICIABORGES
A101: 15.10.25 | B101: 5018308 | C101: NIPLE FERRO GALV. 2" | E101: TRUE | F101: 1 | G101: UN | H101: ELEVATÓRIA PALHADA | I101: JHONATA | J101: LETICIABORGES
A102: 15.10.25 | B102: 5516065 | C102: VALVULA RET VERT LT 2POL PN16 | E102: TRUE | F102: 1 | G102: UN | H102: ELEVATÓRIA PALHADA | I102: JHONATA | J102: LETICIABORGES
A103: 16.10.25 | B103: 5024527 | C103: FITA ISOL PR 750V 19MM ROL 20M P44 | E103: TRUE | F103: 1 | G103: UN | H103: PREVENTIVA GERAL | I103: MÁRCIO LEANDRO | J103: LETICIABORGES
A104: 16.10.25 | B104: 5501606 | C104: =_xlfn.XLOOKUP(B104,'Lista de Materiais'!A:A,'Lista de Materiais'!B:B) -> BOMBA SUBMERSIVEL 8,6M3/H 8,5MCA 0,5CV | E104: TRUE | F104: 1 | G104: UN | H104: ELEVATÓRIA PALHADA | I104: VINICIUS | J104: LETICIABORGES | K104: RJB-23382
A105: 16.10.25 | B105: 5504189 | C105: CHAVE BOIA NIVEL 25A INF/SUP CABO 1,5M/1,2M | E105: TRUE | F105: 1 | G105: UN | H105: ELEVATÓRIA PALHADA | I105: VINICIUS | J105: LETICIABORGES
A106: 16.10.25 | B106: 5000938 | C106: CABO FLEXIVEL PP 1KV 3X1,5MM PRETO | E106: TRUE | F106: 35 | G106: M | H106: ELEVATÓRIA PALHADA | I106: VINICIUS | J106: LETICIABORGES
A107: 16.10.25 | B107: 5008987 | C107: RELE FALTA FASE 220V CA 5 A RMW17-FF01D65 | E107: TRUE | F107: 1 | G107: UN | H107: BOMBA VOLANTE DE QUEIMADOS | I107: VAGNER | J107: LETICIABORGES
A108: 16.10.25 | B108: 5024639 | C108: FITA VEDA ROSCA BR 18MM ROL 50M | E108: TRUE | F108: 1 | G108: UN | H108: BOMBA VOLANTE DE QUEIMADOS | I108: VAGNER | J108: LETICIABORGES
A109: 16.10.25 | B109: 5000942 | C109: CABO FLEXIVEL PP 750V4X10MM2 PT | E109: TRUE | F109: 90 | G109: M | H109: BOMBA VOLANTE DE QUEIMADOS | I109: VAGNER | J109: LETICIABORGES
A110: 16.10.25 | B110: 5513949 | C110: CONECTOR PARAFUSO FENDIDO 70MM2 3A KS23 BURNDY | E110: TRUE | F110: 3 | G110: UN | H110: BOMBA VOLANTE DE QUEIMADOS | I110: VAGNER | J110: LETICIABORGES
A111: 16.10.25 | B111: 5513951 | C111: CONECTOR PARAFUSO FENDIDO 120MM2 3A KS23 BURNDY | E111: TRUE | F111: 1 | G111: UN | H111: BOMBA VOLANTE DE QUEIMADOS | I111: VAGNER | J111: LETICIABORGES
A112: 16.10.25 | B112: 5513948 | C112: CONECTOR PARAFUSO FENDIDO 35MM2 3A KS23 BURNDY | E112: TRUE | F112: 4 | G112: UN | H112: BOMBA VOLANTE DE QUEIMADOS | I112: VAGNER | J112: LETICIABORGES
A113: 16.10.25 | B113: 5021333 | C113: CABO ELET FLEX 0,6/1KV 70MM2 CL5 PT | E113: TRUE | F113: 10 | G113: M | H113: ELEVATÓRIA NOÊMIA VIEIRA | I113: MÁRCIO / JORGE | J113: LETICIABORGES
A114: 16.10.25 | B114: 5504630 | C114: TERMINAL ELET COMP 95MM2 | E114: TRUE | F114: 6 | G114: UN | H114: ELEVATÓRIA NOÊMIA VIEIRA | I114: MÁRCIO / JORGE | J114: LETICIABORGES
A115: 16.10.25 | B115: 5534866 | C115: FITA AUTA TENSÃO FUSÃO19MMX10MTS | E115: TRUE | F115: 1 | G115: UN | H115: ELEVATÓRIA NOÊMIA VIEIRA | I115: MÁRCIO / JORGE | J115: LETICIABORGES
...

Sheet ESTOQUE BXD2
A1: ✏️ Manual | B1: ✏️ Manual | C1: ✏️ Manual | D1: ✅ Fórmula | E1: ✅ Fórmula | F1: ✅ Fórmula | G1: ✏️ Manual
A2: Cod.SAP | C2: unidade | D2: Entrada | E2: Saída | F2: Saldo Estoque | G2: ATUALIZAÇÃO
A3: =_xlfn.XLOOKUP(B3,'Entrada de Materiais'!C:C,'Entrada de Materiais'!B:B) -> 4010017 | B3: *ROLAMENTO ESF RIG 6226/C3 SKF | C3: UND | D3: =SUMIFS('Entrada de Materiais'!D:D, 'Entrada de Materiais'!C:C, B3) -> 4 | E3: =SUMIFS('SAIDA DE MATERIAIS'!F:F,'SAIDA DE MATERIAIS'!C:C,B3) -> 2 | F3: =+D3-E3 -> 2
A4: =_xlfn.XLOOKUP(B4,'Entrada de Materiais'!C:C,'Entrada de Materiais'!B:B) -> 5532022 | B4: _CHAVE SECCIONADORA POTENCIA - 160 A | C4: UND | D4: =SUMIFS('Entrada de Materiais'!D:D, 'Entrada de Materiais'!C:C, B4) -> 1 | E4: =SUMIFS('SAIDA DE MATERIAIS'!F:F,'SAIDA DE MATERIAIS'!C:C,B4) -> 0 | F4: =+D4-E4 -> 1
A5: =_xlfn.XLOOKUP(B5,'Entrada de Materiais'!C:C,'Entrada de Materiais'!B:B) -> 5532023 | B5: _CHAVE SECCIONADORA POTENCIA - 250 A | C5: UND | D5: =SUMIFS('Entrada de Materiais'!D:D, 'Entrada de Materiais'!C:C, B5) -> 2 | E5: =SUMIFS('SAIDA DE MATERIAIS'!F:F,'SAIDA DE MATERIAIS'!C:C,B5) -> 0 | F5: =+D5-E5 -> 2
A6: =_xlfn.XLOOKUP(B6,'Entrada de Materiais'!C:C,'Entrada de Materiais'!B:B) -> 5532024 | B6: _CHAVE SECCIONADORA POTENCIA - 400 A | C6: UND | D6: =SUMIFS('Entrada de Materiais'!D:D, 'Entrada de Materiais'!C:C, B6) -> 2 | E6: =SUMIFS('SAIDA DE MATERIAIS'!F:F,'SAIDA DE MATERIAIS'!C:C,B6) -> 0 | F6: =+D6-E6 -> 2
A7: =_xlfn.XLOOKUP(B7,'Entrada de Materiais'!C:C,'Entrada de Materiais'!B:B) -> 5532025 | B7: _CHAVE SECCIONADORA POTENCIA - 630 A | C7: UND | D7: =SUMIFS('Entrada de Materiais'!D:D, 'Entrada de Materiais'!C:C, B7) -> 2 | E7: =SUMIFS('SAIDA DE MATERIAIS'!F:F,'SAIDA DE MATERIAIS'!C:C,B7) -> 0 | F7: =+D7-E7 -> 2
A8: =_xlfn.XLOOKUP(B8,'Entrada de Materiais'!C:C,'Entrada de Materiais'!B:B) -> 5532031 | B8: _CHAVE SECCIONADORA PUNHO 3P 250A C/FUS | C8: UND | D8: =SUMIFS('Entrada de Materiais'!D:D, 'Entrada de Materiais'!C:C, B8) -> 1 | E8: =SUMIFS('SAIDA DE MATERIAIS'!F:F,'SAIDA DE MATERIAIS'!C:C,B8) -> 0 | F8: =+D8-E8 -> 1
A9: =_xlfn.XLOOKUP(B9,'Entrada de Materiais'!C:C,'Entrada de Materiais'!B:B) -> 5028401 | B9: _CONTATOR 3P 220V CA 1NA 80A | C9: UND | D9: =SUMIFS('Entrada de Materiais'!D:D, 'Entrada de Materiais'!C:C, B9) -> 2 | E9: =SUMIFS('SAIDA DE MATERIAIS'!F:F,'SAIDA DE MATERIAIS'!C:C,B9) -> 0 | F9: =+D9-E9 -> 2
A10: =_xlfn.XLOOKUP(B10,'Entrada de Materiais'!C:C,'Entrada de Materiais'!B:B) -> 5029619 | B10: _RELE SOBRECARGA TERMICO REG 95-120A | C10: UND | D10: =SUMIFS('Entrada de Materiais'!D:D, 'Entrada de Materiais'!C:C, B10) -> 1 | E10: =SUMIFS('SAIDA DE MATERIAIS'!F:F,'SAIDA DE MATERIAIS'!C:C,B10) -> 0 | F10: =+D10-E10 -> 1
A11: =_xlfn.XLOOKUP(B11,'Entrada de Materiais'!C:C,'Entrada de Materiais'!B:B) -> #N/A | B11: _TRANSMISSOR PRESSAO AI A1 TIPO G 0-6BAR | C11: UND | D11: =SUMIFS('Entrada de Materiais'!D:D, 'Entrada de Materiais'!C:C, B11) -> 0 | E11: =SUMIFS('SAIDA DE MATERIAIS'!F:F,'SAIDA DE MATERIAIS'!C:C,B11) -> 0 | F11: =+D11-E11 -> 0
A12: =_xlfn.XLOOKUP(B12,'Entrada de Materiais'!C:C,'Entrada de Materiais'!B:B) -> 3009327 | B12: ABRACADEIRA BAP AC GALV 1200MM 33 FUROS | C12: UND | D12: =SUMIFS('Entrada de Materiais'!D:D, 'Entrada de Materiais'!C:C, B12) -> 23 | E12: =SUMIFS('SAIDA DE MATERIAIS'!F:F,'SAIDA DE MATERIAIS'!C:C,B12) -> 1 | F12: =+D12-E12 -> 22
A13: =_xlfn.XLOOKUP(B13,'Entrada de Materiais'!C:C,'Entrada de Materiais'!B:B) -> 3000011 | B13: ABRACADEIRA COP AC 1020 CZ 1POL 25,4MM | C13: UND | D13: =SUMIFS('Entrada de Materiais'!D:D, 'Entrada de Materiais'!C:C, B13) -> 3 | E13: =SUMIFS('SAIDA DE MATERIAIS'!F:F,'SAIDA DE MATERIAIS'!C:C,B13) -> 0 | F13: =+D13-E13 -> 3
A14: =_xlfn.XLOOKUP(B14,'Entrada de Materiais'!C:C,'Entrada de Materiais'!B:B) -> 3000010 | B14: ABRACADEIRA COP AC 1020 NAT 3/4POL | C14: UND | D14: =SUMIFS('Entrada de Materiais'!D:D, 'Entrada de Materiais'!C:C, B14) -> 3 | E14: =SUMIFS('SAIDA DE MATERIAIS'!F:F,'SAIDA DE MATERIAIS'!C:C,B14) -> 0 | F14: =+D14-E14 -> 3
... A44: =_xlfn.XLOOKUP(B44,'Entrada de Materiais'!C:C,'Entrada de Materiais'!B:B) -> 5025255 | B44: BARRA ROSCADA AC 1POL UNC 1M | C44: UND | D44: =SUMIFS('Entrada de Materiais'!D:D, 'Entrada de Materiais'!C:C, B44) -> 8 | E44: =SUMIFS('SAIDA DE MATERIAIS'!F:F,'SAIDA DE MATERIAIS'!C:C,B44) -> 0 | F44: =+D44-E44 -> 8
A45: =_xlfn.XLOOKUP(B45,'Entrada de Materiais'!C:C,'Entrada de Materiais'!B:B) -> 5024701 | B45: BARRA ROSCADA DE AÇO 1/2" X 1000 | C45: UND | D45: 8 | E45: =SUMIFS('SAIDA DE MATERIAIS'!F:F,'SAIDA DE MATERIAIS'!C:C,B45) -> 0 | F45: =+D45-E45 -> 8
A46: =_xlfn.XLOOKUP(B46,'Entrada de Materiais'!C:C,'Entrada de Materiais'!B:B) -> 5024706 | B46: BARRA ROSCADA DE AÇO 3/4" X 1000 | C46: UND | D46: =SUMIFS('Entrada de Materiais'!D:D, 'Entrada de Materiais'!C:C, B46) -> 13 | E46: =SUMIFS('SAIDA DE MATERIAIS'!F:F,'SAIDA DE MATERIAIS'!C:C,B46) -> 0 | F46: =+D46-E46 -> 13
A47: =_xlfn.XLOOKUP(B47,'Entrada de Materiais'!C:C,'Entrada de Materiais'!B:B) -> 5024711 | B47: BARRA ROSCADA DE AÇO 5/8" X 1000 | C47: UND | D47: =SUMIFS('Entrada de Materiais'!D:D, 'Entrada de Materiais'!C:C, B47) -> 12 | E47: =SUMIFS('SAIDA DE MATERIAIS'!F:F,'SAIDA DE MATERIAIS'!C:C,B47) -> 0 | F47: =+D47-E47 -> 12
A48: =_xlfn.XLOOKUP(B48,'Entrada de Materiais'!C:C,'Entrada de Materiais'!B:B) -> 5024713 | B48: BARRA ROSCADA DE AÇO 7/8" X 1000 | C48: UND | D48: =SUMIFS('Entrada de Materiais'!D:D, 'Entrada de Materiais'!C:C, B48) -> 1 | E48: =SUMIFS('SAIDA DE MATERIAIS'!F:F,'SAIDA DE MATERIAIS'!C:C,B48) -> 0 | F48: =+D48-E48 -> 1
A49: =_xlfn.XLOOKUP(B49,'Entrada de Materiais'!C:C,'Entrada de Materiais'!B:B) -> 5000324 | B49: BASE RELE RET PT 250V 10A 15,6MM | C49: UND | D49: =SUMIFS('Entrada de Materiais'!D:D, 'Entrada de Materiais'!C:C, B49) -> 53 | E49: =SUMIFS('SAIDA DE MATERIAIS'!F:F,'SAIDA DE MATERIAIS'!C:C,B49) -> 0 | F49: =+D49-E49 -> 53
A50: =_xlfn.XLOOKUP(B50,'Entrada de Materiais'!C:C,'Entrada de Materiais'!B:B) -> 5000315 | B50: BASE UNIPOLAR 250A /690v | C50: UND | D50: =SUMIFS('Entrada de Materiais'!D:D, 'Entrada de Materiais'!C:C, B50) -> 1 | E50: =SUMIFS('SAIDA DE MATERIAIS'!F:F,'SAIDA DE MATERIAIS'!C:C,B50) -> 0 | F50: =+D50-E50 -> 1
A51: =_xlfn.XLOOKUP(B51,'Entrada de Materiais'!C:C,'Entrada de Materiais'!B:B) -> 4007463 | B51: BATERIA ALCAL RECARREGAVEL 9V 250MAH | C51: UNID | D51: =SUMIFS('Entrada de Materiais'!D:D, 'Entrada de Materiais'!C:C, B51) -> 20 | E51: =SUMIFS('SAIDA DE MATERIAIS'!F:F,'SAIDA DE MATERIAIS'!C:C,B51) -> 0 | F51: =+D51-E51 -> 20
A52: =_xlfn.XLOOKUP(B52,'Entrada de Materiais'!C:C,'Entrada de Materiais'!B:B) -> 5023164 | B52: BLOCO CONTATO AUX 2NA+2NF | C52: UND | D52: =SUMIFS('Entrada de Materiais'!D:D, 'Entrada de Materiais'!C:C, B52) -> 2 | E52: =SUMIFS('SAIDA DE MATERIAIS'!F:F,'SAIDA DE MATERIAIS'!C:C,B52) -> 0 | F52: =+D52-E52 -> 2
A53: =_xlfn.XLOOKUP(B53,'Entrada de Materiais'!C:C,'Entrada de Materiais'!B:B) -> 5517135 | B53: BOMBA CENTRIFUCA AG 125L/S 85MCA | C53: UND | D53: =SUMIFS('Entrada de Materiais'!D:D, 'Entrada de Materiais'!C:C, B53) -> 0 | E53: =SUMIFS('SAIDA DE MATERIAIS'!F:F,'SAIDA DE MATERIAIS'!C:C,B53) -> 0 | F53: =+D53-E53 -> 0
A54: 5501606 | B54: BOMBA SUBMERSIVEL 8,6M3/H 8,5MCA 0,5CV | C54: UND | D54: =SUMIFS('Entrada de Materiais'!D:D, 'Entrada de Materiais'!C:C, B54) -> 8 | E54: =SUMIFS('SAIDA DE MATERIAIS'!F:F,'SAIDA DE MATERIAIS'!C:C,B54) -> 0 | F54: =+D54-E54 -> 8
A55: =_xlfn.XLOOKUP(B55,'Entrada de Materiais'!C:C,'Entrada de Materiais'!B:B) -> 5503631 | B55: BOTÃO DE COMANDO 22MM COR VERDE | C55: UND | D55: =SUMIFS('Entrada de Materiais'!D:D, 'Entrada de Materiais'!C:C, B55) -> 0 | E55: =SUMIFS('SAIDA DE MATERIAIS'!F:F,'SAIDA DE MATERIAIS'!C:C,B55) -> 0 | F55: =+D55-E55 -> 0
A56: =_xlfn.XLOOKUP(B56,'Entrada de Materiais'!C:C,'Entrada de Materiais'!B:B) -> 5503633 | B56: BOTÃO DE COMANDO 22MM COR VERMELHO | C56: UND | D56: =SUMIFS('Entrada de Materiais'!D:D, 'Entrada de Materiais'!C:C, B56) -> 0 | E56: =SUMIFS('SAIDA DE MATERIAIS'!F:F,'SAIDA DE MATERIAIS'!C:C,B56) -> 0 | F56: =+D56-E56 -> 0
A57: =_xlfn.XLOOKUP(B57,'Entrada de Materiais'!C:C,'Entrada de Materiais'!B:B) -> 5019127 | B57: BOX RETO ELETRODUTO AL D1POL | C57: UND | D57: =SUMIFS('Entrada de Materiais'!D:D, 'Entrada de Materiais'!C:C, B57) -> 19 | E57: =SUMIFS('SAIDA DE MATERIAIS'!F:F,'SAIDA DE MATERIAIS'!C:C,B57) -> 2 | F57: =+D57-E57 -> 17
A58: =_xlfn.XLOOKUP(B58,'Entrada de Materiais'!C:C,'Entrada de Materiais'!B:B) -> 5025311 | B58: BOX RETO ELETRODUTO AL D2 | C58: UND | D58: =SUMIFS('Entrada de Materiais'!D:D, 'Entrada de Materiais'!C:C, B58) -> 0 | E58: =SUMIFS('SAIDA DE MATERIAIS'!F:F,'SAIDA DE MATERIAIS'!C:C,B58) -> 0 | F58: =+D58-E58 -> 0
A59: =_xlfn.XLOOKUP(B59,'Entrada de Materiais'!C:C,'Entrada de Materiais'!B:B) -> 5507206 | B59: BROCA DE AÇO RAPIDO 3,5MM | C59: UND | D59: =SUMIFS('Entrada de Materiais'!D:D, 'Entrada de Materiais'!C:C, B59) -> 0 | E59: =SUMIFS('SAIDA DE MATERIAIS'!F:F,'SAIDA DE MATERIAIS'!C:C,B59) -> 0 | F59: =+D59-E59 -> 0
A60: =_xlfn.XLOOKUP(B60,'Entrada de Materiais'!C:C,'Entrada de Materiais'!B:B) -> 5507217 | B60: BROCA DE AÇO RAPIDO 4MM | C60: UND | D60: =SUMIFS('Entrada de Materiais'!D:D, 'Entrada de Materiais'!C:C, B60) -> 0 | E60: =SUMIFS('SAIDA DE MATERIAIS'!F:F,'SAIDA DE MATERIAIS'!C:C,B60) -> 0 | F60: =+D60-E60 -> 0
A61: =_xlfn.XLOOKUP(B61,'Entrada de Materiais'!C:C,'Entrada de Materiais'!B:B) -> 5507189 | B61: BROCA HELIC CIL HSS DIR 1/4POL 4POL | C61: UND | D61: =SUMIFS('Entrada de Materiais'!D:D, 'Entrada de Materiais'!C:C, B61) -> 0 | E61: =SUMIFS('SAIDA DE MATERIAIS'!F:F,'SAIDA DE MATERIAIS'!C:C,B61) -> 0 | F61: =+D61-E61 -> 0
A62: =_xlfn.XLOOKUP(B62,'Entrada de Materiais'!C:C,'Entrada de Materiais'!B:B) -> 5507191 | B62: BROCA HELIC CIL HSS DIR 10MM | C62: UND | D62: =SUMIFS('Entrada de Materiais'!D:D, 'Entrada de Materiais'!C:C, B62) -> 0 | E62: =SUMIFS('SAIDA DE MATERIAIS'!F:F,'SAIDA DE MATERIAIS'!C:C,B62) -> 0 | F62: =+D62-E62 -> 0
A63: =_xlfn.XLOOKUP(B63,'Entrada de Materiais'!C:C,'Entrada de Materiais'!B:B) -> 5507194 | B63: BROCA HELIC CIL HSS DIR 11MM 142MM | C63: UND | D63: =SUMIFS('Entrada de Materiais'!D:D, 'Entrada de Materiais'!C:C, B63) -> 0 | E63: =SUMIFS('SAIDA DE MATERIAIS'!F:F,'SAIDA DE MATERIAIS'!C:C,B63) -> 0 | F63: =+D63-E63 -> 0
A64: =_xlfn.XLOOKUP(B64,'Entrada de Materiais'!C:C,'Entrada de Materiais'!B:B) -> 5507199 | B64: BROCA HELIC CIL HSS DIR 13MM 151MM | C64: UND | D64: =SUMIFS('Entrada de Materiais'!D:D, 'Entrada de Materiais'!C:C, B64) -> 4 | E64: =SUMIFS('SAIDA DE MATERIAIS'!F:F,'SAIDA DE MATERIAIS'!C:C,B64) -> 0 | F64: =+D64-E64 -> 4
A65: =_xlfn.XLOOKUP(B65,'Entrada de Materiais'!C:C,'Entrada de Materiais'!B:B) -> 5507209 | B65: BROCA HELIC CIL HSS DIR 3/16POL 91MM | C65: UND | D65: =SUMIFS('Entrada de Materiais'!D:D, 'Entrada de Materiais'!C:C, B65) -> 0 | E65: =SUMIFS('SAIDA DE MATERIAIS'!F:F,'SAIDA DE MATERIAIS'!C:C,B65) -> 0 | F65: =+D65-E65 -> 0
A66: =_xlfn.XLOOKUP(B66,'Entrada de Materiais'!C:C,'Entrada de Materiais'!B:B) -> 5507213 | B66: BROCA HELIC CIL HSS DIR 3MM 61MM | C66: UND | D66: =SUMIFS('Entrada de Materiais'!D:D, 'Entrada de Materiais'!C:C, B66) -> 7 | E66: =SUMIFS('SAIDA DE MATERIAIS'!F:F,'SAIDA DE MATERIAIS'!C:C,B66) -> 0 | F66: =+D66-E66 -> 7
... A97: =_xlfn.XLOOKUP(B97,'Entrada de Materiais'!C:C,'Entrada de Materiais'!B:B) -> 5021333 | B97: CABO ELET FLEX 0,6/1KV 70MM2 CL5 PT | C97: M | D97: =SUMIFS('Entrada de Materiais'!D:D, 'Entrada de Materiais'!C:C, B97) -> 0 | E97: =SUMIFS('SAIDA DE MATERIAIS'!F:F,'SAIDA DE MATERIAIS'!C:C,B97) -> 0 | F97: =+D97-E97 -> 0
A98: =_xlfn.XLOOKUP(B98,'Entrada de Materiais'!C:C,'Entrada de Materiais'!B:B) -> 5019991 | B98: CABO ELET FLEX 0,6/1KV1X185MM2 | C98: M | D98: 800 | E98: =SUMIFS('SAIDA DE MATERIAIS'!F:F,'SAIDA DE MATERIAIS'!C:C,B98) -> 18 | F98: =+D98-E98 -> 782
A99: =_xlfn.XLOOKUP(B99,'Entrada de Materiais'!C:C,'Entrada de Materiais'!B:B) -> 5001146 | B99: CABO ELET FLEX 1 X 16MM2 PT | C99: M | D99: =SUMIFS('Entrada de Materiais'!D:D, 'Entrada de Materiais'!C:C, B99) -> 60 | E99: =SUMIFS('SAIDA DE MATERIAIS'!F:F,'SAIDA DE MATERIAIS'!C:C,B99) -> 60 | F99: =+D99-E99 -> 0
A100: =_xlfn.XLOOKUP(B100,'Entrada de Materiais'!C:C,'Entrada de Materiais'!B:B) -> 5001151 | B100: CABO ELET FLEX 1 X 95MM2 PT | C100: M | D100: =SUMIFS('Entrada de Materiais'!D:D, 'Entrada de Materiais'!C:C, B100) -> 200 | E100: =SUMIFS('SAIDA DE MATERIAIS'!F:F,'SAIDA DE MATERIAIS'!C:C,B100) -> 0 | F100: =+D100-E100 -> 200
A101: =_xlfn.XLOOKUP(B101,'Entrada de Materiais'!C:C,'Entrada de Materiais'!B:B) -> 5018072 | B101: CABO ELET FLEX 450/750V 1MM2 CL4 | C101: M | D101: =SUMIFS('Entrada de Materiais'!D:D, 'Entrada de Materiais'!C:C, B101) -> 900 | E101: =SUMIFS('SAIDA DE MATERIAIS'!F:F,'SAIDA DE MATERIAIS'!C:C,B101) -> 102 | F101: =+D101-E101 -> 798
A102: =_xlfn.XLOOKUP(B102,'Entrada de Materiais'!C:C,'Entrada de Materiais'!B:B) -> 5019778 | B102: CABO ELET FLEX 450/750V 1MM2 CL4 CZ | C102: M | D102: =SUMIFS('Entrada de Materiais'!D:D, 'Entrada de Materiais'!C:C, B102) -> 600 | E102: =SUMIFS('SAIDA DE MATERIAIS'!F:F,'SAIDA DE MATERIAIS'!C:C,B102) -> 0 | F102: =+D102-E102 -> 600
A103: =_xlfn.XLOOKUP(B103,'Entrada de Materiais'!C:C,'Entrada de Materiais'!B:B) -> 5019701 | B103: CABO ELET FLEX 750V 1MM2 PT | C103: M | D103: =SUMIFS('Entrada de Materiais'!D:D, 'Entrada de Materiais'!C:C, B103) -> 0 | E103: =SUMIFS('SAIDA DE MATERIAIS'!F:F,'SAIDA DE MATERIAIS'!C:C,B103) -> 0 | F103: =+D103-E103 -> 0
A104: =_xlfn.XLOOKUP(B104,'Entrada de Materiais'!C:C,'Entrada de Materiais'!B:B) -> 5019782 | B104: CABO ELET FLEX 750V 1MM2 CINZA | C104: M | D104: =SUMIFS('Entrada de Materiais'!D:D, 'Entrada de Materiais'!C:C, B104) -> 0 | E104: =SUMIFS('SAIDA DE MATERIAIS'!F:F,'SAIDA DE MATERIAIS'!C:C,B104) -> 0 | F104: =+D104-E104 -> 0
A105: =_xlfn.XLOOKUP(B105,'Entrada de Materiais'!C:C,'Entrada de Materiais'!B:B) -> 5001357 | B105: CABO ELET FLEX 750V 6MM | C105: M | D105: =SUMIFS('Entrada de Materiais'!D:D, 'Entrada de Materiais'!C:C, B105) -> 0 | E105: =SUMIFS('SAIDA DE MATERIAIS'!F:F,'SAIDA DE MATERIAIS'!C:C,B105) -> 0 | F105: =+D105-E105 -> 0
A106: =_xlfn.XLOOKUP(B106,'Entrada de Materiais'!C:C,'Entrada de Materiais'!B:B) -> 5001074 | B106: CABO ELET PP 450 / 750 V 4 X 6MM2 | C106: M | D106: =SUMIFS('Entrada de Materiais'!D:D, 'Entrada de Materiais'!C:C, B106) -> 85 | E106: =SUMIFS('SAIDA DE MATERIAIS'!F:F,'SAIDA DE MATERIAIS'!C:C,B106) -> 85 | F106: =+D106-E106 -> 0
A107: =_xlfn.XLOOKUP(B107,'Entrada de Materiais'!C:C,'Entrada de Materiais'!B:B) -> 5020122 | B107: CABO ELET. FLEX 0.6/1KV 1X1.5MM CL4 C/100mts | C107: M | D107: =SUMIFS('Entrada de Materiais'!D:D, 'Entrada de Materiais'!C:C, B107) -> 600 | E107: =SUMIFS('SAIDA DE MATERIAIS'!F:F,'SAIDA DE MATERIAIS'!C:C,B107) -> 200 | F107: =+D107-E107 -> 400
A108: =_xlfn.XLOOKUP(B108,'Entrada de Materiais'!C:C,'Entrada de Materiais'!B:B) -> 5017790 | B108: CABO ELET. FLEX 0.6/1KV 1X2.5MM CL5 C/100mts | C108: M | D108: =SUMIFS('Entrada de Materiais'!D:D, 'Entrada de Materiais'!C:C, B108) -> 0 | E108: =SUMIFS('SAIDA DE MATERIAIS'!F:F,'SAIDA DE MATERIAIS'!C:C,B108) -> 0 | F108: =+D108-E108 -> 0
A109: =_xlfn.XLOOKUP(B109,'Entrada de Materiais'!C:C,'Entrada de Materiais'!B:B) -> 5000970 | B109: CABO ELETRICO 1,5MM | C109: M | D109: =SUMIFS('Entrada de Materiais'!D:D, 'Entrada de Materiais'!C:C, B109) -> 0 | E109: =SUMIFS('SAIDA DE MATERIAIS'!F:F,'SAIDA DE MATERIAIS'!C:C,B109) -> 0 | F109: =+D109-E109 -> 0
A110: =_xlfn.XLOOKUP(B110,'Entrada de Materiais'!C:C,'Entrada de Materiais'!B:B) -> 5000970 | B110: CABO ELETRICO 1,5MM2 | C110: M | D110: =SUMIFS('Entrada de Materiais'!D:D, 'Entrada de Materiais'!C:C, B110) -> 400 | E110: =SUMIFS('SAIDA DE MATERIAIS'!F:F,'SAIDA DE MATERIAIS'!C:C,B110) -> 3 | F110: =+D110-E110 -> 397
... A150: =_xlfn.XLOOKUP(B150,'Entrada de Materiais'!C:C,'Entrada de Materiais'!B:B) -> 7500350 | B150: CAMISA SEGURANCA ELETRICISTA TAM GG | C150: UND | D150: =SUMIFS('Entrada de Materiais'!D:D, 'Entrada de Materiais'!C:C, B150) -> 3 | E150: =SUMIFS('SAIDA DE MATERIAIS'!F:F,'SAIDA DE MATERIAIS'!C:C,B150) -> 0 | F150: =+D150-E150 -> 3
A151: 7500350 | B151: CAMISA SEGURANCA ELETRICISTA TAM GG | C151: UND | D151: =SUMIFS('Entrada de Materiais'!D:D, 'Entrada de Materiais'!C:C, B151) -> 3 | E151: =SUMIFS('SAIDA DE MATERIAIS'!F:F,'SAIDA DE MATERIAIS'!C:C,B151) -> 0 | F151: =+D151-E151 -> 3
A152: =_xlfn.XLOOKUP(B152,'Entrada de Materiais'!C:C,'Entrada de Materiais'!B:B) -> 7500350 | B152: CAMISA SEGURANÇA ELETRICISTA TAM GG | C152: UND | D152: =SUMIFS('Entrada de Materiais'!D:D, 'Entrada de Materiais'!C:C, B152) -> 0 | E152: =SUMIFS('SAIDA DE MATERIAIS'!F:F,'SAIDA DE MATERIAIS'!C:C,B152) -> 0 | F152: =+D152-E152 -> 0
A153: =_xlfn.XLOOKUP(B153,'Entrada de Materiais'!C:C,'Entrada de Materiais'!B:B) -> 7500277 | B153: CAMISA SEGURANÇA ELETRICISTA TAM M | C153: UND | D153: =SUMIFS('Entrada de Materiais'!D:D, 'Entrada de Materiais'!C:C, B153) -> 0 | E153: =SUMIFS('SAIDA DE MATERIAIS'!F:F,'SAIDA DE MATERIAIS'!C:C,B153) -> 0 | F153: =+D153-E153 -> 0
A154: =_xlfn.XLOOKUP(B154,'Entrada de Materiais'!C:C,'Entrada de Materiais'!B:B) -> 7501070 | B154: CAMISA UNIFORME MANUT MASC LANGA POLO G | C154: UND | D154: =SUMIFS('Entrada de Materiais'!D:D, 'Entrada de Materiais'!C:C, B154) -> 16 | E154: =SUMIFS('SAIDA DE MATERIAIS'!F:F,'SAIDA DE MATERIAIS'!C:C,B154) -> 0 | F154: =+D154-E154 -> 16
A155: =_xlfn.XLOOKUP(B155,'Entrada de Materiais'!C:C,'Entrada de Materiais'!B:B) -> 7501067 | B155: CAMISA UNIFORME MANUT MASC LANGA POLO GG | C155: UND | D155: =SUMIFS('Entrada de Materiais'!D:D, 'Entrada de Materiais'!C:C, B155) -> 3 | E155: =SUMIFS('SAIDA DE MATERIAIS'!F:F,'SAIDA DE MATERIAIS'!C:C,B155) -> 0 | F155: =+D155-E155 -> 3
A156: =_xlfn.XLOOKUP(B156,'Entrada de Materiais'!C:C,'Entrada de Materiais'!B:B) -> 7500374 | B156: CAPA CHUVA CAPUZ ML PVC AM EXGG | C156: UND | D156: =SUMIFS('Entrada de Materiais'!D:D, 'Entrada de Materiais'!C:C, B156) -> 0 | E156: =SUMIFS('SAIDA DE MATERIAIS'!F:F,'SAIDA DE MATERIAIS'!C:C,B156) -> 0 | F156: =+D156-E156 -> 0
A157: =_xlfn.XLOOKUP(B157,'Entrada de Materiais'!C:C,'Entrada de Materiais'!B:B) -> 7500423 | B157: CAPACETE SEG TP I ABA TOTAL AZ JUG CL B | C157: UND | D157: =SUMIFS('Entrada de Materiais'!D:D, 'Entrada de Materiais'!C:C, B157) -> 0 | E157: =SUMIFS('SAIDA DE MATERIAIS'!F:F,'SAIDA DE MATERIAIS'!C:C,B157) -> 0 | F157: =+D157-E157 -> 0
A158: =_xlfn.XLOOKUP(B158,'Entrada de Materiais'!C:C,'Entrada de Materiais'!B:B) -> 7500363 | B158: CAPACETE SEG TPII ABA FRO AZ C/JUG CL B | C158: UND | D158: =SUMIFS('Entrada de Materiais'!D:D, 'Entrada de Materiais'!C:C, B158) -> 16 | E158: =SUMIFS('SAIDA DE MATERIAIS'!F:F,'SAIDA DE MATERIAIS'!C:C,B158) -> 0 | F158: =+D158-E158 -> 16
A159: =_xlfn.XLOOKUP(B159,'Entrada de Materiais'!C:C,'Entrada de Materiais'!B:B) -> 7500203 | B159: CAPUZ SEG BALACLAVA CARRASCO FLASHWEAR | C159: UND | D159: =SUMIFS('Entrada de Materiais'!D:D, 'Entrada de Materiais'!C:C, B159) -> 0 | E159: =SUMIFS('SAIDA DE MATERIAIS'!F:F,'SAIDA DE MATERIAIS'!C:C,B159) -> 0 | F159: =+D159-E159 -> 0
A160: =_xlfn.XLOOKUP(B160,'Entrada de Materiais'!C:C,'Entrada de Materiais'!B:B) -> 5504189 | B160: CHAVE BOIA NIVEL 25A INF/SUP CABO 1,5M/1,2M | C160: UND | D160: =SUMIFS('Entrada de Materiais'!D:D, 'Entrada de Materiais'!C:C, B160) -> 166 | E160: =SUMIFS('SAIDA DE MATERIAIS'!F:F,'SAIDA DE MATERIAIS'!C:C,B160) -> 20 | F160: =+D160-E160 -> 146
A161: =_xlfn.XLOOKUP(B161,'Entrada de Materiais'!C:C,'Entrada de Materiais'!B:B) -> 5516961 | B161: CHAVE SECCIONADORA 3P 690V 400A | C161: UND | D161: =SUMIFS('Entrada de Materiais'!D:D, 'Entrada de Materiais'!C:C, B161) -> 0 | E161: =SUMIFS('SAIDA DE MATERIAIS'!F:F,'SAIDA DE MATERIAIS'!C:C,B161) -> 0 | F161: =+D161-E161 -> 0
A162: =_xlfn.XLOOKUP(B162,'Entrada de Materiais'!C:C,'Entrada de Materiais'!B:B) -> 5505075 | B162: CHAVE SECCIONADORA 3P 690V 630A | C162: UND | D162: =SUMIFS('Entrada de Materiais'!D:D, 'Entrada de Materiais'!C:C, B162) -> 0 | E162: =SUMIFS('SAIDA DE MATERIAIS'!F:F,'SAIDA DE MATERIAIS'!C:C,B162) -> 0 | F162: =+D162-E162 -> 0
A163: =_xlfn.XLOOKUP(B163,'Entrada de Materiais'!C:C,'Entrada de Materiais'!B:B) -> 3010351 | B163: CHUMBADOR 19MM CBA 3/4 X 4.1/2" | C163: UND | D163: =SUMIFS('Entrada de Materiais'!D:D, 'Entrada de Materiais'!C:C, B163) -> 0 | E163: =SUMIFS('SAIDA DE MATERIAIS'!F:F,'SAIDA DE MATERIAIS'!C:C,B163) -> 0 | F163: =+D163-E163 -> 0
... A186: =_xlfn.XLOOKUP(B186,'Entrada de Materiais'!C:C,'Entrada de Materiais'!B:B) -> 5003481 | B186: CONTATOR PRINCIPAL 3P 25A CA 220V 50/60HZ | C186: UND | D186: =SUMIFS('Entrada de Materiais'!D:D, 'Entrada de Materiais'!C:C, B186) -> 0 | E186: =SUMIFS('SAIDA DE MATERIAIS'!F:F,'SAIDA DE MATERIAIS'!C:C,B186) -> 0 | F186: =+D186-E186 -> 0
A187: =_xlfn.XLOOKUP(B187,'Entrada de Materiais'!C:C,'Entrada de Materiais'!B:B) -> 5003469 | B187: CONTATOR PRINCIPAL 3P 32A 220VCA 1NA | C187: UND | D187: 6 | E187: =SUMIFS('SAIDA DE MATERIAIS'!F:F,'SAIDA DE MATERIAIS'!C:C,B187) -> 4 | F187: =+D187-E187 -> 2
A188: =_xlfn.XLOOKUP(B188,'Entrada de Materiais'!C:C,'Entrada de Materiais'!B:B) -> 5003474 | B188: CONTATOR PRINCIPAL 3P 40A CA | C188: UND | D188: =SUMIFS('Entrada de Materiais'!D:D, 'Entrada de Materiais'!C:C, B188) -> 0 | E188: =SUMIFS('SAIDA DE MATERIAIS'!F:F,'SAIDA DE MATERIAIS'!C:C,B188) -> 0 | F188: =+D188-E188 -> 0
A189: =_xlfn.XLOOKUP(B189,'Entrada de Materiais'!C:C,'Entrada de Materiais'!B:B) -> 5003470 | B189: CONTATOR PRINCIPAL 3P 80A 230VCA 1NA 1NF | C189: UND | D189: =SUMIFS('Entrada de Materiais'!D:D, 'Entrada de Materiais'!C:C, B189) -> 2 | E189: =SUMIFS('SAIDA DE MATERIAIS'!F:F,'SAIDA DE MATERIAIS'!C:C,B189) -> 0 | F189: =+D189-E189 -> 2
A190: =_xlfn.XLOOKUP(B190,'Entrada de Materiais'!C:C,'Entrada de Materiais'!B:B) -> 5022812 | B190: CONTATOR TRIPOLAR 65A 220V 60HZ 1NA | C190: UND | D190: =SUMIFS('Entrada de Materiais'!D:D, 'Entrada de Materiais'!C:C, B190) -> 0 | E190: =SUMIFS('SAIDA DE MATERIAIS'!F:F,'SAIDA DE MATERIAIS'!C:C,B190) -> 0 | F190: =+D190-E190 -> 0
A191: =_xlfn.XLOOKUP(B191,'Entrada de Materiais'!C:C,'Entrada de Materiais'!B:B) -> 5022362 | B191: CONTATOR TRIPOLAR AC 3 45A 400V | C191: UND | D191: =SUMIFS('Entrada de Materiais'!D:D, 'Entrada de Materiais'!C:C, B191) -> 1 | E191: =SUMIFS('SAIDA DE MATERIAIS'!F:F,'SAIDA DE MATERIAIS'!C:C,B191) -> 0 | F191: =+D191-E191 -> 1
A192: =_xlfn.XLOOKUP(B192,'Entrada de Materiais'!C:C,'Entrada de Materiais'!B:B) -> 5003467 | B192: CONTATOR TRIPOLAT AC 3 140A 400V | C192: UND | D192: =SUMIFS('Entrada de Materiais'!D:D, 'Entrada de Materiais'!C:C, B192) -> 3 | E192: =SUMIFS('SAIDA DE MATERIAIS'!F:F,'SAIDA DE MATERIAIS'!C:C,B192) -> 0 | F192: =+D192-E192 -> 3
A193: =_xlfn.XLOOKUP(B193,'Entrada de Materiais'!C:C,'Entrada de Materiais'!B:B) -> 4011682 | B193: CORREIA IND DENTADA 5VX 0750 SANTO ELIAS | C193: UND | D193: =SUMIFS('Entrada de Materiais'!D:D, 'Entrada de Materiais'!C:C, B193) -> 8 | E193: =SUMIFS('SAIDA DE MATERIAIS'!F:F,'SAIDA DE MATERIAIS'!C:C,B193) -> 0 | F193: =+D193-E193 -> 8
A194: =_xlfn.XLOOKUP(B194,'Entrada de Materiais'!C:C,'Entrada de Materiais'!B:B) -> 2002960 | B194: CORRENTE ACO INOX 3/16 POLEGADA | C194: UND | D194: =SUMIFS('Entrada de Materiais'!D:D, 'Entrada de Materiais'!C:C, B194) -> 10 | E194: =SUMIFS('SAIDA DE MATERIAIS'!F:F,'SAIDA DE MATERIAIS'!C:C,B194) -> 0 | F194: =+D194-E194 -> 10
A195: =_xlfn.XLOOKUP(B195,'Entrada de Materiais'!C:C,'Entrada de Materiais'!B:B) -> 2004193 | B195: CORRENTE ACO INOX 5/16 POL 400KGF | C195: UND | D195: =SUMIFS('Entrada de Materiais'!D:D, 'Entrada de Materiais'!C:C, B195) -> 15 | E195: =SUMIFS('SAIDA DE MATERIAIS'!F:F,'SAIDA DE MATERIAIS'!C:C,B195) -> 0 | F195: =+D195-E195 -> 15
A196: =_xlfn.XLOOKUP(B196,'Entrada de Materiais'!C:C,'Entrada de Materiais'!B:B) -> 5003731 | B196: CURVA 45° PVC PBA PB JE DN75MM | C196: UND | D196: =SUMIFS('Entrada de Materiais'!D:D, 'Entrada de Materiais'!C:C, B196) -> 0 | E196: =SUMIFS('SAIDA DE MATERIAIS'!F:F,'SAIDA DE MATERIAIS'!C:C,B196) -> 0 | F196: =+D196-E196 -> 0
A197: =_xlfn.XLOOKUP(B197,'Entrada de Materiais'!C:C,'Entrada de Materiais'!B:B) -> 5003737 | B197: CURVA 90 FOFO AG BB JGS DN100 | C197: UND | D197: =SUMIFS('Entrada de Materiais'!D:D, 'Entrada de Materiais'!C:C, B197) -> 4 | E197: =SUMIFS('SAIDA DE MATERIAIS'!F:F,'SAIDA DE MATERIAIS'!C:C,B197) -> 0 | F197: =+D197-E197 -> 4
A198: =_xlfn.XLOOKUP(B198,'Entrada de Materiais'!C:C,'Entrada de Materiais'!B:B) -> 5004095 | B198: CURVA 90 GALV RM BSP DE 2" | C198: UND | D198: =SUMIFS('Entrada de Materiais'!D:D, 'Entrada de Materiais'!C:C, B198) -> 2 | E198: =SUMIFS('SAIDA DE MATERIAIS'!F:F,'SAIDA DE MATERIAIS'!C:C,B198) -> 0 | F198: =+D198-E198 -> 2
A199: =_xlfn.XLOOKUP(B199,'Entrada de Materiais'!C:C,'Entrada de Materiais'!B:B) -> 5504320 | B199: CURVA ELET 90° 3/4POLAL | C199: UND | D199: =SUMIFS('Entrada de Materiais'!D:D, 'Entrada de Materiais'!C:C, B199) -> 3 | E199: =SUMIFS('SAIDA DE MATERIAIS'!F:F,'SAIDA DE MATERIAIS'!C:C,B199) -> 0 | F199: =+D199-E199 -> 3
... A201: =_xlfn.XLOOKUP(B201,'Entrada de Materiais'!C:C,'Entrada de Materiais'!B:B) -> 3001375 | B201: DESENGRIPANTE LIQ. 300ML | C201: UND | D201: =SUMIFS('Entrada de Materiais'!D:D, 'Entrada de Materiais'!C:C, B201) -> 12 | E201: =SUMIFS('SAIDA DE MATERIAIS'!F:F,'SAIDA DE MATERIAIS'!C:C,B201) -> 6 | F201: =+D201-E201 -> 6
A202: =_xlfn.XLOOKUP(B202,'Entrada de Materiais'!C:C,'Entrada de Materiais'!B:B) -> 5004199 | B202: DISCO CORTE S/REV 4.1/2POL 1/8POL AI | C202: UND | D202: 20 | E202: =SUMIFS('SAIDA DE MATERIAIS'!F:F,'SAIDA DE MATERIAIS'!C:C,B202) -> 19 | F202: =+D202-E202 -> 1
A203: =_xlfn.XLOOKUP(B203,'Entrada de Materiais'!C:C,'Entrada de Materiais'!B:B) -> 5004195 | B203: DISCO CORTE S/REV 115MM 1MM A MET FER | C203: UND | D203: =SUMIFS('Entrada de Materiais'!D:D, 'Entrada de Materiais'!C:C, B203) -> 0 | E203: =SUMIFS('SAIDA DE MATERIAIS'!F:F,'SAIDA DE MATERIAIS'!C:C,B203) -> 0 | F203: =+D203-E203 -> 0
A204: =_xlfn.XLOOKUP(B204,'Entrada de Materiais'!C:C,'Entrada de Materiais'!B:B) -> 5023084 | B204: DISCO CORTE S/REV 115MM 22,22MM 1MM META | C204: UND | D204: =SUMIFS('Entrada de Materiais'!D:D, 'Entrada de Materiais'!C:C, B204) -> 0 | E204: =SUMIFS('SAIDA DE MATERIAIS'!F:F,'SAIDA DE MATERIAIS'!C:C,B204) -> 0 | F204: =+D204-E204 -> 0
A205: =_xlfn.XLOOKUP(B205,'Entrada de Materiais'!C:C,'Entrada de Materiais'!B:B) -> 5022410 | B205: DISCO DE DESBASTE AÇO 4.1/2X3/16X7/8 | C205: UND | D205: 0 | E205: =SUMIFS('SAIDA DE MATERIAIS'!F:F,'SAIDA DE MATERIAIS'!C:C,B205) -> 0 | F205: =+D205-E205 -> 0
A206: =_xlfn.XLOOKUP(B206,'Entrada de Materiais'!C:C,'Entrada de Materiais'!B:B) -> 5027166 | B206: DISJUNTOR 4P 400V 200A | C206: UND | D206: =SUMIFS('Entrada de Materiais'!D:D, 'Entrada de Materiais'!C:C, B206) -> 2 | E206: =SUMIFS('SAIDA DE MATERIAIS'!F:F,'SAIDA DE MATERIAIS'!C:C,B206) -> 0 | F206: =+D206-E206 -> 2
A207: =_xlfn.XLOOKUP(B207,'Entrada de Materiais'!C:C,'Entrada de Materiais'!B:B) -> 5027166 | B207: DISJUNTOR 4P 400V 200A | C207: UND | D207: 0 | E207: =SUMIFS('SAIDA DE MATERIAIS'!F:F,'SAIDA DE MATERIAIS'!C:C,B207) -> 0 | F207: =+D207-E207 -> 0
A208: =_xlfn.XLOOKUP(B208,'Entrada de Materiais'!C:C,'Entrada de Materiais'!B:B) -> 5004445 | B208: DISJUNTOR CAIXA MOLDADA SDJS 175A | C208: UND | D208: =SUMIFS('Entrada de Materiais'!D:D, 'Entrada de Materiais'!C:C, B208) -> 16 | E208: =SUMIFS('SAIDA DE MATERIAIS'!F:F,'SAIDA DE MATERIAIS'!C:C,B208) -> 0 | F208: =+D208-E208 -> 16
A209: =_xlfn.XLOOKUP(B209,'Entrada de Materiais'!C:C,'Entrada de Materiais'!B:B) -> 5018096 | B209: DISJUNTOR CAIXA MOLDADA 100A 690VCA | C209: UND | D209: =SUMIFS('Entrada de Materiais'!D:D, 'Entrada de Materiais'!C:C, B209) -> 5 | E209: =SUMIFS('SAIDA DE MATERIAIS'!F:F,'SAIDA DE MATERIAIS'!C:C,B209) -> 0 | F209: =+D209-E209 -> 5
A210: =_xlfn.XLOOKUP(B210,'Entrada de Materiais'!C:C,'Entrada de Materiais'!B:B) -> 5004276 | B210: DISJUNTOR CAIXA MOLDADA 150A | C210: UND | D210: =SUMIFS('Entrada de Materiais'!D:D, 'Entrada de Materiais'!C:C, B210) -> 22 | E210: =SUMIFS('SAIDA DE MATERIAIS'!F:F,'SAIDA DE MATERIAIS'!C:C,B210) -> 0 | F210: =+D210-E210 -> 22
A211: =_xlfn.XLOOKUP(B211,'Entrada de Materiais'!C:C,'Entrada de Materiais'!B:B) -> 5004271 | B211: DISJUNTOR CAIXA MOLDADA 200A | C211: UND | D211: =SUMIFS('Entrada de Materiais'!D:D, 'Entrada de Materiais'!C:C, B211) -> 2 | E211: =SUMIFS('SAIDA DE MATERIAIS'!F:F,'SAIDA DE MATERIAIS'!C:C,B211) -> 0 | F211: =+D211-E211 -> 2
A212: =_xlfn.XLOOKUP(B212,'Entrada de Materiais'!C:C,'Entrada de Materiais'!B:B) -> 5021437 | B212: DISJUNTOR CAIXA MOLDADA 3KA 380V 125A | C212: UND | D212: =SUMIFS('Entrada de Materiais'!D:D, 'Entrada de Materiais'!C:C, B212) -> 0 | E212: =SUMIFS('SAIDA DE MATERIAIS'!F:F,'SAIDA DE MATERIAIS'!C:C,B212) -> 0 | F212: =+D212-E212 -> 0
A213: =_xlfn.XLOOKUP(B213,'Entrada de Materiais'!C:C,'Entrada de Materiais'!B:B) -> 5004272 | B213: DISJUNTOR CAIXA MOLDADA 40A | C213: UND | D213: =SUMIFS('Entrada de Materiais'!D:D, 'Entrada de Materiais'!C:C, B213) -> 8 | E213: =SUMIFS('SAIDA DE MATERIAIS'!F:F,'SAIDA DE MATERIAIS'!C:C,B213) -> 0 | F213: =+D213-E213 -> 8
A214: =_xlfn.XLOOKUP(B214,'Entrada de Materiais'!C:C,'Entrada de Materiais'!B:B) -> 5004273 | B214: DISJUNTOR CAIXA MOLDADA DWP 63A | C214: UND | D214: =SUMIFS('Entrada de Materiais'!D:D, 'Entrada de Materiais'!C:C, B214) -> 2 | E214: =SUMIFS('SAIDA DE MATERIAIS'!F:F,'SAIDA DE MATERIAIS'!C:C,B214) -> 0 | F214: =+D214-E214 -> 2
A215: =_xlfn.XLOOKUP(B215,'Entrada de Materiais'!C:C,'Entrada de Materiais'!B:B) -> 5004464 | B215: DISJUNTOR CAIXA MOLDADA DWP400L 3X400A | C215: UND | D215: =SUMIFS('Entrada de Materiais'!D:D, 'Entrada de Materiais'!C:C, B215) -> 0 | E215: =SUMIFS('SAIDA DE MATERIAIS'!F:F,'SAIDA DE MATERIAIS'!C:C,B215) -> 0 | F215: =+D215-E215 -> 0
A216: =_xlfn.XLOOKUP(B216,'Entrada de Materiais'!C:C,'Entrada de Materiais'!B:B) -> 5004456 | B216: DISJUNTOR CAIXA MOLDADA S225 690V 3X225A | C216: UND | D216: =SUMIFS('Entrada de Materiais'!D:D, 'Entrada de Materiais'!C:C, B216) -> 0 | E216: =SUMIFS('SAIDA DE MATERIAIS'!F:F,'SAIDA DE MATERIAIS'!C:C,B216) -> 0 | F216: =+D216-E216 -> 0
A217: =_xlfn.XLOOKUP(B217,'Entrada de Materiais'!C:C,'Entrada de Materiais'!B:B) -> 5004272 | B217: DISJUNTOR CAIXA TRIPOLAR 40A 400A DJG | C217: UND | D217: =SUMIFS('Entrada de Materiais'!D:D, 'Entrada de Materiais'!C:C, B217) -> 1 | E217: =SUMIFS('SAIDA DE MATERIAIS'!F:F,'SAIDA DE MATERIAIS'!C:C,B217) -> 0 | F217: =+D217-E217 -> 1
A218: =_xlfn.XLOOKUP(B218,'Entrada de Materiais'!C:C,'Entrada de Materiais'!B:B) -> 5503145 | B218: DISJUNTOR CAIXA TRIPOLAR 35KA 3X500A | C218: UND | D218: =SUMIFS('Entrada de Materiais'!D:D, 'Entrada de Materiais'!C:C, B218) -> 0 | E218: =SUMIFS('SAIDA DE MATERIAIS'!F:F,'SAIDA DE MATERIAIS'!C:C,B218) -> 0 | F218: =+D218-E218 -> 0
A219: =_xlfn.XLOOKUP(B219,'Entrada de Materiais'!C:C,'Entrada de Materiais'!B:B) -> 5503145 | B219: DISJUNTOR CAIXA TRIPOLAR BRUM 3X500A | C219: UND | D219: =SUMIFS('Entrada de Materiais'!D:D, 'Entrada de Materiais'!C:C, B219) -> 0 | E219: =SUMIFS('SAIDA DE MATERIAIS'!F:F,'SAIDA DE MATERIAIS'!C:C,B219) -> 0 | F219: =+D219-E219 -> 0
... A252: =_xlfn.XLOOKUP(B252,'Entrada de Materiais'!C:C,'Entrada de Materiais'!B:B) -> 5504880 | B252: ELETRODUTO RIG PVC 3/4POL | C252: UND | D252: =SUMIFS('Entrada de Materiais'!D:D, 'Entrada de Materiais'!C:C, B252) -> 0 | E252: =SUMIFS('SAIDA DE MATERIAIS'!F:F,'SAIDA DE MATERIAIS'!C:C,B252) -> 0 | F252: =+D252-E252 -> 0
A253: =_xlfn.XLOOKUP(B253,'Entrada de Materiais'!C:C,'Entrada de Materiais'!B:B) -> 5504127 | B253: ELETRODUTO SEATUBO CAPA 1POL PT | C253: UND | D253: 10 | E253: =SUMIFS('SAIDA DE MATERIAIS'!F:F,'SAIDA DE MATERIAIS'!C:C,B253) -> 0 | F253: =+D253-E253 -> 10
...
