Workbook

Sheet COORDENADAS
A1: COD_PLANTA | B1: COD_LATITUDE | C1: COD_LONGITUDE
A2: PL-RJB-CTE0002 | B2: -22.8 | C2: -43.4271
A3: PL-RJB-CTE0003 | B3: -22.7883 | C3: -43.4116
A4: PL-RJB-ECT0201 | B4: -22.6565 | C4: -43.6641
A5: PL-RJB-ECT0202 | B5: -22.6859 | C5: -43.4399
A6: PL-RJB-ECT0203 | B6: -22.6541 | C6: -43.5368
A7: PL-RJB-ECT0204 | B7: -22.7084 | C7: -43.4288
A8: PL-RJB-ECT0207 | B8: -22.7972 | C8: -43.5713
A9: PL-RJB-ECT0212 | B9: -22.7778 | C9: -43.3977
A10: PL-RJB-ECT0216 | B10: -22.7969 | C10: -43.5561
A11: PL-RJB-ECT0227 | B11: -22.7639 | C11: -43.4983
A12: PL-RJB-ECT0228 | B12: -22.8098 | C12: -43.5894
A13: PL-RJB-ECT0230 | B13: -22.7163 | C13: -43.5519
... A225: PL-RJB-EEE1100 | B225: -22.7892 | C225: -43.4099
A226: PL-RJB-EEE0073 | C226: -43.4273
A227: PL-RJB-EEE0080 | B227: -22.7792 | C227: -43.433
A228: PL-RJB-EEE0081 | B228: -22.7828 | C228: -43.433
A229: PL-RJB-EEE0082 | B229: -22.7962 | C229: -43.5912
A230: PL-RJB-EEE0083 | B230: -22.8027 | C230: -43.5901
A231: PL-RJB-LJA0003 | B231: -22.7828 | C231: -43.4302
A232: PL-RJB-LJA0005 | B232: -22.644 | C232: -43.6565
A233: PL-RJB-LJA0006 | B233: -22.8095 | C233: -43.4158
A234: PL-RJB-LJA0007 | B234: -22.7154 | C234: -43.5569
A235: PL-RJB-SDA1003 | B235: -22.8113 | C235: -43.4101

Sheet NOVAS ELEVATÓRIAS
B1: Tipo EEAT | C1: Segmento | D1: EEAT | F1: Cidade | G1: População | H1: Status | I1: Fase Atual | J1: Etapas restantes | K1: Observações / Inconformidades
B2: EEAT | C2: Água | D2: Baixo Pedreira | F2: Nova Iguaçu | G2: 1421
B3: Elevatória | C3: Água | D3: Camburi | F3: Queimados | G3: 24707
B4: Elevatória | C4: Água | D4: Nélio Chambarelli | F4: Queimados | G4: 596
B5: Elevatória | C5: Água | D5: Messias | F5: Japeri | G5: 581
B6: Booster | C6: Água | D6: Boa Esperança | F6: Nova Iguaçu
B7: Booster | C7: Água | D7: Tinguazinho | F7: Nova Iguaçu
B8: Elevatória | C8: Água | D8: Bela Vista | F8: Nova Iguaçu
B9: Booster | C9: Água | D9: Comendador Soares | F9: Nova Iguaçu
B10: Booster | C10: Água | D10: Chacrinha | F10: Japeri | G10: 1642
B11: Elevatória | C11: Água | D11: Manoel Dias | F11: Nova Iguaçu
B12: Elevatória | C12: Água | D12: Morro do Tinguazinho | F12: Nova Iguaçu | G12: 3249
C13: Água | D13: Iara
C14: Água | D14: São Joaquim
C15: Água | D15: Bento Rubião
B16: Elevatória | C16: Água | D16: Santa Rita / Corumbá | E16: JÁ INSTALADA
C17: Água | D17: Ambaí
C18: Água | D18: Nova Cidade
B19: Container | C19: Água | D19: Liberdade | E19: JÁ INSTALADA
C20: Água | D20: Beira Linha
B21: Container | C21: Água | D21: BNH | E21: JÁ INSTALADA
C22: Água | D22: Jaqueira
C23: Água | D23: Morro da Paz
C24: Água | D24: Colombo
C25: Água | D25: Beira Rio
C26: Água | D26: Dona Afra
C27: Água | D27: Carlos Monsante
B28: Container | C28: Água | D28: Biquinha | E28: JÁ INSTALADA
C29: Água | D29: São Simão
C30: Água | D30: Adibe Saad

Sheet RELAÇÃO DE ELEVATÓRIAS
A1: DADOS INFORMATIVOS | O1: DADOS DO EQUIPAMENTO INSTALADO | AN1: ALIMENTAÇÃO | AP1: DADOS DA CONCESSIONÁRIA DE ENERGIA | AU1: DIAMETRO DA TUBULACAO | AY1: DADOS GEOGRÁFICOS | BA1: PAINÉIS | BJ1: AUTOMAÇÃO | BR1: SETPOINT | BU1: TOMADA DE RETAGUARDA | BV1: TOMADA DE RECALQUE | BW1: ELETRODO SUPERIOR | BX1: ELETRODO INFERIOR | BY1: TIPO DE RECALQUE | BZ1: COTA NA ELEVATORIA | CA1: COTA MAXIMA | CB1: DISTANCIA DA ELEV. A COORDENACAO | CC1: COMUNIDADES / HOSPITAIS / LOCALIDADES IMPORTANTES ABASTECIDAS | CD1: AREA DE INFLUENCIA
A2: ELEVATORIAS | B2: PLANTA | C2: TIPO | D2: SUPERINTENDÊNCIA | E2: ENDEREÇO | F2: BAIRRO | G2: MUNICIPIO | H2: CEP | I2: LATITUDE | J2: LONGITUDE | K2: Inicio de Operação | L2: CARACTERÍSTICAS DA ÁREA | M2: GRUPO | N2: FUNÇÃO | O2: POTÊNCIA DO MOTOR (CV) | P2: RPM | Q2: MARCA DO MOTOR | R2: CARCAÇA DO MOTOR | S2: TAG DO MOTOR | T2: TENSÃO (V) | U2: CORRENTE (A) | V2: MANCAIS (LA) | W2: MANCAIS (LOA) | X2: MODELO DA BOMBA | Y2: TAG DA BOMBA | Z2: MARCA DA BOMBA | AA2: Ø ROTOR (pol) | AB2: Ø ROTOR (mm) | AC2: TIPO CONSTRUTIVO DA ELEVATORIA | AD2: BOMBA DRENO (SIM/NÃO) | AE2: PONTA DO EIXO DO MOTOR | AF2: SENTIDO DE MONTAGEM DO MOTOR | AG2: FLANGE | AH2: FORMA CONSTRUTIVA DA BOMBA | AI2: VAZÃO APROXIMADA (M³/H) | AJ2: AMT APROXIMADA | AK2: Capacidade de tratamento | AL2: Procedência do MCA | AM2: CÓD SAP | AN2: BT/MT | AO2: TRAFO (KVA) | AP2: N° CLIENTE | AQ2: MEDIDOR | AR2: MEDIDOR APURADO + DATA | AS2: UNIDADE DE CONSUMO | AT2: ENDEREÇO | AU2: SUCCAO | AV2: RECALQUE | AW2: TRONCO | AX2: DISTACIA ATE A ELEV. | AY2: POPULAÇÃO BENEFICIADA EM HABITANTES | AZ2: DOMICILIOS | BA2: FUSÍVEL (PC) | BB2: DISJUNTOR (PC) | BC2: REGULAGEM DO RELE TÉRMICO BIMETÁLICO | BD2: RELÉ DE TEMPO ΔY | BE2: RELÉ DE ELETRODO (NÍVEL) | BF2: MONITOR DE CORRENTE | BG2: TAMANHO DO FUSÍVEL NH | BH2: CORRENTE DO FUSÍVEL NH | BI2: CORRENTE DO FUSÍVEL DZ | BJ2: TAG PAINEL | BK2: TIPO DE ACIONAMENTO | BL2: FABRICANTE DO ACIONAMENTO | BM2: MODELO DE ACIONAMENTO | BN2: Corrente (A) | BO2: TAG DO ACIONAMENTO | BP2: CLP | BQ2: PCP | BR2: RETAGUARDA LIGA | BS2: RETAGUARDA DESLIGA | BT2: RECALQUE
A3: ADOLFO BERGAMINI / ALTO MILITÂO | B3: =_xlfn.XLOOKUP(A:A,'Dados Elevatórias'!D:D,'Dados Elevatórias'!B:B) -> PL-RJB-EAT0093 | C3: =_xlfn.XLOOKUP(B:B,'Dados Elevatórias'!B:B,'Dados Elevatórias'!C:C) -> EAT | D3: BAIXADA 2 | E3: Estr. Gen. Mena Barreto, 821 - Novo Horizonte, Nilópolis - RJ, 26535-330 | F3: Novo Horizonte | G3: NILÓPOLIS | H3: =_xlfn.XLOOKUP(B:B,'Dados Elevatórias'!B:B,'Dados Elevatórias'!G:G) -> 26535-330 | I3: =_xlfn.XLOOKUP(B3,COORDENADAS!A:A,COORDENADAS!B:B) -> -22.8035 | J3: =_xlfn.XLOOKUP(B3,COORDENADAS!A:A,COORDENADAS!C:C) -> -43.4081 | L3: FORMAL | M3: 1 | N3: OPERACIONAL | O3: 25CV | P3: 3480rpm | T3: 220 | U3: 68.4 | X3: HAR25195B1 | Y3: RJB-21219 | Z3: HELBOMBAS | AA3: 3 | AB3: 142mm | AC3: TUBULÂO | AD3: NÃO | AI3: 100m³/h | AN3: =_xlfn.XLOOKUP(A:A,'RELAÇÃO ANTIGA'!A:A,'RELAÇÃO ANTIGA'!AC:AC,X) -> 220V | AP3: 420150274 | AQ3: 5241361 | AR3: 0 | AS3: AGUA - BOOSTER - ADOLFO BERGAMINI | AT3: R JOAO RODRIGUES DA CUNHA SN PX1195 | AU3: 100 | AV3: 150 | AW3: 0 | AX3: 0 | AY3: 0 | AZ3: 0 | BJ3: RJB-14411 | BK3: INVERSOR DE FREQUÊNCIA | BL3: DANFOSS | BM3: VLT Aqua Drive | BN3: 88A | BO3: RJA-03553 | BP3: SIM | BR3: 1 MCA | BS3: < 1 MCA | BT3: 22 MCA | BU3: 1\2º | BV3: 1\2º | BW3: SIM | BY3: EM MARCHA | BZ3: 24 | CA3: 53 | CB3: 0 | CC3: 0 | CD3: Area 1: Rua Adolfo Bergamin (Trecho Rua Mena Barreto A Rua JoAo da Mata Peixoto), Rua Natividade (Trecho Rua Adolfo Bergamin A Rua MArio Valadares), Rua Romilda Alves, Rua Embaixador Von Spritt, Rua Aurea P. Farjado, Rua GenEsio de Barros e pequenas Vilas desse trecho. Area 2: Rua JoAo da Mata Peixoto (Trecho do nº 182 A Rua MArio Valadares), Rua Adolfo Bergamin (Trecho Rua JoAo da Mata Peixoto A Rua Antonio J. Bittencourt), Rua JoAo F. da Silva, Rua Maria InEs QueirOs, Rua AmErico Diamantino Lopes, Rua JosE da Silva Braga (Trecho Rua MArio Valadares A Rua AntOnio J. Bittencourt), Rua Francisco M. da Silva. Area 3: Rua JoAo da Mata Peixoto (Trecho Rua Otacilio Pessoa), Rua JoAo da Cruz Saldanha, Rua Lauro Machado e pequenas Vilas desse trecho.
A4: ADOLFO BERGAMINI / ALTO MILITÂO | B4: =_xlfn.XLOOKUP(A:A,'Dados Elevatórias'!D:D,'Dados Elevatórias'!B:B) -> PL-RJB-EAT0093 | C4: =_xlfn.XLOOKUP(B:B,'Dados Elevatórias'!B:B,'Dados Elevatórias'!C:C) -> EAT | D4: BAIXADA 2 | E4: Estr. Gen. Mena Barreto, 821 - Novo Horizonte, Nilópolis - RJ, 26535-330 | F4: Novo Horizonte | G4: NILÓPOLIS | H4: =_xlfn.XLOOKUP(B:B,'Dados Elevatórias'!B:B,'Dados Elevatórias'!G:G) -> 26535-330 | I4: =_xlfn.XLOOKUP(B4,COORDENADAS!A:A,COORDENADAS!B:B) -> -22.8035 | J4: =_xlfn.XLOOKUP(B4,COORDENADAS!A:A,COORDENADAS!C:C) -> -43.4081 | L4: FORMAL | M4: 2 | N4: OPERACIONAL | O4: 25CV | P4: 3550rpm | Q4: WEG | R4: 160M | S4: RJB-21217 | T4: 220V / 380V / 440V | U4: 60.8 / 35.2 / 30.4A | Y4: RJB-25854 | AA4: 3 | AC4: CONTAINER | AF4: HORIZONTAL | AH4: CONVENSIONAL | AN4: =_xlfn.XLOOKUP(A:A,'RELAÇÃO ANTIGA'!A:A,'RELAÇÃO ANTIGA'!AC:AC,X) -> 220V | AP4: 420150274 | AQ4: 5241361 | AR4: 0 | AS4: AGUA - BOOSTER - ADOLFO BERGAMINI | AT4: R JOAO RODRIGUES DA CUNHA SN PX1195 | AU4: 100 | AV4: 150 | AW4: 0 | AX4: 0 | AY4: 0 | AZ4: 0 | BJ4: RJB-26852 | BK4: INVERSOR DE FREQUÊNCIA | BL4: SIEMENS | BM4: PM240-2 | BN4: 68A | BO4: RJB-30606 | BP4: SIM | BR4: 1 MCA | BS4: < 1 MCA | BT4: 22 MCA | BU4: 1\2º | BV4: 1\2º | BW4: SIM | BY4: EM MARCHA | BZ4: 24 | CA4: 53 | CB4: 0 | CC4: 0 | CD4: Area 1: Rua Adolfo Bergamin (Trecho Rua Mena Barreto A Rua JoAo da Mata Peixoto), Rua Natividade (Trecho Rua Adolfo Bergamin A Rua MArio Valadares), Rua Romilda Alves, Rua Embaixador Von Spritt, Rua Aurea P. Farjado, Rua GenEsio de Barros e pequenas Vilas desse trecho. Area 2: Rua JoAo da Mata Peixoto (Trecho do nº 182 A Rua MArio Valadares), Rua Adolfo Bergamin (Trecho Rua JoAo da Mata Peixoto A Rua Antonio J. Bittencourt), Rua JoAo F. da Silva, Rua Maria InEs QueirOs, Rua AmErico Diamantino Lopes, Rua JosE da Silva Braga (Trecho Rua MArio Valadares A Rua AntOnio J. Bittencourt), Rua Francisco M. da Silva. Area 3: Rua JoAo da Mata Peixoto (Trecho Rua Otacilio Pessoa), Rua JoAo da Cruz Saldanha, Rua Lauro Machado e pequenas Vilas desse trecho.
A5: AMAURI GUIMARAES | B5: =_xlfn.XLOOKUP(A:A,'Dados Elevatórias'!D:D,'Dados Elevatórias'!B:B) -> PL-RJB-EAT0687 | C5: =_xlfn.XLOOKUP(B:B,'Dados Elevatórias'!B:B,'Dados Elevatórias'!C:C) -> EAT | D5: BAIXADA 2 | E5: R. Ângela Maria, 2 - Posse, Nova Iguaçu - RJ, 26089-175 | F5: Floresta | G5: NOVA IGUAÇU | H5: =_xlfn.XLOOKUP(B:B,'Dados Elevatórias'!B:B,'Dados Elevatórias'!G:G) -> 26031-200 | I5: =_xlfn.XLOOKUP(B5,COORDENADAS!A:A,COORDENADAS!B:B) -> -22.736 | J5: =_xlfn.XLOOKUP(B5,COORDENADAS!A:A,COORDENADAS!C:C) -> -43.4782 | L5: FORMAL | M5: 1 | N5: OPERACIONAL | O5: 7.5cv | AC5: TUBULÂO | AF5: ANFÍBIA | AH5: SUBMERSIVEL | AN5: =_xlfn.XLOOKUP(A:A,'RELAÇÃO ANTIGA'!A:A,'RELAÇÃO ANTIGA'!AC:AC,X) -> 220V | AP5: 430248796 | AQ5: 169005 | AR5: 0 | AS5: AGUA - ELEV - AMAURI GUIMARÃES | AT5: RUA GENI SARAIVA E/F 1998 | AU5: 0 | AV5: 0 | AW5: 0 | AX5: 0 | AY5: 0 | AZ5: 0 | BK5: SOFT STARTER | BP5: NÃO | BR5: 0 | BS5: 0 | BT5: 0 | BU5: 0 | BV5: 0 | BW5: SIM | BY5: EM MARCHA | BZ5: 0 | CA5: 0 | CB5: 0 | CC5: 0 | CD5: 0
A6: ÂNGELA MARIA | B6: =_xlfn.XLOOKUP(A:A,'Dados Elevatórias'!D:D,'Dados Elevatórias'!B:B) -> PL-RJB-EAT0088 | C6: =_xlfn.XLOOKUP(B:B,'Dados Elevatórias'!B:B,'Dados Elevatórias'!C:C) -> EAT | D6: BAIXADA 2 | E6: R. Oliveiros Rodrigues Alves, 130 - Jardim da Posse, Nova Iguaçu - RJ, 26030-010 | F6: Jardim da Posse | G6: NOVA IGUAÇU | H6: =_xlfn.XLOOKUP(B:B,'Dados Elevatórias'!B:B,'Dados Elevatórias'!G:G) -> 26030-010 | I6: =_xlfn.XLOOKUP(B6,COORDENADAS!A:A,COORDENADAS!B:B) -> -22.7388 | J6: =_xlfn.XLOOKUP(B6,COORDENADAS!A:A,COORDENADAS!C:C) -> -43.4551 | L6: FORMAL | M6: 1 | N6: OPERACIONAL | O6: 3vc | AC6: CASINHA | AN6: 220V | AP6: 420594529 | AQ6: 73520772 | AR6: 0 | AS6: AGUA - ELEV - ANGELA MARIA | AT6: R ANGELA MARIA SN EF127 | AU6: DN 50 / 2 POL | AV6: DN 50 / 2 POL | AW6: 0 | AX6: 0 | AY6: 0 | AZ6: 0 | BK6: PARTIDA DIRETA | BP6: NÃO | BR6: 0 | BS6: 0 | BT6: 0 | BU6: 1\2º | BV6: 1\2º | BW6: SIM | BY6: EM MARCHA | BZ6: - | CA6: - | CB6: - | CC6: 0 | CD6: 0
A7: ANTONIO VALDIGEM | B7: =_xlfn.XLOOKUP(A:A,'Dados Elevatórias'!D:D,'Dados Elevatórias'!B:B) -> PL-RJB-EAT0736 | C7: =_xlfn.XLOOKUP(B:B,'Dados Elevatórias'!B:B,'Dados Elevatórias'!C:C) -> EAT | D7: BAIXADA 2 | E7: R. Antonio Valdigem, 51 - Queimados, RJ, 26385-300 | F7: Vila das porteiras | G7: QUEIMADOS | H7: =_xlfn.XLOOKUP(B:B,'Dados Elevatórias'!B:B,'Dados Elevatórias'!G:G) -> 26385-300 | I7: =_xlfn.XLOOKUP(B7,COORDENADAS!A:A,COORDENADAS!B:B) -> -22.704 | J7: =_xlfn.XLOOKUP(B7,COORDENADAS!A:A,COORDENADAS!C:C) -> -43.5529 | L7: INFORMAL | M7: 1 | N7: OPERACIONAL | O7: 20cv | P7: 3535rpm | Q7: Weg | R7: 160m | S7: RJB-21457 | T7: 220V / 380V / 440V | U7: 49.8 / 28.8 / 24.9 | X7: GSD-32/200 20.0 | Y7: RJB-21458 | Z7: Ebara | AA7: 2 | AB7: 197mm | AC7: ABRIGADA | AD7: NÃO | AF7: HORIZONTAL | AH7: CONVENSIONAL | AI7: 40M3/h | AJ7: 54mca | AN7: =_xlfn.XLOOKUP(A:A,'RELAÇÃO ANTIGA'!A:A,'RELAÇÃO ANTIGA'!AC:AC,X) -> 220V | AP7: 420630267 | AQ7: 8663425 | AR7: 0 | AS7: AGUA - BVOLANTE - ANTONIO WEINSCHENK | AT7: R ANTONIO VALDIGEM SN CA1 EF25 | AU7: 2 | AV7: 1.1/4 | AW7: 0 | AX7: 0 | AY7: 0 | AZ7: 0 | BJ7: RJB-23520 | BK7: INVERSOR DE FREQUÊNCIA | BL7: ABB | BM7: ACO580-01-089A-2 | BN7: 89/74,8 A | BO7: RJB-23544 | BP7: SIM | BR7: 1 MCA | BS7: 0,2 MCA | BT7: 43 MCA | BU7: NÃO | BV7: NÃO | BW7: NÃO | BX7: NÃO | BY7: EM MARCHA | BZ7: 0 | CA7: 0 | CB7: 0 | CC7: MORRO AZUL | CD7: 0
A8: BEIRA LINHA | B8: =_xlfn.XLOOKUP(A:A,'Dados Elevatórias'!D:D,'Dados Elevatórias'!B:B) -> PL-RJB-EAT0688 | C8: =_xlfn.XLOOKUP(B:B,'Dados Elevatórias'!B:B,'Dados Elevatórias'!C:C) -> EAT | D8: BAIXADA 2 | E8: Av Beira Linha 275 - Miguel Couto - Nova Iguaçu | F8: Miguel Couto | G8: NOVA IGUAÇU | H8: 26070-320 | I8: =_xlfn.XLOOKUP(B8,COORDENADAS!A:A,COORDENADAS!B:B) -> -22.7027 | J8: =_xlfn.XLOOKUP(B8,COORDENADAS!A:A,COORDENADAS!C:C) -> -43.4311 | L8: INFORMAL | M8: 1 | N8: OPERACIONAL | O8: 25cv | P8: 3550rpm | Q8: Weg | R8: 160M | S8: RJB-26491 | T8: 220V / 380V / 440V | U8: 60.9/35/2/30.4 | V8: 6209-ZZ-C3 | W8: 6209-ZZ-C3 | Y8: RJB-26976 | AH8: CONVENSIONAL | AP8: 430086325 | AQ8: 8552185 | BK8: PARTIDA DIRETA | BP8: SIM
A9: BELO HORIZONTE | B9: =_xlfn.XLOOKUP(A:A,'Dados Elevatórias'!D:D,'Dados Elevatórias'!B:B) -> PL-RJB-EAT0083 | C9: =_xlfn.XLOOKUP(B:B,'Dados Elevatórias'!B:B,'Dados Elevatórias'!C:C) -> EAT | D9: BAIXADA 2 | E9: R. Jequitia, 300 - Nova América, Nova Iguaçu - RJ, 26021-630 | F9: Nova América | G9: NOVA IGUAÇU | H9: =_xlfn.XLOOKUP(B:B,'Dados Elevatórias'!B:B,'Dados Elevatórias'!G:G) -> 26021-630 | I9: =_xlfn.XLOOKUP(B9,COORDENADAS!A:A,COORDENADAS!B:B) -> -22.7237 | J9: =_xlfn.XLOOKUP(B9,COORDENADAS!A:A,COORDENADAS!C:C) -> -43.4358 | L9: =_xlfn.XLOOKUP(A:A,'RELAÇÃO ANTIGA'!A:A,'RELAÇÃO ANTIGA'!J:J) -> FORMAL | M9: 1 | N9: OPERACIONAL | O9: 25cv | P9: 3500rpm | S9: RJB-05419 | Y9: RJB-05571 | Z9: WORTHINGTON | AA9: 2 | AC9: ABRIGADA | AF9: VERTICAL | AH9: INLINE | AN9: =_xlfn.XLOOKUP(A:A,'RELAÇÃO ANTIGA'!A:A,'RELAÇÃO ANTIGA'!AC:AC,X) -> 220V | AP9: 412787475 | AQ9: 5241353 | AR9: 0 | AS9: AGUA - BOOSTER - BELO HORIZONTE | AT9: AV BELO HORIZONTE SN FT840 | AU9: 100MM | AV9: 50MM | AW9: 0 | AX9: 0 | AY9: 0 | AZ9: 0 | BK9: INVERSOR DE FREQUÊNCIA | BP9: NÃO | BR9: 1 MCA | BS9: <1MCA | BT9: 0 | BU9: 0 | BV9: 0 | BW9: SIM | BY9: EM MARCHA | BZ9: 0 | CA9: 0 | CB9: 0 | CC9: 0 | CD9: Rua Angico - Rua Belo Horizonte - Rua Brasil - Rua Francisco Alves - Rua General Canraberi - Rua GonCalo Alves - Rua Iris - Rua JequitibA - Rua Leopoldo Machado - Rua Passos - Rua Saudade (parte)
A10: BOOSTER AUSTIN | B10: =_xlfn.XLOOKUP(A:A,'Dados Elevatórias'!D:D,'Dados Elevatórias'!B:B) -> PL-RJB-EAT0695 | C10: =_xlfn.XLOOKUP(B:B,'Dados Elevatórias'!B:B,'Dados Elevatórias'!C:C) -> EAT | D10: BAIXADA 2 | E10: R. Araicas, 27 - Austin, Nova Iguaçu - RJ, 26086-320 | F10: Largo dos peixes | G10: QUEIMADOS | H10: 26086-320 | I10: =_xlfn.XLOOKUP(B10,COORDENADAS!A:A,COORDENADAS!B:B) -> -22.7238 | J10: =_xlfn.XLOOKUP(B10,COORDENADAS!A:A,COORDENADAS!C:C) -> -43.53 | M10: 1 | N10: OPERACIONAL | O10: 400cv | P10: 1190rpm | Q10: WEG | R10: 315S/M | S10: RJB-12396 | T10: 440 | U10: 413 | X10: ZW | Y10: RJB-26840 | Z10: RP | AA10: 6 | AB10: 505mm | AC10: ABRIGADA | AD10: SIM | AE10: CONVENSIONAL | AF10: VERTICAL | AG10: FF | AH10: VERTICAL | AI10: 1908,6 m³/h | AJ10: 47,46 m | AN10: 13.8KV | AO10: 1000kvar | AP10: 0 | AQ10: 0 | AR10: 0 | AS10: 0 | AT10: 0 | BB10: 800A | BJ10: RJB-08633 | BK10: INVERSOR DE FREQUÊNCIA | BL10: WEG | BM10: CFW11 | BN10: 630A | BP10: SIM | BR10: 15 MCA | BS10: 10 MCA | BT10: 45 MCA | BU10: 0 | BV10: 0 | BY10: 0 | BZ10: 0 | CA10: 0 | CB10: 0 | CC10: 0 | CD10: 0
A11: BOOSTER AUSTIN | B11: =_xlfn.XLOOKUP(A:A,'Dados Elevatórias'!D:D,'Dados Elevatórias'!B:B) -> PL-RJB-EAT0695 | C11: =_xlfn.XLOOKUP(B:B,'Dados Elevatórias'!B:B,'Dados Elevatórias'!C:C) -> EAT | D11: BAIXADA 2 | E11: R. Araicas, 27 - Austin, Nova Iguaçu - RJ, 26086-320 | F11: Largo dos peixes | G11: QUEIMADOS | H11: 26086-320 | I11: =_xlfn.XLOOKUP(B11,COORDENADAS!A:A,COORDENADAS!B:B) -> -22.7238 | J11: =_xlfn.XLOOKUP(B11,COORDENADAS!A:A,COORDENADAS!C:C) -> -43.53 | M11: 2 | N11: OPERACIONAL | O11: 400cv | P11: 1190rpm | Q11: WEG | R11: 315S/M | S11: RJB-12370 | T11: 440 | U11: 413 | X11: ZW | Y11: RJB-12362 | Z11: RP | AA11: 6 | AB11: 505mm | AC11: CONTAINER | AD11: SIM | AE11: CONVENSIONAL | AF11: VERTICAL | AG11: FF | AH11: VERTICAL | AI11: 1908,6 m³/h | AJ11: 47,46 m | AN11: 13.8KV | AO11: 1000kvar | AP11: 0 | AQ11: 0 | AR11: 0 | AS11: 0 | AT11: 0 | BJ11: RJB-12356 | BK11: INVERSOR DE FREQUÊNCIA | BL11: WEG | BM11: CFW11 | BN11: 630A | BP11: SIM | BR11: 15 MCA | BS11: 10 MCA | BT11: 45 MCA | BU11: 0 | BV11: 0 | BY11: 0 | BZ11: 0 | CA11: 0 | CB11: 0 | CC11: 0 | CD11: 0
A12: BOOSTER AUSTIN | B12: =_xlfn.XLOOKUP(A:A,'Dados Elevatórias'!D:D,'Dados Elevatórias'!B:B) -> PL-RJB-EAT0695 | C12: =_xlfn.XLOOKUP(B:B,'Dados Elevatórias'!B:B,'Dados Elevatórias'!C:C) -> EAT | D12: BAIXADA 2 | E12: R. Araicas, 27 - Austin, Nova Iguaçu - RJ, 26086-320 | F12: Largo dos peixes | G12: QUEIMADOS | H12: 26086-320 | I12: =_xlfn.XLOOKUP(B12,COORDENADAS!A:A,COORDENADAS!B:B) -> -22.7238 | J12: =_xlfn.XLOOKUP(B12,COORDENADAS!A:A,COORDENADAS!C:C) -> -43.53 | M12: 3 | N12: OPERACIONAL | O12: 400cv | P12: 1190rpm | Q12: WEG | R12: 315S/M | S12: RJB-12392 | T12: 440 | U12: 413 | X12: ZW | Y12: RJB-12376 | Z12: RP | AA12: 6 | AB12: 505mm | AC12: CONTAINER | AD12: SIM | AE12: CONVENSIONAL | AF12: VERTICAL | AG12: FF | AH12: VERTICAL | AI12: 1908,6 m³/h | AJ12: 47,46 m | AN12: 13.8KV | AO12: 1000kvar | AP12: 0 | AQ12: 0 | AR12: 0 | AS12: 0 | AT12: 0 | BJ12: RJB-08630 | BK12: INVERSOR DE FREQUÊNCIA | BL12: WEG | BM12: CFW11 | BN12: 630A | BO12: RJB-30634 | BP12: SIM | BR12: 15 MCA | BS12: 10 MCA | BT12: 45 MCA | BU12: 0 | BV12: 0 | BY12: 0 | BZ12: 0 | CA12: 0 | CB12: 0 | CC12: 0 | CD12: 0
A13: BOOSTER BRASÍLIA | B13: =_xlfn.XLOOKUP(A:A,'Dados Elevatórias'!D:D,'Dados Elevatórias'!B:B) -> PL-RJB-EAT1005 | C13: =_xlfn.XLOOKUP(B:B,'Dados Elevatórias'!B:B,'Dados Elevatórias'!C:C) -> EAT | D13: BAIXADA 2 | E13: R. Prof. Venina Correa Torres, 23 - Centro, Nova Iguaçu - RJ, 26220-100 | F13: Centro | G13: NOVA IGUAÇU | H13: =_xlfn.XLOOKUP(B:B,'Dados Elevatórias'!B:B,'Dados Elevatórias'!G:G) -> 26220-100 | I13: =_xlfn.XLOOKUP(B13,COORDENADAS!A:A,COORDENADAS!B:B) -> -22.7596 | J13: =_xlfn.XLOOKUP(B13,COORDENADAS!A:A,COORDENADAS!C:C) -> -43.4455 | L13: FORMAL | M13: 1 | N13: OPERACIONAL | O13: 100cv | P13: 1783 rpm | Q13: WEG PREMIUM W22 | R13: 250S/M | S13: RJB-23564 | T13: 220V / 380V / 440V | U13: 246A / 142A / 123A | V13: 6314-C3 | W13: 6314-C3 | X13: OMEGA 150-290A | Y13: RJB-23599 | Z13: KSB | AA13: 7 | AB13: 1780mm | AC13: ABRIGADA | AF13: HORIZONTAL | AH13: HORIZONTAL | AI13: 504,0M³/H | AJ13: 33,0MCA | AN13: =_xlfn.XLOOKUP(A:A,'RELAÇÃO ANTIGA'!A:A,'RELAÇÃO ANTIGA'!AC:AC,X) -> 220v | AP13: 0 | AQ13: 0 | AR13: 0 | AS13: 0 | AT13: 0 | BK13: INVERSOR DE FREQUÊNCIA | BP13: SIM | BR13: 6 mca | BS13: 4 mca | BT13: 100 MCA | BU13: 0 | BV13: 0 | BY13: 0 | BZ13: 0 | CA13: 0 | CB13: 0 | CC13: 0 | CD13: 0
A14: BOOSTER BRASÍLIA | B14: =_xlfn.XLOOKUP(A:A,'Dados Elevatórias'!D:D,'Dados Elevatórias'!B:B) -> PL-RJB-EAT1005 | C14: =_xlfn.XLOOKUP(B:B,'Dados Elevatórias'!B:B,'Dados Elevatórias'!C:C) -> EAT | D14: BAIXADA 2 | E14: R. Prof. Venina Correa Torres, 23 - Centro, Nova Iguaçu - RJ, 26220-100 | F14: Centro | G14: NOVA IGUAÇU | H14: =_xlfn.XLOOKUP(B:B,'Dados Elevatórias'!B:B,'Dados Elevatórias'!G:G) -> 26220-100 | I14: =_xlfn.XLOOKUP(B14,COORDENADAS!A:A,COORDENADAS!B:B) -> -22.7596 | J14: =_xlfn.XLOOKUP(B14,COORDENADAS!A:A,COORDENADAS!C:C) -> -43.4455 | L14: FORMAL | M14: 2 | N14: OPERACIONAL | O14: 100cv | P14: 1783 rpm | Q14: WEG PREMIUM W22 | R14: 250S/M | S14: RJB-23528 | T14: 220V / 380V / 440V | U14: 246A / 142A / 123A | V14: 6314-C3 | W14: 6314-C3 | X14: OMEGA 150-290A | Y14: RJB-23577 | Z14: KSB | AA14: 7 | AB14: 1780mm | AC14: ABRIGADA | AF14: HORIZONTAL | AH14: HORIZONTAL | AI14: 504,0M³/H | AJ14: 33,0MCA | AN14: =_xlfn.XLOOKUP(A:A,'RELAÇÃO ANTIGA'!A:A,'RELAÇÃO ANTIGA'!AC:AC,X) -> 220v | AP14: 0 | AQ14: 0 | AR14: 0 | AS14: 0 | AT14: 0 | BK14: INVERSOR DE FREQUÊNCIA | BP14: SIM | BR14: 6 mca | BS14: 4 mca | BT14: 100 MCA | BU14: 0 | BV14: 0 | BY14: 0 | BZ14: 0 | CA14: 0 | CB14: 0 | CC14: 0 | CD14: 0
A15: BOOSTER BRASÍLIA | B15: =_xlfn.XLOOKUP(A:A,'Dados Elevatórias'!D:D,'Dados Elevatórias'!B:B) -> PL-RJB-EAT1005 | C15: =_xlfn.XLOOKUP(B:B,'Dados Elevatórias'!B:B,'Dados Elevatórias'!C:C) -> EAT | D15: BAIXADA 2 | E15: R. Prof. Venina Correa Torres, 23 - Centro, Nova Iguaçu - RJ, 26220-100 | F15: Centro | G15: NOVA IGUAÇU | H15: =_xlfn.XLOOKUP(B:B,'Dados Elevatórias'!B:B,'Dados Elevatórias'!G:G) -> 26220-100 | I15: =_xlfn.XLOOKUP(B15,COORDENADAS!A:A,COORDENADAS!B:B) -> -22.7596 | J15: =_xlfn.XLOOKUP(B15,COORDENADAS!A:A,COORDENADAS!C:C) -> -43.4455 | L15: FORMAL | M15: 3 | N15: OPERACIONAL | O15: 100cv | P15: 1783 rpm | Q15: WEG PREMIUM W22 | R15: 250S/M | S15: RJB-23592 | T15: 220V / 380V / 440V | U15: 246A / 142A / 123A | V15: 6314-C3 | W15: 6314-C3 | X15: OMEGA 150-290A | Y15: RJB-23551 | Z15: KSB | AA15: 7 | AB15: 1780mm | AC15: ABRIGADA | AF15: HORIZONTAL | AH15: HORIZONTAL | AI15: 504,0M³/H | AJ15: 33,0MCA | AN15: =_xlfn.XLOOKUP(A:A,'RELAÇÃO ANTIGA'!A:A,'RELAÇÃO ANTIGA'!AC:AC,X) -> 220v | AP15: 0 | AQ15: 0 | AR15: 0 | AS15: 0 | AT15: 0 | BK15: INVERSOR DE FREQUÊNCIA | BP15: SIM | BR15: 6 mca | BS15: 4 mca | BT15: 100 MCA | BU15: 0 | BV15: 0 | BY15: 0 | BZ15: 0 | CA15: 0 | CB15: 0 | CC15: 0 | CD15: 0
A16: BOOSTER CABUÇU ALTO | B16: =_xlfn.XLOOKUP(A:A,'Dados Elevatórias'!D:D,'Dados Elevatórias'!B:B) -> PL-RJB-EAT0689 | C16: =_xlfn.XLOOKUP(B:B,'Dados Elevatórias'!B:B,'Dados Elevatórias'!C:C) -> EAT | D16: BAIXADA 2 | E16: R. José Cabral, 448 - Cabuçu, Nova Iguaçu - RJ, 26290-048 | F16: Cabuçu | G16: NOVA IGUAÇU | H16: =_xlfn.XLOOKUP(B:B,'Dados Elevatórias'!B:B,'Dados Elevatórias'!G:G) -> 26290-048 | I16: =_xlfn.XLOOKUP(B16,COORDENADAS!A:A,COORDENADAS!B:B) -> -22.764 | J16: =_xlfn.XLOOKUP(B16,COORDENADAS!A:A,COORDENADAS!C:C) -> -43.537 | L16: FORMAL | M16: 1 | N16: OPERACIONAL | O16: 50CV | P16: 1770rpm | Q16: WEG | R16: 200L | S16: RJB-06856 | T16: 220V / 380V / 440V | U16: 122/70.6/61.0 | V16: 6312-C3 | W16: 6212-Z-C3 | X16: OMEGA 150-290A | Y16: RJB-06880 | Z16: KSB | AA16: 4 | AB16: 247mm | AC16: ABRIGADA | AD16: NÃO | AF16: HORIZONTAL | AH16: HORIZONTAL | AI16: 360m³/h | AJ16: 26.1MCA | AN16: 440V | AP16: 430053078 | AQ16: 7891998 | AR16: 0 | AS16: AGUA - ELEV - CABUCU ALTO G1 | AT16: RUA JOSE CABRAL S/NJOSE CABRAL S/N | BK16: INVERSOR DE FREQUÊNCIA | BP16: SIM | BR16: 16 MCA | BS16: 14 MCA | BT16: 45 MCA | BU16: 0 | BV16: 0 | BY16: 0 | BZ16: 0 | CA16: 0 | CB16: 0 | CC16: 0 | CD16: 0
A17: BOOSTER CABUÇU ALTO | B17: =_xlfn.XLOOKUP(A:A,'Dados Elevatórias'!D:D,'Dados Elevatórias'!B:B) -> PL-RJB-EAT0689 | C17: =_xlfn.XLOOKUP(B:B,'Dados Elevatórias'!B:B,'Dados Elevatórias'!C:C) -> EAT | D17: BAIXADA 2 | E17: R. José Cabral, 448 - Cabuçu, Nova Iguaçu - RJ, 26290-048 | F17: Cabuçu | G17: NOVA IGUAÇU | H17: =_xlfn.XLOOKUP(B:B,'Dados Elevatórias'!B:B,'Dados Elevatórias'!G:G) -> 26290-048 | I17: =_xlfn.XLOOKUP(B17,COORDENADAS!A:A,COORDENADAS!B:B) -> -22.764 | J17: =_xlfn.XLOOKUP(B17,COORDENADAS!A:A,COORDENADAS!C:C) -> -43.537 | L17: FORMAL | M17: 2 | N17: OPERACIONAL | O17: 50CV | P17: 1770rpm | Q17: WEG | R17: 200L | S17: RJB-06865 | T17: 220V / 380V / 440V | U17: 122/70.6/61.0 | V17: 6312-C3 | W17: 6212-Z-C3 | X17: OMEGA 150-290A | Y17: SEM INFRA | Z17: KSB | AA17: 4 | AB17: 247mm | AC17: ABRIGADA | AD17: NÃO | AF17: HORIZONTAL | AH17: HORIZONTAL | AI17: 360m³/h | AJ17: 26.1MCA | AN17: 440V | AP17: 430053078 | AQ17: 7891998 | AR17: 0 | AS17: AGUA - ELEV - CABUCU ALTO G1 | AT17: RUA JOSE CABRAL S/NJOSE CABRAL S/N | BK17: INVERSOR DE FREQUÊNCIA | BP17: SIM | BR17: 16 MCA | BS17: 14 MCA | BT17: 45 MCA | BU17: 0 | BV17: 0 | BY17: 0 | BZ17: 0 | CA17: 0 | CB17: 0 | CC17: 0 | CD17: 0
A18: BOOSTER CABUÇU ALTO | B18: =_xlfn.XLOOKUP(A:A,'Dados Elevatórias'!D:D,'Dados Elevatórias'!B:B) -> PL-RJB-EAT0689 | C18: =_xlfn.XLOOKUP(B:B,'Dados Elevatórias'!B:B,'Dados Elevatórias'!C:C) -> EAT | D18: BAIXADA 2 | E18: R. José Cabral, 448 - Cabuçu, Nova Iguaçu - RJ, 26290-048 | F18: Cabuçu | G18: NOVA IGUAÇU | H18: =_xlfn.XLOOKUP(B:B,'Dados Elevatórias'!B:B,'Dados Elevatórias'!G:G) -> 26290-048 | I18: =_xlfn.XLOOKUP(B18,COORDENADAS!A:A,COORDENADAS!B:B) -> -22.764 | J18: =_xlfn.XLOOKUP(B18,COORDENADAS!A:A,COORDENADAS!C:C) -> -43.537 | L18: FORMAL | M18: 3 | N18: RESERVA | O18: 50CV | P18: 1770rpm | Q18: WEG | R18: 200L | S18: RJB-06888 | T18: 220V / 380V / 440V | U18: 122/70.6/61.0 | V18: 6312-C3 | W18: 6212-Z-C3 | X18: OMEGA 150-290A | Y18: RJB-06864 | Z18: KSB | AA18: 4 | AB18: 247mm | AC18: ABRIGADA | AD18: NÃO | AF18: HORIZONTAL | AH18: HORIZONTAL | AI18: 360m³/h | AJ18: 26.1MCA | AN18: 440V | AP18: 430053078 | AQ18: 7891998 | AR18: 0 | AS18: AGUA - ELEV - CABUCU ALTO G1 | AT18: RUA JOSE CABRAL S/NJOSE CABRAL S/N | BK18: INVERSOR DE FREQUÊNCIA | BP18: SIM | BR18: 16 MCA | BS18: 14 MCA | BT18: 45 MCA | BU18: 0 | BV18: 0 | BY18: 0 | BZ18: 0 | CA18: 0 | CB18: 0 | CC18: 0 | CD18: 0
A19: BOOSTER ENGENHEIRO PEDREIRA | B19: =_xlfn.XLOOKUP(A:A,'Dados Elevatórias'!D:D,'Dados Elevatórias'!B:B) -> PL-RJB-EAT0122 | C19: =_xlfn.XLOOKUP(B:B,'Dados Elevatórias'!B:B,'Dados Elevatórias'!C:C) -> EAT | D19: BAIXADA 2 | E19: Cidade Jardim Marajoara, Japeri - RJ, 26420-243 | F19: Jardim Marajoara | G19: JAPERI | H19: =_xlfn.XLOOKUP(B:B,'Dados Elevatórias'!B:B,'Dados Elevatórias'!G:G) -> 26420-243 | I19: =_xlfn.XLOOKUP(B19,COORDENADAS!A:A,COORDENADAS!B:B) -> -22.7075 | J19: =_xlfn.XLOOKUP(B19,COORDENADAS!A:A,COORDENADAS!C:C) -> -43.6287 | M19: 1 | N19: OPERACIONAL | O19: 200cv | P19: 1790rpm | Q19: W22 PREMIUM | R19: 315S/M | S19: RJB-20410 | T19: 220V / 380V / 440V | U19: 476 / 278 / 238A | V19: 6319-C3 | W19: 6316-C3 | X19: OMEGA 150-460B | Y19: RJB-20411 | Z19: KSB | AA19: 4 | AC19: ABRIGADA | AD19: NÃO | AF19: HORIZONTAL | AH19: HORIZONTAL | AI19: 360 m³/h | AJ19: 110MCA | AL19: placa | AN19: 220V | AO19: 250 | AP19: 0 | AQ19: 0 | AR19: 0 | AS19: 0 | AT19: 0 | BK19: INVERSOR DE FREQUÊNCIA | BL19: POWER ELETRONICS | BM19: SD750 | BN19: 250KW | BO19: RJB-18851 | BP19: SIM | BR19: 7 MCA | BS19: 5 MCA | BT19: 99.9 | BU19: 0 | BV19: 0 | BY19: 0 | BZ19: 0 | CA19: 0 | CB19: 0 | CC19: 0 | CD19: 0
A20: BOOSTER ENGENHEIRO PEDREIRA | B20: =_xlfn.XLOOKUP(A:A,'Dados Elevatórias'!D:D,'Dados Elevatórias'!B:B) -> PL-RJB-EAT0122 | C20: =_xlfn.XLOOKUP(B:B,'Dados Elevatórias'!B:B,'Dados Elevatórias'!C:C) -> EAT | D20: BAIXADA 2 | E20: Cidade Jardim Marajoara, Japeri - RJ, 26420-243 | F20: Jardim Marajoara | G20: JAPERI | H20: =_xlfn.XLOOKUP(B:B,'Dados Elevatórias'!B:B,'Dados Elevatórias'!G:G) -> 26420-243 | I20: =_xlfn.XLOOKUP(B20,COORDENADAS!A:A,COORDENADAS!B:B) -> -22.7075 | J20: =_xlfn.XLOOKUP(B20,COORDENADAS!A:A,COORDENADAS!C:C) -> -43.6287 | M20: 2 | N20: OPERACIONAL | O20: 200cv | P20: 1790rpm | Q20: W22 PREMIUM | R20: 315S/M | S20: RJB-20459 | T20: 220V / 380V / 440V | U20: 476 / 276 / 238A | V20: 6319-C3 | W20: 6318-C3 | X20: OMEGA 150-460 B | Y20: RJB-20499 | Z20: KSB | AA20: 4 | AC20: ABRIGADA | AD20: NÃO | AF20: HORIZONTAL | AH20: HORIZONTAL | AI20: 360 m³/h | AJ20: 110MCA | AL20: placa | AN20: 220V | AO20: 250 | AP20: 0 | AQ20: 0 | AR20: 0 | AS20: 0 | AT20: 0 | BK20: INVERSOR DE FREQUÊNCIA | BL20: POWER ELETRONICS | BM20: SD750 | BN20: 400KW | BO20: RJB-26831 | BP20: SIM | BR20: 7 MCA | BS20: 5 MCA | BT20: 99.9 | BU20: 0 | BV20: 0 | BY20: 0 | BZ20: 0 | CA20: 0 | CB20: 0 | CC20: 0 | CD20: 0
A21: BOOSTER JK | B21: =_xlfn.XLOOKUP(A:A,'Dados Elevatórias'!D:D,'Dados Elevatórias'!B:B) -> PL-RJB-EAT0746 | C21: =_xlfn.XLOOKUP(B:B,'Dados Elevatórias'!B:B,'Dados Elevatórias'!C:C) -> EAT | D21: BAIXADA 2 | E21: R. da Cascata, 60 - Pres. Juscelino, Mesquita - RJ, 26557-700 | F21: Pres. Juscelino | G21: MESQUITA | H21: =_xlfn.XLOOKUP(B:B,'Dados Elevatórias'!B:B,'Dados Elevatórias'!G:G) -> 26557-700 | I21: =_xlfn.XLOOKUP(B21,COORDENADAS!A:A,COORDENADAS!B:B) -> -22.7702 | J21: =_xlfn.XLOOKUP(B21,COORDENADAS!A:A,COORDENADAS!C:C) -> -43.4356 | M21: 1 | N21: OPERACIONAL | O21: 450CV | P21: 1793rpm | Q21: WEG | R21: 355.4L | S21: RJB-02539 | T21: 440 | U21: 515 | X21: RDL 250-400 A | Y21: RJB-07474 | Z21: KSB | AA21: 4 | AC21: ABRIGADA | AD21: NÃO | AF21: HORIZONTAL | AH21: HORIZONTAL | AI21: 1070M3/H | AJ21: 85MCA | AN21: 440V | AO21: 1000kvar | AP21: 0 | AQ21: 0 | AR21: 0 | AS21: 0 | AT21: 0 | BK21: INVERSOR DE FREQUÊNCIA | BL21: POWER ELETRONICS | BM21: SD750 | BP21: SIM | BR21: 2 | BS21: 2 | BT21: 0 | BU21: 0 | BV21: 0 | BY21: 0 | BZ21: 0 | CA21: 0 | CB21: 0 | CC21: 0 | CD21: 0
A22: BOOSTER JK | B22: =_xlfn.XLOOKUP(A:A,'Dados Elevatórias'!D:D,'Dados Elevatórias'!B:B) -> PL-RJB-EAT0746 | C22: =_xlfn.XLOOKUP(B:B,'Dados Elevatórias'!B:B,'Dados Elevatórias'!C:C) -> EAT | D22: BAIXADA 2 | E22: R. da Cascata, 60 - Pres. Juscelino, Mesquita - RJ, 26557-700 | F22: Pres. Juscelino | G22: MESQUITA | H22: =_xlfn.XLOOKUP(B:B,'Dados Elevatórias'!B:B,'Dados Elevatórias'!G:G) -> 26557-700 | I22: =_xlfn.XLOOKUP(B22,COORDENADAS!A:A,COORDENADAS!B:B) -> -22.7702 | J22: =_xlfn.XLOOKUP(B22,COORDENADAS!A:A,COORDENADAS!C:C) -> -43.4356 | M22: 2 | N22: OPERACIONAL | O22: 450CV | P22: 1793rpm | Q22: WEG | R22: 355M | S22: RJB-07405 | T22: 440 | U22: 515 | X22: RDL 250-400 A | Y22: RJB-07403 | Z22: KSB | AA22: 4 | AC22: ABRIGADA | AD22: NÃO | AF22: HORIZONTAL | AH22: HORIZONTAL | AI22: 1070M3/H | AJ22: 85MCA | AN22: 440V | AO22: 1000kvar | AP22: 0 | AQ22: 0 | AR22: 0 | AS22: 0 | AT22: 0 | BK22: INVERSOR DE FREQUÊNCIA | BL22: POWER ELETRONICS | BM22: SD750 | BP22: SIM | BR22: 2 | BS22: 2 | BT22: 0 | BU22: 0 | BV22: 0 | BY22: 0 | BZ22: 0 | CA22: 0 | CB22: 0 | CC22: 0 | CD22: 0
A23: BOOSTER JK | B23: =_xlfn.XLOOKUP(A:A,'Dados Elevatórias'!D:D,'Dados Elevatórias'!B:B) -> PL-RJB-EAT0746 | C23: =_xlfn.XLOOKUP(B:B,'Dados Elevatórias'!B:B,'Dados Elevatórias'!C:C) -> EAT | D23: BAIXADA 2 | E23: R. da Cascata, 60 - Pres. Juscelino, Mesquita - RJ, 26557-700 | F23: Pres. Juscelino | G23: MESQUITA | H23: =_xlfn.XLOOKUP(B:B,'Dados Elevatórias'!B:B,'Dados Elevatórias'!G:G) -> 26557-700 | I23: =_xlfn.XLOOKUP(B23,COORDENADAS!A:A,COORDENADAS!B:B) -> -22.7702 | J23: =_xlfn.XLOOKUP(B23,COORDENADAS!A:A,COORDENADAS!C:C) -> -43.4356 | M23: 3 | N23: OPERACIONAL | O23: 250CV | P23: 1790rpm | Q23: WEG | S23: RJB-03614 | T23: 220 / 380 / 440 | U23: 584 / 338 / 292 | Y23: RJB-26813 | Z23: WHORTHINGTON | AA23: 4 | AC23: ABRIGADA | AD23: NÃO | AF23: HORIZONTAL | AH23: HORIZONTAL | AN23: 440V | AO23: 1000kvar | AP23: 0 | AQ23: 0 | AR23: 0 | AS23: 0 | AT23: 0 | BK23: INVERSOR DE FREQUÊNCIA | BL23: POWER ELETRONICS | BM23: SD75070055 | BN23: 315kW | BO23: RJB-20155 | BP23: SIM | BR23: 2 | BS23: 2 | BT23: 0 | BU23: 0 | BV23: 0 | BY23: 0 | BZ23: 0 | CA23: 0 | CB23: 0 | CC23: 0 | CD23: 0
A24: BOOSTER JK | B24: =_xlfn.XLOOKUP(A:A,'Dados Elevatórias'!D:D,'Dados Elevatórias'!B:B) -> PL-RJB-EAT0746 | C24: =_xlfn.XLOOKUP(B:B,'Dados Elevatórias'!B:B,'Dados Elevatórias'!C:C) -> EAT | D24: BAIXADA 2 | E24: R. da Cascata, 60 - Pres. Juscelino, Mesquita - RJ, 26557-700 | F24: Pres. Juscelino | G24: MESQUITA | H24: =_xlfn.XLOOKUP(B:B,'Dados Elevatórias'!B:B,'Dados Elevatórias'!G:G) -> 26557-700 | I24: =_xlfn.XLOOKUP(B24,COORDENADAS!A:A,COORDENADAS!B:B) -> -22.7702 | J24: =_xlfn.XLOOKUP(B24,COORDENADAS!A:A,COORDENADAS!C:C) -> -43.4356 | M24: 4 | N24: OPERACIONAL | O24: 250CV | P24: 1793 a 1850 rpm | Q24: WEG | S24: RJB-18296 | T24: 220V / 380V / 440V | Y24: RJB-07453 | Z24: RJA-08472 | AA24: 4 | AC24: ABRIGADA | AD24: NÃO | AF24: HORIZONTAL | AH24: HORIZONTAL | AN24: 440V | AO24: 1000kvar | AP24: 0 | AQ24: 0 | AR24: 0 | AS24: 0 | AT24: 0 | BK24: INVERSOR DE FREQUÊNCIA | BL24: POWER ELETRONICS | BM24: SD75032055 | BN24: 320A | BO24: RJB-22128 | BP24: SIM | BR24: 2 | BS24: 2 | BT24: 0 | BU24: 0 | BV24: 0 | BY24: 0 | BZ24: 0 | CA24: 0 | CB24: 0 | CC24: 0 | CD24: 0
A25: BOOSTER POSSE | B25: =_xlfn.XLOOKUP(A:A,'Dados Elevatórias'!D:D,'Dados Elevatórias'!B:B) -> PL-RJB-EAT0042 | C25: =_xlfn.XLOOKUP(B:B,'Dados Elevatórias'!B:B,'Dados Elevatórias'!C:C) -> EAT | D25: BAIXADA 2 | E25: Estrada velha de Iguaçu, 812 - Miguel Couto , Belford Roxo - RJ | F25: Miguel Couto | G25: NOVA IGUAÇU | H25: 26145-420 | I25: =_xlfn.XLOOKUP(B25,COORDENADAS!A:A,COORDENADAS!B:B) -> -22.7096 | J25: =_xlfn.XLOOKUP(B25,COORDENADAS!A:A,COORDENADAS!C:C) -> -43.4287 | L25: FORMAL | M25: 1 | N25: OPERACIONAL | O25: 175cv | P25: 1791rpm | Q25: WEG | S25: VERIFICAR | T25: 220 / 380 / 440 | U25: 424 / 245 / 212 | X25: OMEGA 150-460 B | Y25: VERIFICAR | Z25: KSB | AA25: 4 | AB25: Sem Dados | AC25: ABRIGADA | AD25: NÃO | AE25: CONVENSIONAL | AF25: HORIZONTAL | AG25: CONVENSIONAL | AH25: HORIZONTAL | AI25: 450 M³/H | AJ25: 82MCA | AN25: 440V | AO25: 750kva | AP25: 0 | AQ25: 0 | AR25: 0 | AS25: 0 | AT25: 0 | BK25: INVERSOR DE FREQUÊNCIA | BL25: ABB | BM25: ACQ580-430A | BN25: 430A | BP25: SIM | BR25: 4 mca | BS25: 3mca | BT25: 80MCA | BU25: 0 | BV25: 0 | BY25: 0 | BZ25: 0 | CA25: 0 | CB25: 0 | CC25: 0 | CD25: 0
A26: BOOSTER POSSE | B26: =_xlfn.XLOOKUP(A:A,'Dados Elevatórias'!D:D,'Dados Elevatórias'!B:B) -> PL-RJB-EAT0042 | C26: =_xlfn.XLOOKUP(B:B,'Dados Elevatórias'!B:B,'Dados Elevatórias'!C:C) -> EAT | D26: BAIXADA 2 | E26: Estrada velha de Iguaçu, 812 - Miguel Couto , Belford Roxo - RJ | F26: Miguel Couto | G26: NOVA IGUAÇU | H26: 26145-420 | I26: =_xlfn.XLOOKUP(B26,COORDENADAS!A:A,COORDENADAS!B:B) -> -22.7096 | J26: =_xlfn.XLOOKUP(B26,COORDENADAS!A:A,COORDENADAS!C:C) -> -43.4287 | L26: FORMAL | M26: 2 | N26: OPERACIONAL | O26: 175cv | P26: 1791rpm | Q26: WEG | S26: RJB-23844 | T26: 220 / 380 / 440 | U26: 424 / 245 / 212 | X26: OMEGA 150-460 B | Y26: RJB-23847 | Z26: KSB | AA26: 4 | AB26: Sem Dados | AC26: ABRIGADA | AD26: NÃO | AE26: CONVENSIONAL | AF26: HORIZONTAL | AG26: CONVENSIONAL | AH26: HORIZONTAL | AI26: 450 M³/H | AJ26: 82MCA | AN26: 440V | AO26: 750kva | AP26: 0 | AQ26: 0 | AR26: 0 | AS26: 0 | AT26: 0 | BJ26: RJB-23834 | BK26: INVERSOR DE FREQUÊNCIA | BL26: ABB | BM26: ACQ580-430A | BN26: 430A | BO26: RJB-23834 | BP26: SIM | BR26: 6 mca | BS26: 3mca | BT26: 80MCA | BU26: 0 | BV26: 0 | BY26: 0 | BZ26: 0 | CA26: 0 | CB26: 0 | CC26: 0 | CD26: 0
A27: BOOSTER POSSE | B27: =_xlfn.XLOOKUP(A:A,'Dados Elevatórias'!D:D,'Dados Elevatórias'!B:B) -> PL-RJB-EAT0042 | C27: =_xlfn.XLOOKUP(B:B,'Dados Elevatórias'!B:B,'Dados Elevatórias'!C:C) -> EAT | D27: BAIXADA 2 | E27: Estrada velha de Iguaçu, 812 - Miguel Couto , Belford Roxo - RJ | F27: Miguel Couto | G27: NOVA IGUAÇU | H27: 26145-420 | I27: =_xlfn.XLOOKUP(B27,COORDENADAS!A:A,COORDENADAS!B:B) -> -22.7096 | J27: =_xlfn.XLOOKUP(B27,COORDENADAS!A:A,COORDENADAS!C:C) -> -43.4287 | L27: FORMAL | M27: 3 | N27: OPERACIONAL | O27: 175cv | P27: 1791rpm | Q27: WEG | S27: VERIFICAR | T27: 220 / 380 / 440 | U27: 424 / 245 / 212 | X27: OMEGA 150-460 B | Y27: RJB-26816 | Z27: KSB | AA27: 4 | AB27: Sem Dados | AC27: ABRIGADA | AD27: NÃO | AE27: CONVENSIONAL | AF27: HORIZONTAL | AG27: CONVENSIONAL | AH27: HORIZONTAL | AI27: 450 M³/H | AJ27: 82MCA | AN27: 440V | AO27: 750kva | AP27: 0 | AQ27: 0 | AR27: 0 | AS27: 0 | AT27: 0 | BJ27: RJB-23424 | BK27: INVERSOR DE FREQUÊNCIA | BL27: POWER ELETRONICS | BM27: SD 750 | BO27: RJB-23424 | BP27: SIM | BR27: 8 mca | BS27: 3mca | BT27: 80MCA | BU27: 0 | BV27: 0 | BY27: 0 | BZ27: 0 | CA27: 0 | CB27: 0 | CC27: 0 | CD27: 0
A28: BOOSTER POSSE | B28: =_xlfn.XLOOKUP(A:A,'Dados Elevatórias'!D:D,'Dados Elevatórias'!B:B) -> PL-RJB-EAT0042 | C28: =_xlfn.XLOOKUP(B:B,'Dados Elevatórias'!B:B,'Dados Elevatórias'!C:C) -> EAT | D28: BAIXADA 2 | E28: Estrada velha de Iguaçu, 812 - Miguel Couto , Belford Roxo - RJ | F28: Miguel Couto | G28: NOVA IGUAÇU | H28: 26145-420 | I28: =_xlfn.XLOOKUP(B28,COORDENADAS!A:A,COORDENADAS!B:B) -> -22.7096 | J28: =_xlfn.XLOOKUP(B28,COORDENADAS!A:A,COORDENADAS!C:C) -> -43.4287 | L28: FORMAL | M28: 4 | N28: OPERACIONAL | O28: 175cv | P28: 1791rpm | Q28: WEG | S28: VERIFICAR | T28: 220 / 380 / 440 | U28: 424 / 245 / 212 | X28: OMEGA 150-460 B | Y28: VERIFICAR | Z28: KSB | AA28: 4 | AB28: Sem Dados | AC28: ABRIGADA | AD28: NÃO | AE28: CONVENSIONAL | AF28: HORIZONTAL | AG28: CONVENSIONAL | AH28: HORIZONTAL | AI28: 450 M³/H | AJ28: 82MCA | AN28: 440V | AO28: 750kva | AP28: 0 | AQ28: 0 | AR28: 0 | AS28: 0 | AT28: 0 | BK28: INVERSOR DE FREQUÊNCIA | BL28: DANFOSS | BN28: MANUTENÇÃO | BP28: SIM | BS28: 3mca | BT28: 80MCA | BU28: 0 | BV28: 0 | BY28: 0 | BZ28: 0 | CA28: 0 | CB28: 0 | CC28: 0 | CD28: 0
A29: BURITI | B29: =_xlfn.XLOOKUP(A:A,'Dados Elevatórias'!D:D,'Dados Elevatórias'!B:B) -> PL-RJB-EAT0684 | C29: =_xlfn.XLOOKUP(B:B,'Dados Elevatórias'!B:B,'Dados Elevatórias'!C:C) -> EAT | D29: BAIXADA 2 | E29: R. Freitas De Aguiar, 13 - Eucalipto, Japeri - RJ, 26453-325 | F29: Eucalipto | G29: JAPERI | H29: =_xlfn.XLOOKUP(B:B,'Dados Elevatórias'!B:B,'Dados Elevatórias'!G:G) -> 26453-325 | I29: =_xlfn.XLOOKUP(B29,COORDENADAS!A:A,COORDENADAS!B:B) -> -22.6731 | J29: =_xlfn.XLOOKUP(B29,COORDENADAS!A:A,COORDENADAS!C:C) -> -43.6112 | L29: =_xlfn.XLOOKUP(A:A,'RELAÇÃO ANTIGA'!A:A,'RELAÇÃO ANTIGA'!J:J) -> INFORMAL | M29: 1 | N29: OPERACIONAL | O29: 7.5 cv | S29: RJB-17524 | V29: / | X29: 050-032-160 | Y29: RJB-17563 | Z29: SCHNEIDER | AA29: 2 | AB29: 150mm | AC29: ABRIGADA | AF29: HORIZONTAL | AH29: CONVENSIONAL | AI29: 41m3/h | AJ29: 46mca | AN29: =_xlfn.XLOOKUP(A:A,'RELAÇÃO ANTIGA'!A:A,'RELAÇÃO ANTIGA'!AC:AC,X) -> 220V | AP29: 0 | AQ29: 0 | AR29: 0 | AS29: 0 | AT29: 0 | AU29: 2POL | AV29: 1.1/4 | AW29: 0 | AX29: 0 | AY29: 0 | AZ29: 0 | BJ29: RJB-01927 | BK29: PARTIDA DIRETA | BP29: NÃO | BR29: 0 | BS29: 0 | BT29: 0 | BU29: X | BV29: 0 | BY29: EM MARCHA | BZ29: 0 | CA29: 0 | CB29: 0 | CC29: 0 | CD29: 0
A30: CAIÇARA | B30: =_xlfn.XLOOKUP(A:A,'Dados Elevatórias'!D:D,'Dados Elevatórias'!B:B) -> PL-RJB-EAT0048 | C30: =_xlfn.XLOOKUP(B:B,'Dados Elevatórias'!B:B,'Dados Elevatórias'!C:C) -> EAT | D30: BAIXADA 2 | E30: Tv. Benjamim Chanbarelli, 30 - Caonze, Nova Iguaçu - RJ, 26250-120 | F30: Jardim da Posse | G30: NOVA IGUAÇU | H30: =_xlfn.XLOOKUP(B:B,'Dados Elevatórias'!B:B,'Dados Elevatórias'!G:G) -> 26021-072 | I30: =_xlfn.XLOOKUP(B30,COORDENADAS!A:A,COORDENADAS!B:B) -> -22.7284 | J30: =_xlfn.XLOOKUP(B30,COORDENADAS!A:A,COORDENADAS!C:C) -> -43.4433 | L30: =_xlfn.XLOOKUP(A:A,'RELAÇÃO ANTIGA'!A:A,'RELAÇÃO ANTIGA'!J:J) -> FORMAL | M30: 1 | N30: OPERACIONAL | O30: 20cv | P30: 3535rpm | Q30: WEG | S30: RJB-05451 | T30: 220 / 380 | U30: 50.3 / 29.1 | X30: MONOBLOCO | Y30: RJB-05513 | Z30: Ingersoll-Dresser Pumps | AA30: 2 | AB30: 165,1 mm | AC30: ABRIGADA | AD30: NÃO | AF30: HORIZONTAL | AH30: CONVENSIONAL | AP30: 413110570 | AQ30: 5028144 | AR30: 0 | AS30: AGUA - BOOSTER - CAICARA | AT30: PCA OITICICA SN FT52 | AU30: 100MM | AV30: 75MMM | AW30: 0 | AX30: 0 | AY30: 0 | AZ30: 0 | BJ30: RJB-18806 | BK30: INVERSOR DE FREQUÊNCIA | BL30: DANFOSS | BM30: FC-101 | BN30: 22KW/30HP | BO30: RJB-18807 | BP30: NÃO | BR30: 1 MCA | BS30: 1 MCA | BU30: 0 | BV30: 0 | BW30: SIM | BY30: EM MARCHA | BZ30: 0 | CA30: 0 | CB30: 0 | CC30: 0 | CD30: Rua AnambA - Rua Angelina - Rua Bacuri - Rua Eucalipto - Rua GoiAs - Rua Jaras - Rua JatobA - Rua JequitibA Rosa - Rua JequitibA - Rua Leopoldo Machado - Rua Massaranduba - Rua Ocabu - Rua Oiti - Rua Pequim
A31: CAIXA VELHA | B31: =_xlfn.XLOOKUP(A:A,'Dados Elevatórias'!D:D,'Dados Elevatórias'!B:B) -> PL-RJB-EAT0011 | C31: =_xlfn.XLOOKUP(B:B,'Dados Elevatórias'!B:B,'Dados Elevatórias'!C:C) -> EAT | D31: BAIXADA 2 | E31: R. Tab. Murilo Costa, 140 - Centro | F31: Centro | G31: NOVA IGUAÇU | H31: 26255-130 | I31: =_xlfn.XLOOKUP(B31,COORDENADAS!A:A,COORDENADAS!B:B) -> -22.7631 | J31: =_xlfn.XLOOKUP(B31,COORDENADAS!A:A,COORDENADAS!C:C) -> -43.4531 | L31: =_xlfn.XLOOKUP(A:A,'RELAÇÃO ANTIGA'!A:A,'RELAÇÃO ANTIGA'!J:J) -> FORMAL | M31: 1 | N31: OPERACIONAL | O31: 40cv | P31: 3550rpm | Q31: WEG | S31: RJB-12016 | T31: 220 / 380 | U31: 97.6 / 56.5 | Y31: RJB-04532 | AA31: 2 | AC31: ABRIGADA | AD31: NÃO | AF31: VERTICAL | AH31: INLINE | AN31: =_xlfn.XLOOKUP(A:A,'RELAÇÃO ANTIGA'!A:A,'RELAÇÃO ANTIGA'!AC:AC,X) -> 220V | AP31: 411457794 | AQ31: 7516646 | AR31: 0 | AS31: AGUA - ELEV - BRASILIA | AT31: R TABE MURILO COSTA 141 | AU31: 100MM | AV31: 150MM | AW31: 0 | AX31: 0 | AY31: 0 | AZ31: 0 | BJ31: RJB-00159 | BK31: INVERSOR DE FREQUÊNCIA | BL31: DANFOSS | BM31: VLT Aqua Drive | BO31: RJB-16854 | BP31: SIM | BR31: 1 MCA | BS31: 1 MCA | BT31: 80MCA | BU31: 0 | BV31: 0 | BW31: SIM | BY31: EM MARCHA | BZ31: 0 | CA31: 0 | CB31: 0 | CC31: 0 | CD31: Rua 15 de Agosto - Rua 1º de Maio - Rua 23 de Abril - Rua 25 de Dezembro - Rua AntOnio de Almeida - Rua da Liberdade - Rua das Mangueiras - Rua do GDRM-11tAo - Rua Dona Rita - Rua Dr. Tibau - Rua Juiz Antonio Belot de Souza - Rua Rangel Pestana - Rua Rejane Pedro Equi - Rua SebastiAo dos Reis - Rua SebastiAo Herculano de Matos (parte) - Rua TabeliAo Murilo Costa (parte) - Rua Zilda - Travessa Dr. Tibau - Travessa Maria JosE - Travessa Shirley - Travessa Soares
A32: CABUÇU BAIXO | B32: =_xlfn.XLOOKUP(A:A,'Dados Elevatórias'!D:D,'Dados Elevatórias'!B:B) -> PL-RJB-EAT0847 | C32: =_xlfn.XLOOKUP(B:B,'Dados Elevatórias'!B:B,'Dados Elevatórias'!C:C) -> EAT | D32: BAIXADA 2 | E32: Av. Abílio Augusto Távora, 5157 - Vl Valverde, Nova Iguaçu - RJ, 26290-717 | F32: Vl Valverde | G32: NOVA IGUAÇU | H32: =_xlfn.XLOOKUP(B:B,'Dados Elevatórias'!B:B,'Dados Elevatórias'!G:G) -> 26290-717 | I32: =_xlfn.XLOOKUP(B32,COORDENADAS!A:A,COORDENADAS!B:B) -> -22.7759 | J32: =_xlfn.XLOOKUP(B32,COORDENADAS!A:A,COORDENADAS!C:C) -> -43.5315 | M32: 1 | N32: OPERACIONAL | O32: 75CV | P32: 3500rpm | Q32: HELIBOMBAS | T32: 220V / 380V | U32: 187,1A/108,3A | X32: HAM-75/305-1 | Z32: HELIBOMAS | AC32: ABRIGADA | AD32: SIM | AF32: ANFÍBIA | AI32: 750M³/H | AJ32: 16,5MCA | AN32: 380V | AP32: 0 | AQ32: 0 | AR32: 0 | AS32: 0 | AT32: 0 | AU32: 0 | AV32: 0 | AW32: 0 | AX32: 0 | AY32: 0 | AZ32: 0 | BJ32: RJB-23752 | BK32: INVERSOR DE FREQUÊNCIA | BL32: ABB | BN32: 145/124 A | BO32: RJB-24088 | BP32: SIM | BR32: 0 | BS32: 0 | BT32: 0 | BU32: 0 | BV32: 0 | BY32: 0 | BZ32: 0 | CA32: 0 | CB32: 0 | CC32: 0 | CD32: 0
A33: CANADENSE | B33: =_xlfn.XLOOKUP(A:A,'Dados Elevatórias'!D:D,'Dados Elevatórias'!B:B) -> PL-RJB-EAT0056 | C33: =_xlfn.XLOOKUP(B:B,'Dados Elevatórias'!B:B,'Dados Elevatórias'!C:C) -> EAT | D33: BAIXADA 2 | E33: Rua Gen. Olímpio da Fonseca, 917 - Paiol de Pólvora, Nilópolis - RJ, 26545-470 | F33: Paiol de Pólvora | G33: NILÓPOLIS | H33: =_xlfn.XLOOKUP(B:B,'Dados Elevatórias'!B:B,'Dados Elevatórias'!G:G) -> 26545-470 | I33: =_xlfn.XLOOKUP(B33,COORDENADAS!A:A,COORDENADAS!B:B) -> -22.8137 | J33: =_xlfn.XLOOKUP(B33,COORDENADAS!A:A,COORDENADAS!C:C) -> -43.3945 | L33: =_xlfn.XLOOKUP(A:A,'RELAÇÃO ANTIGA'!A:A,'RELAÇÃO ANTIGA'!J:J) -> INFORMAL | M33: 1 | N33: OPERACIONAL | O33: 4,5CV | P33: 3450RPM | Q33: VANBRO | R33: VMSP | T33: 220V / 380V / 440V | U33: 13.8/8.0 | X33: VBSP.67X.02.045.Y | Z33: VANBRO | AA33: 2 | AB33: 140mm | AC33: SUBMERSA | AF33: SUBMERSA VERTICAL | AH33: SUBMERSA | AI33: 24m³/h | AJ33: 33,5mca | AL33: RESERVA FRIA | AM33: 5501608 | AN33: 220V | AP33: 420149824 | AQ33: 5404178 | AR33: 0 | AS33: AGUA - BOOSTER - UNIVERSAL CANADENSE | AT33: R JOAO DIEZ LIMA 97 | AU33: 0 | AV33: 0 | AW33: 0 | AX33: 0 | AY33: 0 | AZ33: 0 | BK33: SOFT STARTER | BL33: WEG | BM33: SSW07 | BP33: NÃO | BR33: 0 | BS33: 0 | BT33: 0 | BU33: 0 | BV33: 0 | BW33: SIM | BY33: EM MARCHA | BZ33: 0 | CA33: 0 | CB33: 0 | CC33: PAIOL | CD33: Rua OlImpio da Fonseca (Trecho Rua Major Leite de Castro A Rua Canadense), Rua Dona Vicentina (Trecho Rua Carlos de S. Fernandes A Rua Manoel Pinto), Rua Canadense (Trecho Rua JosE Couto GuimarAes A Rua Manoel Pinto, Rua Jorge LOssio, Rua Carlos de S. Fernandes (Trecho Rua Dona Vicentina A Rua Canadense) e pequenas Vilas desse trecho.
A34: CARAMUJOS | B34: =_xlfn.XLOOKUP(A:A,'Dados Elevatórias'!D:D,'Dados Elevatórias'!B:B) -> PL-RJB-EAT0835 | C34: =_xlfn.XLOOKUP(B:B,'Dados Elevatórias'!B:B,'Dados Elevatórias'!C:C) -> EAT | D34: BAIXADA 2 | E34: R. Cruz Alta, 2-8 - Parque do Ipanema, Queimados - RJ, 26320-330 | F34: Parque do Ipanema | G34: QUEIMADOS | H34: =_xlfn.XLOOKUP(B:B,'Dados Elevatórias'!B:B,'Dados Elevatórias'!G:G) -> 26320-330 | I34: =_xlfn.XLOOKUP(B34,COORDENADAS!A:A,COORDENADAS!B:B) -> -22.7063 | J34: =_xlfn.XLOOKUP(B34,COORDENADAS!A:A,COORDENADAS!C:C) -> -43.5825 | M34: 1 | N34: OPERACIONAL | O34: 12.5CV | P34: 3535rpm | Q34: WEG | R34: 132M | S34: RJB-21905 | T34: 220 / 380 / 440 | U34: 30.2 / 17.5 / 15.1 | Y34: RJB-21906 | Z34: W22 premium | AA34: 2 | AB34: 132mm | AC34: ABRIGADA | AD34: NÃO | AF34: ANFÍBIA | AH34: CONVENSIONAL | AN34: =_xlfn.XLOOKUP(A:A,'RELAÇÃO ANTIGA'!A:A,'RELAÇÃO ANTIGA'!AC:AC,X) -> 220v | AP34: 0 | AQ34: 0 | AR34: 0 | AS34: 0 | AT34: 0 | AU34: 0 | AV34: 0 | AW34: 0 | AX34: 0 | AY34: 0 | AZ34: 0 | BK34: INVERSOR DE FREQUÊNCIA | BP34: SIM | BR34: 0 | BS34: 0 | BT34: 0 | BU34: 0 | BV34: 0 | BY34: 0 | BZ34: 0 | CA34: 0 | CB34: 0 | CC34: 0 | CD34: 0
A35: CARLOS SAMPAIO | B35: =_xlfn.XLOOKUP(A:A,'Dados Elevatórias'!D:D,'Dados Elevatórias'!B:B) -> PL-RJB-EAT0822 | C35: =_xlfn.XLOOKUP(B:B,'Dados Elevatórias'!B:B,'Dados Elevatórias'!C:C) -> EAT | D35: BAIXADA 2 | E35: R. Lúcia Maria Piper, 50 - Adrianópolis, Nova Iguaçu - RJ, 26053-075 | F35: Adrianopolis | G35: NOVA IGUAÇU | H35: =_xlfn.XLOOKUP(B:B,'Dados Elevatórias'!B:B,'Dados Elevatórias'!G:G) -> 0 | I35: =_xlfn.XLOOKUP(B35,COORDENADAS!A:A,COORDENADAS!B:B) -> -22.6594 | J35: =_xlfn.XLOOKUP(B35,COORDENADAS!A:A,COORDENADAS!C:C) -> -43.4876 | M35: 1 | N35: OPERACIONAL | O35: 100CV | P35: 1785rpm | Q35: SEW EURODRIVE | S35: RJB-20145 | T35: 220/380/440 | U35: 200 / 131 / 151 | V35: 6317-2Z-C4 | W35: 6315-2RS-C3 | X35: CONJ.GS - 125/400 | Y35: RJB-23961 | Z35: EBARA | AA35: 4 | AB35: 356 | AC35: ABRIGADA | AD35: NÃO | AF35: HORIZONTAL | AH35: CONVENSIONAL | AI35: 275.0 m³/h | AJ35: 55MCA | AL35: Placa | AN35: =_xlfn.XLOOKUP(A:A,'RELAÇÃO ANTIGA'!A:A,'RELAÇÃO ANTIGA'!AC:AC,X) -> 220v | AP35: 0 | AQ35: 0 | AR35: 0 | AS35: 0 | AT35: 0 | AU35: 0 | AV35: 0 | AW35: 0 | AX35: 0 | AY35: 0 | AZ35: 0 | BJ35: RJB-23645 | BK35: INVERSOR DE FREQUÊNCIA | BL35: ABB | BM35: ACO580-01-145A-4 | BN35: 145A | BO35: RJB-23646 | BP35: SIM | BR35: 15 MCA | BS35: 8MCA | BT35: 70 MCA | BU35: 0 | BV35: 0 | BY35: 0 | BZ35: 0 | CA35: 0 | CB35: 0 | CC35: 0 | CD35: 0
A36: CAONZE | B36: =_xlfn.XLOOKUP(A:A,'Dados Elevatórias'!D:D,'Dados Elevatórias'!B:B) -> PL-RJB-EAT0821 | C36: =_xlfn.XLOOKUP(B:B,'Dados Elevatórias'!B:B,'Dados Elevatórias'!C:C) -> EAT | D36: BAIXADA 2 | E36: R. Ver. Hélcio Chambarelli - Caonze, Nova Iguaçu - RJ, 26250-170 | F36: Caonze | G36: NOVA IGUAÇU | H36: =_xlfn.XLOOKUP(B:B,'Dados Elevatórias'!B:B,'Dados Elevatórias'!G:G) -> 26250-170 | I36: =_xlfn.XLOOKUP(B36,COORDENADAS!A:A,COORDENADAS!B:B) -> -22.7665 | J36: =_xlfn.XLOOKUP(B36,COORDENADAS!A:A,COORDENADAS!C:C) -> -43.4429 | M36: 1 | N36: OPERACIONAL | O36: 15cv | P36: 3530rpm | S36: RJB-18613 | AC36: ABRIGADA | AF36: HORIZONTAL | AH36: CONVENSIONAL | AP36: 0 | AQ36: 0 | AR36: 0 | AS36: 0 | AT36: 0 | AU36: 0 | AV36: 0 | AW36: 0 | AX36: 0 | AY36: 0 | AZ36: 0 | BK36: INVERSOR DE FREQUÊNCIA | BP36: NÃO | BR36: 0 | BS36: 0 | BT36: 0 | BU36: 0 | BV36: 0 | BY36: 0 | BZ36: 0 | CA36: 0 | CB36: 0 | CC36: 0 | CD36: 0
A37: CASA DE CUSTÓDIA COTRIN NETO | B37: =_xlfn.XLOOKUP(A:A,'Dados Elevatórias'!D:D,'Dados Elevatórias'!B:B) -> PL-RJB-EAT1016 | C37: =_xlfn.XLOOKUP(B:B,'Dados Elevatórias'!B:B,'Dados Elevatórias'!C:C) -> EAT | D37: BAIXADA 2 | E37: R. Assul, Jd Belo Horizonte, Japeri - RJ, 26480-400 | F37: Jd Belo Horizonte | G37: JAPERI | H37: =_xlfn.XLOOKUP(B:B,'Dados Elevatórias'!B:B,'Dados Elevatórias'!G:G) -> 26480-400 | I37: =_xlfn.XLOOKUP(B37,COORDENADAS!A:A,COORDENADAS!B:B) -> -22.673 | J37: =_xlfn.XLOOKUP(B37,COORDENADAS!A:A,COORDENADAS!C:C) -> -43.5826 | M37: 1 | N37: OPERACIONAL | O37: 12.5CV | P37: 3460rpm | Q37: WEG | R37: E56J | S37: RJB-30668 | T37: 220 / 380 | U37: 7.81 / 4.52 | AC37: ABRIGADA | AF37: HORIZONTAL | AH37: CONVENSIONAL | AP37: 0 | AQ37: 0 | AR37: 0 | AS37: 0 | AT37: 0 | AU37: 0 | AV37: 0 | AW37: 0 | AX37: 0 | AY37: 0 | AZ37: 0 | BK37: PARTIDA DIRETA | BP37: NÃO | BR37: 0 | BS37: 0 | BT37: 0 | BU37: 0 | BV37: 0 | BY37: 0 | BZ37: 0 | CA37: 0 | CB37: 0 | CC37: 0 | CD37: 0
A38: CEFET | B38: PL-RJB-EAT0108 | C38: EAT | D38: BAIXADA 2 | E38: R. Ademar Guimarães, 17 - Jardim Monte Castelo, Nova Iguaçu - RJ, 26041-600 | F38: Santa Rita | G38: NOVA IGUAÇU | H38: =_xlfn.XLOOKUP(B:B,'Dados Elevatórias'!B:B,'Dados Elevatórias'!G:G) -> 26041-271 | I38: =_xlfn.XLOOKUP(B38,COORDENADAS!A:A,COORDENADAS!B:B) -> -22.7009 | J38: =_xlfn.XLOOKUP(B38,COORDENADAS!A:A,COORDENADAS!C:C) -> -43.4645 | L38: =_xlfn.XLOOKUP(A:A,'RELAÇÃO ANTIGA'!A:A,'RELAÇÃO ANTIGA'!J:J) -> FORMAL | M38: 1 | N38: OPERACIONAL | O38: 7,5cv | P38: 3515rpm | AC38: SUBMERSA | AN38: 220V | AP38: 420268697 | AQ38: 6617672-7 | AR38: 0 | AS38: AGUA - BOOSTER - CEFET | AT38: EST ADRIANOPOLIS SN EF2174 | AU38: 0 | AV38: 0 | AW38: 0 | AX38: 0 | AY38: 1800 | AZ38: 0 | BK38: SOFT STARTER | BL38: WEG | BM38: SSW07 | BP38: NÃO | BR38: 0 | BS38: 0 | BT38: 0 | BU38: 0 | BV38: 0 | BW38: SIM | BY38: EM MARCHA | BZ38: 35 | CA38: 46 | CB38: 0 | CC38: 0 | CD38: 0
A39: CHATUBA | B39: =_xlfn.XLOOKUP(A:A,'Dados Elevatórias'!D:D,'Dados Elevatórias'!B:B) -> PL-RJB-EAT0741 | C39: =_xlfn.XLOOKUP(B:B,'Dados Elevatórias'!B:B,'Dados Elevatórias'!C:C) -> EAT | D39: BAIXADA 2 | E39: Rua Marques Canário, 667 - Chatuba - Mesquita - RJ, 26585-520 | F39: Chatuba | G39: MESQUITA | H39: =_xlfn.XLOOKUP(B:B,'Dados Elevatórias'!B:B,'Dados Elevatórias'!G:G) -> 26585-520 | I39: =_xlfn.XLOOKUP(B39,COORDENADAS!A:A,COORDENADAS!B:B) -> -22.804 | J39: =_xlfn.XLOOKUP(B39,COORDENADAS!A:A,COORDENADAS!C:C) -> -43.4408 | L39: =_xlfn.XLOOKUP(A:A,'RELAÇÃO ANTIGA'!A:A,'RELAÇÃO ANTIGA'!J:J) -> INFORMAL | M39: 1 | N39: OPERACIONAL | O39: 100cv | P39: 3500 | R39: 250S/M | S39: RJB-21052 | T39: 220V / 380V | X39: 4x3x10 | Y39: RJB-30605 | AA39: 10 | AB39: 254mm | AC39: TUBULÂO | AD39: SIM | AE39: JM | AF39: VERTICAL | AG39: FC | AH39: INLINE | AI39: 129,25 M³/H | AJ39: 80MCA | AN39: MT | AP39: 400139840 | AQ39: 1999622 | AR39: 0 | AS39: AGUA - BOOSTER - CHATUBA | AT39: R MARQUES DE CANARIO SN LT8 | AU39: 0 | AV39: 0 | AW39: 0 | AX39: 0 | AY39: 0 | AZ39: 0 | BJ39: RJB-11687 | BK39: INVERSOR DE FREQUÊNCIA | BL39: WEG | BM39: SSW 11 | BN39: 89A | BO39: RJB-11695 | BP39: SIM | BR39: < 1 MCA | BS39: 0 | BT39: 0 | BU39: 0 | BV39: 0 | BY39: EM MARCHA | BZ39: 0 | CA39: 0 | CB39: 0 | CC39: CHATUBA | CD39: Rua atendidas: Arizona, Plaza, AstOria, Toneleiros, AssU, Adolfo de Albuquerque, IcaraI, Aquidauana, Itaqui, AbaetE e Boatafogo. Comunidade da Chatuba
A40: CITROPOLIS | B40: =_xlfn.XLOOKUP(A:A,'Dados Elevatórias'!D:D,'Dados Elevatórias'!B:B) -> PL-RJB-EAT0833 | C40: =_xlfn.XLOOKUP(B:B,'Dados Elevatórias'!B:B,'Dados Elevatórias'!C:C) -> EAT | D40: BAIXADA 2 | E40: R. Tóquio, 38 - Citrópolis, Japeri - RJ, 26425-340 | F40: Citrópolis | G40: JAPERI | H40: =_xlfn.XLOOKUP(B:B,'Dados Elevatórias'!B:B,'Dados Elevatórias'!G:G) -> 26425-340 | I40: =_xlfn.XLOOKUP(B40,COORDENADAS!A:A,COORDENADAS!B:B) -> -22.682 | J40: =_xlfn.XLOOKUP(B40,COORDENADAS!A:A,COORDENADAS!C:C) -> -43.6049 | M40: 1 | N40: OPERACIONAL | O40: 10CV | P40: 3535 RPM | Q40: WEG | R40: 132S | S40: RJB-21460 | T40: 220V / 380V / 440V | U40: 25.0 / 14.5 / 12.5 | V40: 6309-Z-C3 | W40: 6207-ZZ | X40: THS-18 TRIF IP5 | Y40: RJB-21480 | Z40: EBARA | AA40: 2 | AB40: 179mm | AC40: ABRIGADA | AF40: HORIZONTAL | AH40: CONVENSIONAL | AI40: 30m3/h | AJ40: 55mca | AL40: placa | AN40: VERIFICAR | AO40: VERIFICAR | AU40: 0 | AV40: 0 | AW40: 0 | AX40: 0 | AY40: 0 | AZ40: 0 | BJ40: RJB-23511 | BK40: INVERSOR DE FREQUÊNCIA | BL40: ABB | BM40: ACS310-03E-34A1-2 | BN40: 7,5KW - 10HP | BO40: RJB-23515 | BP40: SIM | BR40: 0 | BS40: 0 | BT40: 0 | BU40: 0 | BV40: 0 | BY40: 0 | BZ40: 0 | CA40: 0 | CB40: 0 | CC40: 0 | CD40: 0
A41: DANON | B41: =_xlfn.XLOOKUP(A:A,'Dados Elevatórias'!D:D,'Dados Elevatórias'!B:B) -> PL-RJB-EAT0816 | C41: =_xlfn.XLOOKUP(B:B,'Dados Elevatórias'!B:B,'Dados Elevatórias'!C:C) -> EAT | D41: BAIXADA 2 | E41: R. Luís Ferreira, 3 - Pioneiro, Nova Iguaçu - RJ, 26294-300 | F41: Pioneiro | G41: NOVA IGUAÇU | H41: =_xlfn.XLOOKUP(B:B,'Dados Elevatórias'!B:B,'Dados Elevatórias'!G:G) -> 26271-350 | I41: =_xlfn.XLOOKUP(B41,COORDENADAS!A:A,COORDENADAS!B:B) -> -22.7684 | J41: =_xlfn.XLOOKUP(B41,COORDENADAS!A:A,COORDENADAS!C:C) -> -43.5068 | L41: =_xlfn.XLOOKUP(A:A,'RELAÇÃO ANTIGA'!A:A,'RELAÇÃO ANTIGA'!J:J) -> Nova | M41: 1 | N41: OPERACIONAL | O41: 7,5cv | P41: 3515 | Q41: WEG | R41: 112M | S41: RJB-21481 | T41: 220V / 380V / 440V | U41: 19.4 / 11.3 / 9.72 | X41: PX-15/2 | Y41: RJB-21482 | Z41: THEBE | AA41: 2 | AB41: 138mm | AC41: ABRIGADA | AD41: NÃO | AF41: HORIZONTAL | AH41: INLINE | AI41: 10,55M3/H | AJ41: 50MCA | AP41: 0 | AQ41: 0 | AR41: 0 | AS41: 0 | AT41: 0 | AU41: 1.1/2 | AV41: 1.1/2 | AW41: 0 | AX41: 0 | AY41: 0 | AZ41: 0 | BJ41: RJB-17683 | BK41: INVERSOR DE FREQUÊNCIA | BL41: ABB | BM41: ACS8310-035E-26A8-2 | BN41: 5.5 KW (7 1/2 HP) | BP41: SIM | BR41: 1 MCA | BS41: < 1 MCA | BT41: 75 MCA | BU41: 0 | BV41: 0 | BY41: 0 | BZ41: 0 | CA41: 0 | CB41: 0 | CC41: 0 | CD41: 0
A42: DAS ROSAS | B42: =_xlfn.XLOOKUP(A:A,'Dados Elevatórias'!D:D,'Dados Elevatórias'!B:B) -> PL-RJB-EAT0836 | C42: =_xlfn.XLOOKUP(B:B,'Dados Elevatórias'!B:B,'Dados Elevatórias'!C:C) -> EAT | D42: BAIXADA 2 | E42: Rancho Fundo, Nova Iguaçu - RJ, 26051-370 | F42: Rancho Fundo | G42: NOVA IGUAÇU | H42: =_xlfn.XLOOKUP(B:B,'Dados Elevatórias'!B:B,'Dados Elevatórias'!G:G) -> 26051-370 | I42: =_xlfn.XLOOKUP(B42,COORDENADAS!A:A,COORDENADAS!B:B) -> -22.6943 | J42: =_xlfn.XLOOKUP(B42,COORDENADAS!A:A,COORDENADAS!C:C) -> -43.4584 | M42: 1 | N42: OPERACIONAL | O42: 15cv | P42: 3530 | Q42: WEG | R42: 132M | S42: RJB-21901 | T42: 220V / 380V / 440V | U42: 36.8 / 21.3 / 18.4A | X42: Megablock | Y42: RJB-21902 | AA42: 2 | AB42: 161 | AC42: ABRIGADA | AF42: HORIZONTAL | AH42: CONVENSIONAL | AI42: 33M3/h | AJ42: 54MCA | AL42: SAP | AM42: 5513316 | AN42: =_xlfn.XLOOKUP(A:A,'RELAÇÃO ANTIGA'!A:A,'RELAÇÃO ANTIGA'!AC:AC,X) -> 220v | AP42: 0 | AQ42: 0 | AR42: 0 | AS42: 0 | AT42: 0 | AU42: 2.1/2POL | AV42: 1.1/2POL | AW42: 0 | AX42: 0 | AY42: 0 | AZ42: 0 | BK42: INVERSOR DE FREQUÊNCIA | BP42: SIM | BR42: 0 | BS42: 0 | BT42: 0 | BU42: 0 | BV42: 0 | BY42: 0 | BZ42: 0 | CA42: 0 | CB42: 0 | CC42: 0 | CD42: 0
A43: DA SERRA | B43: =_xlfn.XLOOKUP(A:A,'Dados Elevatórias'!D:D,'Dados Elevatórias'!B:B) -> PL-RJB-EAT0848 | C43: =_xlfn.XLOOKUP(B:B,'Dados Elevatórias'!B:B,'Dados Elevatórias'!C:C) -> EAT | D43: BAIXADA 2 | E43: R. Soares Couto, 361 - Santa Terezinha, Mesquita - RJ, 26554-220 | F43: Santa Terezinha | G43: MESQUITA | H43: =_xlfn.XLOOKUP(B:B,'Dados Elevatórias'!B:B,'Dados Elevatórias'!G:G) -> 26554-220 | I43: =_xlfn.XLOOKUP(B43,COORDENADAS!A:A,COORDENADAS!B:B) -> -22.7896 | J43: =_xlfn.XLOOKUP(B43,COORDENADAS!A:A,COORDENADAS!C:C) -> -43.4383 | M43: 1 | N43: OPERACIONAL | O43: 20CV | P43: 3530 | Q43: WEG | R43: 160M | S43: RJB-22369 | T43: 220V / 380V / 440V | U43: 49.8 / 28.8 / 24.9 | AA43: 2 | AC43: ABRIGADA | AD43: NÃO | AF43: VERTICAL | AH43: INLINE | AJ43: 60mca | AL43: Preventiva | AN43: =_xlfn.XLOOKUP(A:A,'RELAÇÃO ANTIGA'!A:A,'RELAÇÃO ANTIGA'!AC:AC,X) -> 220v | AP43: 0 | AQ43: 0 | AR43: 0 | AS43: 0 | AT43: 0 | AU43: 0 | AV43: 0 | AW43: 0 | AX43: 0 | AY43: 0 | AZ43: 0 | BJ43: RJB-23287 | BK43: INVERSOR DE FREQUÊNCIA | BL43: SCHNEIDER | BM43: Atv320 | BN43: 15kW | BO43: RJB-22284 | BP43: SIM | BR43: 0 | BS43: 0 | BT43: 0 | BU43: 0 | BV43: 0 | BY43: 0 | BZ43: 0 | CA43: 0 | CB43: 0 | CC43: 0 | CD43: 0
A44: DINAMARCO REIS | B44: =_xlfn.XLOOKUP(A:A,'Dados Elevatórias'!D:D,'Dados Elevatórias'!B:B) -> PL-RJB-EAT0069 | C44: =_xlfn.XLOOKUP(B:B,'Dados Elevatórias'!B:B,'Dados Elevatórias'!C:C) -> EAT | D44: BAIXADA 2 | E44: R. Dinamarco Réis, 48 - Joaquim De Almeida Flores, Nilópolis - RJ, 26545-230 | F44: Joaquim De Almeida Flores | G44: NILÓPOLIS | H44: =_xlfn.XLOOKUP(B:B,'Dados Elevatórias'!B:B,'Dados Elevatórias'!G:G) -> 26545-230 | I44: =_xlfn.XLOOKUP(B44,COORDENADAS!A:A,COORDENADAS!B:B) -> -22.8153 | J44: =_xlfn.XLOOKUP(B44,COORDENADAS!A:A,COORDENADAS!C:C) -> -43.401 | L44: =_xlfn.XLOOKUP(A:A,'RELAÇÃO ANTIGA'!A:A,'RELAÇÃO ANTIGA'!J:J) -> FORMAL | M44: 1 | N44: OPERACIONAL | O44: 20CV | P44: 3545 | Q44: WEG | R44: 160M | S44: RJB-22359 | T44: 220V / 380V / 440V | U44: 49.8 / 28.8 / 24.9 | V44: 6309-ZZ-C3 | W44: 6209-ZZ-C3 | X44: VOLUTA | AA44: 2 | AB44: 165mm | AC44: TUBULÂO | AD44: SIM | AE44: JM | AF44: VERTICAL | AG44: FC | AH44: HORIZONTAL | AN44: 220V | AP44: 413497046 | AQ44: 7667390 | AR44: 0 | AS44: AGUA - BOOSTER - DINAMARCO REIS | AT44: R DINAMARCO REIS SN | AU44: 100MM | AV44: 100MM | AW44: 0 | AX44: 0 | AY44: 0 | AZ44: 0 | BJ44: RJB-20218 | BK44: INVERSOR DE FREQUÊNCIA | BL44: DANFOSS | BM44: FC-202P18KT2E20H2 | BN44: 68A | BO44: RJB-20218 | BP44: NÃO | BR44: 1 MCA | BS44: < 1 MCA | BT44: 0 | BU44: 0 | BV44: 0 | BW44: SIM | BY44: EM MARCHA | BZ44: 0 | CA44: 0 | CB44: 0 | CC44: 0 | CD44: Rua Dinamarco Reis (Trecho Rua Carlos de Souza Fernandes ao Final da Rua), Rua JosE Couto GuimarAes (Trecho Rua Rodrigues Alves A Rua Cândida), Rua Maria Gama (Trecho Rua Carlos de Souza Fernandes A Rua Candida), Rua Amadeu Lara (Trecho Rua Carlos de souza Fernandes A Rua Candida) e pequenas Vilas desse Trecho.
A45: DIVINO | B45: =_xlfn.XLOOKUP(A:A,'Dados Elevatórias'!D:D,'Dados Elevatórias'!B:B) -> PL-RJB-EAT0834 | C45: =_xlfn.XLOOKUP(B:B,'Dados Elevatórias'!B:B,'Dados Elevatórias'!C:C) -> EAT | D45: BAIXADA 2 | E45: Av. Luigi Giobi, 26 - Vila do Tinguá, Queimados - RJ, 26383-340 | F45: Vila do Tinguá | G45: QUEIMADOS | H45: =_xlfn.XLOOKUP(B:B,'Dados Elevatórias'!B:B,'Dados Elevatórias'!G:G) -> 26383-340 | I45: =_xlfn.XLOOKUP(B45,COORDENADAS!A:A,COORDENADAS!B:B) -> -22.7027 | J45: =_xlfn.XLOOKUP(B45,COORDENADAS!A:A,COORDENADAS!C:C) -> -43.559 | M45: 1 | N45: OPERACIONAL | O45: 20CV | P45: 3545rpm | Q45: WEG | R45: 160m | S45: RJB-21949 | T45: 220V / 380V / 440V | U45: 49.8/28.8/24.9 | Y45: RJB-21913 | Z45: W22 premium | AC45: ABRIGADA | AN45: =_xlfn.XLOOKUP(A:A,'RELAÇÃO ANTIGA'!A:A,'RELAÇÃO ANTIGA'!AC:AC,X) -> 220v | AP45: 0 | AQ45: 0 | AR45: 0 | AS45: 0 | AT45: 0 | AU45: 0 | AV45: 0 | AW45: 0 | AX45: 0 | AY45: 0 | AZ45: 0 | BK45: INVERSOR DE FREQUÊNCIA | BP45: SIM | BR45: 1 MCA | BS45: < 1 MCA | BT45: SEM SENSOR | BU45: 0 | BV45: 0 | BY45: 0 | BZ45: 0 | CA45: 0 | CB45: 0 | CC45: 0 | CD45: 0
A46: DORALICE | B46: =_xlfn.XLOOKUP(A:A,'Dados Elevatórias'!D:D,'Dados Elevatórias'!B:B) -> PL-RJB-EAT0761 | C46: =_xlfn.XLOOKUP(B:B,'Dados Elevatórias'!B:B,'Dados Elevatórias'!C:C) -> EAT | D46: BAIXADA 2 | E46: Rua Doralice 235, Caixa DAgua - Queimados | F46: Caixa DAgua | G46: QUEIMADOS | H46: =_xlfn.XLOOKUP(B:B,'Dados Elevatórias'!B:B,'Dados Elevatórias'!G:G) -> 0 | I46: =_xlfn.XLOOKUP(B46,COORDENADAS!A:A,COORDENADAS!B:B) -> -22.7121 | J46: =_xlfn.XLOOKUP(B46,COORDENADAS!A:A,COORDENADAS!C:C) -> -43.5516 | M46: 1 | N46: OPERACIONAL | O46: 5CV | P46: 3475rpm | Q46: WEG | R46: 100L | S46: RJB-23738 | T46: 220V / 380V / 440V | U46: 12.8 / 7.39 / 6.38 | Y46: RJB-20022 | Z46: DANCOR | AA46: 2 | AC46: CASINHA | AD46: NÃO | AF46: HORIZONTAL | AG46: FC | AH46: CONVENSIONAL | AP46: 0 | AQ46: 0 | AR46: 0 | AS46: 0 | AT46: 0 | AU46: 0 | AV46: 0 | AW46: 0 | AX46: 0 | AY46: 0 | AZ46: 0 | BK46: PARTIDA DIRETA | BP46: NÃO | BR46: 0 | BS46: 0 | BT46: 0 | BU46: 0 | BV46: 0 | BY46: 0 | BZ46: 0 | CA46: 0 | CB46: 0 | CC46: 0 | CD46: 0
A47: EDNA | B47: =_xlfn.XLOOKUP(A:A,'Dados Elevatórias'!D:D,'Dados Elevatórias'!B:B) -> PL-RJB-EAT0062 | C47: =_xlfn.XLOOKUP(B:B,'Dados Elevatórias'!B:B,'Dados Elevatórias'!C:C) -> EAT | D47: BAIXADA 2 | E47: Av. Henrique Duque Estrada Meyer, 690-798 - Ponto Chic, Nova Iguaçu - RJ, 26041-061 | F47: Ponto Chic | G47: NOVA IGUAÇU | H47: =_xlfn.XLOOKUP(B:B,'Dados Elevatórias'!B:B,'Dados Elevatórias'!G:G) -> 26041-061 | I47: =_xlfn.XLOOKUP(B47,COORDENADAS!A:A,COORDENADAS!B:B) -> -22.7319 | J47: =_xlfn.XLOOKUP(B47,COORDENADAS!A:A,COORDENADAS!C:C) -> -43.4611 | L47: =_xlfn.XLOOKUP(A:A,'RELAÇÃO ANTIGA'!A:A,'RELAÇÃO ANTIGA'!J:J) -> FORMAL | M47: 1 | N47: OPERACIONAL | O47: 5CV | P47: 3515 | Q47: HERCULES | S47: RJB-23803 | T47: 220V / 380V / 440V | U47: 13.84 / 7.99 / 6.02A | Y47: RJB-05478 | Z47: DANCOR | AC47: ABRIGADA | AD47: NÃO | AF47: HORIZONTAL | AH47: CONVENSIONAL | AP47: 413424336 | AQ47: 2417316 | AR47: 0 | AS47: AGUA - BOOSTER - EDNA | AT47: R EDNA SN EF16 | AU47: 0 | AV47: 0 | AW47: 0 | AX47: 0 | AY47: 0 | AZ47: 0 | BJ47: RJA-18531 | BK47: INVERSOR DE FREQUÊNCIA | BL47: ABB | BM47: AC2310-03E-50A8-2 | BN47: 11kW | BO47: RJA-18531 | BP47: NÃO | BR47: 0 | BS47: 0 | BT47: 0 | BU47: 0 | BV47: 0 | BY47: 0 | BZ47: 0 | CA47: 0 | CB47: 0 | CC47: 0 | CD47: Rua Edna - Rua ParaguaCu - Rua ParanaguA - Rua Sueli
A48: EDUARDO CELIDÔNIO | B48: =_xlfn.XLOOKUP(A:A,'Dados Elevatórias'!D:D,'Dados Elevatórias'!B:B) -> PL-RJB-EAT0693 | C48: =_xlfn.XLOOKUP(B:B,'Dados Elevatórias'!B:B,'Dados Elevatórias'!C:C) -> EAT | D48: BAIXADA 2 | E48: R. A, 1 - Vila Camarim, Queimados - RJ, 26383-522 | F48: Vila Camarim | G48: QUEIMADOS | H48: =_xlfn.XLOOKUP(B:B,'Dados Elevatórias'!B:B,'Dados Elevatórias'!G:G) -> 26383-522 | I48: =_xlfn.XLOOKUP(B48,COORDENADAS!A:A,COORDENADAS!B:B) -> -22.7002 | J48: =_xlfn.XLOOKUP(B48,COORDENADAS!A:A,COORDENADAS!C:C) -> -43.5694 | L48: =_xlfn.XLOOKUP(A:A,'RELAÇÃO ANTIGA'!A:A,'RELAÇÃO ANTIGA'!J:J) -> INFORMAL | M48: 1 | N48: OPERACIONAL | O48: 10CV | P48: 3510rpm | Q48: WEG | R48: 132S | S48: RJA-11604 | T48: 220V / 380V | U48: 25.7 / 14.9 | X48: 660 | Y48: RJB-07208 | Z48: DANCOR | AA48: 2 | AC48: CASINHA | AN48: 220V | AP48: 0 | AQ48: 0 | AR48: 0 | AS48: 0 | AT48: 0 | AU48: 2POL | AV48: 2POL | AW48: 0 | AX48: 0 | AY48: 0 | AZ48: 0 | BK48: PARTIDA DIRETA | BP48: NÃO | BR48: 0 | BS48: 0 | BT48: 0 | BU48: 0 | BV48: 0 | BY48: EM MARCHA | BZ48: 0 | CA48: 0 | CB48: 0 | CC48: 0 | CD48: 0
A49: EL SHADAY | B49: =_xlfn.XLOOKUP(A:A,'Dados Elevatórias'!D:D,'Dados Elevatórias'!B:B) -> PL-RJB-EAT0104 | C49: =_xlfn.XLOOKUP(B:B,'Dados Elevatórias'!B:B,'Dados Elevatórias'!C:C) -> EAT | D49: BAIXADA 2 | E49: R. Márcio Vieira de Oliveira, 372 - Austin, Nova Iguaçu - RJ, 26086-215 | F49: AUSTIN | G49: NOVA IGUAÇU | H49: 26086-215 | I49: =_xlfn.XLOOKUP(B49,COORDENADAS!A:A,COORDENADAS!B:B) -> -22.7234 | J49: =_xlfn.XLOOKUP(B49,COORDENADAS!A:A,COORDENADAS!C:C) -> -43.5258 | L49: =_xlfn.XLOOKUP(A:A,'RELAÇÃO ANTIGA'!A:A,'RELAÇÃO ANTIGA'!J:J) -> INFORMAL | M49: 1 | N49: OPERACIONAL | O49: 4,5cv | P49: 3450 rpm | Q49: LEÃO | R49: R28A | S49: RJB-21452 | X49: 20E8H | Y49: RJB-21452 | Z49: LEÃO | AB49: 98.5mm | AC49: SUBMERSA | AD49: NÃO | AF49: SUBMERSA VERTICAL | AI49: 20 A 36M³/H | AJ49: 37MCA | AN49: 220V | AP49: 420758197 | AQ49: 7802169 | AR49: 0 | AS49: AGUA - BOOSTER - ELSHADAI | AT49: R MARCIO VIEIRA DE OLIVEIRA SN EF370 | AU49: 100MM | AV49: 100MM | AW49: 0 | AX49: 0 | AY49: 475 | AZ49: 95 | BK49: PARTIDA DIRETA | BP49: NÃO | BR49: 0 | BS49: 0 | BT49: 0 | BU49: 0 | BV49: 0 | BW49: SIM | BY49: EM MARCHA | BZ49: 44 | CA49: 68 | CB49: 0 | CC49: EL SHADAY | CD49: Ladeira el Shaday, Rua Barroso, Rua Aristides, Rua Bela Vista e Rua Calma.
A50: ENGENHARIA | B50: =_xlfn.XLOOKUP(A:A,'Dados Elevatórias'!D:D,'Dados Elevatórias'!B:B) -> PL-RJB-EAT0117 | C50: =_xlfn.XLOOKUP(B:B,'Dados Elevatórias'!B:B,'Dados Elevatórias'!C:C) -> EAT | D50: BAIXADA 2 | E50: Av. Henrique Duque Estrada Meyer, 395 - Alto da Posse, Nova Iguaçu - RJ, 26030-380 | F50: Posse | G50: NOVA IGUAÇU | H50: =_xlfn.XLOOKUP(B:B,'Dados Elevatórias'!B:B,'Dados Elevatórias'!G:G) -> 26041-061 | I50: =_xlfn.XLOOKUP(B50,COORDENADAS!A:A,COORDENADAS!B:B) -> -22.7351 | J50: =_xlfn.XLOOKUP(B50,COORDENADAS!A:A,COORDENADAS!C:C) -> -43.4591 | L50: =_xlfn.XLOOKUP(A:A,'RELAÇÃO ANTIGA'!A:A,'RELAÇÃO ANTIGA'!J:J) -> FORMAL | M50: 1 | N50: OPERACIONAL | O50: 14CV | P50: 3450rpm | Q50: EBARA | S50: RJB-20955 | X50: 650-04 | Y50: RJB-20955 | AC50: SUBMERSA | AF50: SUBMERSA VERTICAL | AH50: SUBMERSA | AI50: 50 m³/h | AN50: =_xlfn.XLOOKUP('RELAÇÃO DE ELEVATÓRIAS'!A:A,'RELAÇÃO ANTIGA'!A:A,'RELAÇÃO ANTIGA'!AC:AC) -> 220V | AP50: 420203527 | AQ50: 6277280 | AR50: 0 | AS50: AGUA - BOOSTER - ENGENHARIA | AT50: AV HENRIQUE DUQUE ESTRADA MEYER SN EF407 | AU50: 100MM | AV50: 100MM | AW50: 0 | AX50: 0 | AY50: 0 | AZ50: 0 | BK50: SOFT STARTER | BL50: WEG | BM50: SSW05 | BP50: NÃO | BR50: 0 | BS50: 0 | BT50: 0 | BU50: 0 | BV50: 0 | BY50: 0 | BZ50: 0 | CA50: 0 | CB50: 0 | CC50: 0 | CD50: 0
A51: ESPLANADA | B51: =_xlfn.XLOOKUP(A:A,'Dados Elevatórias'!D:D,'Dados Elevatórias'!B:B) -> PL-RJB-EAT0075 | C51: =_xlfn.XLOOKUP(B:B,'Dados Elevatórias'!B:B,'Dados Elevatórias'!C:C) -> EAT | D51: BAIXADA 2 | E51: Estr. da Fazenda, 2-264 - Jardim da Viga, Nova Iguaçu - RJ, 26013-470 | F51: Jardim da Viga | G51: NOVA IGUAÇU | H51: =_xlfn.XLOOKUP(B:B,'Dados Elevatórias'!B:B,'Dados Elevatórias'!G:G) -> 26013-470 | I51: =_xlfn.XLOOKUP(B51,COORDENADAS!A:A,COORDENADAS!B:B) -> -22.7426 | J51: =_xlfn.XLOOKUP(B51,COORDENADAS!A:A,COORDENADAS!C:C) -> -43.4458 | L51: =_xlfn.XLOOKUP(A:A,'RELAÇÃO ANTIGA'!A:A,'RELAÇÃO ANTIGA'!J:J) -> FORMAL | M51: 1 | N51: OPERACIONAL | O51: 25CV | P51: 3530rpm | Q51: WEG | S51: RJB-30617 | AC51: ABRIGADA | AN51: =_xlfn.XLOOKUP('RELAÇÃO DE ELEVATÓRIAS'!A:A,'RELAÇÃO ANTIGA'!A:A,'RELAÇÃO ANTIGA'!AC:AC) -> 220V | AP51: 411189247 | AQ51: 5003079 | AR51: 0 | AS51: AGUA - ELEV - ESPLANADA (CAIXA BAIXA) * E ANEXOS | AT51: R FAZENDA 256 | AU51: 150MM | AV51: 100MM | AW51: 0 | AX51: 0 | AY51: 0 | AZ51: 0 | BK51: PARTIDA DIRETA | BP51: SIM | BR51: 1 MCA | BS51: < 1MCA | BT51: 0 | BU51: 0 | BV51: 0 | BW51: SIM | BY51: EM MARCHA | BZ51: 0 | CA51: 0 | CB51: 0 | CC51: 0 | CD51: Av. Esplanada - Rua Araci - Rua Baltimore - Rua Canavieira - Rua da Conquista - Rua da Fazenda - Rua FiladElfia - Rua Iguape - Rua Itabuna - Rua JundiaI - Rua Pedro I - Rua Pedro II - Rua Pensilvânia - Rua Pontal do Sul - Rua Quieve - Rua UbatA - Rua Variante Barros JUnior (parte)
A52: EXPEDICIONARIOS | B52: =_xlfn.XLOOKUP(A:A,'Dados Elevatórias'!D:D,'Dados Elevatórias'!B:B) -> PL-RJB-EAT0066 | C52: =_xlfn.XLOOKUP(B:B,'Dados Elevatórias'!B:B,'Dados Elevatórias'!C:C) -> EAT | D52: BAIXADA 2 | E52: Estrada dos Expedicionário, 1264, Paiol, Nilópolis - RJ, 26540-020 | F52: Paiol | G52: NILÓPOLIS | H52: =_xlfn.XLOOKUP(B:B,'Dados Elevatórias'!B:B,'Dados Elevatórias'!G:G) -> 26540-020 | I52: =_xlfn.XLOOKUP(B52,COORDENADAS!A:A,COORDENADAS!B:B) -> -22.805 | J52: =_xlfn.XLOOKUP(B52,COORDENADAS!A:A,COORDENADAS!C:C) -> -43.4028 | L52: =_xlfn.XLOOKUP(A:A,'RELAÇÃO ANTIGA'!A:A,'RELAÇÃO ANTIGA'!J:J) -> INFORMAL | M52: 1 | N52: OPERACIONAL | O52: 12cv | S52: RJB-30616 | T52: 221 / 219 | AC52: SUBMERSA | AN52: =_xlfn.XLOOKUP('RELAÇÃO DE ELEVATÓRIAS'!A:A,'RELAÇÃO ANTIGA'!A:A,'RELAÇÃO ANTIGA'!AC:AC) -> 220V | AP52: 400379484 | AQ52: 5668080 | AR52: 0 | AS52: AGUA - ELEV - EXPEDICIONARIOS | AT52: EST EXPEDICIONARIOS SN EF1254 | AU52: 100MM | AV52: 100MM | AW52: 0 | AX52: 0 | AY52: 0 | AZ52: 0 | BK52: SOFT STARTER | BP52: SIM | BR52: 0 | BS52: 0 | BT52: 0 | BU52: 0 | BV52: 0 | BW52: SIM | BY52: EM MARCHA | BZ52: 0 | CA52: 0 | CB52: 0 | CC52: CABUIS | CD52: Rua dos ExpedicionArio (Trecho Rua JoAo Castro ao final da Rua), Rua Sargento Manoel Rodrigues (Trecho Rua Antonio P. de Carvalho A Rua Maestro D. do Carmo), Rua Maestro Djalma do Carmo (Trecho Rua Sargento Manoel Rodrigues ao final da Rua), Rua Trav. sargento Manoel Rodrigues, Trav. JosE das Chagas Barros, rua JoAo M. Santiago e pequenas Vilas desses trechos.
A53: ETE LAGOINHA | B53: =_xlfn.XLOOKUP(A:A,'Dados Elevatórias'!D:D,'Dados Elevatórias'!B:B) -> PL-RJB-ETE0040 | C53: =_xlfn.XLOOKUP(B:B,'Dados Elevatórias'!B:B,'Dados Elevatórias'!C:C) -> ETE | D53: BAIXADA 2 | E53: R. Dez, 47 - Lagoinha, Nova Iguaçu - RJ, 26296-069 | F53: Lagoinha | G53: NOVA IGUAÇU | H53: =_xlfn.XLOOKUP(B:B,'Dados Elevatórias'!B:B,'Dados Elevatórias'!G:G) -> 26296-069 | I53: =_xlfn.XLOOKUP(B53,COORDENADAS!A:A,COORDENADAS!B:B) -> -22.7985 | J53: =_xlfn.XLOOKUP(B53,COORDENADAS!A:A,COORDENADAS!C:C) -> -43.5892 | L53: =_xlfn.XLOOKUP(A:A,'RELAÇÃO ANTIGA'!A:A,'RELAÇÃO ANTIGA'!J:J) -> FORMAL | M53: 1 | N53: OPERACIONAL | O53: 25cv | Q53: WEG | S53: RJB-12623 | Y53: RJA-15138 | Z53: WEG | AC53: ABRIGADA | AF53: VERTICAL | AH53: SUBMERSA | AK53: 11,7 L/S | AP53: 0 | AQ53: 0 | AR53: 0 | AS53: 0 | AT53: 0 | AU53: 0 | AV53: 0 | AW53: 0 | AX53: 0 | AY53: 0 | AZ53: 0 | BK53: SOFT STARTER | BP53: SIM | BR53: 0 | BS53: 0 | BT53: 0 | BU53: 0 | BV53: 0 | BY53: 0 | BZ53: 0 | CA53: 0 | CB53: 0 | CC53: 0 | CD53: 0
A54: FLORESTA MIRANDA | B54: =_xlfn.XLOOKUP(A:A,'Dados Elevatórias'!D:D,'Dados Elevatórias'!B:B) -> PL-RJB-EAT0065 | C54: =_xlfn.XLOOKUP(B:B,'Dados Elevatórias'!B:B,'Dados Elevatórias'!C:C) -> EAT | D54: BAIXADA 2 | E54: Rua Floresta Miranda, 257 - Centro, Nova Iguaçu - RJ, 26250-060 | F54: Centro | G54: NOVA IGUAÇU | H54: =_xlfn.XLOOKUP(B:B,'Dados Elevatórias'!B:B,'Dados Elevatórias'!G:G) -> 26250-060 | I54: =_xlfn.XLOOKUP(B54,COORDENADAS!A:A,COORDENADAS!B:B) -> -22.764 | J54: =_xlfn.XLOOKUP(B54,COORDENADAS!A:A,COORDENADAS!C:C) -> -43.4489 | L54: =_xlfn.XLOOKUP(A:A,'RELAÇÃO ANTIGA'!A:A,'RELAÇÃO ANTIGA'!J:J) -> FORMAL | M54: 1 | N54: OPERACIONAL | O54: 5CV | P54: 3510rpm | Q54: DANCOR | R54: 100L | S54: RJB-00199 | T54: 220/380V | U54: 12.8 / 7.39 | X54: W22 Premium | Y54: RJB-18145 | Z54: WEG | AC54: ABRIGADA | AN54: =_xlfn.XLOOKUP('RELAÇÃO DE ELEVATÓRIAS'!A:A,'RELAÇÃO ANTIGA'!A:A,'RELAÇÃO ANTIGA'!AC:AC) -> 220V | AP54: 411456713 | AQ54: 4454750 | AR54: 0 | AS54: AGUA - BOOSTER - FLORESTA MIRANDA | AT54: R FLORESTA MIRANDA 256 | AU54: 2POL | AV54: 2POL | AW54: 0 | AX54: 0 | AY54: 0 | AZ54: 20 | BK54: SOFT STARTER | BL54: WEG | BM54: CFW500 | BP54: NÃO | BR54: 0 | BS54: 0 | BT54: 0 | BU54: 0 | BV54: 0 | BW54: SIM | BY54: EM MARCHA | BZ54: 0 | CA54: 0 | CB54: 0 | CC54: 0 | CD54: Rua Anverino Floresta de Miranda (toda), Rua Darci Froes da Cruz (toda)
A55: FRANCISCO XAVIER | B55: =_xlfn.XLOOKUP(A:A,'Dados Elevatórias'!D:D,'Dados Elevatórias'!B:B) -> PL-RJB-EAT0082 | C55: =_xlfn.XLOOKUP(B:B,'Dados Elevatórias'!B:B,'Dados Elevatórias'!C:C) -> EAT | D55: BAIXADA 2 | E55: Próximo a R. Francisco Xavier, 801 - São Gabriel, Nova Iguaçu - RJ, 26021-650 | F55: São Gabriel | G55: NOVA IGUAÇU | H55: =_xlfn.XLOOKUP(B:B,'Dados Elevatórias'!B:B,'Dados Elevatórias'!G:G) -> 26021-650 | I55: =_xlfn.XLOOKUP(B55,COORDENADAS!A:A,COORDENADAS!B:B) -> -22.723 | J55: =_xlfn.XLOOKUP(B55,COORDENADAS!A:A,COORDENADAS!C:C) -> -43.4356 | L55: =_xlfn.XLOOKUP(A:A,'RELAÇÃO ANTIGA'!A:A,'RELAÇÃO ANTIGA'!J:J) -> FORMAL | M55: 1 | N55: OPERACIONAL | O55: 7.5CV | P55: 3515rpm | Q55: WEG | AC55: ABRIGADA | AN55: =_xlfn.XLOOKUP('RELAÇÃO DE ELEVATÓRIAS'!A:A,'RELAÇÃO ANTIGA'!A:A,'RELAÇÃO ANTIGA'!AC:AC) -> 220V | AP55: 410417203 | AQ55: 8268575-4 | AR55: 0 | AS55: AGUA - ELEV - MARACANA (VILA CAVA) | AT55: R FRANCISCO XAVIER 810 | AU55: 75MM | AV55: 75MMM | AW55: 0 | AX55: 0 | AY55: 0 | AZ55: 0 | BK55: INVERSOR DE FREQUÊNCIA | BL55: ABB | BP55: NÃO | BR55: 1 MCA | BS55: < 1MCA | BT55: 0 | BU55: 0 | BV55: 0 | BW55: SIM | BY55: EM MARCHA | BZ55: 0 | CA55: 0 | CB55: 0 | CC55: 0 | CD55: Rua Fernanda - Rua Flexas - Rua Joaquim Soares Neto - Rua Planaltina
A56: GAMA | B56: =_xlfn.XLOOKUP(A:A,'Dados Elevatórias'!D:D,'Dados Elevatórias'!B:B) -> PL-RJB-EAT0110 | C56: =_xlfn.XLOOKUP(B:B,'Dados Elevatórias'!B:B,'Dados Elevatórias'!C:C) -> EAT | D56: BAIXADA 2 | E56: Estr. da Gama, 721 - Cerâmica, Nova Iguaçu - RJ, 26035-220 | F56: Posse | G56: NOVA IGUAÇU | H56: =_xlfn.XLOOKUP(B:B,'Dados Elevatórias'!B:B,'Dados Elevatórias'!G:G) -> 26030-200 | I56: =_xlfn.XLOOKUP(B56,COORDENADAS!A:A,COORDENADAS!B:B) -> -22.7342 | J56: =_xlfn.XLOOKUP(B56,COORDENADAS!A:A,COORDENADAS!C:C) -> -43.4658 | L56: =_xlfn.XLOOKUP(A:A,'RELAÇÃO ANTIGA'!A:A,'RELAÇÃO ANTIGA'!J:J) -> FORMAL | M56: 1 | N56: OPERACIONAL | S56: FICTÍCIA | Y56: NÃO TEM | AC56: SUBMERSA | AN56: =_xlfn.XLOOKUP('RELAÇÃO DE ELEVATÓRIAS'!A:A,'RELAÇÃO ANTIGA'!A:A,'RELAÇÃO ANTIGA'!AC:AC) -> 220V | AP56: 430171491 | AQ56: 9732192 | AR56: 0 | AS56: AGUA - ELEV - GAMA | AT56: R A SN SV BOMBA EQ R GAMA | AU56: 100MM | AV56: 100MM | AW56: 0 | AX56: 0 | AY56: 0 | AZ56: 0 | BK56: SOFT STARTER | BP56: SIM | BR56: 0 | BS56: 0 | BT56: 0 | BU56: 0 | BV56: 0 | BW56: SIM | BY56: EM MARCHA | BZ56: 0 | CA56: 0 | CB56: 0 | CC56: 0 | CD56: Condomínio sito à Rua Oliveiros Rodrigues Alves
A57: GOLDEN GATE | B57: =_xlfn.XLOOKUP(A:A,'Dados Elevatórias'!D:D,'Dados Elevatórias'!B:B) -> PL-RJB-EAT0691 | C57: =_xlfn.XLOOKUP(B:B,'Dados Elevatórias'!B:B,'Dados Elevatórias'!C:C) -> EAT | D57: BAIXADA 2 | E57: R. Amazor Moreira Prisco, 154 - Centro, Nova Iguaçu - RJ, 26255-250 | F57: Centro | G57: NOVA IGUAÇU | H57: =_xlfn.XLOOKUP(B:B,'Dados Elevatórias'!B:B,'Dados Elevatórias'!G:G) -> 26255-250 | I57: =_xlfn.XLOOKUP(B57,COORDENADAS!A:A,COORDENADAS!B:B) -> -22.7613 | J57: =_xlfn.XLOOKUP(B57,COORDENADAS!A:A,COORDENADAS!C:C) -> -43.456 | L57: =_xlfn.XLOOKUP(A:A,'RELAÇÃO ANTIGA'!A:A,'RELAÇÃO ANTIGA'!J:J) -> FORMAL | M57: 1 | N57: OPERACIONAL | O57: 7.5CV | P57: 1765rpm | Q57: WEG | R57: 132S | S57: RJA-10229 | T57: 220/380/440 | U57: 19.2 / 11.1 / 9.60 | AA57: 4 | AB57: 132mm | AC57: TUBULÂO | AD57: SIM | AG57: Fc-184 | AN57: =_xlfn.XLOOKUP('RELAÇÃO DE ELEVATÓRIAS'!A:A,'RELAÇÃO ANTIGA'!A:A,'RELAÇÃO ANTIGA'!AC:AC) -> 220V | AP57: 430001397 | AQ57: 0 | AR57: 0 | AS57: 0 | AT57: 0 | AU57: 100MM | AV57: 100MM | AW57: 0 | AX57: 0 | AY57: 0 | AZ57: 0 | BK57: INVERSOR DE FREQUÊNCIA | BP57: NÃO | BR57: 0 | BS57: 0 | BT57: 0 | BU57: 0 | BV57: 0 | BW57: SIM | BY57: EM MARCHA | BZ57: 0 | CA57: 0 | CB57: 0 | CC57: 0 | CD57: 0
A58: GRAMA | B58: =_xlfn.XLOOKUP(A:A,'Dados Elevatórias'!D:D,'Dados Elevatórias'!B:B) -> PL-RJB-EAT0745 | C58: =_xlfn.XLOOKUP(B:B,'Dados Elevatórias'!B:B,'Dados Elevatórias'!C:C) -> EAT | D58: BAIXADA 2 | E58: Estr. da Grama, 1743 - Jardim Fonte Sao Miguel, Nova Iguaçu - RJ, 26060-015 | F58: Jardim Fonte Sao Miguel | G58: NOVA IGUAÇU | H58: =_xlfn.XLOOKUP(B:B,'Dados Elevatórias'!B:B,'Dados Elevatórias'!G:G) -> 26060-015 | I58: =_xlfn.XLOOKUP(B58,COORDENADAS!A:A,COORDENADAS!B:B) -> -22.7018 | J58: =_xlfn.XLOOKUP(B58,COORDENADAS!A:A,COORDENADAS!C:C) -> -43.4312 | L58: =_xlfn.XLOOKUP(A:A,'RELAÇÃO ANTIGA'!A:A,'RELAÇÃO ANTIGA'!J:J) -> INFORMAL | M58: 1 | N58: OPERACIONAL | O58: 15cv | P58: 3540rpm | Q58: VOGES | S58: RJB-19111 | T58: 220V / 380V | V58: 6309 ZZC3 | W58: 6309 ZZC | Y58: RJB-30608 | AA58: 2 | AC58: TUBULÂO | AD58: NÃO | AP58: 420149935 | AQ58: 4784298 | AR58: 0 | AS58: AGUA - BOOSTER - GRAMA | AT58: EST GRAMA 333 | AU58: 0 | AV58: 0 | AW58: 0 | AX58: 0 | AY58: 0 | AZ58: 0 | BK58: INVERSOR DE FREQUÊNCIA | BP58: SIM | BR58: 1 MCA | BS58: < 1MCA | BT58: 0 | BU58: 0 | BV58: 0 | BY58: 0 | BZ58: 0 | CA58: 0 | CB58: 0 | CC58: GRAMA | CD58: Estrada da Grama - Estrada Piteira - Rua "A" - Rua "B" - Rua "G" - Rua Abreu Filho - Rua Arnaldo - Rua BelizArio Pena - Rua Benjamim Batista - Rua Daniel Almeida - Rua Diva - Rua Ednelson de Souza Brasiliano - Rua Eduardo Meireles - Rua EmIlia Mendes - Rua Esterlita Ling - Rua Gisela - Rua Lauro Carvalho Barros - Rua Minas Gerais - Rua ParA - Rua Paulo Cezar - Rua Presidente Leme - Rua Renilda Mayer - Rua Rocha Faria - Rua Santa BArbara - Rua SAo Paulo - Rua Torres Homem - Rua Zaida - Travessa 4 - Travessa 5
A59: GRANJA ROSALINA | B59: =_xlfn.XLOOKUP(A:A,'Dados Elevatórias'!D:D,'Dados Elevatórias'!B:B) -> PL-RJB-EAT0811 | C59: =_xlfn.XLOOKUP(B:B,'Dados Elevatórias'!B:B,'Dados Elevatórias'!C:C) -> EAT | D59: BAIXADA 2 | E59: Rua José Alexandre esquina com a Estr. Campo Alegre | F59: Granja Rosalina | G59: QUEIMADOS | H59: =_xlfn.XLOOKUP(B:B,'Dados Elevatórias'!B:B,'Dados Elevatórias'!G:G) -> 26317-180 | I59: =_xlfn.XLOOKUP(B59,COORDENADAS!A:A,COORDENADAS!B:B) -> -22.7172 | J59: =_xlfn.XLOOKUP(B59,COORDENADAS!A:A,COORDENADAS!C:C) -> -43.5819 | M59: 1 | N59: OPERACIONAL | O59: 7.5 (10cv) | P59: 3535 RPM | Q59: Weg | R59: 132S | S59: RJB-18367 | T59: 220V / 380V / 440V | U59: 25.0/14.5/12.5 | X59: PX-15/3 KN BR T | Y59: RJB-18368 | Z59: THEBE | AA59: 2 | AC59: ABRIGADA | AG59: FF-265 | AP59: 0 | AQ59: 0 | AR59: 0 | AS59: 0 | AT59: 0 | AU59: 0 | AV59: 0 | AW59: 0 | AX59: 0 | AY59: 0 | AZ59: 0 | BK59: INVERSOR DE FREQUÊNCIA | BP59: NÃO | BR59: 0 | BS59: 0 | BT59: 0 | BU59: 0 | BV59: 0 | BY59: 0 | BZ59: 0 | CA59: 0 | CB59: 0 | CC59: 0 | CD59: 0
A60: HADDOCK LOBO | B60: =_xlfn.XLOOKUP(A:A,'Dados Elevatórias'!D:D,'Dados Elevatórias'!B:B) -> PL-RJB-EAT1013 | C60: =_xlfn.XLOOKUP(B:B,'Dados Elevatórias'!B:B,'Dados Elevatórias'!C:C) -> EAT | D60: BAIXADA 2 | E60: R. Adoc Lôbo, 10 - Vila do Tinguá, Queimados - RJ, 26385-380 | F60: Vila do Tinguá | G60: QUEIMADOS | H60: =_xlfn.XLOOKUP(B:B,'Dados Elevatórias'!B:B,'Dados Elevatórias'!G:G) -> 26385380 | I60: =_xlfn.XLOOKUP(B60,COORDENADAS!A:A,COORDENADAS!B:B) -> -22.7051 | J60: =_xlfn.XLOOKUP(B60,COORDENADAS!A:A,COORDENADAS!C:C) -> -43.5555 | L60: =_xlfn.XLOOKUP(A:A,'RELAÇÃO ANTIGA'!A:A,'RELAÇÃO ANTIGA'!J:J) -> FORMAL | M60: 1 | N60: OPERACIONAL | O60: 7.5CV | P60: 1793rpm | AC60: CASINHA | AP60: 0 | AQ60: 0 | AR60: 0 | AS60: 0 | AT60: 0 | AU60: 0 | AV60: 0 | AW60: 0 | AX60: 0 | AY60: 0 | AZ60: 0 | BK60: PARTIDA DIRETA | BP60: NÃO | BR60: 0 | BS60: 0 | BT60: 0 | BU60: 0 | BV60: 0 | BY60: 0 | BZ60: 0 | CA60: 0 | CB60: 0 | CC60: 0 | CD60: 0
A61: IARA | B61: =_xlfn.XLOOKUP(A:A,'Dados Elevatórias'!D:D,'Dados Elevatórias'!B:B) -> PL-RJB-EAT0837 | C61: =_xlfn.XLOOKUP(B:B,'Dados Elevatórias'!B:B,'Dados Elevatórias'!C:C) -> EAT | D61: BAIXADA 2 | E61: R. Manuel Rodrigues de Sá Panela, 214-302 - Cacuia, Nova Iguaçu - RJ, 26082-215 | F61: Cacuia | G61: NOVA IGUAÇU | H61: =_xlfn.XLOOKUP(B:B,'Dados Elevatórias'!B:B,'Dados Elevatórias'!G:G) -> 26082-215 | I61: =_xlfn.XLOOKUP(B61,COORDENADAS!A:A,COORDENADAS!B:B) -> -22.7295 | J61: =_xlfn.XLOOKUP(B61,COORDENADAS!A:A,COORDENADAS!C:C) -> -43.5089 | M61: 1 | N61: OPERACIONAL | O61: 15CV | P61: 3530rpm | Q61: WEG | R61: 132M | S61: RJB-21995 | T61: 220V / 380V / 440V | U61: 36.8 / 21.3 / 18.4 | Y61: RJB-21996 | Z61: WEG | AA61: 2 | AC61: ABRIGADA | AN61: =_xlfn.XLOOKUP(A:A,'RELAÇÃO ANTIGA'!A:A,'RELAÇÃO ANTIGA'!AC:AC,X) -> 220v | AP61: 0 | AQ61: 0 | AR61: 0 | AS61: 0 | AT61: 0 | AU61: 0 | AV61: 0 | AW61: 0 | AX61: 0 | AY61: 0 | AZ61: 0 | BK61: INVERSOR DE FREQUÊNCIA | BP61: SIM | BR61: 0 | BS61: 0 | BT61: 0 | BU61: 0 | BV61: 0 | BY61: 0 | BZ61: 0 | CA61: 0 | CB61: 0 | CC61: 0 | CD61: 0
A62: INDIA PORTUGUESA | B62: =_xlfn.XLOOKUP(A:A,'Dados Elevatórias'!D:D,'Dados Elevatórias'!B:B) -> PL-RJB-EAT0087 | C62: =_xlfn.XLOOKUP(B:B,'Dados Elevatórias'!B:B,'Dados Elevatórias'!C:C) -> EAT | D62: BAIXADA 2 | E62: R. Antônio Pereira de Carvalho, 34 - Centro, Nilópolis - RJ, 26540-000 | F62: Centro | G62: NILÓPOLIS | H62: =_xlfn.XLOOKUP(B:B,'Dados Elevatórias'!B:B,'Dados Elevatórias'!G:G) -> 26540-000 | I62: =_xlfn.XLOOKUP(B62,COORDENADAS!A:A,COORDENADAS!B:B) -> -22.8127 | J62: =_xlfn.XLOOKUP(B62,COORDENADAS!A:A,COORDENADAS!C:C) -> -43.4116 | L62: =_xlfn.XLOOKUP(A:A,'RELAÇÃO ANTIGA'!A:A,'RELAÇÃO ANTIGA'!J:J) -> FORMAL | M62: 1 | N62: OPERACIONAL | AC62: SUBMERSA | AN62: =_xlfn.XLOOKUP('RELAÇÃO DE ELEVATÓRIAS'!A:A,'RELAÇÃO ANTIGA'!A:A,'RELAÇÃO ANTIGA'!AC:AC) -> 220V | AP62: 411112102 | AQ62: 2580837 | AR62: 0 | AS62: AGUA - BOOSTER - INDIA PORTUGUESA (CONSUMO BASE 2013) | AT62: 0 | AU62: 100MM | AV62: 75MM | AW62: 0 | AX62: 0 | AY62: 0 | AZ62: 0 | BK62: SOFT STARTER | BM62: SSW07 | BP62: NÃO | BQ62: SIM | BR62: 0 | BS62: 0 | BT62: 0 | BU62: 0 | BV62: 0 | BW62: SIM | BY62: EM MARCHA | BZ62: 0 | CA62: 0 | CB62: 0 | CC62: 0 | CD62: 0
A63: ITAPEMIRIM | B63: =_xlfn.XLOOKUP(A:A,'Dados Elevatórias'!D:D,'Dados Elevatórias'!B:B) -> PL-RJB-EAT0109 | C63: =_xlfn.XLOOKUP(B:B,'Dados Elevatórias'!B:B,'Dados Elevatórias'!C:C) -> EAT | D63: BAIXADA 2 | E63: R. Rio Douro, 79 - Itaipu, Belford Roxo - RJ, 26143-500 | F63: Itaipu | G63: BELFORD ROXO | H63: =_xlfn.XLOOKUP(B:B,'Dados Elevatórias'!B:B,'Dados Elevatórias'!G:G) -> 26143-500 | I63: =_xlfn.XLOOKUP(B63,COORDENADAS!A:A,COORDENADAS!B:B) -> -22.7168 | J63: =_xlfn.XLOOKUP(B63,COORDENADAS!A:A,COORDENADAS!C:C) -> -43.4273 | L63: =_xlfn.XLOOKUP(A:A,'RELAÇÃO ANTIGA'!A:A,'RELAÇÃO ANTIGA'!J:J) -> INFORMAL | M63: 1 | N63: OPERACIONAL | O63: 20cv | P63: 3530rpm | Q63: WEG | R63: 160M | S63: RJB-04092 | T63: 220 / 380V | U63: 49,8 / 28,8 | Y63: RJB-30641 | AA63: 2 | AC63: ABRIGADA | AD63: NÃO | AN63: =_xlfn.XLOOKUP('RELAÇÃO DE ELEVATÓRIAS'!A:A,'RELAÇÃO ANTIGA'!A:A,'RELAÇÃO ANTIGA'!AC:AC) -> 220V | AP63: 413269259 | AQ63: 5027615 | AR63: 0 | AS63: AGUA - BOOSTER - ITAPEMIRIM | AT63: AV ITAPEMIRIM SN LD815 | AU63: 75MM | AV63: 75MM | AW63: 0 | AX63: 0 | AY63: 0 | AZ63: 0 | BJ63: RJB-20230 | BK63: INVERSOR DE FREQUÊNCIA | BL63: DANFOSS | BM63: FC-202P18KT2E20H2 | BN63: 18,5 KW / 25 HP | BO63: RJB-20232 | BP63: SIM | BR63: 1 MCA | BS63: < 1MCA | BT63: 0 | BU63: 0 | BV63: 0 | BW63: SIM | BY63: EM MARCHA | BZ63: 0 | CA63: 0 | CB63: 0 | CC63: BOA ESPERANÇA | CD63: Rua Benjamim Ferreira _ Rua Boa EsperanCa - Rua Cedro Rosa - Rua George Sandi - Rua Ipe Roxo - Rua Itapemirim - Rua Jacaranda Branco - Rua Tacaronda - Rua Vinhatico
A64: ITAPAGE | B64: =_xlfn.XLOOKUP(A:A,'Dados Elevatórias'!D:D,'Dados Elevatórias'!B:B) -> PL-RJB-EAT0830 | C64: =_xlfn.XLOOKUP(B:B,'Dados Elevatórias'!B:B,'Dados Elevatórias'!C:C) -> EAT | D64: BAIXADA 2 | E64: R. Itapage, 440, Queimados - RJ, 26381-429 | F64: Laranjal | G64: QUEIMADOS | H64: =_xlfn.XLOOKUP(B:B,'Dados Elevatórias'!B:B,'Dados Elevatórias'!G:G) -> 26381-429 | I64: =_xlfn.XLOOKUP(B64,COORDENADAS!A:A,COORDENADAS!B:B) -> -22.6943 | J64: =_xlfn.XLOOKUP(B64,COORDENADAS!A:A,COORDENADAS!C:C) -> -43.5573 | L64: =_xlfn.XLOOKUP(A:A,'RELAÇÃO ANTIGA'!A:A,'RELAÇÃO ANTIGA'!J:J) -> Nova | M64: 1 | N64: OPERACIONAL | O64: 5.5 (7.5cv) | P64: 3515rpm | Q64: Weg | R64: 112M | S64: RJB-21476 | T64: 220V / 380V / 440V | U64: 19.4/11.3/9.72 | X64: PX-15/2 | Y64: RJB-21477 | Z64: W22 Premium | AA64: 2 | AB64: 112mm | AC64: ABRIGADA | AG64: FF-215 | AP64: 0 | AQ64: 0 | AR64: 0 | AS64: 0 | AT64: 0 | AU64: 0 | AV64: 0 | AW64: 0 | AX64: 0 | AY64: 0 | AZ64: 0 | BK64: INVERSOR DE FREQUÊNCIA | BP64: SIM | BR64: 1 MCA | BS64: <1 MCA | BT64: 0 | BU64: 0 | BV64: 0 | BY64: 0 | BZ64: 0 | CA64: 0 | CB64: 0 | CC64: 0 | CD64: 0
A65: ITORORÓ | B65: =_xlfn.XLOOKUP(A:A,'Dados Elevatórias'!D:D,'Dados Elevatórias'!B:B) -> PL-RJB-EAT0748 | C65: =_xlfn.XLOOKUP(B:B,'Dados Elevatórias'!B:B,'Dados Elevatórias'!C:C) -> EAT | D65: BAIXADA 2 | E65: R. Itororó, 246 - Vila Guimaraes, Queimados - RJ, 26340-250 | F65: Vila Guimaraes | G65: QUEIMADOS | H65: =_xlfn.XLOOKUP(B:B,'Dados Elevatórias'!B:B,'Dados Elevatórias'!G:G) -> 26340-250 | I65: =_xlfn.XLOOKUP(B65,COORDENADAS!A:A,COORDENADAS!B:B) -> -22.7068 | J65: =_xlfn.XLOOKUP(B65,COORDENADAS!A:A,COORDENADAS!C:C) -> -43.5357 | L65: INFORMAL | M65: 1 | N65: OPERACIONAL | S65: FICTÍCIA | Y65: FICTÍCIA | AC65: SUBMERSA | AN65: 220V | AP65: 0 | AQ65: 0 | AR65: 0 | AS65: 0 | AT65: 0 | AU65: 100MM | AV65: 100MM | AW65: 0 | AX65: 0 | AY65: 0 | AZ65: 0 | BJ65: RJB-16937 | BK65: SOFT STARTER | BL65: WEG | BM65: SSW07 | BO65: RJB-16049 | BP65: NÃO | BR65: 0 | BS65: 0 | BT65: 0 | BU65: 0 | BV65: 0 | BW65: SIM | BY65: EM MARCHA | BZ65: 0 | CA65: 0 | CB65: 0 | CC65: 0 | CD65: 0
A66: IVO MIRANDA | B66: =_xlfn.XLOOKUP(A:A,'Dados Elevatórias'!D:D,'Dados Elevatórias'!B:B) -> PL-RJB-EAT0053 | C66: =_xlfn.XLOOKUP(B:B,'Dados Elevatórias'!B:B,'Dados Elevatórias'!C:C) -> EAT | D66: BAIXADA 2 | E66: Rua Ivo de Miranda Monte, 28, Banco de Areia, Mesquita - RJ, 26574-770 | F66: Banco de Areia | G66: MESQUITA | H66: =_xlfn.XLOOKUP(B:B,'Dados Elevatórias'!B:B,'Dados Elevatórias'!G:G) -> 26574-770 | I66: =_xlfn.XLOOKUP(B66,COORDENADAS!A:A,COORDENADAS!B:B) -> -22.7788 | J66: =_xlfn.XLOOKUP(B66,COORDENADAS!A:A,COORDENADAS!C:C) -> -43.4122 | L66: =_xlfn.XLOOKUP(A:A,'RELAÇÃO ANTIGA'!A:A,'RELAÇÃO ANTIGA'!J:J) -> INFORMAL | M66: 1 | N66: OPERACIONAL | O66: 10 CV | P66: 3535 RPM | S66: NÃO TEM | Y66: FICTÍCIA | AC66: SUBMERSA | AN66: =_xlfn.XLOOKUP('RELAÇÃO DE ELEVATÓRIAS'!A:A,'RELAÇÃO ANTIGA'!A:A,'RELAÇÃO ANTIGA'!AC:AC) -> 220V | AP66: 421142751 | AQ66: 8541558 | AR66: 0 | AS66: AGUA - ELEV- IVO DE MIRANDA | AT66: R IVO MIRANDA MONTES SN CN.CEDAE | AU66: 100MM | AV66: 100MM | AW66: 0 | AX66: 0 | AY66: 2860 | AZ66: 0 | BK66: SOFT STARTER | BL66: WEG | BM66: SSW07 | BP66: NÃO | BR66: 0 | BS66: 0 | BT66: 0 | BU66: 0 | BV66: 0 | BW66: SIM | BY66: EM MARCHA | BZ66: 12.4 | CA66: 37 | CB66: 0 | CC66: IVO MIRANDA | CD66: 0
A67: JOSE VIRGILIO DO PRADO | B67: =_xlfn.XLOOKUP(A:A,'Dados Elevatórias'!D:D,'Dados Elevatórias'!B:B) -> PL-RJB-EAT0694 | C67: =_xlfn.XLOOKUP(B:B,'Dados Elevatórias'!B:B,'Dados Elevatórias'!C:C) -> EAT | D67: BAIXADA 2 | E67: R. das Crianças, 257 - Vila Nascente, Queimados - RJ, 26327-210 | F67: Vila Nascente | G67: QUEIMADOS | H67: =_xlfn.XLOOKUP(B:B,'Dados Elevatórias'!B:B,'Dados Elevatórias'!G:G) -> 26325-030 | I67: =_xlfn.XLOOKUP(B67,COORDENADAS!A:A,COORDENADAS!B:B) -> -22.7254 | J67: =_xlfn.XLOOKUP(B67,COORDENADAS!A:A,COORDENADAS!C:C) -> -43.5543 | L67: =_xlfn.XLOOKUP(A:A,'RELAÇÃO ANTIGA'!A:A,'RELAÇÃO ANTIGA'!J:J) -> INFORMAL | M67: 1 | N67: OPERACIONAL | O67: 10CV | Q67: WEG | S67: RJB-14880 | T67: 220V / 380V / 440V | Y67: RJB-14837 | AC67: CASINHA | AN67: =_xlfn.XLOOKUP('RELAÇÃO DE ELEVATÓRIAS'!A:A,'RELAÇÃO ANTIGA'!A:A,'RELAÇÃO ANTIGA'!AC:AC) -> 220V | AP67: 0 | AQ67: 0 | AR67: 0 | AS67: 0 | AT67: 0 | AU67: 2POL | AV67: 2POL | AW67: 0 | AX67: 0 | AY67: 0 | AZ67: 0 | BK67: PARTIDA DIRETA | BP67: NÃO | BR67: 0 | BS67: 0 | BT67: 0 | BU67: 0 | BV67: 0 | BW67: SIM | BY67: EM MARCHA | BZ67: 0 | CA67: 0 | CB67: 0 | CC67: 0 | CD67: 0
A68: LAGOINHA | B68: =_xlfn.XLOOKUP(A:A,'Dados Elevatórias'!D:D,'Dados Elevatórias'!B:B) -> PL-RJB-EEE0082 | C68: =_xlfn.XLOOKUP(B:B,'Dados Elevatórias'!B:B,'Dados Elevatórias'!C:C) -> EEE | D68: BAIXADA 2 | E68: R. Quarenta e Sete, 62 - Conj. Campo Belo, Nova Iguaçu - RJ, 26296-099 | F68: Campo Belo | G68: NOVA IGUAÇU | H68: =_xlfn.XLOOKUP(B:B,'Dados Elevatórias'!B:B,'Dados Elevatórias'!G:G) -> 26296-099 | I68: =_xlfn.XLOOKUP(B68,COORDENADAS!A:A,COORDENADAS!B:B) -> -22.7962 | J68: =_xlfn.XLOOKUP(B68,COORDENADAS!A:A,COORDENADAS!C:C) -> -43.5912 | M68: 1 | N68: OPERACIONAL | P68: 1750rpm | S68: NÃO TEM | X68: RGB 801T-EI | Y68: RJB-30664 | AC68: ABRIGADA | AI68: 66m³/h | AJ68: 13.3mca | AN68: VERIFICAR | AO68: VERIFICAR | AP68: 0 | AQ68: 0 | AR68: 0 | AS68: 0 | AT68: 0 | AU68: 0 | AV68: 0 | AW68: 0 | AX68: 0 | AY68: 0 | AZ68: 0 | BK68: SOFT STARTER | BP68: NÃO | BR68: 0 | BS68: 0 | BT68: 0 | BU68: 0 | BV68: 0 | BY68: 0 | BZ68: 0 | CA68: 0 | CB68: 0 | CC68: 0 | CD68: 0
A69: LAGOINHA II | B69: =_xlfn.XLOOKUP(A:A,'Dados Elevatórias'!D:D,'Dados Elevatórias'!B:B) -> PL-RJB-EEE0083 | C69: =_xlfn.XLOOKUP(B:B,'Dados Elevatórias'!B:B,'Dados Elevatórias'!C:C) -> EEE | D69: BAIXADA 2 | E69: R. Zero, 195 - Lagoinha, Nova Iguaçu - RJ, 26296-024 | F69: Campo Belo | G69: NOVA IGUAÇU | H69: =_xlfn.XLOOKUP(B:B,'Dados Elevatórias'!B:B,'Dados Elevatórias'!G:G) -> 0 | I69: =_xlfn.XLOOKUP(B69,COORDENADAS!A:A,COORDENADAS!B:B) -> -22.8027 | J69: =_xlfn.XLOOKUP(B69,COORDENADAS!A:A,COORDENADAS!C:C) -> -43.5901 | M69: 1 | N69: OPERACIONAL | O69: 2,0CV | P69: 1750rpm | Q69: ABS | S69: RJB-22575 | T69: 220V | U69: 10A | X69: ZULZER EJ20BX | Y69: RJB-22575 | Z69: ZULZER | AC69: ABRIGADA | AF69: SUBMERSA VERTICAL | AH69: SUBMERSIVEL | AI69: 18m³/h | AJ69: 10mca | AM69: 5539980 | AN69: VERIFICAR | AO69: VERIFICAR | AP69: 0 | AQ69: 0 | AR69: 0 | AS69: 0 | AT69: 0 | AU69: 0 | AV69: 0 | AW69: 0 | AX69: 0 | AY69: 0 | AZ69: 0 | BK69: SOFT STARTER | BP69: NÃO | BR69: 0 | BS69: 0 | BT69: 0 | BU69: 0 | BV69: 0 | BY69: 0 | BZ69: 0 | CA69: 0 | CB69: 0 | CC69: 0 | CD69: 0
A70: LIBANEA | B70: =_xlfn.XLOOKUP(A:A,'Dados Elevatórias'!D:D,'Dados Elevatórias'!B:B) -> PL-RJB-EAT0046 | C70: =_xlfn.XLOOKUP(B:B,'Dados Elevatórias'!B:B,'Dados Elevatórias'!C:C) -> EAT | D70: BAIXADA 2 | E70: R. Libânia, 2-144 - Vila Emil, Mesquita - RJ, 26551-200 | F70: Vila Emil | G70: MESQUITA | H70: =_xlfn.XLOOKUP(B:B,'Dados Elevatórias'!B:B,'Dados Elevatórias'!G:G) -> 26551-200 | I70: =_xlfn.XLOOKUP(B70,COORDENADAS!A:A,COORDENADAS!B:B) -> -22.7792 | J70: =_xlfn.XLOOKUP(B70,COORDENADAS!A:A,COORDENADAS!C:C) -> -43.4247 | L70: =_xlfn.XLOOKUP(A:A,'RELAÇÃO ANTIGA'!A:A,'RELAÇÃO ANTIGA'!J:J) -> FORMAL | M70: 1 | N70: OPERACIONAL | O70: 6 CV | P70: 3330 RPM | S70: NÃO TEM | T70: 220V | U70: 22A / 23A / 19A | Y70: RJB-04936 | AA70: 2 | AC70: SUBMERSA | AN70: =_xlfn.XLOOKUP('RELAÇÃO DE ELEVATÓRIAS'!A:A,'RELAÇÃO ANTIGA'!A:A,'RELAÇÃO ANTIGA'!AC:AC) -> 220V | AP70: 420187783 | AQ70: 6144582 | AR70: 0 | AS70: AGUA - ELEV - LIBANEA | AT70: R LIBANIA SN EF15 EF15A | AU70: 100MM | AV70: 100MM | AW70: 0 | AX70: 0 | AY70: 0 | AZ70: 0 | BK70: PARTIDA DIRETA | BP70: NÃO | BR70: 0 | BS70: 0 | BT70: 0 | BU70: 0 | BV70: 0 | BW70: SIM | BY70: EM MARCHA | BZ70: 0 | CA70: 0 | CB70: 0 | CC70: 0 | CD70: 0
A71: LIBERDADE | B71: =_xlfn.XLOOKUP(A:A,'Dados Elevatórias'!D:D,'Dados Elevatórias'!B:B) -> PL-RJB-EAT0045 | C71: =_xlfn.XLOOKUP(B:B,'Dados Elevatórias'!B:B,'Dados Elevatórias'!C:C) -> EAT | D71: BAIXADA 2 | E71: Rua Mario Pereira Lima, 140 - Lote 9 - Austin - Nova Iguaçu | F71: Austin | G71: NOVA IGUAÇU | H71: =_xlfn.XLOOKUP(B:B,'Dados Elevatórias'!B:B,'Dados Elevatórias'!G:G) -> 0 | I71: =_xlfn.XLOOKUP(B71,COORDENADAS!A:A,COORDENADAS!B:B) -> -22.719 | J71: =_xlfn.XLOOKUP(B71,COORDENADAS!A:A,COORDENADAS!C:C) -> -43.5184 | M71: 1 | N71: OPERACIONAL | O71: 7,5 cv | S71: RJB-00461 | Y71: RJB-00460 | AC71: CONTAINER | AP71: 0 | AQ71: 0 | AR71: 0 | AS71: 0 | AT71: 0 | AU71: 0 | AV71: 0 | AW71: 0 | AX71: 0 | AY71: 0 | AZ71: 0 | BK71: PARTIDA DIRETA | BP71: NÃO | BR71: 0 | BS71: 0 | BT71: 0 | BU71: 0 | BV71: 0 | BY71: 0 | BZ71: 0 | CA71: 0 | CB71: 0 | CC71: 0 | CD71: 0
A72: LUCIO TAVARES | B72: =_xlfn.XLOOKUP(A:A,'Dados Elevatórias'!D:D,'Dados Elevatórias'!B:B) -> PL-RJB-EAT0043 | C72: =_xlfn.XLOOKUP(B:B,'Dados Elevatórias'!B:B,'Dados Elevatórias'!C:C) -> EAT | D72: BAIXADA 2 | E72: R. Lúcio Tavares - Centro, Nilópolis - RJ, 26535-001 | F72: Centro | G72: NILÓPOLIS | H72: =_xlfn.XLOOKUP(B:B,'Dados Elevatórias'!B:B,'Dados Elevatórias'!G:G) -> 26535-001 | I72: =_xlfn.XLOOKUP(B72,COORDENADAS!A:A,COORDENADAS!B:B) -> -22.8061 | J72: =_xlfn.XLOOKUP(B72,COORDENADAS!A:A,COORDENADAS!C:C) -> -43.4152 | L72: =_xlfn.XLOOKUP(A:A,'RELAÇÃO ANTIGA'!A:A,'RELAÇÃO ANTIGA'!J:J) -> FORMAL | M72: 1 | N72: OPERACIONAL | P72: 3535 RPM | S72: NÃO TEM | Y72: NÃO TEM | AC72: SUBMERSA | AN72: =_xlfn.XLOOKUP('RELAÇÃO DE ELEVATÓRIAS'!A:A,'RELAÇÃO ANTIGA'!A:A,'RELAÇÃO ANTIGA'!AC:AC) -> 220V | AP72: 400380547 | AQ72: 6923505 | AR72: 0 | AS72: AGUA - ELEV - LUCIO TAVARES | AT72: R LUCIO TAVARES SN EF329 | AU72: 150MM | AV72: 150MM | AW72: 0 | AX72: 0 | AY72: 0 | AZ72: 0 | BK72: PARTIDA DIRETA | BP72: NÃO | BQ72: SIM | BR72: 0 | BS72: 0 | BT72: 0 | BU72: 0 | BV72: 0 | BW72: SIM | BY72: EM MARCHA | BZ72: 0 | CA72: 0 | CB72: 0 | CC72: 0 | CD72: Rua LUcio Tavares (Trecho Rua AntOnio JosE Bittencourt A Av. Oswaldo Cruz), Rua Orlando Bernardino Lopes (Trecho Rua Carmela Dutra ao final da Rua), Rua Dr. Silvio, Rua AntOnio Cardoso Leal (Trecho Rua AntOnio Bittencourt A Av. Oswaldo Cruz), Rua Dr. Rufino GonCalves Ferreira (Trecho Rua AntOnio JosE Bitencourt A Av. Oswaldo Cruz) e pequenas Vilas desse trecho
A73: MACIEL | B73: =_xlfn.XLOOKUP(A:A,'Dados Elevatórias'!D:D,'Dados Elevatórias'!B:B) -> PL-RJB-EAT0747 | C73: =_xlfn.XLOOKUP(B:B,'Dados Elevatórias'!B:B,'Dados Elevatórias'!C:C) -> EAT | D73: BAIXADA 2 | E73: R. Ver. José Virgílio do Prado, 79 - Vila Nascente, Queimados - RJ, 26325-050 | F73: Vila Nascente | G73: QUEIMADOS | H73: =_xlfn.XLOOKUP(B:B,'Dados Elevatórias'!B:B,'Dados Elevatórias'!G:G) -> 26325-050 | I73: =_xlfn.XLOOKUP(B73,COORDENADAS!A:A,COORDENADAS!B:B) -> -22.7227 | J73: =_xlfn.XLOOKUP(B73,COORDENADAS!A:A,COORDENADAS!C:C) -> -43.5521 | L73: =_xlfn.XLOOKUP(A:A,'RELAÇÃO ANTIGA'!A:A,'RELAÇÃO ANTIGA'!J:J) -> INFORMAL | M73: 1 | N73: OPERACIONAL | O73: 15cv | Q73: WEG | S73: RJA-01036 | Y73: RJB-03110 | Z73: DANCOR | AC73: ABRIGADA | AN73: =_xlfn.XLOOKUP('RELAÇÃO DE ELEVATÓRIAS'!A:A,'RELAÇÃO ANTIGA'!A:A,'RELAÇÃO ANTIGA'!AC:AC) -> 220V | AP73: 420631920 | AQ73: 8878387 | AR73: 0 | AS73: AGUA - BVOLANTE - MACIEL | AT73: R MACIEL SN EF113 | AU73: 2POL | AV73: 2POL | AW73: 0 | AX73: 0 | AY73: 0 | AZ73: 0 | BK73: PARTIDA DIRETA | BP73: NÃO | BR73: 1 MCA | BS73: < 1MCA | BT73: 0 | BU73: 0 | BV73: 0 | BW73: SIM | BY73: EM MARCHA | BZ73: 0 | CA73: 0 | CB73: 0 | CC73: 0 | CD73: 0
A74: MANOEL REIS | B74: =_xlfn.XLOOKUP(A:A,'Dados Elevatórias'!D:D,'Dados Elevatórias'!B:B) -> PL-RJB-EAT0040 | C74: =_xlfn.XLOOKUP(B:B,'Dados Elevatórias'!B:B,'Dados Elevatórias'!C:C) -> EAT | D74: BAIXADA 2 | E74: R. Dr. Manoel Reis, 405 - Olinda, Nilópolis - RJ, 26510-182 | F74: Olinda | G74: NILÓPOLIS | H74: =_xlfn.XLOOKUP(B:B,'Dados Elevatórias'!B:B,'Dados Elevatórias'!G:G) -> 26510-182 | I74: =_xlfn.XLOOKUP(B74,COORDENADAS!A:A,COORDENADAS!B:B) -> -22.8147 | J74: =_xlfn.XLOOKUP(B74,COORDENADAS!A:A,COORDENADAS!C:C) -> -43.4159 | L74: =_xlfn.XLOOKUP(A:A,'RELAÇÃO ANTIGA'!A:A,'RELAÇÃO ANTIGA'!J:J) -> FORMAL | M74: 1 | N74: OPERACIONAL | O74: 5cv | P74: 3450rpm | S74: NÃO TEM | T74: 220V / 380V | U74: 18A / 18A / 18A | X74: VBSP67.1782 T | Y74: RJB-19615 | Z74: VAMBRO | AA74: 4 | AC74: TUBULÂO | AI74: 27m³/h | AJ74: 14mca | AN74: =_xlfn.XLOOKUP('RELAÇÃO DE ELEVATÓRIAS'!A:A,'RELAÇÃO ANTIGA'!A:A,'RELAÇÃO ANTIGA'!AC:AC) -> 220V | AP74: 414605743 | AQ74: 5187019 | AR74: 0 | AS74: AGUA - ELEV - MANOEL REIS | AT74: EST DR MANOEL REIS SN EF395 | AU74: 75MM | AV74: 75MM | AW74: 0 | AX74: 0 | AY74: 0 | AZ74: 0 | BK74: SOFT STARTER | BL74: WEG | BM74: SSW07 | BP74: NÃO | BR74: 0 | BS74: 0 | BT74: 0 | BU74: 0 | BV74: 0 | BW74: SIM | BY74: EM MARCHA | BZ74: 0 | CA74: 0 | CB74: 0 | CC74: 0 | CD74: Area 1: Rua JosE do PatrocInio (trecho Rua Alberto Teixeira da Cunha A Av. Mirandela), Rua VirgIlio R. de Oliveira (trecho Rua Alberto Teixeira da Cunha A Av. Mirandela), Rua Jornalista Hungria (trecho Rua Alberto Teixeira da Cunha A Av. Mirandela, Rua Alberto Teixeira da Cunha (trecho Rua JoAo Pessoa A Rua wallace Paes Leme). Area 2: Rua JosE do PatrocInio (trecho Rua AntOnio JoAo MendonCa A Rua Alberto Teixeira da Cunha), Rua VirgIlio R. de Oliveira (trecho Rua Antonio JoAo MendonCa A Rua Alberto Teixeira da Cunha), Rua Manoel Brigido Tinoco, Rua Cap. Manoel de Melo, Rua JoAo Pessoa (trecho Rua Antonio JoAo MendonCa A Rua Alberto Teixeira da Cunha), Rua Geovana Santana Drumond, Rua Antonio JoAo MendonCa (trecho Rua JoAo Pessoa A Rua Wallace Paes Leme). Area 3: Rua Feliciano SodrE, Rua FlorianOpolis, Rua Maria Teresa de Paula, Rua Maria Chambarele, Rua JoAo Evangelista de Carvalho (trecho Rua Dr. Manoel Reis A Rua Antonio JoAo MendonCa).
A75: MAURICIA BORGES | B75: =_xlfn.XLOOKUP(A:A,'Dados Elevatórias'!D:D,'Dados Elevatórias'!B:B) -> PL-RJB-EAT0032 | C75: =_xlfn.XLOOKUP(B:B,'Dados Elevatórias'!B:B,'Dados Elevatórias'!C:C) -> EAT | D75: BAIXADA 2 | E75: Rua Maurícia Borges, 314 - Banco de Areia, Mesquita - RJ, 26564-021 | F75: Banco de Areia | G75: MESQUITA | H75: =_xlfn.XLOOKUP(B:B,'Dados Elevatórias'!B:B,'Dados Elevatórias'!G:G) -> 26564-021 | I75: =_xlfn.XLOOKUP(B75,COORDENADAS!A:A,COORDENADAS!B:B) -> -22.7776 | J75: =_xlfn.XLOOKUP(B75,COORDENADAS!A:A,COORDENADAS!C:C) -> -43.4193 | L75: =_xlfn.XLOOKUP(A:A,'RELAÇÃO ANTIGA'!A:A,'RELAÇÃO ANTIGA'!J:J) -> FORMAL | M75: 1 | N75: OPERACIONAL | P75: 3450rpm | S75: NÃO TEM | X75: VBOP64 . 6097 T | Y75: RJB-16423 | Z75: Bombas Vanbro LTDA | AA75: 4 | AC75: CASINHA | AI75: 13 a 17m³/h | AN75: =_xlfn.XLOOKUP('RELAÇÃO DE ELEVATÓRIAS'!A:A,'RELAÇÃO ANTIGA'!A:A,'RELAÇÃO ANTIGA'!AC:AC) -> 220V | AP75: 420187776 | AQ75: 6141673 | AR75: 0 | AS75: AGUA - ELEV - MAURICIA BORGES | AT75: TR MAURICIA BORGES SN PX303 | AU75: 100MM | AV75: 100MM | AW75: 0 | AX75: 0 | AY75: 0 | AZ75: 0 | BK75: PARTIDA DIRETA | BP75: NÃO | BR75: 0 | BS75: 0 | BT75: 0 | BU75: 0 | BV75: 0 | BW75: SIM | BY75: EM MARCHA | BZ75: 0 | CA75: 0 | CB75: 0 | CC75: 0 | CD75: 0
A76: MELVIN JONES | B76: =_xlfn.XLOOKUP(A:A,'Dados Elevatórias'!D:D,'Dados Elevatórias'!B:B) -> PL-RJB-EAT0031 | C76: =_xlfn.XLOOKUP(B:B,'Dados Elevatórias'!B:B,'Dados Elevatórias'!C:C) -> EAT | D76: BAIXADA 2 | E76: R. Gov. Portela, 331 - Centro, Nova Iguaçu - RJ, 26221-030 | F76: Centro | G76: NOVA IGUAÇU | H76: =_xlfn.XLOOKUP(B:B,'Dados Elevatórias'!B:B,'Dados Elevatórias'!G:G) -> 26221-130 | I76: =_xlfn.XLOOKUP(B76,COORDENADAS!A:A,COORDENADAS!B:B) -> -22.764 | J76: =_xlfn.XLOOKUP(B76,COORDENADAS!A:A,COORDENADAS!C:C) -> -43.4385 | L76: =_xlfn.XLOOKUP(A:A,'RELAÇÃO ANTIGA'!A:A,'RELAÇÃO ANTIGA'!J:J) -> FORMAL | M76: 1 | N76: OPERACIONAL | S76: RJB-18602 | U76: 221A / 22A | Y76: RJB-18603 | AC76: SUBMERSA | AN76: =_xlfn.XLOOKUP('RELAÇÃO DE ELEVATÓRIAS'!A:A,'RELAÇÃO ANTIGA'!A:A,'RELAÇÃO ANTIGA'!AC:AC) -> 220V | AP76: 413730985 | AQ76: 5028143 | AR76: 0 | AS76: AGUA - BOOSTER - MELVIM JONES | AT76: TR MELVIM JONES SN LD41 | AU76: 75MM | AV76: 75MM | AW76: 0 | AX76: 0 | AY76: 0 | AZ76: 0 | BK76: SOFT STARTER | BM76: SSW07 | BP76: NÃO | BR76: 0 | BS76: 0 | BT76: 0 | BU76: 0 | BV76: 0 | BW76: SIM | BY76: EM MARCHA | BZ76: 0 | CA76: 0 | CB76: 0 | CC76: 0 | CD76: Rua Melvin Jones
A77: MENA BARRETO | B77: =_xlfn.XLOOKUP(A:A,'Dados Elevatórias'!D:D,'Dados Elevatórias'!B:B) -> PL-RJB-EAT0030 | C77: =_xlfn.XLOOKUP(B:B,'Dados Elevatórias'!B:B,'Dados Elevatórias'!C:C) -> EAT | D77: BAIXADA 2 | E77: R. Otaciano, 96 - Novo Horizonte, Nilópolis - RJ, 26535-430 | F77: Novo Horizonte | G77: NILÓPOLIS | H77: =_xlfn.XLOOKUP(B:B,'Dados Elevatórias'!B:B,'Dados Elevatórias'!G:G) -> 26535-430 | I77: =_xlfn.XLOOKUP(B77,COORDENADAS!A:A,COORDENADAS!B:B) -> -22.8018 | J77: =_xlfn.XLOOKUP(B77,COORDENADAS!A:A,COORDENADAS!C:C) -> -43.4052 | L77: =_xlfn.XLOOKUP(A:A,'RELAÇÃO ANTIGA'!A:A,'RELAÇÃO ANTIGA'!J:J) -> INFORMAL | M77: 1 | N77: OPERACIONAL | O77: 12cv | AC77: SUBMERSA | AN77: =_xlfn.XLOOKUP('RELAÇÃO DE ELEVATÓRIAS'!A:A,'RELAÇÃO ANTIGA'!A:A,'RELAÇÃO ANTIGA'!AC:AC) -> 220V | AP77: 414857558 | AQ77: 5789840 | AR77: 0 | AS77: AGUA - BVOLANTE - MENA BARRETO | AT77: EST GAL MENA BARRETO SN EF863 | AU77: 0 | AV77: 0 | AW77: 0 | AX77: 0 | AY77: 0 | AZ77: 0 | BK77: SOFT STARTER | BP77: NÃO | BR77: 0 | BS77: 0 | BT77: 0 | BU77: 0 | BV77: 0 | BW77: SIM | BY77: EM MARCHA | BZ77: 0 | CA77: 0 | CB77: 0 | CC77: CABUIS | CD77: Estrada Mena Barreto (trecho), Rua Nadir Trindade (trecho), Rua Natividade (trecho), Rua OtacIlio Pessoa (trecho).
A78: MESQUITA G1 | B78: =_xlfn.XLOOKUP(A:A,'Dados Elevatórias'!D:D,'Dados Elevatórias'!B:B) -> PL-RJB-EAT0086 | C78: =_xlfn.XLOOKUP(B:B,'Dados Elevatórias'!B:B,'Dados Elevatórias'!C:C) -> EAT | D78: BAIXADA 2 | E78: Rua Augusto Cardoso, 240 - Coréia, Mesquita, RJ - 26556-030 | F78: Coréia | G78: MESQUITA | H78: =_xlfn.XLOOKUP(B:B,'Dados Elevatórias'!B:B,'Dados Elevatórias'!G:G) -> 26556-030 | I78: =_xlfn.XLOOKUP(B78,COORDENADAS!A:A,COORDENADAS!B:B) -> -22.7805 | J78: =_xlfn.XLOOKUP(B78,COORDENADAS!A:A,COORDENADAS!C:C) -> -43.4361 | L78: INFORMAL | M78: 1 | N78: OPERACIONAL | O78: 100cv | P78: 3510rpm | Q78: WEG | S78: RJB-02885 | T78: 220V / 380V | U78: 228 / 132 A | Y78: RJB-11656 | AC78: ABRIGADA | AN78: 220V/MT | AP78: 400131474 | AQ78: 7267348 | AR78: 0 | AS78: AGUA - BOOSTER - MESQUITA | AT78: R AUGUSTO CARDOSO SN | AU78: DN45X200 | AV78: DN45X200 | AW78: 0 | AX78: 0 | AY78: 0 | AZ78: 0 | BK78: SOFT STARTER | BL78: WEG | BM78: SSW07 | BP78: SIM | BR78: 0 | BS78: 0 | BT78: 0 | BU78: 0 | BV78: 0 | BW78: SIM | BY78: EM MARCHA | BZ78: 0 | CA78: 0 | CB78: 0 | CC78: CORÉIA | CD78: Ruas Guararema, guaraUna, JapuIra, Itacy, Capivari, Patativa, Uruguai, Campestre, Siriema, PompIlio, Rua da Valam Quito, Canavial, Arrozal, Javali, Paraguai, JosE Dias GuimarAes, JardinOpolis, Pintassilgo, Araripe, GuaporE, Luanda, Capivara
A79: MESQUITA G1 | B79: =_xlfn.XLOOKUP(A:A,'Dados Elevatórias'!D:D,'Dados Elevatórias'!B:B) -> PL-RJB-EAT0086 | C79: =_xlfn.XLOOKUP(B:B,'Dados Elevatórias'!B:B,'Dados Elevatórias'!C:C) -> EAT | D79: BAIXADA 2 | E79: Rua Augusto Cardoso, 240 - Coréia, Mesquita, RJ - 26556-030 | F79: Coréia | G79: MESQUITA | H79: =_xlfn.XLOOKUP(B:B,'Dados Elevatórias'!B:B,'Dados Elevatórias'!G:G) -> 26556-030 | I79: =_xlfn.XLOOKUP(B79,COORDENADAS!A:A,COORDENADAS!B:B) -> -22.7805 | J79: =_xlfn.XLOOKUP(B79,COORDENADAS!A:A,COORDENADAS!C:C) -> -43.4361 | L79: RESERVA | M79: 2 | N79: OPERACIONAL | O79: 100CV | P79: 3560rpm | Q79: WEG | S79: RJB-13964 | T79: 220V / 380V / 440V | Y79: RJB-11659 | AN79: 220V/MT | AP79: 400131474 | AQ79: 7267348 | AR79: 0 | AS79: AGUA - BOOSTER - MESQUITA | AT79: R AUGUSTO CARDOSO SN | AU79: DN45X200 | AV79: DN45X200 | AW79: 0 | AX79: 0 | AY79: 0 | AZ79: 0 | BK79: SOFT STARTER | BL79: WEG | BM79: SSW07 | BP79: SIM | BR79: 0 | BS79: 0 | BT79: 0 | BU79: 0 | BV79: 0 | BW79: SIM | BY79: EM MARCHA | BZ79: 0 | CA79: 0 | CB79: 0 | CC79: CORÉIA | CD79: Ruas Guararema, guaraUna, JapuIra, Itacy, Capivari, Patativa, Uruguai, Campestre, Siriema, PompIlio, Rua da Valam Quito, Canavial, Arrozal, Javali, Paraguai, JosE Dias GuimarAes, JardinOpolis, Pintassilgo, Araripe, GuaporE, Luanda, Capivara
A80: MORRO DA COCADA | B80: =_xlfn.XLOOKUP(A:A,'Dados Elevatórias'!D:D,'Dados Elevatórias'!B:B) -> PL-RJB-EAT0068 | C80: =_xlfn.XLOOKUP(B:B,'Dados Elevatórias'!B:B,'Dados Elevatórias'!C:C) -> EAT | D80: BAIXADA 2 | E80: R. Doná Orminda, 23 - Andrade Araujo, Nova Iguaçu - RJ, 26010-450 | F80: Andrade Araujo | G80: NOVA IGUAÇU | H80: =_xlfn.XLOOKUP(B:B,'Dados Elevatórias'!B:B,'Dados Elevatórias'!G:G) -> 26010-450 | I80: =_xlfn.XLOOKUP(B80,COORDENADAS!A:A,COORDENADAS!B:B) -> -22.7567 | J80: =_xlfn.XLOOKUP(B80,COORDENADAS!A:A,COORDENADAS!C:C) -> -43.4207 | L80: =_xlfn.XLOOKUP(A:A,'RELAÇÃO ANTIGA'!A:A,'RELAÇÃO ANTIGA'!J:J) -> FORMAL | M80: 1 | N80: OPERACIONAL | O80: 4,5 CV | P80: 3500 RPM | S80: NÃO TEM | Y80: NÃO TEM | AC80: SUBMERSA | AN80: =_xlfn.XLOOKUP(A:A,'RELAÇÃO ANTIGA'!A:A,'RELAÇÃO ANTIGA'!AC:AC,X) -> 220V | AP80: 0 | AQ80: 7254021 | AR80: 0 | AS80: AGUA - ELEV - MORRO DA COCADA | AT80: R DONA ORMINDA SN PX25 | AU80: 150MM | AV80: 150MM | AW80: 0 | AX80: 0 | AY80: 0 | AZ80: 0 | BK80: SOFT STARTER | BP80: SIM | BR80: 0 | BS80: 0 | BT80: 0 | BU80: 0 | BV80: 0 | BW80: SIM | BY80: EM MARCHA | BZ80: 0 | CA80: 0 | CB80: 0 | CC80: 0 | CD80: 0
A81: MORRO DA TORRE | B81: =_xlfn.XLOOKUP(A:A,'Dados Elevatórias'!D:D,'Dados Elevatórias'!B:B) -> PL-RJB-EAT1014 | C81: =_xlfn.XLOOKUP(B:B,'Dados Elevatórias'!B:B,'Dados Elevatórias'!C:C) -> EAT | D81: BAIXADA 2 | E81: R. Mirante, 289-193 - Flesmam, Queimados - RJ, 26325-200 | F81: Flesmam | G81: QUEIMADOS | H81: =_xlfn.XLOOKUP(B:B,'Dados Elevatórias'!B:B,'Dados Elevatórias'!G:G) -> 26325-200 | I81: =_xlfn.XLOOKUP(B81,COORDENADAS!A:A,COORDENADAS!B:B) -> -22.7211 | J81: =_xlfn.XLOOKUP(B81,COORDENADAS!A:A,COORDENADAS!C:C) -> -43.5516 | M81: 1 | N81: OPERACIONAL | O81: 10 | P81: 3515rpm | Q81: WEG | R81: 132S | S81: RJB-07199 | T81: 220 / 380 / 440 | U81: 25.0 / 14.5 / 12.5 | Y81: RJB-07185 | Z81: DANCOR | AA81: 2 | AC81: ABRIGADA | AD81: NÃO | AF81: HORIZONTAL | AH81: CONVENSIONAL | AP81: 0 | AQ81: 0 | AR81: 0 | AS81: 0 | AT81: 0 | AU81: 0 | AV81: 0 | AW81: 0 | AX81: 0 | AY81: 0 | AZ81: 0 | BC81: NÃO | BD81: SIM | BE81: SIM | BJ81: RJB-22285 | BK81: INVERSOR DE FREQUÊNCIA | BL81: ABB | BM81: ACS355 | BN81: 41A | BO81: RJB-23832 | BP81: NÃO | BR81: 1 mca | BS81: <1MCA | BT81: 0 | BU81: 0 | BV81: 0 | BY81: 0 | BZ81: 0 | CA81: 0 | CB81: 0 | CC81: 0 | CD81: 0
A82: MORRO DA MOENDA | B82: =_xlfn.XLOOKUP(A:A,'Dados Elevatórias'!D:D,'Dados Elevatórias'!B:B) -> PL-RJB-EAT0039 | C82: =_xlfn.XLOOKUP(B:B,'Dados Elevatórias'!B:B,'Dados Elevatórias'!C:C) -> EAT | D82: BAIXADA 2 | E82: Rua Manuel Rodrigues de Sá Panela, 25 - Cacuia - Nova Iguaçu -RJ | F82: Cacuia | G82: NOVA IGUAÇU | H82: 26082-250 | I82: =_xlfn.XLOOKUP(B82,COORDENADAS!A:A,COORDENADAS!B:B) -> -22.7306 | J82: =_xlfn.XLOOKUP(B82,COORDENADAS!A:A,COORDENADAS!C:C) -> -43.5146 | L82: INFORMAL | M82: 1 | N82: OPERACIONAL | O82: 8 cv | P82: 3500rpm | Q82: LEAO | S82: RJB-25663 | T82: 220V / 380V | U82: 24.0 / 24.0 / 24.0 | Y82: RJB-26857 | Z82: LEAO | AC82: SUBMERSA | AN82: =_xlfn.XLOOKUP(A:A,'RELAÇÃO ANTIGA'!A:A,'RELAÇÃO ANTIGA'!AC:AC,X) -> 220V | AP82: 420160768 | AQ82: 6098958 | AR82: 0 | AS82: AGUA - BOOSTER - MORRO DA MOENDA | AT82: R C SN EF21 | AU82: 100MM | AV82: 100MM | AW82: 0 | AX82: 0 | AY82: 0 | AZ82: 0 | BK82: SOFT STARTER | BP82: NÃO | BR82: 0 | BS82: 0 | BT82: 0 | BU82: 0 | BV82: 0 | BW82: SIM | BY82: EM MARCHA | BZ82: 0 | CA82: 0 | CB82: 0 | CC82: MOENDA | CD82: Rua Altinopolis, Rua Jeronimo de Ornelas, Rua Caninare, Rua Almirante Pestana, Rua Dante Santoro, Rua 7 Barras, Rua Wilde Lustosa, Rua Tambaquim.
A83: MORRO DO TEMPERO | B83: =_xlfn.XLOOKUP(A:A,'Dados Elevatórias'!D:D,'Dados Elevatórias'!B:B) -> PL-RJB-EAT0738 | C83: =_xlfn.XLOOKUP(B:B,'Dados Elevatórias'!B:B,'Dados Elevatórias'!C:C) -> EAT | D83: BAIXADA 2 | E83: Estrada Carlos Sampaio ,78 - Austin - Nova Iguaçu | F83: Austin | G83: NOVA IGUAÇU | H83: 26088-230 | I83: =_xlfn.XLOOKUP(B83,COORDENADAS!A:A,COORDENADAS!B:B) -> -22.7029 | J83: =_xlfn.XLOOKUP(B83,COORDENADAS!A:A,COORDENADAS!C:C) -> -43.5334 | L83: INFORMAL | M83: 1 | N83: OPERACIONAL | O83: 15 CV | P83: 3545RPM | Q83: WEG W22 IR3 Premium | R83: 132M/L | T83: 220V / 380V / 440V | U83: 36.8 / 21.3 / 18.4 | V83: 6207-ZZ | W83: 6307-ZZ | X83: FN2F-T-T15,0CV | Y83: NÃO TEM | Z83: FAMAC | AA83: 1,9 | AB83: 172mm | AC83: CONTAINER | AD83: NÃO | AI83: 87 m³/h | AJ83: 52mca | AN83: =_xlfn.XLOOKUP(A:A,'RELAÇÃO ANTIGA'!A:A,'RELAÇÃO ANTIGA'!AC:AC,X) -> 220V | AP83: 0 | AQ83: 0 | AR83: 0 | AS83: 0 | AT83: 0 | AU83: 150MM | AV83: 150MM | AW83: 0 | AX83: 0 | AY83: 0 | AZ83: 0 | BK83: INVERSOR DE FREQUÊNCIA | BP83: SIM | BR83: 5 MCA | BS83: 1 MCA | BT83: 0 | BU83: 0 | BV83: 0 | BW83: SIM | BY83: EM MARCHA | BZ83: 0 | CA83: 0 | CB83: 0 | CC83: 0 | CD83: 0
A84: MORRO DOS 40 | B84: =_xlfn.XLOOKUP(A:A,'Dados Elevatórias'!D:D,'Dados Elevatórias'!B:B) -> PL-RJB-EAT0832 | C84: =_xlfn.XLOOKUP(B:B,'Dados Elevatórias'!B:B,'Dados Elevatórias'!C:C) -> EAT | D84: BAIXADA 2 | E84: R. José Assis Ferreira, 91 - Centro de Japeri, Japeri - RJ, 26435-267 | F84: Centro | G84: JAPERI | H84: =_xlfn.XLOOKUP(B:B,'Dados Elevatórias'!B:B,'Dados Elevatórias'!G:G) -> 26435-267 | I84: =_xlfn.XLOOKUP(B84,COORDENADAS!A:A,COORDENADAS!B:B) -> -22.6419 | J84: =_xlfn.XLOOKUP(B84,COORDENADAS!A:A,COORDENADAS!C:C) -> -43.6546 | M84: 1 | N84: OPERACIONAL | O84: 10 CV | P84: 3515 RPM | AC84: ABRIGADA | AH84: CONVENSIONAL | AI84: 87 m³/h | AJ84: 52mca | AN84: =_xlfn.XLOOKUP(A:A,'RELAÇÃO ANTIGA'!A:A,'RELAÇÃO ANTIGA'!AC:AC,X) -> 220v | AP84: 0 | AQ84: 0 | AR84: 0 | AT84: 0 | AU84: 0 | AV84: 0 | AW84: 0 | AX84: 0 | AY84: 0 | AZ84: 0 | BK84: INVERSOR DE FREQUÊNCIA | BL84: ABB | BM84: ACS310-03E-34A1-2 | BN84: 7,5KW - 10HP | BP84: SIM | BR84: 0.5 MCA | BS84: 0.2 MCA | BT84: 0 | BU84: 0 | BV84: 0 | BY84: 0 | BZ84: 0 | CA84: 0 | CB84: 0 | CC84: 0 | CD84: 0
A85: NESTOR MARINHO | B85: =_xlfn.XLOOKUP(A:A,'Dados Elevatórias'!D:D,'Dados Elevatórias'!B:B) -> PL-RJB-EAT0825 | C85: =_xlfn.XLOOKUP(B:B,'Dados Elevatórias'!B:B,'Dados Elevatórias'!C:C) -> EAT | D85: BAIXADA 2 | E85: R. Nestor Marinho, 14 - Jardim Nossa Sra. das Gracas, Nova Iguaçu - RJ, 26261-230 | F85: Jardim Alvorada | G85: NOVA IGUAÇU | H85: 26261-230 | I85: =_xlfn.XLOOKUP(B85,COORDENADAS!A:A,COORDENADAS!B:B) -> -22.762 | J85: =_xlfn.XLOOKUP(B85,COORDENADAS!A:A,COORDENADAS!C:C) -> -43.4836 | M85: 1 | N85: OPERACIONAL | O85: 11 (15)CV | P85: 3530rpm | R85: 1332M | S85: NÃO TEM | T85: 220V / 380V / 440V | U85: 36.8 / 21.3 / 18.4 | Y85: RJB-21944 | Z85: W22 Premium | AC85: ABRIGADA | AN85: =_xlfn.XLOOKUP(A:A,'RELAÇÃO ANTIGA'!A:A,'RELAÇÃO ANTIGA'!AC:AC,X) -> 220v | AP85: 0 | AQ85: 0 | AR85: 0 | AS85: 0 | AT85: 0 | AU85: 0 | AV85: 0 | AW85: 0 | AX85: 0 | AY85: 0 | AZ85: 0 | BK85: INVERSOR DE FREQUÊNCIA | BP85: NÃO | BR85: 0 | BS85: 0 | BT85: 0 | BU85: 0 | BV85: 0 | BY85: 0 | BZ85: 0 | CA85: 0 | CB85: 0 | CC85: 0 | CD85: 0
A86: NILÓPOLIS | B86: =_xlfn.XLOOKUP(A:A,'Dados Elevatórias'!D:D,'Dados Elevatórias'!B:B) -> PL-RJB-EAT0113 | C86: =_xlfn.XLOOKUP(B:B,'Dados Elevatórias'!B:B,'Dados Elevatórias'!C:C) -> EAT | D86: BAIXADA 2 | E86: Av. Nazaré, 3076 - Olinda, Nilópolis - RJ, 21645-010 | F86: Olinda | G86: NILÓPOLIS | H86: =_xlfn.XLOOKUP(B:B,'Dados Elevatórias'!B:B,'Dados Elevatórias'!G:G) -> 21645-010 | I86: =_xlfn.XLOOKUP(B86,COORDENADAS!A:A,COORDENADAS!B:B) -> -22.8207 | J86: =_xlfn.XLOOKUP(B86,COORDENADAS!A:A,COORDENADAS!C:C) -> -43.4072 | L86: FORMAL | M86: 1 | N86: OPERACIONAL | O86: 200CV | P86: 1351rpm | Q86: WEG W22 IR3 Premium | S86: RJB-01827 | T86: 440 | U86: 258 | X86: 10 LR 18 A | Y86: RJB-01829 | Z86: Worthington | AA86: 6 | AB86: 420MM | AC86: ABRIGADA | AD86: NÃO | AF86: HORIZONTAL | AH86: HORIZONTAL | AI86: 1080M³/H | AJ86: 26 | AN86: 440V | AP86: 0 | AQ86: 0 | AR86: 0 | AS86: 0 | AT86: 0 | AU86: 0 | AV86: 0 | AW86: 0 | AX86: 0 | AY86: 0 | AZ86: 0 | BK86: INVERSOR DE FREQUÊNCIA | BL86: WEG | BM86: CFW11 | BN86: 370A | BO86: RJA-12938 | BP86: SIM | BR86: 15 MCA | BS86: 0 | BT86: 53.6 MCA | BU86: 1\2 | BV86: 1\2 | BY86: 0 | BZ86: 0 | CA86: 0 | CB86: 0 | CC86: 0 | CD86: 0
A87: NILÓPOLIS | B87: =_xlfn.XLOOKUP(A:A,'Dados Elevatórias'!D:D,'Dados Elevatórias'!B:B) -> PL-RJB-EAT0113 | C87: =_xlfn.XLOOKUP(B:B,'Dados Elevatórias'!B:B,'Dados Elevatórias'!C:C) -> EAT | D87: BAIXADA 2 | E87: Av. Nazaré, 3076 - Olinda, Nilópolis - RJ, 21645-010 | F87: Olinda | G87: NILÓPOLIS | H87: =_xlfn.XLOOKUP(B:B,'Dados Elevatórias'!B:B,'Dados Elevatórias'!G:G) -> 21645-010 | I87: =_xlfn.XLOOKUP(B87,COORDENADAS!A:A,COORDENADAS!B:B) -> -22.8207 | J87: =_xlfn.XLOOKUP(B87,COORDENADAS!A:A,COORDENADAS!C:C) -> -43.4072 | L87: FORMAL | M87: 2 | N87: OPERACIONAL | O87: 200CV | P87: 1351rpm | Q87: WEG W22 IR3 Premium | S87: RJB-04066 | T87: 440 | U87: 258 | X87: 10 LR 18 A | Y87: RJB-01387 | Z87: Worthington | AA87: 6 | AB87: 420MM | AC87: ABRIGADA | AD87: NÃO | AF87: HORIZONTAL | AH87: HORIZONTAL | AI87: 1080M³/H | AJ87: 26 | AN87: 440V | AP87: 0 | AQ87: 0 | AR87: 0 | AS87: 0 | AT87: 0 | AU87: 0 | AV87: 0 | AW87: 0 | AX87: 0 | AY87: 0 | AZ87: 0 | BK87: INVERSOR DE FREQUÊNCIA | BL87: WEG | BM87: CFW11 | BN87: 370A | BO87: RJB-01893 | BP87: SIM | BR87: 15 MCA | BS87: 0 | BT87: 53.6 MCA | BU87: 1\2 | BV87: 1\2 | BY87: 0 | BZ87: 0 | CA87: 0 | CB87: 0 | CC87: 0 | CD87: 0
A88: NILÓPOLIS | B88: =_xlfn.XLOOKUP(A:A,'Dados Elevatórias'!D:D,'Dados Elevatórias'!B:B) -> PL-RJB-EAT0113 | C88: =_xlfn.XLOOKUP(B:B,'Dados Elevatórias'!B:B,'Dados Elevatórias'!C:C) -> EAT | D88: BAIXADA 2 | E88: Av. Nazaré, 3076 - Olinda, Nilópolis - RJ, 21645-010 | F88: Olinda | G88: NILÓPOLIS | H88: =_xlfn.XLOOKUP(B:B,'Dados Elevatórias'!B:B,'Dados Elevatórias'!G:G) -> 21645-010 | I88: =_xlfn.XLOOKUP(B88,COORDENADAS!A:A,COORDENADAS!B:B) -> -22.8207 | J88: =_xlfn.XLOOKUP(B88,COORDENADAS!A:A,COORDENADAS!C:C) -> -43.4072 | L88: FORMAL | M88: 3 | N88: OPERACIONAL | O88: 200CV | P88: 1351rpm | Q88: WEG W22 IR3 Premium | S88: RJB-01391 | T88: 440 | U88: 258 | X88: 10 LR 18 A | Y88: RJB-01879 | Z88: Worthington | AA88: 6 | AB88: 420MM | AC88: ABRIGADA | AD88: NÃO | AF88: HORIZONTAL | AH88: HORIZONTAL | AI88: 1080M³/H | AJ88: 26 | AN88: 440V | AP88: 0 | AQ88: 0 | AR88: 0 | AS88: 0 | AT88: 0 | AU88: 0 | AV88: 0 | AW88: 0 | AX88: 0 | AY88: 0 | AZ88: 0 | BK88: INVERSOR DE FREQUÊNCIA | BL88: POWER ELETRONICS | BM88: Sd75032055 | BN88: 160kW | BO88: RJB-07856 | BP88: SIM | BR88: 15 MCA | BS88: 0 | BT88: 53.6 MCA | BU88: 1\2 | BV88: 1\2 | BY88: 0 | BZ88: 0 | CA88: 0 | CB88: 0 | CC88: 0 | CD88: 0
A89: NILO PECANHA (CEMITERIO) | B89: =_xlfn.XLOOKUP(A:A,'Dados Elevatórias'!D:D,'Dados Elevatórias'!B:B) -> PL-RJB-EAT0024 | C89: =_xlfn.XLOOKUP(B:B,'Dados Elevatórias'!B:B,'Dados Elevatórias'!C:C) -> EAT | D89: BAIXADA 2 | E89: R. Dep. Andrade Figueira, 826 - Cabuís, Nilópolis - RJ, 26545-191 | F89: Cabuís | G89: NILÓPOLIS | H89: =_xlfn.XLOOKUP(B:B,'Dados Elevatórias'!B:B,'Dados Elevatórias'!G:G) -> 26545-191 | I89: =_xlfn.XLOOKUP(B89,COORDENADAS!A:A,COORDENADAS!B:B) -> -22.8104 | J89: =_xlfn.XLOOKUP(B89,COORDENADAS!A:A,COORDENADAS!C:C) -> -43.4044 | M89: 1 | N89: OPERACIONAL | S89: NÃO TEM | Y89: FICTÍCIA | AC89: TUBULÂO | AN89: 220V | AP89: 400375870 | AQ89: 8402966 | AR89: 0 | AS89: AGUA - ELEV - NILO PECANHA | AT89: AV NILO PECANHA SN EF826 | AU89: 100MM | AV89: 150MM | AW89: 0 | AX89: 0 | AY89: 0 | AZ89: 0 | BK89: PARTIDA DIRETA | BP89: NÃO | BR89: 0 | BS89: 0 | BT89: 0 | BU89: 0 | BV89: 0 | BW89: SIM | BY89: EM MARCHA | BZ89: 0 | CA89: 0 | CB89: 0 | CC89: 0 | CD89: Rua Deputado andrade Figueira (trecho Rua Nilo PeCanha A Rua Cândido), Rua Cândida (trecho Rua amadeu Lara a Rua joAo de Castro), Rua Amadeu Lara (trecho de Rua Cândido atE a Rua Nilo PeCanaha), Rua Dulce (trecho Rua Cândido atE a Rua Nilo PeCanha), Rua CapitAo alfredo Antunes (trecho Rua JosE c. GuimarAes), Rua Fernando GonCalves de Almeida (Rua Nilo PeCanha a Rua JosE Couto GuimarAes) e pequenas vilas deste trecho
A90: ODILON BRAGA | B90: =_xlfn.XLOOKUP(A:A,'Dados Elevatórias'!D:D,'Dados Elevatórias'!B:B) -> PL-RJB-EAT0737 | C90: =_xlfn.XLOOKUP(B:B,'Dados Elevatórias'!B:B,'Dados Elevatórias'!C:C) -> EAT | D90: BAIXADA 2 | E90: R. Odilon Braga, 119 - Queimados, RJ, 26310-190 | F90: Centro | G90: QUEIMADOS | H90: =_xlfn.XLOOKUP(B:B,'Dados Elevatórias'!B:B,'Dados Elevatórias'!G:G) -> 26310-190 | I90: =_xlfn.XLOOKUP(B90,COORDENADAS!A:A,COORDENADAS!B:B) -> -22.7157 | J90: =_xlfn.XLOOKUP(B90,COORDENADAS!A:A,COORDENADAS!C:C) -> -43.5602 | L90: =_xlfn.XLOOKUP(A:A,'RELAÇÃO ANTIGA'!A:A,'RELAÇÃO ANTIGA'!J:J) -> INFORMAL | M90: 1 | N90: OPERACIONAL | O90: 20CV | P90: 3540rpm | Q90: WEG | S90: RJB-03134 | T90: 220 / 380 / 440 | U90: 50.3 / 29.1 / 25.2 | AA90: 2 | AC90: CASINHA | AF90: HORIZONTAL | AH90: HORIZONTAL | AN90: =_xlfn.XLOOKUP(A:A,'RELAÇÃO ANTIGA'!A:A,'RELAÇÃO ANTIGA'!AC:AC,X) -> 220V | AP90: 0 | AQ90: 0 | AR90: 0 | AS90: 0 | AT90: 0 | AU90: 2POL | AV90: 2POL | AW90: 0 | AX90: 0 | AY90: 0 | AZ90: 0 | BK90: INVERSOR DE FREQUÊNCIA | BP90: NÃO | BR90: 0 | BS90: 0 | BT90: 0 | BU90: 0 | BV90: 0 | BW90: SIM | BY90: EM MARCHA | BZ90: 0 | CA90: 0 | CB90: 0 | CC90: 0 | CD90: 0
A91: NOÊMIA VIEIRA | B91: =_xlfn.XLOOKUP(A:A,'Dados Elevatórias'!D:D,'Dados Elevatórias'!B:B) -> PL-RJB-EAT0124 | C91: =_xlfn.XLOOKUP(B:B,'Dados Elevatórias'!B:B,'Dados Elevatórias'!C:C) -> EAT | D91: BAIXADA 2 | E91: Av. Abílio Augusto Távora, 3715 - Jardim Alvorada, Nova Iguaçu - RJ, 26265-090 | F91: Jardim Alvorada | G91: NOVA IGUAÇU | H91: =_xlfn.XLOOKUP(B:B,'Dados Elevatórias'!B:B,'Dados Elevatórias'!G:G) -> 26265-090 | I91: =_xlfn.XLOOKUP(B91,COORDENADAS!A:A,COORDENADAS!B:B) -> -22.7627 | J91: =_xlfn.XLOOKUP(B91,COORDENADAS!A:A,COORDENADAS!C:C) -> -43.4862 | M91: 1 | N91: OPERACIONAL | O91: 22 (30)CV | P91: 3555rpm | Q91: WEG | R91: 180M | S91: RJB-21997 | T91: 220V / 380V / 440V | Y91: RJB-23829 | AA91: 2 | AC91: TUBULÂO | AN91: 220V | AP91: 413341469 | AQ91: 7596746 | AR91: 0 | AS91: AGUA - BOOSTER - NOEMIA VIEIRA | AT91: R DONA NOEMIA VIEIRA SN FT171 | AU91: 100MM | AV91: 100MM | AW91: 0 | AX91: 0 | AY91: 0 | AZ91: 0 | BK91: SOFT STARTER | BP91: SIM | BR91: 0 | BS91: 0 | BT91: 0 | BU91: 0 | BV91: 0 | BW91: SIM | BY91: EM MARCHA | BZ91: 0 | CA91: 0 | CB91: 0 | CC91: 0 | CD91: Rua GerOncio Pimenta - Rua JosE Augusto - Rua Maria GonCalves dos Anjos - Rua Ministro Afrânio Costa - Rua NoEmia Vieira
A92: OLIVIA MARIA MACHADO | B92: =_xlfn.XLOOKUP(A:A,'Dados Elevatórias'!D:D,'Dados Elevatórias'!B:B) -> PL-RJB-EAT0735 | C92: =_xlfn.XLOOKUP(B:B,'Dados Elevatórias'!B:B,'Dados Elevatórias'!C:C) -> EAT | D92: BAIXADA 2 | E92: R. Olívia Maria Machado, 145 - Vila Santa Catarina, Queimados - RJ, 26323-400 | F92: Vila Santa Catarina | G92: QUEIMADOS | H92: =_xlfn.XLOOKUP(B:B,'Dados Elevatórias'!B:B,'Dados Elevatórias'!G:G) -> 26323-400 | I92: =_xlfn.XLOOKUP(B92,COORDENADAS!A:A,COORDENADAS!B:B) -> -22.7237 | J92: =_xlfn.XLOOKUP(B92,COORDENADAS!A:A,COORDENADAS!C:C) -> -43.5571 | L92: =_xlfn.XLOOKUP(A:A,'RELAÇÃO ANTIGA'!A:A,'RELAÇÃO ANTIGA'!J:J) -> FORMAL | M92: 1 | N92: OPERACIONAL | O92: 15CV | P92: 3520rpm | Q92: WEG | R92: 132M | S92: RJA-00323 | Y92: RJB-07285 | AC92: CASINHA | AN92: =_xlfn.XLOOKUP(A:A,'RELAÇÃO ANTIGA'!A:A,'RELAÇÃO ANTIGA'!AC:AC,X) -> 220V | AP92: 430097071 | AQ92: 8576702 | AR92: 0 | AS92: AGUA - ELEV - OLIVIA MACHADO | AT92: R OLIVIA MARIA MACHADO 1SN FT9 | AU92: 2POL | AV92: 2POL | AW92: 0 | AX92: 0 | AY92: 0 | AZ92: 0 | BK92: PARTIDA DIRETA | BP92: NÃO | BR92: 0 | BS92: 0 | BT92: 0 | BU92: 0 | BV92: 0 | BY92: EM MARCHA | BZ92: 0 | CA92: 0 | CB92: 0 | CC92: 0 | CD92: 0
A93: PADRE VIEIRA | B93: =_xlfn.XLOOKUP(A:A,'Dados Elevatórias'!D:D,'Dados Elevatórias'!B:B) -> PL-RJB-EAT0022 | C93: =_xlfn.XLOOKUP(B:B,'Dados Elevatórias'!B:B,'Dados Elevatórias'!C:C) -> EAT | D93: BAIXADA 2 | E93: Rua Nair Dias, 657 - Vila São Luís, Nova Iguaçu - RJ, 26012-451 | F93: Vila São Luís | G93: NOVA IGUAÇU | H93: =_xlfn.XLOOKUP(B:B,'Dados Elevatórias'!B:B,'Dados Elevatórias'!G:G) -> 26012-451 | I93: =_xlfn.XLOOKUP(B93,COORDENADAS!A:A,COORDENADAS!B:B) -> -22.7386 | J93: =_xlfn.XLOOKUP(B93,COORDENADAS!A:A,COORDENADAS!C:C) -> -43.4343 | L93: =_xlfn.XLOOKUP(A:A,'RELAÇÃO ANTIGA'!A:A,'RELAÇÃO ANTIGA'!J:J) -> FORMAL | M93: 1 | N93: OPERACIONAL | O93: 6CV | P93: 3450rpm | Q93: VANBRO | R93: 500/003/X | S93: RJB-23689 | T93: 220V / 380V | U93: 13.8 / 8.0 A | X93: VBSP67.1781 T | Y93: RJB-30626 | Z93: VANBRO | AA93: 2 | AC93: SUBMERSA | AI93: 27m³/h | AN93: =_xlfn.XLOOKUP(A:A,'RELAÇÃO ANTIGA'!A:A,'RELAÇÃO ANTIGA'!AC:AC,X) -> 220V | AP93: 430054507 | AQ93: 9464391 | AR93: 0 | AS93: 0 | AT93: 0 | AU93: 75MM | AV93: 100MM | AW93: 0 | AX93: 0 | AY93: 0 | AZ93: 0 | BK93: SOFT STARTER | BL93: WEG | BM93: SSW07 | BP93: SIM | BR93: 0 | BS93: 0 | BT93: 0 | BU93: 0 | BV93: 0 | BW93: SIM | BY93: EM MARCHA | BZ93: 0 | CA93: 0 | CB93: 0 | CC93: VILA OPERARIA | CD93: 0
A94: PAIOL | B94: =_xlfn.XLOOKUP(A:A,'Dados Elevatórias'!D:D,'Dados Elevatórias'!B:B) -> PL-RJB-EAT0050 | C94: =_xlfn.XLOOKUP(B:B,'Dados Elevatórias'!B:B,'Dados Elevatórias'!C:C) -> EAT | D94: BAIXADA 2 | E94: Rua Gen. Olímpio da Fonseca, 917 - Paiol de Pólvora, Nilópolis - RJ, 26545-470 | F94: Paiol de Pólvora | G94: NILÓPOLIS | H94: =_xlfn.XLOOKUP(B:B,'Dados Elevatórias'!B:B,'Dados Elevatórias'!G:G) -> 26545-470 | I94: =_xlfn.XLOOKUP(B94,COORDENADAS!A:A,COORDENADAS!B:B) -> -22.8152 | J94: =_xlfn.XLOOKUP(B94,COORDENADAS!A:A,COORDENADAS!C:C) -> -43.3967 | L94: =_xlfn.XLOOKUP(A:A,'RELAÇÃO ANTIGA'!A:A,'RELAÇÃO ANTIGA'!J:J) -> INFORMAL | M94: 1 | N94: OPERACIONAL | O94: 10cv | P94: 3450rpm | AC94: SUBMERSA | AN94: =_xlfn.XLOOKUP(A:A,'RELAÇÃO ANTIGA'!A:A,'RELAÇÃO ANTIGA'!AC:AC,X) -> 220V | AP94: 414658235 | AQ94: 5411350 | AR94: 0 | AS94: AGUA - ELEV - JOAO DIAS DE LIMA | AT94: R JOAO DIEZ LIMA SN EF13 | AU94: 100MM | AV94: 100MM | AW94: 0 | AX94: 0 | AY94: 0 | AZ94: 0 | BK94: SOFT STARTER | BP94: SIM | BR94: 0 | BS94: 0 | BT94: 0 | BU94: 0 | BV94: 0 | BW94: SIM | BY94: EM MARCHA | BZ94: 0 | CA94: 0 | CB94: 0 | CC94: PAIOL | CD94: Rua JoAo Diaz de Lima (Trecho Rua OlImpio da Fonseca A Rua JosE Couto GuimarAes), Rua Carlos de Souza Fernandes (Trecho Rua Cap. Alfredo Antunes A Rua Cap. Antunes Vasconcelos), Rua Maria Paris (Trecho Rua JosE Couto GuimarAes ao Final da Rua), Travessa Maria Paris, Rua JoAo Alves, Rua JoAo Alves, Rua Humberto Perlingeiro, Rua Ravelo, Rua Leonor Roque, Rua EugEnio Santana, Rua AntOnio M. da Costa, Rua Acacia Torres e pequenas Vilas desse trechos.
A95: PALHADA | B95: =_xlfn.XLOOKUP(A:A,'Dados Elevatórias'!D:D,'Dados Elevatórias'!B:B) -> PL-RJB-EAT0044 | C95: =_xlfn.XLOOKUP(B:B,'Dados Elevatórias'!B:B,'Dados Elevatórias'!C:C) -> EAT | D95: BAIXADA 2 | E95: Estr. da Palhada, 2337 - Valverde, Nova Iguaçu - RJ, 26290-006 | F95: Valverde | G95: NOVA IGUAÇU | H95: =_xlfn.XLOOKUP(B:B,'Dados Elevatórias'!B:B,'Dados Elevatórias'!G:G) -> 26290-006 | I95: =_xlfn.XLOOKUP(B95,COORDENADAS!A:A,COORDENADAS!B:B) -> -22.7528 | J95: =_xlfn.XLOOKUP(B95,COORDENADAS!A:A,COORDENADAS!C:C) -> -43.5189 | L95: =_xlfn.XLOOKUP(A:A,'RELAÇÃO ANTIGA'!A:A,'RELAÇÃO ANTIGA'!J:J) -> FORMAL | M95: 1 | N95: OPERACIONAL | O95: 15CV | P95: 3500rpm | Q95: WEG | R95: 132S | S95: RJB-18179 | T95: 220V / 380V / 440V | U95: 36,8 A | Y95: FICTÍCIA | AC95: TUBULÂO | AD95: SIM | AG95: C-200 | AN95: =_xlfn.XLOOKUP(A:A,'RELAÇÃO ANTIGA'!A:A,'RELAÇÃO ANTIGA'!AC:AC,X) -> 220V | AP95: 412957699 | AQ95: 5516825 | AR95: 0 | AS95: AGUA - BOOSTER - PALHADA | AT95: EST GOVR LEONEL BRIZOLA 2338 FT | AU95: 100MM | AV95: 100MM | AW95: 0 | AX95: 0 | AY95: 0 | AZ95: 0 | BK95: INVERSOR DE FREQUÊNCIA | BP95: NÃO | BR95: 0 | BS95: 0 | BT95: 0 | BU95: 0 | BV95: 0 | BW95: SIM | BY95: EM MARCHA | BZ95: 0 | CA95: 0 | CB95: 0 | CC95: 0 | CD95: Rua Ana Paula - Rua Eliane Azevedo - Rua LUcia - Rua Maria Paula - Rua Mario Roberto - Rua Rafael Luiz
A96: PARQUE MARAVILHA | B96: =_xlfn.XLOOKUP(A:A,'Dados Elevatórias'!D:D,'Dados Elevatórias'!B:B) -> PL-RJB-EAT0733 | C96: =_xlfn.XLOOKUP(B:B,'Dados Elevatórias'!B:B,'Dados Elevatórias'!C:C) -> EAT | D96: BAIXADA 2 | E96: Estrada da Gama, 815 - Oliveira - Nova Iguaçu | F96: Oliveira | G96: NOVA IGUAÇU | H96: =_xlfn.XLOOKUP(B:B,'Dados Elevatórias'!B:B,'Dados Elevatórias'!G:G) -> 0 | I96: =_xlfn.XLOOKUP(B96,COORDENADAS!A:A,COORDENADAS!B:B) -> -22.7338 | J96: =_xlfn.XLOOKUP(B96,COORDENADAS!A:A,COORDENADAS!C:C) -> -43.4664 | L96: =_xlfn.XLOOKUP(A:A,'RELAÇÃO ANTIGA'!A:A,'RELAÇÃO ANTIGA'!J:J) -> INFORMAL | M96: 1 | N96: OPERACIONAL | O96: 5CV | P96: 1750 RPM | Q96: WEG | S96: NÃO TEM | T96: 220V / 380V | Y96: FICTÍCIA | Z96: FLOWSERV | AB96: 7.10 | AC96: TUBULÂO | AD96: SIM | AI96: 170m³/h | AJ96: 43mca | AN96: =_xlfn.XLOOKUP(A:A,'RELAÇÃO ANTIGA'!A:A,'RELAÇÃO ANTIGA'!AC:AC,X) -> 220V | AP96: 420398927 | AQ96: 8585236 | AR96: 0 | AS96: AGUA - BOOSTER - PARQUE MARAVILHA | AT96: EST GAMA SN EF813 | AU96: 0 | AV96: 0 | AW96: 0 | AX96: 0 | AY96: 0 | AZ96: 0 | BK96: PARTIDA DIRETA | BP96: NÃO | BR96: 0 | BS96: 0 | BT96: 0 | BU96: 0 | BV96: 0 | BW96: SIM | BY96: EM MARCHA | BZ96: 0 | CA96: 0 | CB96: 0 | CC96: 0 | CD96: 0
A97: PASTOR ANTONIO MARTINS | B97: =_xlfn.XLOOKUP(A:A,'Dados Elevatórias'!D:D,'Dados Elevatórias'!B:B) -> PL-RJB-EAT0823 | C97: =_xlfn.XLOOKUP(B:B,'Dados Elevatórias'!B:B,'Dados Elevatórias'!C:C) -> EAT | D97: BAIXADA 2 | E97: R. Rui Chagas, 07 - q 17 loja 01 sala 04 - Flesmam, Queimados - RJ, 26383-320 | F97: Flesmam | G97: QUEIMADOS | H97: =_xlfn.XLOOKUP(B:B,'Dados Elevatórias'!B:B,'Dados Elevatórias'!G:G) -> 26383-320 | I97: =_xlfn.XLOOKUP(B97,COORDENADAS!A:A,COORDENADAS!B:B) -> -22.7124 | J97: =_xlfn.XLOOKUP(B97,COORDENADAS!A:A,COORDENADAS!C:C) -> -43.5478 | M97: 1 | N97: OPERACIONAL | O97: 40CV | P97: 3565 RPM | Q97: WEG | R97: 200M | S97: RJB-21937 | T97: 220V / 380V / 440V | U97: 101/58.7/50.7 AMP | V97: 6312-ZZ-C3 | W97: 6312-ZZ-C3 | X97: W22 PREMIUM | Y97: RJB-21938 | Z97: KSB MEGABLOC 100-65-160GG | AA97: 1.9 | AB97: 172MM | AC97: ABRIGADA | AH97: CONVENSIONAL | AI97: 170M³/H | AJ97: 43MCA | AN97: =_xlfn.XLOOKUP('RELAÇÃO DE ELEVATÓRIAS'!A:A,'RELAÇÃO ANTIGA'!A:A,'RELAÇÃO ANTIGA'!AC:AC) -> 220v | AP97: 0 | AQ97: 0 | AR97: 0 | AS97: 0 | AT97: 0 | AU97: 0 | AV97: 0 | AW97: 0 | AX97: 0 | AY97: 0 | AZ97: 0 | BK97: INVERSOR DE FREQUÊNCIA | BL97: DANFOSS | BM97: VLT 102 | BN97: 104A | BP97: SIM | BR97: 1 MCA | BS97: <1 MCA | BT97: 0 | BU97: 0 | BV97: 0 | BY97: 0 | BZ97: 0 | CA97: 0 | CB97: 0 | CC97: 0 | CD97: 0
A98: PRAÇA DA BÍBLIA | B98: =_xlfn.XLOOKUP(A:A,'Dados Elevatórias'!D:D,'Dados Elevatórias'!B:B) -> PL-RJB-EAT0692 | C98: =_xlfn.XLOOKUP(B:B,'Dados Elevatórias'!B:B,'Dados Elevatórias'!C:C) -> EAT | D98: BAIXADA 2 | E98: R. Olímpia Silva, 16 - Centro, Queimados - RJ, 26327-380 | F98: Pacaembu | G98: QUEIMADOS | H98: =_xlfn.XLOOKUP(B:B,'Dados Elevatórias'!B:B,'Dados Elevatórias'!G:G) -> 26330-260 | I98: =_xlfn.XLOOKUP(B98,COORDENADAS!A:A,COORDENADAS!B:B) -> -22.718 | J98: =_xlfn.XLOOKUP(B98,COORDENADAS!A:A,COORDENADAS!C:C) -> -43.5471 | L98: INFORMAL | M98: 1 | N98: OPERACIONAL | O98: 12.5cv | P98: 3515rpm | Q98: WEG | R98: 132m | S98: RJB-03133 | T98: 220V / 380V / 440V | U98: 30.0 / 17.4 / 15 | X98: BC-21 | Y98: RJB-03119 | Z98: SCHNEIDER | AA98: 2 | AC98: CASINHA | AD98: NÃO | AF98: HORIZONTAL | AH98: CONVENSIONAL | AN98: 220V | AP98: 0 | AQ98: 0 | AR98: 0 | AS98: 0 | AT98: 0 | AU98: 2POL | AV98: 2POL | AW98: 0 | AX98: 0 | AY98: 0 | AZ98: 0 | BJ98: RJB-22567 | BK98: INVERSOR DE FREQUÊNCIA | BL98: DANFOSS | BM98: VLT | BO98: RJB-20226 | BP98: NÃO | BR98: 0 | BS98: 0 | BT98: 0 | BU98: 0 | BV98: 0 | BW98: SIM | BY98: EM MARCHA | BZ98: 0 | CA98: 0 | CB98: 0 | CC98: 0 | CD98: 0
A99: QUEIMADOS | B99: =_xlfn.XLOOKUP(A:A,'Dados Elevatórias'!D:D,'Dados Elevatórias'!B:B) -> PL-RJB-EAT0697 | C99: =_xlfn.XLOOKUP(B:B,'Dados Elevatórias'!B:B,'Dados Elevatórias'!C:C) -> EAT | D99: BAIXADA 2 | E99: Estr. Carlos Sampaio, 176 - São Simao, Queimados - RJ, 26327-410 | F99: São Simao | G99: QUEIMADOS | H99: =_xlfn.XLOOKUP(B:B,'Dados Elevatórias'!B:B,'Dados Elevatórias'!G:G) -> 26327-410 | I99: =_xlfn.XLOOKUP(B99,COORDENADAS!A:A,COORDENADAS!B:B) -> -22.7115 | J99: =_xlfn.XLOOKUP(B99,COORDENADAS!A:A,COORDENADAS!C:C) -> -43.554 | L99: =_xlfn.XLOOKUP(A:A,'RELAÇÃO ANTIGA'!A:A,'RELAÇÃO ANTIGA'!J:J) -> INFORMAL | M99: 1 | N99: OPERACIONAL | O99: 20cv | P99: 3540rpm | Q99: Weg | R99: 112M | S99: RJB-21476 | T99: 220/380/440V | U99: 19.4 / 11.3 / 9.72 | X99: MONOBLOCO | Y99: RJB-07160 | AA99: 2 | AB99: 112M | AC99: ABRIGADA | AN99: =_xlfn.XLOOKUP(A:A,'RELAÇÃO ANTIGA'!A:A,'RELAÇÃO ANTIGA'!AC:AC,X) -> 220V | AP99: 420227639 | AQ99: 6381594 | AR99: 0 | AS99: extraIdo no consumo custo ano base 2015. Cadastrado como Agua - ReservatOrio - Morro da Caixa D Agua (GRB) | AT99: 0 | AU99: 2POL | AV99: 2POL | AW99: 0 | AX99: 0 | AY99: 0 | AZ99: 0 | BK99: INVERSOR DE FREQUÊNCIA | BP99: SIM | BR99: 1 MCA | BS99: < 1 MCA | BT99: 0 | BU99: 0 | BV99: 0 | BW99: SIM | BY99: EM MARCHA | BZ99: 0 | CA99: 0 | CB99: 0 | CC99: SAO SIMAO | CD99: 0
A100: QUISSUCO | B100: =_xlfn.XLOOKUP(A:A,'Dados Elevatórias'!D:D,'Dados Elevatórias'!B:B) -> PL-RJB-EAT0102 | C100: =_xlfn.XLOOKUP(B:B,'Dados Elevatórias'!B:B,'Dados Elevatórias'!C:C) -> EAT | D100: BAIXADA 2 | E100: Estr. Padre José Anchieta, 76 - Laranjal Santo Antonio | F100: Laranjal | G100: QUEIMADOS | H100: =_xlfn.XLOOKUP(B:B,'Dados Elevatórias'!B:B,'Dados Elevatórias'!G:G) -> 0 | I100: =_xlfn.XLOOKUP(B100,COORDENADAS!A:A,COORDENADAS!B:B) -> -22.6932 | J100: =_xlfn.XLOOKUP(B100,COORDENADAS!A:A,COORDENADAS!C:C) -> -43.5581 | L100: =_xlfn.XLOOKUP(A:A,'RELAÇÃO ANTIGA'!A:A,'RELAÇÃO ANTIGA'!J:J) -> INFORMAL | M100: 1 | N100: OPERACIONAL | O100: 7.5 | P100: 3535RPM | Q100: WEG | R100: 112M | S100: RJB-20209 | T100: 220V / 380V / 440V | U100: 18.8 / 10.9 / 9.38 | V100: 6307-ZZ | W100: 6206-ZZ | Y100: RJB-23833 | AC100: TUBULÂO | AD100: SIM | AN100: =_xlfn.XLOOKUP(A:A,'RELAÇÃO ANTIGA'!A:A,'RELAÇÃO ANTIGA'!AC:AC,X) -> 220V | AP100: 420395552 | AQ100: 6748339 | AR100: 0 | AS100: AGUA - BOOSTER - QUISSUCO | AT100: R ITAPERAVA SN EF712 | AU100: 100MM | AV100: 100MM | AW100: 0 | AX100: 0 | AY100: 0 | AZ100: 0 | BK100: INVERSOR DE FREQUÊNCIA | BP100: NÃO | BR100: 1 MCA | BS100: < 1 MCA | BT100: 0 | BU100: 0 | BV100: 0 | BW100: SIM | BY100: EM MARCHA | BZ100: 0 | CA100: 0 | CB100: 0 | CC100: QUISSUCO | CD100: 0
...

Sheet Planilha1
A2: SÃO SIMÃO | B2: Cadastrar
A3: Praça do Cabuçu | B3: Cadastrar
A4: Paulo Miranda | B4: Cadastrar
A5: CAIXA VELHA | B5: PL-RJB-EAT0011 | C5: =B5&" - "&A5 -> PL-RJB-EAT0011 - CAIXA VELHA
A6: SANTO ANTÔNIO | B6: PL-RJB-EAT0014 | C6: =B6&" - "&A6 -> PL-RJB-EAT0014 - SANTO ANTÔNIO
A7: ROLDAO GONCALVES | B7: PL-RJB-EAT0017 | C7: =B7&" - "&A7 -> PL-RJB-EAT0017 - ROLDAO GONCALVES
A8: PADRE VIEIRA | B8: PL-RJB-EAT0022 | C8: =B8&" - "&A8 -> PL-RJB-EAT0022 - PADRE VIEIRA
A9: NILO PECANHA (CEMITERIO) | B9: PL-RJB-EAT0024 | C9: =B9&" - "&A9 -> PL-RJB-EAT0024 - NILO PECANHA (CEMITERIO)
A10: MENA BARRETO | B10: PL-RJB-EAT0030 | C10: =B10&" - "&A10 -> PL-RJB-EAT0030 - MENA BARRETO
A11: MELVIN JONES | B11: PL-RJB-EAT0031 | C11: =B11&" - "&A11 -> PL-RJB-EAT0031 - MELVIN JONES
A12: MAURICIA BORGES | B12: PL-RJB-EAT0032 | C12: =B12&" - "&A12 -> PL-RJB-EAT0032 - MAURICIA BORGES
A13: MORRO DA MOENDA | B13: PL-RJB-EAT0039 | C13: =B13&" - "&A13 -> PL-RJB-EAT0039 - MORRO DA MOENDA
A14: MANOEL REIS | B14: PL-RJB-EAT0040 | C14: =B14&" - "&A14 -> PL-RJB-EAT0040 - MANOEL REIS
A15: BOOSTER POSSE | B15: PL-RJB-EAT0042 | C15: =B15&" - "&A15 -> PL-RJB-EAT0042 - BOOSTER POSSE
A16: LUCIO TAVARES | B16: PL-RJB-EAT0043 | C16: =B16&" - "&A16 -> PL-RJB-EAT0043 - LUCIO TAVARES
... A122: RESERVATÓRIO CABUÇU ALTO | B122: PL-RJB-RES0113 | C122: =B122&" - "&A122 -> PL-RJB-RES0113 - RESERVATÓRIO CABUÇU ALTO
A123: AMBAÍ
A124: MORRO DA PAZ
A125: COLOMBO
A126: DONA AFRA
A127: CARLOS MONSANTE
A128: BEIRA RIO
A129: NÉLIO CHAMBARELLI
A130: MESSIAS
A131: CHACRINHA
A132: NOVA CIDADE
A133: BOA ESPERANÇA
A134: TINGUAZINHO
... A142: BNH 2

Sheet RELAÇÃO BOOSTERS
A1: ELEVATÓRIA | B1: PLANTA | C1: GRUPO | D1: INFLUÊNCIA | E1: VAZÃO APROXIMADA (m³/h) | F1: AMT (MCA) | G1: PRESSÃO DE SUCÇÃO | H1: PRESSÃO DE RECALQUE | I1: DIÂMETRO DA TUBULAÇÃO | J1: TAG DO MOTOR | K1: POTÊNCIA DO MOTOR (CV) | L1: RPM | M1: CARCAÇA DO MOTOR | N1: MANCAIS (LA / LOA) | O1: PONTA DO EIXO | P1: TAG DA BOMBA | Q1: MODELO DA BOMBA | R1: MARCA DA BOMBA | S1: Ø ROTOR | T1: FORMA CONSTRUTIVA DA BOMBA | U1: BOMBA DRENO (Sim/Não) | V1: TENSÃO (V) | W1: CORRENTE (A) | X1: TIPO DE ACIONAMENTO | Y1: FABRICANTE DO ACIONAMENTO | Z1: MODELO ACIONAMENTO
A2: BOOSTER AUSTIN | B2: =_xlfn.XLOOKUP(A:A,'Dados Elevatórias'!D:D,'Dados Elevatórias'!B:B) -> PL-RJB-EAT0695 | C2: 1 | K2: 400cv | L2: 1190rpm
A3: BOOSTER AUSTIN | B3: =_xlfn.XLOOKUP(A:A,'Dados Elevatórias'!D:D,'Dados Elevatórias'!B:B) -> PL-RJB-EAT0695 | C3: 2 | K3: 400cv | L3: 1190rpm
A4: BOOSTER AUSTIN | B4: =_xlfn.XLOOKUP(A:A,'Dados Elevatórias'!D:D,'Dados Elevatórias'!B:B) -> PL-RJB-EAT0695 | C4: 3 | K4: 400cv | L4: 1190rpm
A5: BOOSTER BRASÍLIA | B5: =_xlfn.XLOOKUP(A:A,'Dados Elevatórias'!D:D,'Dados Elevatórias'!B:B) -> PL-RJB-EAT1005 | C5: 1 | K5: 100cv | L5: 1783 rpm
A6: BOOSTER BRASÍLIA | B6: =_xlfn.XLOOKUP(A:A,'Dados Elevatórias'!D:D,'Dados Elevatórias'!B:B) -> PL-RJB-EAT1005 | C6: 2 | K6: 100cv | L6: 1783 rpm
A7: BOOSTER BRASÍLIA | B7: =_xlfn.XLOOKUP(A:A,'Dados Elevatórias'!D:D,'Dados Elevatórias'!B:B) -> PL-RJB-EAT1005 | C7: 3 | K7: 100cv | L7: 1783 rpm
A8: BOOSTER CABUÇU ALTO | B8: =_xlfn.XLOOKUP(A:A,'Dados Elevatórias'!D:D,'Dados Elevatórias'!B:B) -> PL-RJB-EAT0689 | C8: 1 | K8: 50CV | L8: 1770rpm
A9: BOOSTER CABUÇU ALTO | B9: =_xlfn.XLOOKUP(A:A,'Dados Elevatórias'!D:D,'Dados Elevatórias'!B:B) -> PL-RJB-EAT0689 | C9: 2 | K9: 50CV | L9: 1770rpm
A10: BOOSTER CABUÇU ALTO | B10: =_xlfn.XLOOKUP(A:A,'Dados Elevatórias'!D:D,'Dados Elevatórias'!B:B) -> PL-RJB-EAT0689 | C10: 3 | K10: 50CV | L10: 1770rpm
A11: BOOSTER ENGENHEIRO PEDREIRA | B11: =_xlfn.XLOOKUP(A:A,'Dados Elevatórias'!D:D,'Dados Elevatórias'!B:B) -> PL-RJB-EAT0122 | C11: 1 | K11: 200cv | L11: 1790rpm
A12: BOOSTER ENGENHEIRO PEDREIRA | B12: =_xlfn.XLOOKUP(A:A,'Dados Elevatórias'!D:D,'Dados Elevatórias'!B:B) -> PL-RJB-EAT0122 | C12: 2 | K12: 200cv | L12: 1790rpm
A13: BOOSTER JK | B13: =_xlfn.XLOOKUP(A:A,'Dados Elevatórias'!D:D,'Dados Elevatórias'!B:B) -> PL-RJB-EAT0746 | C13: 1 | K13: 450CV | L13: 1793rpm | P13: RJB-07474
A14: BOOSTER JK | B14: =_xlfn.XLOOKUP(A:A,'Dados Elevatórias'!D:D,'Dados Elevatórias'!B:B) -> PL-RJB-EAT0746 | C14: 2 | K14: 450CV | L14: 1793rpm
A15: BOOSTER JK | B15: =_xlfn.XLOOKUP(A:A,'Dados Elevatórias'!D:D,'Dados Elevatórias'!B:B) -> PL-RJB-EAT0746 | C15: 3 | K15: 250CV | L15: 1790rpm
A16: BOOSTER JK | B16: =_xlfn.XLOOKUP(A:A,'Dados Elevatórias'!D:D,'Dados Elevatórias'!B:B) -> PL-RJB-EAT0746 | C16: 4 | K16: 250CV | L16: 1793 a 1850 rpm
A17: BOOSTER POSSE | B17: =_xlfn.XLOOKUP(A:A,'Dados Elevatórias'!D:D,'Dados Elevatórias'!B:B) -> PL-RJB-EAT0042 | C17: 1 | K17: 175cv | L17: 1791rpm
A18: BOOSTER POSSE | B18: =_xlfn.XLOOKUP(A:A,'Dados Elevatórias'!D:D,'Dados Elevatórias'!B:B) -> PL-RJB-EAT0042 | C18: 2 | K18: 175cv | L18: 1791rpm
A19: BOOSTER POSSE | B19: =_xlfn.XLOOKUP(A:A,'Dados Elevatórias'!D:D,'Dados Elevatórias'!B:B) -> PL-RJB-EAT0042 | C19: 3 | K19: 175cv | L19: 1791rpm
A20: BOOSTER POSSE | B20: =_xlfn.XLOOKUP(A:A,'Dados Elevatórias'!D:D,'Dados Elevatórias'!B:B) -> PL-RJB-EAT0042 | C20: 4 | K20: 175cv | L20: 1791rpm
A21: MESQUITA G1 | B21: =_xlfn.XLOOKUP(A:A,'Dados Elevatórias'!D:D,'Dados Elevatórias'!B:B) -> PL-RJB-EAT0086 | C21: 1 | K21: 100cv | L21: 3510rpm
A22: MESQUITA G1 | B22: =_xlfn.XLOOKUP(A:A,'Dados Elevatórias'!D:D,'Dados Elevatórias'!B:B) -> PL-RJB-EAT0086 | C22: 2 | K22: 100CV | L22: 3560rpm

Sheet INFORMATIVO
C4: TABELAS
C5: CARACTERÍSTICAS DA ÁREA | D5: FORMAL | E5: INFORMAL | F5: NOVA
C6: TIPO DE ACIONAMENTO | D6: SOFT STARTER | E6: INVERSOR DE FREQUÊNCIA | F6: PARTIDA DIRETA | G6: ENT. TRIANGULO
C7: SIM OU NÃO | D7: SIM | E7: NÃO
C8: Ponta de eixo | D8: CONVENSIONAL | E8: JET PUMP | F8: JM | G8: JP | H8: ESP
C9: Tipo construtivo Elev. | D9: CONTAINER | E9: SUBMERSA | F9: TUBULÂO | G9: ABRIGADA | H9: CASINHA | I9: ANFÍBIA
C10: FLANGE | D10: CONVENSIONAL | E10: FC | F10: FF
C11: FORMA CONSTRUTIVA DA BOMBA | D11: CONVENSIONAL | E11: INLINE | F11: HORIZONTAL | G11: DELTA | H11: SUBMERSA | I11: SUBMERSIVEL | J11: AUTOESCORVANTE | K11: ANFÍBIA
C12: TIPO DE MONTAGEM MOTOR | D12: ANFÍBIA | E12: HORIZONTAL | F12: VERTICAL | G12: SUBMERSA VERTICAL
C13: FABRICANTE ACIONAMENTO | D13: DANFOSS | E13: ABB | F13: WEG | G13: POWER ELETRONICS | H13: SCHNEIDER | I13: SIEMENS
C14: TENSÃO | D14: 220V | E14: 380V | F14: 440V | G14: 380V / 440V | H14: 220V / 380V | I14: 220V / 440V | J14: 220V / 380V / 440V | K14: 440V / 760v

Sheet INDICADORES
A1: =COUNTIFS('RELAÇÃO DE ELEVATÓRIAS'!M:M, "2") -> 12 | B1: =COUNTIFS('RELAÇÃO DE ELEVATÓRIAS'!M:M, "3") -> 6 | C1: =COUNTIFS('RELAÇÃO DE ELEVATÓRIAS'!M:M, "4") -> 2 | D1: =COUNTIFS('RELAÇÃO DE ELEVATÓRIAS'!M:M, "5") -> 0 | E1: =SUM(A1:D1) -> 20
F9: Total de Elevatórias | G9: Elevatórias Novas | H9: Elevatórias de esgoto | I9: Com CLT | J9: Sem CLP
F10: =COUNTA('RELAÇÃO DE ELEVATÓRIAS'!A3:A191)-E1 -> 140 | G10: =COUNTA('NOVAS ELEVATÓRIAS'!D2:D87) -> 29 | H10: 10 | I10: 54 | J10: =COUNTIF('RELAÇÃO DE ELEVATÓRIAS'!BP:BP,"NÃO") -> 52

Sheet RELAÇÃO ANTIGA
A1: ELEVATORIAS | B1: PLANTA | C1: TIPO | D1: SUPERITENDENCIA | E1: ENDEREÇO | F1: BAIRRO | H1: MUNICIPIO | I1: CEP | J1: CARACTERÍSTICAS DA ÁREA | K1: GRUPO | L1: FUNÇÃO | M1: DADOS DO EQUIPAMENTO INSTALADO | AC1: ALIMENTAÇÃO | AE1: DADOS DA CONCESSIONÁRIA DE ENERGIA | AJ1: DIAMETRO DA TUBULACAO | AN1: POPULAÇÃO BENEFICIADA EM HABITANTES | AO1: DOMICILIOS | AP1: D A D O S E T E S T E S A T U A L I Z A D O | AY1: D A D O S E T E S T E S A N T I G O | BH1: PAINEL | CC1: AUTOMAÇÃO | CF1: TOMADA DE PRESSAO | CH1: ELETRODOS | CK1: TIPO DE RECALQUE | CL1: COTA NA ELEVATORIA | CM1: COTA MAXIMA | CN1: DISTANCIA DA ELEV. A COORDENACAO | CO1: COMUNIDADES / HOSPITAIS / LOCALIDADES IMPORTANTES ABASTECIDAS | CP1: AREA DE INFLUENCIA
M2: MOTOR | P2: BOMBA | S2: Ø ROTOR | U2: TIPO CONSTRUTIVO DA ELEVATORIA | V2: BOMBA DRENO | W2: CO | X2: SENTIDO DE MONTAGEM DO MOTOR | Y2: TIPO DE FIXAÇAO | Z2: FORMA CONSTRUTIVA DA BOMBA | AA2: VAZÃO APROXIMADA (M³/H) | AB2: AMT | AP2: N O R M A L | AT2: S H U T T - O F F | AY2: N O R M A L | BC2: S H U T T - O F F | BH2: CONTATORA (K1) | BJ2: CONTATORA (K2) | BL2: CONTATORA (K3) | BN2: PC | BP2: RELE TERMICO BIMET. | BQ2: RELE DE TEMPO (Δ Y) | BR2: RELE DE ELETRODO (nIvel) | BS2: MONITOR DE CORRENTE | BT2: FUSIVEIS NH | BV2: FUSIVEIS DZ | BW2: TIPO DE AUTOMATISMO | CC2: SETPOINT
AB3: APROXIMADA
M4: (CV) | N4: RPM | O4: TAG | P4: MODELO | Q4: TAG | R4: MARCA | S4: POL | T4: MM | AB4: (MCA) | AC4: BT/MT | AD4: TRAFO (KVA) | AE4: N° CLIENTE | AF4: MEDIDOR | AG4: MEDIDOR APURADO + DATA | AH4: UNIDADE DE CONSUMO | AI4: ENDEREÇO | AJ4: SUCCAO | AK4: RECALQUE | AL4: TRONCO | AM4: DISTACIA ATE A ELEV. | AP4: TENSAO | AQ4: CORRENTE (A) | AR4: SUCCAO | AS4: RECALQUE | AT4: TENSAO | AU4: CORRENTE | AV4: SUCCAO | AW4: RECALQUE | AX4: DATA | AY4: TENSAO | AZ4: CORRENTE | BA4: SUCCAO | BB4: RECALQUE | BC4: TENSAO | BD4: CORRENTE | BE4: SUCCAO | BF4: RECALQUE | BG4: DATA | BH4: FABRICANTE | BI4: MODELO | BJ4: FABRICANTE | BK4: MODELO | BL4: FABRICANTE | BM4: MODELO | BN4: FUSIVEL | BO4: DISJUNTOR | BP4: REGULAGEM | BQ4: SIM / NÃO | BR4: SIM / NÃO | BS4: SIM / NÃO | BT4: TAMANHO | BU4: CORRENTE (A) | BV4: CORRENTE (A) | BW4: INVERSOR DE FREQUÊNCIA | BX4: SOFT STARTER | BY4: PARTIDA DIRETA | BZ4: COMPENSADA (EST. TRIÂNGULO) | CA4: CLP | CB4: CENTRAL DE ALARME | CC4: RETAGUARDA LIGA | CD4: RETAGUARDA DESLIGA | CE4: RECALQUE | CF4: SUCCAO | CG4: RECALQUE | CH4: SUPERIOR | CI4: INFERIOR | CJ4: COMUM
A6: ADOLFO BERGAMINI / ALTO MILITÂO | B6: =_xlfn.XLOOKUP(A:A,'Dados Elevatórias'!D:D,'Dados Elevatórias'!B:B) -> PL-RJB-EAT0093 | C6: EEAT (93) | D6: BAIXADA II | E6: RUA ADOLFO BERGAMINI E/F Nº 16 ESQU. C/ RUA MENA BARRETO | F6: NOVO HORIZONTE - CENTRO | H6: NILOPOLIS | I6: 26535-590 | J6: FORMAL | K6: 1 | L6: OPERACIONAL | M6: 25 | N6: 3480 | O6: RJB-21219 | P6: HAR25195B1 | Q6: RJB-21219 | R6: HELIBOMBAS | S6: 0.84 | T6: 142 | U6: TUBULAO | V6: NÃO | W6: ? | X6: ANFIBIA | Y6: ? | Z6: HORIZONTAL | AA6: 100 | AB6: 24 | AC6: 220V | AE6: 420150274 | AF6: 5241361 | AH6: AGUA - BOOSTER - ADOLFO BERGAMINI | AI6: R JOAO RODRIGUES DA CUNHA SN PX1195 | AJ6: 100 | AK6: 150 | AP6: 215/216/215 | AQ6: 47/46/47 | AR6: 14MCA | AS6: 50 | AT6: 215/216/215 | AU6: 37/36/37 | AV6: 50MCA | AW6: ? | AX6: 45407 | AY6: 218/216/218 | AZ6: 50/49/51 | BA6: 13MCA | BB6: 22MCA | BC6: 218/216/218 | BD6: ? | BE6: ? | BF6: ? | BG6: 45330 | BH6: X | BI6: X | BJ6: X | BK6: X | BL6: X | BM6: X | BN6: 160A | BP6: NÃO | BQ6: NÃO | BR6: SIM | BS6: NÃO | BT6: 0 | BU6: 160A | BV6: X | BW6: SIM | BX6: NÃO | BY6: NÃO | BZ6: NÃO | CA6: SIM | CB6: SIM | CC6: 1 MCA | CD6: < 1 MCA | CE6: 22 MCA | CF6: 45689 | CG6: 45689 | CH6: SIM | CJ6: SIM | CK6: EM MARCHA | CL6: 24 | CM6: 53 | CP6: Area 1: Rua Adolfo Bergamin (Trecho Rua Mena Barreto A Rua JoAo da Mata Peixoto), Rua Natividade (Trecho Rua Adolfo Bergamin A Rua MArio Valadares), Rua Romilda Alves, Rua Embaixador Von Spritt, Rua Aurea P. Farjado, Rua GenEsio de Barros e pequenas Vilas desse trecho. Area 2: Rua JoAo da Mata Peixoto (Trecho do nº 182 A Rua MArio Valadares), Rua Adolfo Bergamin (Trecho Rua JoAo da Mata Peixoto A Rua Antonio J. Bittencourt), Rua JoAo F. da Silva, Rua Maria InEs QueirOs, Rua AmErico Diamantino Lopes, Rua JosE da Silva Braga (Trecho Rua MArio Valadares A Rua AntOnio J. Bittencourt), Rua Francisco M. da Silva. Area 3: Rua JoAo da Mata Peixoto (Trecho Rua Otacilio Pessoa), Rua JoAo da Cruz Saldanha, Rua Lauro Machado e pequenas Vilas desse trecho.
A7: AMAURI GUIMARAES | B7: =_xlfn.XLOOKUP(A:A,'Dados Elevatórias'!D:D,'Dados Elevatórias'!B:B) -> PL-RJB-EAT0687 | C7: EEAT (687) | D7: BAIXADA II | E7: RUA GENI SARAIVA E/F 1998 | F7: FLORESTA | H7: NOVA IGUACU | I7: 26031-200 | J7: FORMAL | K7: 1 | L7: OPERACIONAL | M7: 7.5 | N7: 3500 | O7: RJB-15668 | P7: 3x1 1/2x6 | Q7: RJB-15667 | R7: WORTHINGTON | S7: 5.6 | T7: 142.24 | U7: TUBULAO | X7: VERTICAL | Z7: INLINE | AA7: 32.5 | AB7: 35 | AC7: 220V | AE7: 430248796 | AF7: 169005 | AH7: AGUA - ELEV - AMAURI GUIMARÃES | AI7: RUA GENI SARAIVA E/F 1998 | AP7: 208/209/208 | AQ7: 14.15.14 | AR7: 6MCA | AS7: 30MCA | AT7: 208/209/209 | AU7: X | AV7: X | AW7: X | AX7: 44928 | BN7: 100A | BP7: NÃO | BQ7: NÃO | BR7: SIM | BS7: SIM | BT7: 0 | BU7: 100A | BV7: X | BW7: SIM | BX7: NÃO | BY7: NÃO | BZ7: NÃO | CA7: NÃO | CB7: SIM | CH7: SIM | CJ7: SIM | CK7: EM MARCHA
A8: ÂNGELA MARIA | B8: =_xlfn.XLOOKUP(A:A,'Dados Elevatórias'!D:D,'Dados Elevatórias'!B:B) -> PL-RJB-EAT0088 | C8: EEAT (88) | D8: BAIXADA II | E8: RUA ÂNGELA S/N EF 127 ESQ RUA OLIVEIA RODRIGUES ALVES | F8: POSSE | H8: NOVA IGUACU | I8: 26013-500 | J8: FORMAL | K8: 1 | L8: OPERACIONAL | M8: 1.5 | N8: 3510 | O8: RJB-05581 | P8: CAM W6 | Q8: RJB-05491 | R8: DANCOR | S8: 5.35 | T8: 135.89 | U8: ABRIGADA | X8: HORIZONTAL | Z8: DELTA | AA8: 6.5 | AC8: 220V | AD8: - | AE8: 420594529 | AF8: 73520772 | AH8: AGUA - ELEV - ANGELA MARIA | AI8: R ANGELA MARIA SN EF127 | AJ8: DN 50 / 2 POL | AK8: DN 50 / 2 POL | AP8: 215/215/217 | AQ8: 05.06.05 | AR8: 7MCA | AS8: 19MCA | AT8: 216/216/216 | AU8: 3.3.4 | AW8: 50MCA | AX8: 44956 | AY8: 218X217X217 | AZ8: 3,6X3,6X3,6 | BA8: 4 | BB8: 25 | BD8: 2,4X2,4X2,3 | BE8: 4 | BF8: 40 | BG8: 43359 | BH8: Siemens Sirius | BI8: BYU100626 | BJ8: - | BK8: - | BL8: - | BM8: - | BN8: 35A | BP8: 7A | BQ8: NÃO | BR8: SIM | BS8: NÃO | BT8: 0 | BU8: 35A | BV8: X | BW8: NÃO | BX8: NÃO | BY8: SIM | BZ8: NÃO | CA8: NÃO | CB8: SIM | CF8: 45750 | CG8: 45689 | CH8: SIM | CI8: - | CJ8: SIM | CK8: EM MARCHA | CL8: - | CM8: - | CN8: -
A9: ANTONIO VALDIGEM | B9: =_xlfn.XLOOKUP(A:A,'Dados Elevatórias'!D:D,'Dados Elevatórias'!B:B) -> PL-RJB-EAT0736 | C9: EEAT (736) | D9: BAIXADA II | E9: R ANTONIO VALDIGEM SN CA1 EF25 | F9: PORTEIRA | H9: QUEIMADOS | I9: 26385-300 | J9: INFORMAL | K9: 1 | L9: OPERACIONAL | M9: 15 | N9: 3510 | O9: RJB-07290 | P9: 687 | Q9: RJB-07246 | R9: WORTHINGTON | U9: ABRIGADA | X9: HORIZONTAL | Z9: CONV. | AA9: 45 | AC9: 220V | AE9: 420630267 | AF9: 8663425 | AH9: AGUA - BVOLANTE - ANTONIO WEINSCHENK | AI9: R ANTONIO VALDIGEM SN CA1 EF25 | AK9: 2POL | AP9: 220/217/219 | AQ9: 26.24.27 | AR9: X | AS9: X | AT9: 218/217/218 | AX9: 44960 | BH9: X | BI9: X | BJ9: X | BK9: X | BL9: X | BM9: X | BN9: X | BO9: 100A | BP9: NÃO | BQ9: NÃO | BR9: NÃO | BS9: NÃO | BT9: X | BU9: X | BV9: X | BW9: NÃO | BX9: NÃO | BY9: SIM | BZ9: NÃO | CA9: NÃO | CB9: SIM | CC9: 1 MCA | CD9: 0,2 MCA | CE9: 43 MCA | CF9: NÃO | CG9: NÃO | CH9: NÃO | CI9: NÃO | CJ9: NÃO | CK9: EM MARCHA | CO9: MORRO AZUL
A10: PRAÇA DA BÍBLIA | B10: =_xlfn.XLOOKUP(A:A,'Dados Elevatórias'!D:D,'Dados Elevatórias'!B:B) -> PL-RJB-EAT0692 | C10: EEAT (692) | D10: BAIXADA II | E10: R ASSEMBLEIA 1SN - PRAÇA DA BÍBLIA | F10: CENTRO | H10: QUEIMADOS | I10: 26327-410 | J10: INFORMAL | K10: 1 | L10: OPERACIONAL | M10: 12.5 | N10: 3515 | O10: RJB-03133 | P10: BC-21 | Q10: RJB-03119 | R10: SCHNEIDER | U10: ABRIGADA | X10: HORIZONTAL | Z10: DELTA | AA10: 24.5 | AC10: 220V | AJ10: 2POL | AK10: 2POL | AP10: 213/213/212 | AQ10: 17.19.18 | AR10: X | AS10: 31MCA | AT10: 215/215/215 | AU10: 16.16.13 | AV10: X | AW10: 39MCA | AX10: 44910 | BH10: DIL | BI10: M50 | BJ10: X | BK10: X | BL10: X | BM10: X | BP10: 30A | BQ10: NÃO | BR10: SIM | BS10: NÃO | BT10: X | BU10: X | BV10: X | BW10: NÃO | BX10: NÃO | BY10: SIM | BZ10: NÃO | CA10: NÃO | CB10: SIM | CH10: SIM | CJ10: SIM | CK10: EM MARCHA
A11: BEIRA LINHA | B11: =_xlfn.XLOOKUP(A:A,'Dados Elevatórias'!D:D,'Dados Elevatórias'!B:B) -> PL-RJB-EAT0688 | C11: EEAT (688) | D11: BAIXADA II | E11: AVENIDA BEIRA LINHA, sn EF275, ESQUINA COM ESTRADA VELHA DE IGUAÇU | F11: GRAMA | H11: NOVA IGUACU | I11: 25045-366 | J11: INFORMAL | K11: 1 | L11: OPERACIONAL | M11: 70 | N11: --- | P11: S200R-03 | R11: LEAO | U11: SUBMERSA VERTICAL | W11: X | X11: X | Y11: X | Z11: SUBMERSA | AE11: 430086325 | AF11: 8552185 | AQ11: 182x183x184 | AR11: 21 | AS11: 95 | AT11: 126x127x128 | AU11: 126x127x128 | AV11: 12 | AW11: 146 | AX11: 43390
A12: BELO HORIZONTE | B12: =_xlfn.XLOOKUP(A:A,'Dados Elevatórias'!D:D,'Dados Elevatórias'!B:B) -> PL-RJB-EAT0083 | C12: EEAT (83) | D12: BAIXADA II | E12: RUA BELO HORIZONTE ESQ./ RUA JEQUITIA | F12: VILA SAO TEODORO | H12: NOVA IGUACU | I12: 26021-630 | J12: FORMAL | K12: 1 | L12: OPERACIONAL | M12: 25 | N12: 3500 | O12: RJB-05419 | P12: 3X11/2X8 | Q12: RJB-05571 | R12: WORTHINGTON | S12: 7.99 | T12: 202.95 | U12: ABRIGADA | W12: JM | X12: VERTICAL | Y12: FC | Z12: INLINE | AC12: 220V | AE12: 412787475 | AF12: 5241353 | AH12: AGUA - BOOSTER - BELO HORIZONTE | AI12: AV BELO HORIZONTE SN FT840 | AJ12: 100MM | AK12: 50MM | AP12: 214/214/215 | AQ12: 48.46.49 | AR12: 4MCA | AS12: 10MCA | AT12: 215/215/216 | AU12: 35.37.35 | AV12: 10MCA | AW12: 45MCA | AX12: 44955 | AY12: 214X215X214X | AZ12: 60X61X62 | BA12: 0 | BB12: 60 | BC12: 219X219X219 | BD12: 32X34X33 | BE12: 3 | BF12: 98 | BG12: 43293 | BH12: X | BI12: X | BJ12: X | BK12: X | BL12: X | BM12: X | BN12: 125A | BP12: NÃO | BQ12: NÃO | BR12: SIM | BS12: NÃO | BT12: 0 | BU12: 150 | BV12: X | BW12: SIM | BX12: NÃO | BY12: NÃO | BZ12: NÃO | CA12: NÃO | CB12: SIM | CC12: 1 MCA | CD12: <1MCA | CH12: SIM | CJ12: SIM | CK12: EM MARCHA | CP12: Rua Angico - Rua Belo Horizonte - Rua Brasil - Rua Francisco Alves - Rua General Canraberi - Rua GonCalo Alves - Rua Iris - Rua JequitibA - Rua Leopoldo Machado - Rua Passos - Rua Saudade (parte)
A13: CAIXA VELHA | B13: =_xlfn.XLOOKUP(A:A,'Dados Elevatórias'!D:D,'Dados Elevatórias'!B:B) -> PL-RJB-EAT0011 | C13: EEAT (11) | D13: BAIXADA II | E13: RUA TABELIAO MURILO COSTA E/F Nº 161 | F13: JOANA D`ARC | H13: NOVA IGUACU | I13: 28255-130 | J13: FORMAL | K13: 1 | L13: OPERACIONAL | M13: 40 | N13: 3540 | O13: RJB-04948 | P13: 4X3X8 | Q13: RJB-04532 | R13: WORTHINGTON | S13: 8 | T13: 203.2 | U13: ABRIGADA | W13: JM | X13: VERTICAL | Y13: FC | Z13: INLINE | AA13: 160 | AB13: 70 | AC13: 220V | AE13: 411457794 | AF13: 7516646 | AH13: AGUA - ELEV - BRASILIA | AI13: R TABE MURILO COSTA 141 | AJ13: 100MM | AK13: 150MM | AP13: 205/206/208 | AQ13: 109110111 | AR13: 5MCA | AS13: 82MCA | AT13: 206206205 | AU13: 71.72.70 | AV13: 4MCA | AW13: 101MCA | AX13: 44964 | AY13: 206X206X207 | AZ13: 107X110X111 | BA13: 3 | BB13: 90 | BG13: 42469 | BH13: X | BI13: X | BJ13: X | BK13: X | BL13: X | BM13: X | BN13: 160A | BP13: NÃO | BQ13: NÃO | BR13: SIM | BS13: NÃO | BT13: 0 | BU13: 160 | BV13: X | BW13: SIM | BX13: NÃO | BY13: NÃO | BZ13: NÃO | CA13: NÃO | CB13: SIM | CH13: SIM | CJ13: SIM | CK13: EM MARCHA | CP13: Rua 15 de Agosto - Rua 1º de Maio - Rua 23 de Abril - Rua 25 de Dezembro - Rua AntOnio de Almeida - Rua da Liberdade - Rua das Mangueiras - Rua do GDRM-11tAo - Rua Dona Rita - Rua Dr. Tibau - Rua Juiz Antonio Belot de Souza - Rua Rangel Pestana - Rua Rejane Pedro Equi - Rua SebastiAo dos Reis - Rua SebastiAo Herculano de Matos (parte) - Rua TabeliAo Murilo Costa (parte) - Rua Zilda - Travessa Dr. Tibau - Travessa Maria JosE - Travessa Shirley - Travessa Soares
A14: BURITI | B14: =_xlfn.XLOOKUP(A:A,'Dados Elevatórias'!D:D,'Dados Elevatórias'!B:B) -> PL-RJB-EAT0684 | C14: EEAT (684) | D14: BAIXADA II | E14: RUA DOS BURITIS S/N | F14: JD. TRANSMONTANO | H14: JAPERI | I14: 26453-365 | J14: INFORMAL | K14: 1 | L14: OPERACIONAL | M14: 7.5 | N14: 3510 | O14: RJB-00433 | P14: 645 | Q14: RJB-00441 | R14: DANCOR | U14: ABRIGADA | X14: HORIZONTAL | Z14: DELTA | AA14: 32.5 | AC14: 220V | AJ14: 2POL | AK14: 2POL | AP14: 210/210/210 | AQ14: 22.24.22 | AR14: X | AS14: 10MCA | AT14: 200201200 | AU14: 10.08.12 | AV14: X | AW14: 54MCA | AX14: 44954 | BH14: Siemens | BI14: 3TS34 | BJ14: X | BK14: X | BL14: X | BM14: X | BN14: X | BO14: 32A | BP14: 20A | BQ14: NÃO | BR14: NÃO | BS14: NÃO | BT14: X | BU14: X | BV14: 5A | BW14: NÃO | BX14: NÃO | BY14: SIM | BZ14: NÃO | CA14: NÃO | CB14: SIM | CF14: X | CH14: X | CI14: X | CJ14: X | CK14: EM MARCHA
A15: BOOSTER CABUÇU ALTO | B15: =_xlfn.XLOOKUP(A:A,'Dados Elevatórias'!D:D,'Dados Elevatórias'!B:B) -> PL-RJB-EAT0689 | C15: EEAT (689) | D15: BAIXADA II | E15: RUA JOSE CABRAL, SN | F15: VALVERDE | H15: NOVA IGUACU | I15: 26290-048 | J15: FORMAL | K15: 1 | L15: OPERACIONAL | M15: 50 | N15: 1750 | O15: RJB-06856 | Q15: RJB-06864 | R15: KSB-OMEGA | T15: 247 | U15: ABRIGADA | W15: JM | X15: HORIZONTAL | Z15: CONV. | AA15: 360 | AC15: 440V | AE15: 430053078 | AF15: 7891998 | AH15: AGUA - ELEV - CABUCU ALTO G1 | AI15: RUA JOSE CABRAL S/NJOSE CABRAL S/N | AP15: 437/432/435 | AQ15: reserva | AR15: reserva | AS15: reserva | AT15: X | AU15: X | AV15: X | AW15: X | AX15: 44932 | BW15: SIM | BX15: NÃO | BY15: NÃO | BZ15: NÃO | CB15: SIM | CC15: 16 MCA | CD15: 14 MCA | CE15: 45 MCA
B16: PL-RJB-EAT0689 | C16: EEAT (689) | D16: BAIXADA II | E16: RUA JOSE CABRAL, SN | F16: VALVERDE | H16: NOVA IGUACU | I16: 26290-048 | J16: FORMAL | K16: 2 | L16: OPERACIONAL | M16: 50 | N16: 1750 | O16: RJB-06865 | P16: KSB-OMEGA | Q16: RJB-06880 | R16: KSB-OMEGA | T16: 247 | U16: ABRIGADA | W16: JM | X16: HORIZONTAL | Z16: CONV. | AC16: 440V | AE16: 430053078 | AF16: 7891998 | AH16: AGUA - ELEV - CABUCU ALTO G2 | AI16: RUA JOSE CABRAL S/NJOSE CABRAL S/N | AP16: 437/432/436 | AQ16: 39.37.40 | AR16: 2.4KGF | AS16: 5.1KGF | AT16: X | AU16: X | AV16: X | AW16: X | AX16: 44932 | BW16: SIM | BX16: NÃO | BY16: NÃO | BZ16: NÃO
B17: PL-RJB-EAT0689 | C17: EEAT (689) | D17: BAIXADA II | E17: RUA JOSE CABRAL, SN | F17: VALVERDE | H17: NOVA IGUACU | I17: 26290-048 | J17: FORMAL | K17: 3 | L17: RESERVA | M17: 50 | N17: 1750 | O17: RJB-06888 | P17: KSB-OMEGA | Q17: RJB-06887 | R17: KSB-OMEGA | T17: 247 | U17: ABRIGADA | W17: JM | X17: HORIZONTAL | Z17: CONV. | AC17: 440V | AE17: 430053078 | AF17: 7891998 | AH17: AGUA - ELEV - CABUCU ALTO G2 | AI17: RUA JOSE CABRAL S/NJOSE CABRAL S/N | AP17: 437/432/437 | AQ17: 122.70.66 | AR17: 2.4KGF | AS17: 5.1KGF | AT17: X | AU17: X | AV17: X | AW17: X | AX17: 44932 | BW17: SIM | BX17: NÃO | BY17: NÃO | BZ17: NÃO
A18: BOOSTER/RES CABUCU BAIXO | B18: =_xlfn.XLOOKUP(A:A,'Dados Elevatórias'!D:D,'Dados Elevatórias'!B:B) -> #N/A | C18: EEAT (690) | D18: BAIXADA II | E18: RUA OZORIO, 200 | F18: VALVERDE | H18: NOVA IGUACU | I18: 26290-369 | J18: FORMAL | K18: 1 | L18: OPERACIONAL | M18: 20 | N18: 3560 | O18: - | R18: IMBIL | T18: 310 | U18: TUBULAO | V18: NÃO | W18: JM | X18: HORIZONTAL | Z18: DELTA | AA18: 58 | AC18: 220V | AE18: 430139021 | AF18: 9622957 | AH18: AUGA-ELEV-CABUCU BAIXO | AI18: RUA COLORADO LOTE 29 | AK18: 150DN | AP18: 218/218/217 | AQ18: 36.34.36 | AX18: 44942 | BH18: X | BI18: X | BJ18: X | BK18: X | BL18: X | BM18: X | BN18: 100A | BP18: X | BQ18: NÃO | BR18: NÃO | BS18: NÃO | BT18: 0 | BU18: 100A | BW18: SIM | BX18: NÃO | BY18: NÃO | BZ18: NÃO | CA18: NÃO | CB18: SIM
A19: CAIÇARA | B19: =_xlfn.XLOOKUP(A:A,'Dados Elevatórias'!D:D,'Dados Elevatórias'!B:B) -> PL-RJB-EAT0048 | C19: EEAT (48) | D19: BAIXADA II | E19: RUA JOAO VENANCIO DE FIGUEIREDO EF AO Nº 52 OITICICA | F19: KENNEDY | H19: NOVA IGUACU | I19: 26020-001 | J19: FORMAL | K19: 1 | L19: OPERACIONAL | M19: 20 | N19: 3535 | P19: 3X2X6 | Q19: RJB-05451 | R19: WORTHINGTON | S19: 6.57 | T19: 166.88 | U19: ABRIGADA | X19: HORIZONTAL | Z19: DELTA | AA19: 55,27 | AB19: 60 | AE19: 413110570 | AF19: 5028144 | AH19: AGUA - BOOSTER - CAICARA | AI19: PCA OITICICA SN FT52 | AJ19: 100MM | AK19: 75MMM | AP19: 220/220/219 | AQ19: 23.25.25 | AR19: 2 | AS19: 45 | AT19: 219/219/219 | AU19: 27.23.25 | AW19: 56MCA | AX19: 44964 | AY19: 210X206X208 | AZ19: 36X38X35 | BB19: 50 | BC19: 213X210X209 | BD19: 32X33X30 | BE19: 9 | BF19: 65 | BG19: 42490 | BH19: X | BI19: X | BJ19: X | BK19: X | BL19: X | BM19: X | BN19: 63A | BQ19: NÃO | BR19: SIM | BS19: NÃO | BT19: 0 | BU19: 63A | BW19: SIM | BX19: NÃO | BY19: NÃO | BZ19: NÃO | CA19: NÃO | CB19: SIM | CH19: SIM | CJ19: SIM | CK19: em marcha | CP19: Rua AnambA - Rua Angelina - Rua Bacuri - Rua Eucalipto - Rua GoiAs - Rua Jaras - Rua JatobA - Rua JequitibA Rosa - Rua JequitibA - Rua Leopoldo Machado - Rua Massaranduba - Rua Ocabu - Rua Oiti - Rua Pequim
A20: CANADENSE | B20: =_xlfn.XLOOKUP(A:A,'Dados Elevatórias'!D:D,'Dados Elevatórias'!B:B) -> PL-RJB-EAT0056 | C20: EEAT (56) | D20: BAIXADA II | E20: RUA GENERAL OLIMPIO DA FONSECA E/F A COMLURB | F20: NILOPOLIS | H20: NILOPOLIS | I20: 26545-470 | J20: INFORMAL | K20: 1 | L20: OPERACIONAL | M20: 4 | N20: --- | O20: X | P20: S6S-30-02-04 | R20: CRI | T20: - | U20: SUBMERSA VERTICAL | W20: X | X20: VERTICAL SUB | Y20: X | Z20: SUBMERSA | AA20: 34 | AB20: 22 | AC20: 220V | AE20: 420149824 | AF20: 5404178 | AH20: AGUA - BOOSTER - UNIVERSAL CANADENSE | AI20: R JOAO DIEZ LIMA 97 | AP20: 213/209/211 | AQ20: 16.15.15 | AR20: X | AS20: 40MCA | AT20: 213/214/216 | AU20: 10.11.13 | AV20: X | AW20: 53MCA | AX20: 44962 | AY20: 211X212X214 | AZ20: 17X18X18 | BB20: 30 | BG20: 43416 | BJ20: X | BK20: X | BL20: X | BM20: X | BN20: 63A | BP20: 24A | BQ20: NÃO | BR20: SIM | BS20: SIM | BT20: 0 | BU20: 63A | BV20: 5A | BW20: NÃO | BX20: NÃO | BY20: SIM | BZ20: NÃO | CA20: NÃO | CB20: SIM | CH20: SIM | CJ20: SIM | CK20: em marcha | CO20: PAIOL | CP20: Rua OlImpio da Fonseca (Trecho Rua Major Leite de Castro A Rua Canadense), Rua Dona Vicentina (Trecho Rua Carlos de S. Fernandes A Rua Manoel Pinto), Rua Canadense (Trecho Rua JosE Couto GuimarAes A Rua Manoel Pinto, Rua Jorge LOssio, Rua Carlos de S. Fernandes (Trecho Rua Dona Vicentina A Rua Canadense) e pequenas Vilas desse trecho.
A21: CEFET | B21: =_xlfn.XLOOKUP(A:A,'Dados Elevatórias'!D:D,'Dados Elevatórias'!B:B) -> PL-RJB-EAT0108 | C21: EEAT (108) | D21: BAIXADA II | E21: ESTRADA DE ANDREANOPOLIS S/N E/F CEFET | F21: SANTA RITA | H21: NOVA IGUACU | I21: 26050-000 | J21: FORMAL | K21: 1 | L21: OPERACIONAL | M21: 4.5 | N21: -- | O21: RJB-15643 | P21: S30-02 | Q21: RJB-15646 | R21: LEAO | T21: - | U21: SUBMERSA VERTICAL | W21: X | X21: VERTICAL SUB | Y21: X | Z21: SUBMERSA | AA21: 27,20 | AB21: 23 | AC21: 220V | AE21: 420268697 | AF21: 6617672-7 | AH21: AGUA - BOOSTER - CEFET | AI21: EST ADRIANOPOLIS SN EF2174 | AN21: 1800 | AP21: 219/220/218 | AQ21: 11.13.10 | AR21: 1 | AS21: 35MCA | AT21: 218/218/219 | AU21: 10.10.9 | AV21: 2MCA | AW21: 39MCA | AX21: 44956 | AY21: 207X206X205 | AZ21: 10X10X11 | BG21: 42623 | BH21: X | BI21: X | BJ21: X | BK21: X | BL21: X | BM21: X | BN21: 100A | BP21: X | BQ21: X | BR21: SIM | BS21: NÃO | BT21: 0 | BU21: 100A | BV21: X | BW21: NÃO | BX21: SIM | BY21: NÃO | BZ21: NÃO | CA21: NÃO | CB21: SM | CH21: SIM | CJ21: SIM | CK21: em marcha | CL21: 35 | CM21: 46
A22: CHATUBA | B22: =_xlfn.XLOOKUP(A:A,'Dados Elevatórias'!D:D,'Dados Elevatórias'!B:B) -> PL-RJB-EAT0741 | C22: EEAT (741) | D22: BAIXADA II | E22: RUA MARQUES DE CANARIO, AO LADO DO Nº 458 | F22: CHATUBA | H22: MESQUITA | I22: 26587-650 | J22: INFORMAL | K22: 1 | L22: OPERACIONAL | M22: 75 | N22: 3500 | P22: 4x3x10 | R22: WORTHINGTON | S22: 10 | T22: 254 | U22: TUBULAO | V22: SIM | W22: JM | X22: VERTICAL | Y22: FC | Z22: INLINE | AA22: 129,25 | AB22: 80 | AC22: MT | AE22: 400139840 | AF22: 1999622 | AH22: AGUA - BOOSTER - CHATUBA | AI22: R MARQUES DE CANARIO SN LT8 | AP22: 218/219/216 | AQ22: 167X170X175 | AR22: 0 | AS22: 85 | AT22: 220 | AU22: 125X130X138 | AV22: 10 | AW22: 100 | AX22: 44956 | AY22: 220X219X220 | AZ22: 170X169X178 | BB22: 40 | BC22: 220X219X220 | BE22: 4 | BF22: 110 | BG22: 42562 | BH22: x | BI22: x | BJ22: x | BK22: x | BL22: x | BM22: x | BN22: x | BP22: x | BQ22: x | BS22: NÃO | BW22: SIM | BX22: NÃO | BY22: NÃO | BZ22: NÃO | CA22: SIM | CB22: SIM | CC22: < 1 MCA | CK22: em marcha | CO22: CHATUBA | CP22: Rua atendidas: Arizona, Plaza, AstOria, Toneleiros, AssU, Adolfo de Albuquerque, IcaraI, Aquidauana, Itaqui, AbaetE e Boatafogo. Comunidade da Chatuba
A23: DINAMARCO REIS | B23: =_xlfn.XLOOKUP(A:A,'Dados Elevatórias'!D:D,'Dados Elevatórias'!B:B) -> PL-RJB-EAT0069 | C23: EEAT (69) | D23: BAIXADA II | E23: RUA DINAMARCO REIS C/ CARLOS SOUZA FERNANDES | F23: OLINDA | H23: NILOPOLIS | I23: 26545-230 | J23: FORMAL | K23: 1 | L23: OPERACIONAL | M23: 20 | N23: 3500 | P23: 3X2X6 | Q23: RJB-05507 | R23: WORTHINGTON | S23: 6.57 | T23: 166.88 | U23: TUBULAO | W23: JM | X23: VERTICAL | Y23: FC | Z23: INLINE | AA23: 62,93 | AB23: 60 | AE23: 413497046 | AF23: 7667390 | AH23: AGUA - BOOSTER - DINAMARCO REIS | AI23: R DINAMARCO REIS SN | AJ23: 100MM | AK23: 100MM | AP23: 220/219/219 | AQ23: 46.45.49 | AR23: 1MCA | AS23: 41MCA | AT23: 219/218/219 | AU23: 27.29.28 | AV23: 7MCA | AW23: 66MCA | AX23: 44929 | AY23: 215-211-212 | AZ23: 38-38-36 | BA23: 5 | BB23: 46 | BC23: 216-216-218 | BD23: 20-21-22 | BE23: 15 | BF23: 80 | BG23: 42374 | BH23: X | BI23: X | BJ23: X | BK23: X | BL23: X | BM23: X | BN23: 160A | BP23: X | BQ23: X | BR23: SIM | BS23: NÃO | BT23: 0 | BU23: 160A | BV23: X | BW23: SIM | BX23: NÃO | BY23: NÃO | BZ23: NÃO | CA23: NÃO | CB23: SIM | CC23: 1 MCA | CD23: < 1 MCA | CH23: SIM | CJ23: SIM | CK23: em marcha | CP23: Rua Dinamarco Reis (Trecho Rua Carlos de Souza Fernandes ao Final da Rua), Rua JosE Couto GuimarAes (Trecho Rua Rodrigues Alves A Rua Cândida), Rua Maria Gama (Trecho Rua Carlos de Souza Fernandes A Rua Candida), Rua Amadeu Lara (Trecho Rua Carlos de souza Fernandes A Rua Candida) e pequenas Vilas desse Trecho.
A24: EDNA | B24: =_xlfn.XLOOKUP(A:A,'Dados Elevatórias'!D:D,'Dados Elevatórias'!B:B) -> PL-RJB-EAT0062 | C24: EEAT (62) | D24: BAIXADA II | E24: RUA EDNA SN EF AO 16 | F24: VILA TREZE DE MAIO | H24: NOVA IGUACU | I24: 26030-430 | J24: FORMAL | K24: 1 | L24: OPERACIONAL | M24: 5 | N24: 3500 | O24: 90201166 | P24: 620 | R24: DANCOR | S24: 6.37 | T24: 161.8 | U24: ABRIGADA | X24: HORIZONTAL | Z24: CONV. | AA24: 17.01 | AB24: 45 | AC24: BT | AE24: 413424336 | AF24: 2417316 | AH24: AGUA - BOOSTER - EDNA | AI24: R EDNA SN EF16 | AP24: 220X222X225 | AQ24: 13X12X12 | AS24: 28 | AT24: 220X222X225 | AU24: 7X8X7 | AV24: 1 | AW24: 45 | AX24: 43158 | AY24: 211X217X217 | AZ24: 14X14X18 | BG24: 42639 | BW24: SIM | BY24: NÃO | CB24: SIM | CP24: Rua Edna - Rua ParaguaCu - Rua ParanaguA - Rua Sueli
A25: EDUARDO CELIDÔNIO | B25: =_xlfn.XLOOKUP(A:A,'Dados Elevatórias'!D:D,'Dados Elevatórias'!B:B) -> PL-RJB-EAT0693 | C25: EEAT (693) | D25: BAIXADA II | E25: AV EDUARDO CELIDONIO 1SN | F25: FANCHEM | H25: QUEIMADOS | I25: 26383-535 | J25: INFORMAL | K25: 1 | L25: OPERACIONAL | M25: 10 | N25: 3520 | O25: RJB- | Q25: RJB-07208 | R25: DANCOR | U25: ABRIGADA | X25: HORIZONTAL | Z25: CONV. | AC25: 220V | AJ25: 2POL | AK25: 2POL | AP25: 211/212/214 | AQ25: 20.23.23 | AR25: X | AS25: 20MCA | AT25: 213/213/213 | AX25: 44962 | BH25: SIEMENS | BJ25: X | BK25: X | BL25: X | BM25: X | BN25: X | BO25: 80A | BP25: 26A | BQ25: NÃO | BR25: NÃO | BS25: NÃO | BT25: X | BU25: X | BV25: X | BW25: NÃO | BX25: NÃO | BY25: SIM | BZ25: NÃO | CA25: NÃO | CB25: SIM | CH25: X | CI25: X | CJ25: X | CK25: EM MARCHA
A26: EL SHADAY | B26: =_xlfn.XLOOKUP(A:A,'Dados Elevatórias'!D:D,'Dados Elevatórias'!B:B) -> PL-RJB-EAT0104 | C26: EEAT (104) | D26: BAIXADA II | E26: LADEIRA EL SHADAY | F26: AUSTIN | H26: NOVA IGUACU | I26: 26292-039 | J26: INFORMAL | K26: 1 | L26: OPERACIONAL | M26: 3 | N26: 3500 | O26: RJB-06903 | P26: BHS511-03 | Q26: RJB-06941 | R26: EBARA | T26: - | U26: SUBMERSA VERTICAL | W26: X | X26: VERTICAL | Y26: X | Z26: SUBMERSA | AA26: 28,48 | AB26: 40 | AC26: 220V | AE26: 420758197 | AF26: 7802169 | AH26: AGUA - BOOSTER - ELSHADAI | AI26: R MARCIO VIEIRA DE OLIVEIRA SN EF370 | AJ26: 100MM | AK26: 100MM | AN26: 475 | AO26: 95 | AP26: 216/218/217 | AQ26: 09.09.08 | AR26: 17MCA | AS26: 60MCA | AX26: 44949 | AY26: 201X204X203 | AZ26: 10X11X10 | BG26: 42412 | BH26: DIL | BI26: M25-10 | BJ26: X | BK26: X | BL26: X | BM26: X | BN26: 63A | BP26: 13A | BQ26: NÃO | BR26: NÃO | BS26: SIM | BT26: 0 | BU26: 63A | BV26: 5A | BW26: NÃO | BX26: NÃO | BY26: SIM | BZ26: NÃO | CA26: NÃO | CB26: SIM | CH26: SIM | CJ26: SIM | CK26: EM MARCHA | CL26: 44 | CM26: 68 | CO26: EL SHADAY | CP26: Ladeira el Shaday, Rua Barroso, Rua Aristides, Rua Bela Vista e Rua Calma.
A27: ENGENHARIA | B27: =_xlfn.XLOOKUP(A:A,'Dados Elevatórias'!D:D,'Dados Elevatórias'!B:B) -> PL-RJB-EAT0117 | C27: EEAT (117) | D27: BAIXADA II | E27: Av. Henrique Duque Estrada Meyer, 378-456 - Posse, Nova Iguaçu - RJ, 26041-061 | F27: POSSE | H27: NOVA IGUACU | I27: 26041-061 | J27: FORMAL | K27: 1 | L27: OPERACIONAL | M27: 15 | N27: 3535 | O27: - | P27: S6S-48-04-15 | Q27: RJB-05533 | R27: CRI | T27: - | U27: SUBMERSA VERTICAL | W27: X | X27: VERTICAL | Y27: X | Z27: SUBMERSA | AA27: 50 | AB27: 55 | AC27: 220V | AE27: 420203527 | AF27: 6277280 | AH27: AGUA - BOOSTER - ENGENHARIA | AI27: AV HENRIQUE DUQUE ESTRADA MEYER SN EF407 | AJ27: 100MM | AK27: 100MM | AP27: 211/210/208 | AQ27: 43.38.37 | AR27: X | AS27: 30MCA | AT27: 212/213/212 | AU27: 38.38.40 | AV27: X | AW27: 84MCA | AX27: 44957 | AY27: 209x212x209 | AZ27: 47x46x49 | BB27: 40 | BC27: 209x212x209 | BD27: 29x26x29 | BE27: 20 | BF27: 100 | BG27: 42721 | BJ27: X | BK27: X | BL27: X | BM27: X | BN27: X | BX27: SIM | BY27: NÃO | CB27: SIM
A28: ESPLANADA | B28: =_xlfn.XLOOKUP(A:A,'Dados Elevatórias'!D:D,'Dados Elevatórias'!B:B) -> PL-RJB-EAT0075 | C28: EEAT (75) | D28: BAIXADA II | E28: RUA DA FAZENDA Nº 256 | F28: ESPLANADA | H28: NOVA IGUAÇU | I28: 26013-470 | J28: FORMAL | K28: 1 | L28: OPERACIONAL | M28: 25 | N28: 3530 | O28: RJB-04511 | P28: 3X11/2X8 | Q28: RJB-15629 | R28: WORTHINGTON | S28: 8.03 | T28: 203.96 | U28: ABRIGADA | W28: JM | X28: VERTICAL | Y28: FC | Z28: INLINE | AA28: 50 | AB28: 90 | AC28: 220V | AE28: 411189247 | AF28: 5003079 | AH28: AGUA - ELEV - ESPLANADA (CAIXA BAIXA) * E ANEXOS | AI28: R FAZENDA 256 | AJ28: 150MM | AK28: 100MM | AP28: 218/215/218 | AQ28: 57/57/52 | AR28: 3MCA | AS28: 46MCA | AT28: 219/219/220 | AU28: 42.42.40 | AV28: 3MCA | AW28: 82MCA | AX28: 44957 | AY28: 220X220X218 | AZ28: 53X53X55 | BB28: 60 | BC28: 220X220X218 | BD28: 40X40X43 | BF28: 90 | BG28: 42443 | BH28: X | BI28: X | BJ28: X | BK28: X | BL28: X | BM28: X | BN28: 125A | BP28: X | BQ28: NÃO | BR28: SIM | BS28: NÃO | BT28: 0 | BU28: 125A | BV28: X | BW28: SIM | BX28: NÃO | BY28: NÃO | BZ28: NÃO | CA28: NÃO | CB28: SIM | CC28: 1 MCA | CD28: < 1MCA | CH28: SIM | CJ28: SIM | CK28: em marcha | CP28: Av. Esplanada - Rua Araci - Rua Baltimore - Rua Canavieira - Rua da Conquista - Rua da Fazenda - Rua FiladElfia - Rua Iguape - Rua Itabuna - Rua JundiaI - Rua Pedro I - Rua Pedro II - Rua Pensilvânia - Rua Pontal do Sul - Rua Quieve - Rua UbatA - Rua Variante Barros JUnior (parte)
A29: EXPEDICIONARIOS | B29: =_xlfn.XLOOKUP(A:A,'Dados Elevatórias'!D:D,'Dados Elevatórias'!B:B) -> PL-RJB-EAT0066 | C29: EEAT (66) | D29: BAIXADA II | E29: Estrada dos Expedicionário, 1264, Paiol, Nilópolis - RJ, 26540-020 | F29: CABUIS | H29: NILOPOLIS | I29: 26540-023 | J29: INFORMAL | K29: 1 | L29: OPERACIONAL | M29: 12.5 | N29: 3530 | O29: RJB-11514 | P29: S6S-22-06-12,5 | Q29: RJB-06847 | R29: CRI | S29: / | T29: / | U29: SUBMERSA VERTICAL | W29: X | X29: VERTICAL | Y29: X | Z29: SUBMERSA | AA29: 24,5 | AB29: 75 | AC29: 220V | AE29: 400379484 | AF29: 5668080 | AH29: AGUA - ELEV - EXPEDICIONARIOS | AI29: EST EXPEDICIONARIOS SN EF1254 | AJ29: 100MM | AK29: 100MM | AP29: 215/214/216 | AQ29: 26.30.31 | AX29: 44962 | BH29: DLI | BI29: M40 | BJ29: X | BK29: X | BL29: X | BM29: X | BN29: 100A | BP29: 35A | BQ29: NÃO | BR29: SIM | BT29: 0 | BU29: 100A | BV29: 5A | BW29: NÃO | BX29: SIM | BY29: NÃO | BZ29: NÃO | CA29: NÃO | CB29: SIM | CH29: SIM | CJ29: SIM | CK29: em marcha | CO29: CABUIS | CP29: Rua dos ExpedicionArio (Trecho Rua JoAo Castro ao final da Rua), Rua Sargento Manoel Rodrigues (Trecho Rua Antonio P. de Carvalho A Rua Maestro D. do Carmo), Rua Maestro Djalma do Carmo (Trecho Rua Sargento Manoel Rodrigues ao final da Rua), Rua Trav. sargento Manoel Rodrigues, Trav. JosE das Chagas Barros, rua JoAo M. Santiago e pequenas Vilas desses trechos.
A30: FLORESTA MIRANDA | B30: =_xlfn.XLOOKUP(A:A,'Dados Elevatórias'!D:D,'Dados Elevatórias'!B:B) -> PL-RJB-EAT0065 | C30: EEAT (65) | D30: BAIXADA II | E30: RUA DOUTOR FLORESTA MIRANDA Nº 256 | F30: CENTRO | H30: NOVA IGUACU | I30: 26250-060 | J30: FORMAL | K30: 1 | L30: OPERACIONAL | M30: 5 | N30: 3510 | P30: 618 | Q30: RJB-00199 | R30: DANCOR | S30: 6.1 | T30: 154.94 | U30: ABRIGADA | X30: HORIZONTAL | Z30: CONV. | AA30: 17,01 | AB30: 40 | AC30: 220V | AE30: 411456713 | AF30: 4454750 | AH30: AGUA - BOOSTER - FLORESTA MIRANDA | AI30: R FLORESTA MIRANDA 256 | AJ30: 2POL | AK30: 2POL | AO30: 20 | AP30: 214214215 | AQ30: 9.10.10 | AR30: 4MCA | AS30: 52MCA | AT30: 214214215 | AU30: 8.8.9 | AV30: 4MCA | AW30: 50MCA | AX30: 45002 | AY30: 220X220X219 | AZ30: 17-17-19 | BA30: 3 | BB30: 20 | BC30: 220X220X219 | BD30: 41589 | BE30: 5 | BF30: 45 | BG30: 40785 | BJ30: X | BK30: X | BL30: X | BM30: X | BN30: 40A | BP30: 20A | BQ30: NÃO | BR30: SIM | BS30: NÃO | BT30: 0 | BU30: 40A | BV30: 5A | BW30: SIM | BX30: NÃO | BY30: NÃO | BZ30: NÃO | CA30: NÃO | CB30: SIM | CH30: SIM | CJ30: SIM | CK30: em marcha | CP30: Rua Anverino Floresta de Miranda (toda), Rua Darci Froes da Cruz (toda)
A31: FRANCISCO XAVIER | B31: =_xlfn.XLOOKUP(A:A,'Dados Elevatórias'!D:D,'Dados Elevatórias'!B:B) -> PL-RJB-EAT0082 | C31: EEAT (82) | D31: BAIXADA II | E31: RUA CAIOBA Nº 810 | F31: NOVA AMERICA | H31: NOVA IGUACU | I31: 26012-503 | J31: FORMAL | K31: 1 | L31: OPERACIONAL | M31: 7.5 | N31: 3480 | O31: RJB-11730 | P31: 645 | Q31: RJB- | R31: DANCOR | T31: - | U31: ABRIGADA | X31: HORIZONTAL | Z31: DELTA | AA31: 32.5 | AB31: 40 | AC31: 220V | AE31: 410417203 | AF31: 8268575-4 | AH31: AGUA - ELEV - MARACANA (VILA CAVA) | AI31: R FRANCISCO XAVIER 810 | AJ31: 75MM | AK31: 75MMM | AP31: 221/220/220 | AQ31: 20.22.20 | AR31: 1 | AS31: 40 | AV31: 1 | AW31: 45 | AX31: 44964 | AY31: 222X221X223 | AZ31: 14,5X15,5X16 | BB31: 50 | BF31: 60 | BG31: 42825 | BH31: X | BI31: X | BJ31: X | BK31: X | BL31: X | BM31: X | BN31: 125A | BP31: X | BQ31: NÃO | BR31: SIM | BS31: NÃO | BT31: 0 | BU31: 125A | BV31: X | BW31: SIM | BX31: NÃO | BY31: NÃO | BZ31: NÃO | CA31: NÃO | CB31: SIM | CC31: 1 MCA | CD31: < 1MCA | CH31: SIM | CJ31: SIM | CK31: em marcha | CP31: Rua Fernanda - Rua Flexas - Rua Joaquim Soares Neto - Rua Planaltina
A32: GAMA | B32: =_xlfn.XLOOKUP(A:A,'Dados Elevatórias'!D:D,'Dados Elevatórias'!B:B) -> PL-RJB-EAT0110 | C32: EEAT (110) | D32: BAIXADA II | E32: RUA A, SN EQ RUA GAMA | F32: CERÂMICA | H32: NOVA IGUACU | I32: 26030-200 | J32: FORMAL | K32: 1 | L32: OPERACIONAL | M32: 3 | N32: -- | O32: RJB-15660 | P32: R20-03 | Q32: RJB-15618 | R32: LEAO | U32: SUBMERSA VERTICAL | Z32: SUBMERSA | AA32: 10,8 | AB32: 23 | AC32: 220V | AE32: 430171491 | AF32: 9732192 | AH32: AGUA - ELEV - GAMA | AI32: R A SN SV BOMBA EQ R GAMA | AJ32: 100MM | AK32: 100MM | AP32: 217/217/218 | AQ32: 11.12.11 | AR32: 8MCA | AS32: 21MCA | AT32: 218/218/217 | AU32: 8.8.9 | AV32: 20MCA | AW32: 87MCA | AX32: 44962 | BH32: X | BI32: X | BJ32: X | BK32: X | BL32: X | BM32: X | BN32: 40A | BP32: X | BQ32: NÃO | BR32: SIM | BS32: NÃO | BT32: 0 | BU32: 40A | BV32: X | BW32: NÃO | BX32: SIM | BY32: NÃO | BZ32: NÃO | CA32: NÃO | CB32: SIM | CH32: SIM | CJ32: SIM | CK32: em marcha | CP32: Condomínio sito à Rua Oliveiros Rodrigues Alves
A33: GOLDEN GATE | B33: =_xlfn.XLOOKUP(A:A,'Dados Elevatórias'!D:D,'Dados Elevatórias'!B:B) -> PL-RJB-EAT0691 | C33: EEAT (691) | D33: BAIXADA II | E33: RUA AMAZOR MOREIRA PRISCO, sn. ESQUINA COM AV ABÍLIO AUGUSTO TÁVORA | F33: CENTRO | H33: NOVA IGUACU | I33: 26255-250 | J33: FORMAL | K33: 1 | L33: OPERACIONAL | M33: 7.5 | N33: 1715 | P33: 4X3X8 | R33: WORTHINGTON | S33: 7.7 | T33: 195.58 | U33: TUBULAO | V33: NÃO | W33: JM | X33: VERTICAL | Y33: FC | Z33: INLINE | AC33: 220V | AE33: 430001397 | AJ33: 100MM | AK33: 100MM | AP33: 220/222/219 | AQ33: 11.11.11 | AR33: 14MCA | AS33: 39MCA | AT33: 219/219/220 | AX33: 44964 | BH33: X | BI33: X | BJ33: X | BK33: X | BL33: X | BM33: X | BN33: 50A | BP33: X | BQ33: NÃO | BR33: SIM | BS33: SIM | BT33: 0 | BU33: 50A | BV33: 5A | BW33: SIM | BX33: NÃO | BY33: NÃO | BZ33: NÃO | CA33: NÃO | CB33: SIM | CH33: SIM | CJ33: SIM | CK33: em marcha
A34: GRAMA | B34: =_xlfn.XLOOKUP(A:A,'Dados Elevatórias'!D:D,'Dados Elevatórias'!B:B) -> PL-RJB-EAT0745 | C34: EEAT (745) | D34: BAIXADA II | E34: EST. DA GRAMA Nº 333 E/F (CIEP) CACILDA BECKER | F34: GRAMA | H34: NOVA IGUACU | I34: 26060-015 | J34: INFORMAL | K34: 1 | L34: OPERACIONAL | M34: 25 | N34: 3500 | O34: 60201192 | P34: 4X3X8 | R34: WORTHINGTON | S34: 6.02 | T34: 153 | U34: TUBULAO | V34: NÃO | W34: JM | X34: VERTICAL | Y34: FC | Z34: INLINE | AA34: 85,04 | AB34: 45 | AE34: 420149935 | AF34: 4784298 | AH34: AGUA - BOOSTER - GRAMA | AI34: EST GRAMA 333 | AP34: 208X209X210 | AQ34: 44X47X49 | AX34: 43279 | AY34: 209x209x216 | AZ34: 46-50-50 | BA34: 3 | BB34: 25 | BD34: 32-35-35 | BE34: 7 | BF34: 70 | BG34: 42088 | BW34: SIM | BX34: NÃO | BY34: NÃO | BZ34: NÃO | CB34: SIM | CC34: 1 MCA | CD34: < 1MCA | CO34: GRAMA | CP34: Estrada da Grama - Estrada Piteira - Rua "A" - Rua "B" - Rua "G" - Rua Abreu Filho - Rua Arnaldo - Rua BelizArio Pena - Rua Benjamim Batista - Rua Daniel Almeida - Rua Diva - Rua Ednelson de Souza Brasiliano - Rua Eduardo Meireles - Rua EmIlia Mendes - Rua Esterlita Ling - Rua Gisela - Rua Lauro Carvalho Barros - Rua Minas Gerais - Rua ParA - Rua Paulo Cezar - Rua Presidente Leme - Rua Renilda Mayer - Rua Rocha Faria - Rua Santa BArbara - Rua SAo Paulo - Rua Torres Homem - Rua Zaida - Travessa 4 - Travessa 5
A35: GRAMA | B35: =_xlfn.XLOOKUP(A:A,'Dados Elevatórias'!D:D,'Dados Elevatórias'!B:B) -> PL-RJB-EAT0745 | CO35: GENECIANO
A36: HADDOCK LOBO | B36: =_xlfn.XLOOKUP(A:A,'Dados Elevatórias'!D:D,'Dados Elevatórias'!B:B) -> PL-RJB-EAT1013 | C36: EEAT (1013) | D36: BAIXADA II | E36: Rua Haddock Lobo, EF 2 | F36: VILA DO TINGUA | H36: QUEIMADOS | I36: 26385-380 | J36: FORMAL | K36: 1 | L36: OPERACIONAL | M36: 7.5 | N36: 3500 | P36: 645 | R36: DANCOR | S36: 7.48 | T36: 190 | U36: ABRIGADA | Z36: CONV. | AA36: 32.5 | BW36: SIM | BX36: NÃO | BY36: NÃO | BZ36: NÃO | CB36: SIM
A37: INDIA PORTUGUESA | B37: =_xlfn.XLOOKUP(A:A,'Dados Elevatórias'!D:D,'Dados Elevatórias'!B:B) -> PL-RJB-EAT0087 | C37: EEAT (87) | D37: BAIXADA II | E37: RUA ANTONIO PEREIRA S/Nº | F37: CENTRO | H37: NILOPOLIS | I37: 26540-000 | J37: FORMAL | K37: 1 | L37: OPERACIONAL | M37: 7.5 | N37: -- | O37: RJB-04571 | P37: R28-06 | Q37: RJB-04549 | R37: LEAO | S37: LEAO | U37: SUBMERSA VERTICAL | W37: X | X37: X | Y37: X | Z37: SUBMERSA | AA37: 10,4 | AB37: 60 | AC37: 220V | AE37: 411112102 | AF37: 2580837 | AH37: AGUA - BOOSTER - INDIA PORTUGUESA (CONSUMO BASE 2013) | AJ37: 100MM | AK37: 75MM | AP37: 220/220/220 | AQ37: 16.16.16 | AR37: 14 | AS37: 55 | AT37: 219/220/220 | AU37: 13.12.13 | AX37: 44953 | AY37: 217X218X219 | AZ37: 15X16X16 | BA37: 12 | BB37: 60 | BC37: 218X220X221 | BD37: 12X11X12 | BE37: 16 | BF37: 75 | BG37: 43429 | BH37: X | BI37: X | BJ37: X | BK37: X | BL37: X | BM37: X | BN37: 125A | BP37: X | BQ37: NÃO | BR37: SIM | BS37: NÃO | BT37: 0 | BU37: 125A | BV37: X | BW37: NÃO | BX37: SIM | BY37: NÃO | BZ37: NÃO | CA37: NÃO | CB37: SIM | CH37: SIM | CJ37: SIM | CK37: EM MARCHA
A38: ITAPEMIRIM | B38: =_xlfn.XLOOKUP(A:A,'Dados Elevatórias'!D:D,'Dados Elevatórias'!B:B) -> PL-RJB-EAT0109 | C38: EEAT (109) | D38: BAIXADA II | E38: ESTR. DE IGUACU E/F LOTE 2 QUADRA 18 B (AV. DO RIO OURO E/F AO Nº 78) | F38: PARQUE BOA ESPERANCA | H38: NOVA IGUACU | I38: 26060-410 | J38: INFORMAL | K38: 1 | L38: OPERACIONAL | M38: 20 | N38: 3500 | O38: RJB-04092 | P38: 3X2X6 | Q38: S/TAG | R38: WORTHINGTON | S38: 6.5 | T38: 165.1 | U38: ABRIGADA | W38: JM | X38: HORIZONTAL | Y38: FC | Z38: DELTA | AA38: 80 | AB38: 60 | AC38: 220V | AE38: 413269259 | AF38: 5027615 | AH38: AGUA - BOOSTER - ITAPEMIRIM | AI38: AV ITAPEMIRIM SN LD815 | AJ38: 75MM | AK38: 75MM | AP38: 217219218 | AX38: 44956 | AY38: 222X222X222 | AZ38: 27X27X27 | BB38: 55 | BG38: 42653 | BH38: X | BI38: X | BJ38: X | BK38: X | BL38: X | BM38: X | BN38: 125A | BP38: X | BQ38: NÃO | BR38: SIM | BS38: NÃO | BT38: 0 | BU38: 125A | BV38: X | BW38: SIM | BX38: NÃO | BY38: NÃO | BZ38: NÃO | CA38: NÃO | CB38: SIM | CC38: 1 MCA | CD38: < 1MCA | CH38: SIM | CJ38: SIM | CK38: EM MARCHA | CO38: BOA ESPERANÇA | CP38: Rua Benjamim Ferreira _ Rua Boa EsperanCa - Rua Cedro Rosa - Rua George Sandi - Rua Ipe Roxo - Rua Itapemirim - Rua Jacaranda Branco - Rua Tacaronda - Rua Vinhatico
A39: ITORORÓ | B39: =_xlfn.XLOOKUP(A:A,'Dados Elevatórias'!D:D,'Dados Elevatórias'!B:B) -> PL-RJB-EAT0748 | C39: EEAT (748) | D39: BAIXADA II | E39: RUA ITORORO, SN EF N8 | F39: AUSTIN | H39: QUEIMADOS | I39: 26385-500 | J39: INFORMAL | K39: 1 | L39: OPERACIONAL | M39: 1.5 | N39: -- | O39: RJB-16775 | P39: R7-04 | Q39: RJB-16967 | R39: LEAO | U39: SUBMERSA VERTICAL | Z39: SUBMERSA | AA39: 6.5 | AC39: 220V | AJ39: 100MM | AK39: 100MM | AP39: 216216217 | AX39: 44957 | BH39: X | BI39: X | BJ39: X | BK39: X | BL39: X | BM39: X | BN39: 125A | BP39: X | BQ39: NÃO | BR39: SIM | BS39: NÃO | BT39: 0 | BU39: 125A | BV39: X | BW39: NÃO | BX39: SIM | BY39: NÃO | BZ39: NÃO | CA39: NÃO | CB39: SIM | CH39: SIM | CJ39: SIM | CK39: EM MARCHA
A40: IVO MIRANDA | B40: =_xlfn.XLOOKUP(A:A,'Dados Elevatórias'!D:D,'Dados Elevatórias'!B:B) -> PL-RJB-EAT0053 | C40: EEAT (53) | D40: BAIXADA II | E40: RUA IVO MIRANDA ESQ. AV. GOVERNADOR CELSO PECANHA | F40: BANCO DE AREIA | H40: MESQUITA | I40: 26574-770 | J40: INFORMAL | K40: 1 | L40: OPERACIONAL | M40: 10 | N40: 3535 | O40: - | P40: S40-04 | R40: LEAO | U40: SUBMERSA VERTICAL | W40: X | X40: X | Y40: X | Z40: SUBMERSA | AA40: 55 | AB40: 45 | AC40: 220V | AE40: 421142751 | AF40: 8541558 | AH40: AGUA - ELEV- IVO DE MIRANDA | AI40: R IVO MIRANDA MONTES SN CN.CEDAE | AJ40: 100MM | AK40: 100MM | AN40: 2860 | AP40: 205/205/204 | AQ40: 28.29.27 | AR40: 10MCA | AS40: 29MCA | AT40: 205/205/204 | AU40: 16/17/17 | AX40: 44963 | AY40: 214X212X213 | AZ40: 26-27-28 | BA40: 4 | BB40: 50 | BC40: 214X212X213 | BD40: 24-24-26 | BE40: 5 | BF40: 85 | BG40: 42403 | BH40: X | BI40: X | BJ40: X | BK40: X | BL40: X | BM40: X | BN40: 40A | BP40: X | BQ40: NÃO | BR40: SIM | BS40: NÃO | BT40: 0 | BU40: 40A | BV40: X | BW40: NÃO | BX40: SIM | BY40: NÃO | BZ40: NÃO | CA40: NÃO | CB40: SIM | CH40: SIM | CJ40: SIM | CK40: EM MARCHA | CL40: 12.4 | CM40: 37 | CO40: IVO MIRANDA
B41: PL-RJB-EAT0053 | CO41: BANCO DE AREIA
A42: JOSE VIRGILIO DO PRADO | B42: =_xlfn.XLOOKUP(A:A,'Dados Elevatórias'!D:D,'Dados Elevatórias'!B:B) -> PL-RJB-EAT0694 | C42: EEAT (694) | D42: BAIXADA II | E42: R VER JOSE VIRGILIO DO PRADO 1 SN | F42: VILA NASCENTE | H42: QUEIMADOS | I42: 26325-050 | J42: INFORMAL | K42: 1 | L42: OPERACIONAL | M42: 15 | N42: 3515 | O42: RJB-03111 | P42: BC-21 | Q42: RJB-03110 | R42: SCHNEIDER | U42: ABRIGADA | Z42: CONV. | AC42: 220V | AJ42: 2POL | AK42: 2POL | AP42: 219/218/217 | AQ42: 18.19.19 | AR42: 18MCA | AS42: 70MCA | AT42: 219/218/217 | AU42: 21/23/23 | AW42: 74MCA | AX42: 1/27/2023 | BJ42: X | BK42: X | BL42: X | BM42: X | BN42: 80A | BP42: 25A | BQ42: NÃO | BR42: SIM | BS42: NÃO | BT42: 0 | BU42: 80A | BV42: X | BW42: NÃO | BX42: NÃO | BY42: SIM | BZ42: NÃO | CA42: NÃO | CB42: SIM | CH42: SIM | CJ42: SIM | CK42: EM MARCHA
A43: LIBANEA | B43: =_xlfn.XLOOKUP(A:A,'Dados Elevatórias'!D:D,'Dados Elevatórias'!B:B) -> PL-RJB-EAT0046 | C43: EEAT (46) | D43: BAIXADA II | E43: RUA LIBANEA C/ RUA GOVERNADOR CELSO PECANHA | F43: CENTRO | H43: MESQUITA | I43: 26551-120 | J43: FORMAL | K43: 1 | L43: OPERACIONAL | M43: 6 | N43: 3330 | P43: S6S-18-04-05 | Q43: RJB-04936 | R43: CRI | S43: / | T43: / | U43: SUBMERSA VERTICAL | W43: X | X43: X | Y43: X | Z43: SUBMERSA | AA43: 15.73 | AB43: 40 | AC43: 220V | AE43: 420187783 | AF43: 6144582 | AH43: AGUA - ELEV - LIBANEA | AI43: R LIBANIA SN EF15 EF15A | AJ43: 100MM | AK43: 100MM | AP43: 217/218/220 | AQ43: 17.17.14 | AR43: 10MCA | AS43: 50MCA | AT43: 217/218/220 | AU43: 12.09.11 | AW43: 64MCA | AX43: 44963 | AY43: 205X205X203 | AZ43: 9X10X10 | BA43: 1 | BB43: 25 | BC43: 206X202X202 | BD43: 18X18X16 | BE43: 5 | BF43: 60 | BG43: 42730 | BJ43: X | BK43: X | BL43: X | BM43: X | BN43: X | BO43: 32A | BP43: 25A | BQ43: NÃO | BR43: SIM | BS43: NÃO | BT43: X | BU43: X | BV43: X | BW43: NÃO | BX43: NÃO | BY43: SIM | BZ43: NÃO | CA43: NÃO | CB43: SIM | CH43: SIM | CJ43: SIM | CK43: EM MARCHA
A44: LUCIO TAVARES | B44: =_xlfn.XLOOKUP(A:A,'Dados Elevatórias'!D:D,'Dados Elevatórias'!B:B) -> PL-RJB-EAT0043 | C44: EEAT (43) | D44: BAIXADA II | E44: RUA LUCIO TAVARES | F44: CENTRO | H44: NILOPOLIS | I44: 26530-060 | J44: FORMAL | K44: 1 | L44: OPERACIONAL | M44: 12 | N44: 3500 | O44: - | P44: S35-04 | Q44: RJB-00181 | R44: LEAO | S44: / | T44: / | U44: SUBMERSA VERTICAL | W44: X | X44: X | Y44: X | Z44: SUBMERSA | AA44: 37.5 | AB44: 36 | AC44: 220V | AE44: 400380547 | AF44: 6923505 | AH44: AGUA - ELEV - LUCIO TAVARES | AI44: R LUCIO TAVARES SN EF329 | AJ44: 150MM | AK44: 150MM | AP44: 220/220/220 | AQ44: 25.22.24 | AR44: 15MCA | AS44: 45MCA | AT44: 219/220/220 | AU44: 28/26/22 | AW44: 86MCA | AX44: 44963 | AY44: 219X200X219 | AZ44: 26X27X27 | BA44: 3.5 | BB44: 50 | BC44: 219X218X221 | BD44: 38X39X38 | BE44: 5 | BF44: 65 | BG44: 43420 | BH44: DIL | BI44: M150 | BJ44: X | BK44: X | BL44: X | BM44: X | BN44: 63A | BP44: 40A | BQ44: NÃO | BR44: SIM | BS44: SIM | BT44: 0 | BU44: 63A | BV44: 5A | BW44: NÃO | BX44: NÃO | BY44: SIM | BZ44: NÃO | CA44: NÃO | CB44: SIM | CH44: SIM | CJ44: SIM | CK44: EM MARCHA | CP44: Rua LUcio Tavares (Trecho Rua AntOnio JosE Bittencourt A Av. Oswaldo Cruz), Rua Orlando Bernardino Lopes (Trecho Rua Carmela Dutra ao final da Rua), Rua Dr. Silvio, Rua AntOnio Cardoso Leal (Trecho Rua AntOnio Bittencourt A Av. Oswaldo Cruz), Rua Dr. Rufino GonCalves Ferreira (Trecho Rua AntOnio JosE Bitencourt A Av. Oswaldo Cruz) e pequenas Vilas desse trecho
A45: MACIEL | B45: =_xlfn.XLOOKUP(A:A,'Dados Elevatórias'!D:D,'Dados Elevatórias'!B:B) -> PL-RJB-EAT0747 | C45: EEAT (747) | D45: BAIXADA II | E45: R. Ver. José Virgílio do Prado, 79 - Vila Nascente, Queimados - RJ, 26325-050 | F45: CENTRO | H45: QUEIMADOS | I45: 26393-060 | J45: INFORMAL | K45: 1 | L45: OPERACIONAL | M45: 15 | N45: 3515 | P45: 680 | Q45: RJB-03110 | R45: DANCOR | U45: ABRIGADA | Z45: CONV. | AA45: 45 | AC45: 220V | AE45: 420631920 | AF45: 8878387 | AH45: AGUA - BVOLANTE - MACIEL | AI45: R MACIEL SN EF113 | AJ45: 2POL | AK45: 2POL | AP45: 219/218/217 | AQ45: 18.19.19 | AR45: 18MCA | AS45: 70MCA | AT45: 219/218/217 | AU45: 21.23.23 | AW45: 74MCA | AX45: 44953 | BH45: DIL | BI45: M65 | BJ45: X | BK45: X | BL45: X | BM45: X | BN45: 80A | BP45: 25A | BQ45: NÃO | BR45: SIM | BS45: NÃO | BT45: 0 | BU45: 80A | BV45: X | BW45: SIM | BX45: NÃO | BY45: NÃO | BZ45: NÃO | CA45: NÃO | CB45: SIM | CC45: 1 MCA | CD45: < 1MCA | CH45: SIM | CJ45: SIM | CK45: EM MARCHA
A46: MANOEL REIS | B46: =_xlfn.XLOOKUP(A:A,'Dados Elevatórias'!D:D,'Dados Elevatórias'!B:B) -> PL-RJB-EAT0040 | C46: EEAT (40) | D46: BAIXADA II | E46: RUA MANOEL REIS, ESQUINA COM RUA JOAO PESSOA | F46: NILOPOLIS | H46: NILOPOLIS | I46: 26510-112 | J46: FORMAL | K46: 1 | L46: OPERACIONAL | M46: 5 | N46: -- | O46: RJB-19612 | P46: R28-02 | Q46: RJB-19615 | R46: LEAO | T46: - | U46: SUBMERSA VERTICAL | W46: X | X46: X | Y46: X | Z46: SUBMERSA | AA46: 27,55 | AB46: 25 | AC46: 220V | AE46: 414605743 | AF46: 5187019 | AH46: AGUA - ELEV - MANOEL REIS | AI46: EST DR MANOEL REIS SN EF395 | AJ46: 75MM | AK46: 75MM | AP46: 223/222/222 | AQ46: 19.20.17 | AR46: 10MCA | AS46: 30MCA | AT46: 223/222/222 | AU46: 14.15.14 | AV46: 17MCA | AW46: 58MCA | AX46: 44960 | AY46: 215X217X218 | AZ46: 11,2X2,5X13 | BA46: 6 | BB46: 27 | BE46: 9 | BF46: 50 | BG46: 42717 | BH46: X | BI46: X | BJ46: X | BK46: X | BL46: X | BM46: X | BN46: 35A | BP46: X | BQ46: NÃO | BR46: SIM | BS46: NÃO | BT46: 0 | BU46: 35A | BV46: X | BW46: NÃO | BX46: SIM | BY46: NÃO | BZ46: NÃO | CA46: NÃO | CB46: SIM | CH46: SIM | CJ46: SIM | CK46: EM MARCHA | CP46: Area 1: Rua JosE do PatrocInio (trecho Rua Alberto Teixeira da Cunha A Av. Mirandela), Rua VirgIlio R. de Oliveira (trecho Rua Alberto Teixeira da Cunha A Av. Mirandela), Rua Jornalista Hungria (trecho Rua Alberto Teixeira da Cunha A Av. Mirandela, Rua Alberto Teixeira da Cunha (trecho Rua JoAo Pessoa A Rua wallace Paes Leme). Area 2: Rua JosE do PatrocInio (trecho Rua AntOnio JoAo MendonCa A Rua Alberto Teixeira da Cunha), Rua VirgIlio R. de Oliveira (trecho Rua Antonio JoAo MendonCa A Rua Alberto Teixeira da Cunha), Rua Manoel Brigido Tinoco, Rua Cap. Manoel de Melo, Rua JoAo Pessoa (trecho Rua Antonio JoAo MendonCa A Rua Alberto Teixeira da Cunha), Rua Geovana Santana Drumond, Rua Antonio JoAo MendonCa (trecho Rua JoAo Pessoa A Rua Wallace Paes Leme). Area 3: Rua Feliciano SodrE, Rua FlorianOpolis, Rua Maria Teresa de Paula, Rua Maria Chambarele, Rua JoAo Evangelista de Carvalho (trecho Rua Dr. Manoel Reis A Rua Antonio JoAo MendonCa).
A47: MAURICIA BORGES | B47: =_xlfn.XLOOKUP(A:A,'Dados Elevatórias'!D:D,'Dados Elevatórias'!B:B) -> PL-RJB-EAT0032 | C47: EEAT (32) | D47: BAIXADA II | E47: RUA MAURICIA BORGES, 303 | F47: BANCO DE AREIA | H47: MESQUITA | I47: 26564-020 | J47: FORMAL | K47: 1 | L47: OPERACIONAL | M47: 7 | N47: 3510 | O47: RJB-13402 | P47: R20-04 | Q47: RJB-13425 | R47: LEAO | T47: - | U47: SUBMERSA VERTICAL | W47: X | X47: X | Y47: X | Z47: SUBMERSA | AA47: 20 | AB47: 50 | AC47: 220V | AE47: 420187776 | AF47: 6141673 | AH47: AGUA - ELEV - MAURICIA BORGES | AI47: TR MAURICIA BORGES SN PX303 | AJ47: 100MM | AK47: 100MM | AP47: 220/220/220 | AQ47: 13.14.10 | AR47: 7MCA | AS47: 30MCA | AT47: 223/224/222 | AU47: 10.11.10 | AV47: 9MCA | AW47: 52MCA | AX47: 44957 | AY47: 220X220X218 | AZ47: 15X15X16 | BB47: 13 | BC47: 220X220X218 | BE47: 5 | BF47: 60 | BG47: 42610 | BH47: DIL | BI47: M40 | BJ47: X | BK47: X | BL47: X | BM47: X | BN47: X | BO47: 32A | BP47: 22A | BQ47: NÃO | BR47: SIM | BS47: NÃO | BT47: X | BU47: X | BV47: X | BW47: NÃO | BX47: NÃO | BY47: SIM | BZ47: NÃO | CA47: NÃO | CB47: SIM | CH47: SIM | CJ47: SIM | CK47: EM MARCHA
A48: MELVIN JONES | B48: =_xlfn.XLOOKUP(A:A,'Dados Elevatórias'!D:D,'Dados Elevatórias'!B:B) -> PL-RJB-EAT0031 | C48: EEAT (31) | D48: BAIXADA II | E48: RUA MELVIM JONES | F48: CENTRO | H48: NOVA IGUACU | I48: 26221-130 | J48: FORMAL | K48: 1 | L48: OPERACIONAL | M48: 2 | N48: 3500 | O48: RJB-18602 | P48: R11-3-2CV | Q48: RJB-15651 | R48: LEÃO | S48: - | T48: - | U48: SUBMERSA VERTICAL | W48: X | X48: X | Y48: X | Z48: SUBMERSA | AA48: ? | AB48: ? | AC48: 220V | AE48: 413730985 | AF48: 5028143 | AH48: AGUA - BOOSTER - MELVIM JONES | AI48: TR MELVIM JONES SN LD41 | AJ48: 75MM | AK48: 75MM | AP48: 217/219/219 | AQ48: 5.6.5 | AR48: 22MCA | AS48: 70MCA | AT48: 220/219/219 | AX48: 44963 | BH48: EATON DIL | BI48: M25 | BJ48: X | BK48: X | BL48: X | BM48: X | BN48: X | BO48: 40A | BP48: 16A | BQ48: NÃO | BR48: SIM | BS48: NÃO | BT48: X | BU48: X | BV48: X | BW48: NÃO | BX48: NÃO | BY48: SIM | BZ48: NÃO | CA48: NÃO | CB48: SIM | CH48: SIM | CJ48: SIM | CK48: EM MARCHA | CP48: Rua Melvin Jones
A49: MENA BARRETO | B49: =_xlfn.XLOOKUP(A:A,'Dados Elevatórias'!D:D,'Dados Elevatórias'!B:B) -> PL-RJB-EAT0030 | C49: EEAT (30) | D49: BAIXADA II | E49: RUA MENA BARRETO, ESQUINA COM RUA JOAO DE CASTRO | F49: NOVO HORIZONTE | H49: NILOPOLIS | I49: 26535-331 | J49: INFORMAL | K49: 1 | L49: OPERACIONAL | M49: 2.5 | N49: 3530 | P49: R28-05 | R49: LEAO | T49: - | U49: SUBMERSA VERTICAL | W49: X | X49: X | Y49: X | Z49: SUBMERSA | AA49: 22,10 | AB49: 75 | AC49: 220V | AE49: 414857558 | AF49: 5789840 | AH49: AGUA - BVOLANTE - MENA BARRETO | AI49: EST GAL MENA BARRETO SN EF863 | AP49: 215/214/215 | AQ49: 20/19/20 | AX49: 44956 | AY49: 209X208X205 | AZ49: 34X33X32 | BA49: 11 | BB49: 60 | BC49: 209X208X205 | BD49: 31X32X33 | BE49: 15 | BF49: 120 | BG49: 42753 | BJ49: X | BK49: X | BL49: X | BM49: X | BN49: 50A | BP49: 34A | BQ49: NÃO | BR49: SIM | BS49: NÃO | BT49: 0 | BU49: 50A | BV49: X | BW49: NÃO | BX49: NÃO | BY49: SIM | BZ49: NÃO | CA49: NÃO | CB49: SIM | CH49: SIM | CJ49: SIM | CK49: EM MARCHA | CO49: CABUIS | CP49: Estrada Mena Barreto (trecho), Rua Nadir Trindade (trecho), Rua Natividade (trecho), Rua OtacIlio Pessoa (trecho).
A50: MESQUITA G1/G2 | B50: PL-RJB-EAT0086 | C50: EEAT (86) | D50: BAIXADA II | E50: RUA AUGUSTO CARDOSO,Nº 234 AO LADO DO COLEGIO ANA NERI MESQUITA | F50: COREIA | H50: MESQUITA | I50: 26556-030 | J50: INFORMAL | K50: 1 | L50: OPERACIONAL | M50: 100 | N50: 3560 | P50: 4DBE104 | Q50: RJB-11656 | R50: WORTHINGTON | S50: 8.32 | T50: 211.33 | U50: ABRIGADA | X50: VERTICAL | Y50: FC | Z50: DELTA | AA50: 233,8 | AB50: 80 | AC50: 220V/MT | AE50: 400131474 | AF50: 7267348 | AH50: AGUA - BOOSTER - MESQUITA | AI50: R AUGUSTO CARDOSO SN | AJ50: DN45X200 | AK50: DN45X200 | AP50: 221/222/221 | AQ50: 203205196 | AR50: 18MCA | AS50: 94MCA | AT50: 221/222/221 | AU50: 153170157 | AW50: 110MCA | AX50: 45079 | AY50: G1(217X216X218)G2(217X216X218) | AZ50: G1(228X239X240)G2(194X197X201) | BA50: G1(22)G2(22) | BB50: G1(94)G2(57) | BC50: G1(219X220X220) G2(219X220X220) | BD50: G1(165X180X172) G2(146X149X155) | BE50: G1(22)G2(24) | BF50: G1(113)G2(101) | BG50: 43355 | BH50: X | BI50: X | BJ50: X | BK50: X | BL50: X | BM50: X | BN50: 710A | BP50: X | BQ50: NÃO | BR50: SIM | BS50: SIM | BT50: 0 | BU50: 710A | BV50: X | BW50: NÃO | BX50: SIM | BY50: NÃO | BZ50: NÃO | CA50: NÃO | CB50: SIM | CH50: SIM | CJ50: SIM | CK50: EM MARCHA | CO50: CORÉIA | CP50: Ruas Guararema, guaraUna, JapuIra, Itacy, Capivari, Patativa, Uruguai, Campestre, Siriema, PompIlio, Rua da Valam Quito, Canavial, Arrozal, Javali, Paraguai, JosE Dias GuimarAes, JardinOpolis, Pintassilgo, Araripe, GuaporE, Luanda, Capivara
A51: MESQUITA G1/G2 | B51: PL-RJB-EAT0086 | C51: EEAT (86) | D51: BAIXADA II | E51: RUA AUGUSTO CARDOSO,Nº 234 AO LADO DO COLEGIO ANA NERI MESQUITA | F51: COREIA | H51: MESQUITA | I51: 26556-030 | J51: INFORMAL | K51: 2 | L51: RESERVA | M51: 100 | N51: 3560 | O51: RJB-11657 | P51: 6X4X10*3DBE103 | Q51: RJB-11659 | R51: WORTHINGTON | S51: 8.34 | T51: 211.84 | U51: ABRIGADA | X51: VERTICAL | Y51: FC | Z51: DELTA | AA51: 270 | AB51: 70 | AC51: 220V/MT | AE51: 400131474 | AF51: 7267348 | AH51: AGUA - BOOSTER - MESQUITA | AI51: R AUGUSTO CARDOSO SN | AJ51: DN45X200 | AK51: DN45X200 | AP51: 221/220/222 | AR51: 33MCA | BH51: EATON DIL | BI51: M225A | BJ51: EATON DIL | BK51: M185 | BL51: SIEMENS | BM51: 3TFT50 | BN51: 400A | BP51: 160A | BQ51: SIM | BR51: SIM | BS51: SIM | BT51: 0 | BU51: 400A | BV51: X | BW51: NÃO | BY51: NÃO | BZ51: NÃO | CA51: NÃO | CB51: SIM | CH51: SIM | CJ51: SIM | CK51: EM MARCHA | CO51: CORÉIA | CP51: Ruas Guararema, guaraUna, JapuIra, Itacy, Capivari, Patativa, Uruguai, Campestre, Siriema, PompIlio, Rua da Valam Quito, Canavial, Arrozal, Javali, Paraguai, JosE Dias GuimarAes, JardinOpolis, Pintassilgo, Araripe, GuaporE, Luanda, Capivara
A52: MORRO DA COCADA | B52: =_xlfn.XLOOKUP(A:A,'Dados Elevatórias'!D:D,'Dados Elevatórias'!B:B) -> PL-RJB-EAT0068 | C52: EEAT (68) | D52: BAIXADA II | E52: RUA DONA ORMINDA E/F AO Nº 23 ESQ. C/ RUA FLORA DE ARAUJO | F52: PRATA | H52: NOVA IGUACU | I52: 26010-450 | J52: FORMAL | K52: 1 | L52: OPERACIONAL | M52: 7.5 | N52: 3354 | O52: - | P52: S65-03 | R52: LEAO | T52: - | U52: SUBMERSA VERTICAL | W52: X | X52: X | Y52: X | Z52: SUBMERSA | AA52: 70 | AB52: 30 | AC52: 220V | AF52: 7254021 | AH52: AGUA - ELEV - MORRO DA COCADA | AI52: R DONA ORMINDA SN PX25 | AJ52: 150MM | AK52: 150MM | AP52: 215/215/215 | AQ52: 21.20.21 | AR52: 1MCA | AS52: 13MCA | AT52: 215/216/217 | AU52: 19.19.18 | AV52: 11MCA | AW52: 62MCA | AX52: 44957 | AY52: 220X218X218 | AZ52: 28X26X24 | BA52: 8 | BB52: 15 | BC52: 220X218X218 | BD52: 13X14X13 | BE52: 12 | BF52: 37 | BG52: 43545 | BH52: X | BI52: X | BJ52: X | BK52: X | BL52: X | BM52: X | BN52: 80A | BP52: X | BQ52: NÃO | BR52: SIM | BS52: NÃO | BT52: 0 | BU52: 80A | BV52: X | BW52: NÃO | BX52: SIM | BY52: NÃO | BZ52: NÃO | CA52: NÃO | CB52: SIM | CH52: SIM | CJ52: SIM | CK52: EM MARCHA
A53: MORRO DA MOENDA | B53: =_xlfn.XLOOKUP(A:A,'Dados Elevatórias'!D:D,'Dados Elevatórias'!B:B) -> PL-RJB-EAT0039 | C53: EEAT (39) | D53: BAIXADA II | E53: RUA MANOEL RODRIGUES SN | F53: CACUIA | H53: NOVA IGUACU | I53: 26030-245 | J53: INFORMAL | K53: 1 | L53: OPERACIONAL | M53: 8 | N53: 3500 | O53: RJB-06932 | P53: S40-06 | Q53: RJB-06929 | R53: LEAO | T53: - | U53: SUBMERSA VERTICAL | W53: X | X53: X | Y53: X | Z53: SUBMERSA | AA53: 30,61 | AB53: 35 | AC53: 220V | AE53: 420160768 | AF53: 6098958 | AH53: AGUA - BOOSTER - MORRO DA MOENDA | AI53: R C SN EF21 | AJ53: 100MM | AK53: 100MM | AP53: 214/215/214 | AX53: 44942 | AY53: 213X214X214 | AZ53: 15X15X15 | BB53: 20 | BC53: 213X214X214 | BD53: 9X16X11 | BE53: 45689 | BF53: 50 | BG53: 42743 | BH53: X | BI53: X | BJ53: X | BK53: X | BL53: X | BM53: X | BN53: 160A | BP53: X | BQ53: NÃO | BR53: SIM | BS53: NÃO | BT53: 0 | BU53: 160A | BV53: X | BW53: NÃO | BX53: SIM | BY53: NÃO | BZ53: NÃO | CA53: NÃO | CB53: SIM | CH53: SIM | CJ53: SIM | CK53: EM MARCHA | CO53: MOENDA | CP53: Rua Altinopolis, Rua Jeronimo de Ornelas, Rua Caninare, Rua Almirante Pestana, Rua Dante Santoro, Rua 7 Barras, Rua Wilde Lustosa, Rua Tambaquim.
A54: MORRO DO TEMPERO | B54: =_xlfn.XLOOKUP(A:A,'Dados Elevatórias'!D:D,'Dados Elevatórias'!B:B) -> PL-RJB-EAT0738 | C54: EEAT (738) | D54: BAIXADA II | E54: RUA ARAGUÁ ESQ. COM RUA ARAPÁ | F54: AUSTIN | H54: NOVA IGUACU | I54: 26086-040 | J54: INFORMAL | K54: 1 | L54: OPERACIONAL | M54: 12 | N54: 3500 | P54: S65-03 | R54: LEAO | U54: SUBMERSA VERTICAL | Z54: SUBMERSA | AA54: 30 | AC54: 220V | AJ54: 150MM | AK54: 150MM | AP54: 215/216/216 | AQ54: 32.33.33 | AR54: 5MCA | AS54: 32MCA | AT54: 216/216/216 | AU54: 36.36.36 | AV54: 9MCA | AW54: 58MCA | AX54: 44960 | BH54: X | BI54: X | BJ54: X | BK54: X | BL54: X | BM54: X | BN54: 125A | BP54: X | BQ54: NÃO | BR54: SIM | BS54: NÃO | BT54: 0 | BU54: 1225A | BV54: X | BW54: NÃO | BX54: SIM | BY54: NÃO | BZ54: NÃO | CA54: NÃO | CB54: SIM | CC54: 5 MCA | CD54: 1 MCA | CH54: SIM | CJ54: SIM | CK54: EM MARCHA
A55: NILO PEÇANHA (CEMITERIO) | B55: PL-RJB-EAT0024 | C55: EEAT (24) | D55: BAIXADA II | E55: RUA NILO PECANHA (CEMITERIO) | F55: NILOPOLIS | H55: NILOPOLIS | I55: 26545-202 | J55: FORMAL | K55: 1 | L55: OPERACIONAL | M55: 2.5 | N55: -- | O55: - | P55: BHS511-02 | Q55: RJB-05516 | R55: EBARA | T55: - | U55: SUBMERSA VERTICAL | W55: X | X55: X | Y55: X | Z55: SUBMERSA | AA55: 15,31 | AB55: 25 | AC55: 220V | AE55: 400375870 | AF55: 8402966 | AH55: AGUA - ELEV - NILO PECANHA | AI55: AV NILO PECANHA SN EF826 | AJ55: 100MM | AK55: 150MM | AP55: 218/218/217 | AQ55: 12.12.12 | AR55: 27MCA | AS55: 32MCA | AT55: 218/217/217 | AU55: 10.11.10 | AW55: 48MCA | AX55: 44956 | BH55: DIL | BI55: M32-10 | BJ55: X | BK55: X | BL55: X | BM55: X | BN55: 63A | BP55: 14A | BQ55: NÃO | BR55: SIM | BS55: SIM | BT55: 0 | BU55: 63A | BV55: 5A | BW55: NÃO | BX55: NÃO | BY55: SIM | BZ55: NÃO | CA55: NÃO | CB55: SIM | CH55: SIM | CJ55: SIM | CK55: EM MARCHA | CP55: Rua Deputado andrade Figueira (trecho Rua Nilo PeCanha A Rua Cândido), Rua Cândida (trecho Rua amadeu Lara a Rua joAo de Castro), Rua Amadeu Lara (trecho de Rua Cândido atE a Rua Nilo PeCanaha), Rua Dulce (trecho Rua Cândido atE a Rua Nilo PeCanha), Rua CapitAo alfredo Antunes (trecho Rua JosE c. GuimarAes), Rua Fernando GonCalves de Almeida (Rua Nilo PeCanha a Rua JosE Couto GuimarAes) e pequenas vilas deste trecho
A56: NOEMIA VIEIRA | B56: PL-RJB-EAT0124 | C56: EEAT (124) | D56: BAIXADA II | E56: AV. ABILIO AUGUSTO TAVORA ESQU. C/RUA NOEMIA VIEIRA E/F Nº 171 | F56: JARDIM ALVORADA | H56: NOVA IGUACU | I56: 26275-580 | J56: FORMAL | K56: 1 | L56: OPERACIONAL | M56: 30 | N56: 3500 | O56: 80201046 | P56: 3X11/2X10 | R56: WORTHINGTON | S56: 8.74 | T56: 222 | U56: TUBULAO | V56: SIM | W56: JM | X56: VERTICAL | Y56: FC | Z56: INLINE | AA56: 48,47 | AB56: 120 | AC56: 220V | AE56: 413341469 | AF56: 7596746 | AH56: AGUA - BOOSTER - NOEMIA VIEIRA | AI56: R DONA NOEMIA VIEIRA SN FT171 | AJ56: 100MM | AK56: 100MM | AP56: 220/218/219 | AQ56: 79.74.75 | AR56: 13MCA | AS56: 80MCA | AT56: 219/219/218 | AU56: 50.46.49 | AV56: 15MCA | AW56: 127MCA | AX56: 44956 | AY56: 215X220X220 | AZ56: 73X71X71 | BA56: 14 | BB56: 90 | BC56: 212X213X212 | BD56: 40X43X40 | BE56: 20 | BF56: 130 | BG56: 42684 | BH56: X | BI56: X | BJ56: XX | BK56: X | BL56: X | BM56: X | BN56: 250A | BP56: X | BQ56: NÃO | BR56: SIM | BS56: NÃO | BT56: 0 | BU56: 250A | BV56: 5A | BW56: NÃO | BX56: SIM | BY56: NÃO | BZ56: NÃO | CA56: NÃO | CB56: SIM | CH56: SIM | CJ56: SIM | CK56: EM MARCHA | CP56: Rua GerOncio Pimenta - Rua JosE Augusto - Rua Maria GonCalves dos Anjos - Rua Ministro Afrânio Costa - Rua NoEmia Vieira
A57: ODILON BRAGA | B57: =_xlfn.XLOOKUP(A:A,'Dados Elevatórias'!D:D,'Dados Elevatórias'!B:B) -> PL-RJB-EAT0737 | C57: EEAT (737) | D57: BAIXADA II | E57: R MIN ODILON BRAGA SN LD26 | F57: CENTRO | H57: QUEIMADOS | I57: 26310-190 | J57: INFORMAL | K57: 1 | L57: OPERACIONAL | M57: 20 | N57: 3540 | O57: - | P57: 3X2X8 | R57: WORTHINGTON | U57: ABRIGADA | Z57: CONV. | AC57: 220V | AJ57: 2POL | AK57: 2POL | AP57: 218/218/217 | AQ57: 25.24.24 | AR57: 12MCA | AS57: 60MCA | AT57: 219/219/218 | AU57: 20.20.20 | AW57: 68MCA | AX57: 44958 | BH57: DIL | BI57: M40 | BN57: 80A | BP57: 32A | BQ57: SIM | BR57: SIM | BS57: SIM | BT57: 0 | BU57: 80A | BV57: 5A | BW57: NÃO | BX57: NÃO | BY57: SIM | BZ57: SIM | CA57: NÃO | CB57: SIM | CH57: SIM | CJ57: SIM | CK57: EM MARCHA
A58: OLIVIA MARIA MACHADO | B58: =_xlfn.XLOOKUP(A:A,'Dados Elevatórias'!D:D,'Dados Elevatórias'!B:B) -> PL-RJB-EAT0735 | C58: EEAT (735) | D58: BAIXADA II | E58: R OLIVIA MARIA MACHADO 1SN FT9 | F58: SANTA CATARINA | H58: QUEIMADOS | I58: 26323-400 | J58: FORMAL | K58: 1 | L58: OPERACIONAL | M58: 15 | N58: 3500 | O58: RJB-03173 | P58: 2 1/2 x 1 1/2 x 8 | Q58: RJB-07285 | R58: FLOWSERVE | S58: 15 | U58: ABRIGADA | Z58: CONV. | AC58: 220V | AE58: 430097071 | AF58: 8576702 | AH58: AGUA - ELEV - OLIVIA MACHADO | AI58: R OLIVIA MARIA MACHADO 1SN FT9 | AJ58: 2POL | AK58: 2POL | AP58: 220/219/220 | AQ58: 35.33.32 | AR58: 2MCA | AS58: 58MCA | AX58: 44954 | BH58: DIL | BI58: M40 | BJ58: X | BK58: X | BL58: X | BM58: X | BN58: X | BO58: 50A | BP58: 50A | BQ58: NÃO | BR58: NÃO | BS58: NÃO | BT58: X | BU58: X | BV58: 5A | BW58: NÃO | BX58: NÃO | BY58: SIM | BZ58: NÃO | CA58: NÃO | CB58: SIM | CH58: X | CI58: X | CJ58: X | CK58: EM MARCHA
A59: PADRE VIEIRA | B59: =_xlfn.XLOOKUP(A:A,'Dados Elevatórias'!D:D,'Dados Elevatórias'!B:B) -> PL-RJB-EAT0022 | C59: EEAT (22) | D59: BAIXADA II | E59: RUA NAIR DIAS EF AO 650 | F59: VILA OPERARIA | H59: NOVA IGUACU | I59: 26012-450 | J59: FORMAL | K59: 1 | L59: OPERACIONAL | M59: 3 | N59: 3510 | P59: R20-02 | R59: LEAO | S59: / | T59: / | U59: SUBMERSA HORIZONTAL | W59: X | X59: X | Y59: X | Z59: SUBMERSA | AA59: 40.1 | AB59: 25 | AC59: 220V | AE59: 430054507 | AF59: 9464391 | AJ59: 75MM | AK59: 100MM | AP59: 219/218/215 | AQ59: 11.10.10 | AR59: 6MCA | AS59: 30MCA | AT59: 219/221/222 | AU59: 9.9.9 | AW59: 60MCA | AX59: 44957 | AY59: 214X217X216 | AZ59: 8,2X7,9X7,2 | BA59: 30 | BB59: 4 | BC59: 214X212X218 | BD59: 6X6,2X5,8 | BE59: 40 | BF59: 8 | BG59: 43280 | BH59: DIL | BI59: M17-10 | BJ59: X | BK59: X | BL59: X | BM59: X | BN59: 25A | BP59: 12A | BQ59: NÃO | BR59: SIM | BS59: SIM | BT59: 0 | BU59: 25A | BV59: 5A | BW59: NÃO | BX59: SIM | BY59: NÃO | BZ59: NÃO | CA59: NÃO | CB59: SIM | CH59: SIM | CJ59: SIM | CK59: EM MARCHA | CO59: VILA OPERARIA
A60: PAIOL | B60: =_xlfn.XLOOKUP(A:A,'Dados Elevatórias'!D:D,'Dados Elevatórias'!B:B) -> PL-RJB-EAT0050 | C60: EEAT (50) | D60: BAIXADA II | E60: RUA JOAO DIAS DE LIMA, ESQUINA COM RUA OLIMPIO DA FONSECA | F60: CABRAL | H60: NILOPOLIS | I60: 21330-380 | J60: INFORMAL | K60: 1 | L60: OPERACIONAL | M60: 12.5 | N60: 3500 | P60: S35-04 | R60: LEAO | T60: - | U60: SUBMERSA VERTICAL | W60: X | X60: X | Y60: X | Z60: SUBMERSA | AA60: 30.61 | AB60: 55 | AC60: 220V | AE60: 414658235 | AF60: 5411350 | AH60: AGUA - ELEV - JOAO DIAS DE LIMA | AI60: R JOAO DIEZ LIMA SN EF13 | AJ60: 100MM | AK60: 100MM | AP60: 211/216/214 | AQ60: 26.30.31 | AR60: 10MCA | AS60: 40MCA | AT60: 214/212/213 | AW60: 80MCA | AX60: 44962 | AY60: 209X209X210 | AZ60: 32X30X32 | BA60: 13 | BB60: 42 | BC60: 209X212X212 | BD60: 27X25X26 | BE60: 17 | BF60: 95 | BG60: 42769 | BH60: DIL | BI60: M40 | BJ60: X | BK60: X | BL60: X | BM60: X | BN60: 100A | BP60: 35A | BQ60: NÃO | BR60: SIM | BS60: NÃO | BT60: 0 | BU60: 100A | BV60: 5A | BW60: NÃO | BX60: NÃO | BY60: SIM | BZ60: NÃO | CA60: NÃO | CB60: SIM | CH60: SIM | CJ60: SIM | CK60: EM MARCHA | CO60: PAIOL | CP60: Rua JoAo Diaz de Lima (Trecho Rua OlImpio da Fonseca A Rua JosE Couto GuimarAes), Rua Carlos de Souza Fernandes (Trecho Rua Cap. Alfredo Antunes A Rua Cap. Antunes Vasconcelos), Rua Maria Paris (Trecho Rua JosE Couto GuimarAes ao Final da Rua), Travessa Maria Paris, Rua JoAo Alves, Rua JoAo Alves, Rua Humberto Perlingeiro, Rua Ravelo, Rua Leonor Roque, Rua EugEnio Santana, Rua AntOnio M. da Costa, Rua Acacia Torres e pequenas Vilas desse trechos.
A61: PALHADA | B61: =_xlfn.XLOOKUP(A:A,'Dados Elevatórias'!D:D,'Dados Elevatórias'!B:B) -> PL-RJB-EAT0044 | C61: EEAT (44) | D61: BAIXADA II | E61: Estr. da Palhada, 2337 - Valverde, Nova Iguaçu - RJ, 26290-006 | F61: ROSA DOS VENTOS | H61: NOVA IGUACU | I61: 26290-414 | J61: FORMAL | K61: 1 | L61: OPERACIONAL | M61: 15 | N61: 3500 | O61: 60201324 | P61: 3X2X6 | R61: WORTHINGTON | S61: 5.67 | T61: 144.02 | U61: TUBULAO | V61: NÃO | W61: JM | X61: VERTICAL | Y61: FC | Z61: INLINE | AA61: 65 | AB61: 50 | AC61: 220V | AE61: 412957699 | AF61: 5516825 | AH61: AGUA - BOOSTER - PALHADA | AI61: EST GOVR LEONEL BRIZOLA 2338 FT | AJ61: 100MM | AK61: 100MM | AP61: 222/224/222 | AQ61: 25.26.26 | AR61: 8MCA | AS61: 20MCA | AT61: 221/222/223 | AX61: 44943 | AY61: 218X217X219 | AZ61: 16,5X17X17,5 | BG61: 42802 | BH61: X | BI61: X | BJ61: X | BK61: X | BL61: X | BM61: X | BN61: 100A | BP61: X | BQ61: NÃO | BR61: SIM | BS61: SIM | BT61: 0 | BU61: 100A | BV61: 5A | BW61: NÃO | BX61: SIM | BY61: NÃO | BZ61: NÃO | CA61: NÃO | CB61: SIM | CH61: SIM | CJ61: SIM | CK61: EM MARCHA | CP61: Rua Ana Paula - Rua Eliane Azevedo - Rua LUcia - Rua Maria Paula - Rua Mario Roberto - Rua Rafael Luiz
A62: PARQUE MARAVILHA | B62: =_xlfn.XLOOKUP(A:A,'Dados Elevatórias'!D:D,'Dados Elevatórias'!B:B) -> PL-RJB-EAT0733 | C62: EEAT (733) | D62: BAIXADA II | E62: Estrada Gama, SN EF 813 | F62: CERÂMICA | H62: NOVA IGUACU | I62: 26030-200 | J62: INFORMAL | K62: 1 | L62: OPERACIONAL | M62: 5 | N62: 1720 | O62: RJB-06922 | P62: 3X11/2X8 | Q62: RJB-06910 | R62: WORTHINGTON | S62: 7.1 | T62: 180.34 | U62: TUBULAO | V62: SIM | W62: JM | X62: VERTICAL | Y62: FC | Z62: INLINE | AB62: 25 | AC62: 220V | AE62: 420398927 | AF62: 8585236 | AH62: AGUA - BOOSTER - PARQUE MARAVILHA | AI62: EST GAMA SN EF813 | AP62: 216/215/216 | AQ62: 7.8.9 | AR62: 7MCA | AS62: 23MCA | AX62: 44956 | AZ62: 39637 | BA62: 0 | BB62: 20 | BE62: 4 | BJ62: X | BK62: X | BL62: X | BM62: X | BN62: 35A | BP62: 16A | BQ62: NÃO | BR62: SIM | BS62: NÃO | BT62: 0 | BU62: 35A | BV62: X | BW62: SIM | BX62: NÃO | BY62: NÃO | BZ62: NÃO | CA62: NÃO | CB62: SIM | CH62: SIM | CJ62: SIM | CK62: EM MARCHA
A63: PINDORAMA | B63: =_xlfn.XLOOKUP(A:A,'Dados Elevatórias'!D:D,'Dados Elevatórias'!B:B) -> PL-RJB-EAT0099 | C63: EEAT (99) | D63: BAIXADA II | E63: R. Itaparica, 16 - Banco de Areia, Mesquita - RJ, 26570-250 | F63: BANCO DE AREIA | H63: MESQUITA | I63: 26570-000 | J63: FORMAL | K63: 1 | L63: OPERACIONAL | M63: 15 | N63: 3510 | O63: 130201008 | P63: 3X2X6 | Q63: RJB-02260 | R63: WORTHINGTON | S63: 6.18 | T63: 156.97 | U63: TUBULAO | V63: SIM | W63: JM | X63: VERTICAL | Y63: FC | Z63: INLINE | AA63: 53,75 | AB63: 50 | AC63: 220V | AE63: 421230257 | AF63: 9039847 | AH63: AGUA - BOOSTER - PINDORAMA | AI63: PCA PINDORAMA SN | AJ63: 100MM | AK63: 100MM | AP63: 217/220/217 | AQ63: 39.42.39 | AR63: 15MCA | AX63: 44960 | AY63: 215X215X214 | AZ63: 31X33X30 | BA63: 4 | BB63: 45 | BC63: 220X218X218 | BD63: 23X25X25 | BE63: 7 | BF63: 65 | BG63: 42608 | BH63: X | BI63: X | BJ63: X | BK63: X | BL63: X | BM63: X | BN63: 125A | BP63: X | BQ63: NÃO | BR63: SIM | BS63: NÃO | BT63: 0 | BU63: 125A | BV63: X | BW63: SIM | BX63: NÃO | BY63: NÃO | BZ63: NÃO | CA63: NÃO | CB63: SIM | CC63: 1 MCA | CD63: < 1 MCA | CH63: SIM | CJ63: SIM | CK63: EM MARCHA | CP63: Ruas Itapemirim, EugEnio Ferreira, PiaCava, Itaparica, Jequitinhonha, Ipanema, MastruCo, Trav. PiaCava, Bicuiba, Dona Amelia, Juraci, Guapo, Valtire, Jane, Mnaca, Herondina, Prof. JoAo Ribeiro Filho.
